Workbook

Sheet Balance
A1: Capital One — Average Balance by line item ($mm)
A2: Average balance over the quarter. Actuals through Q2:25; Q3:25–Q2:26 forecast from the macro-driven monthly schedule.
A4: Line item (as disclosed) | B4: 2023-03-31 | C4: 2023-06-30 | D4: 2023-09-30 | E4: 2023-12-31 (D) | F4: 2024-03-31 | G4: 2024-06-30 | H4: 2024-09-30 | I4: 2024-12-31 (D) | J4: 2025-03-31 | K4: 2025-06-30 | L4: 2025-09-30 (F) | M4: 2025-12-31 (F) | N4: 2026-03-31 (F) | O4: 2026-06-30 (F)
A5: INTEREST-EARNING ASSETS
A6: Credit card | B6: 134669 | C6: 138762 | D6: 144053 | E6: 149112 | F6: 150049 | G6: 150866 | H6: 154160 | I6: 157360 | J6: 156408 | K6: 209693 | L6: =SUM('Monthly EOP Balance'!AF6:'Monthly EOP Balance'!AI6)/4 -> 243413.58 | M6: =SUM('Monthly EOP Balance'!AI6:'Monthly EOP Balance'!AL6)/4 -> 243537.96 | N6: =SUM('Monthly EOP Balance'!AL6:'Monthly EOP Balance'!AO6)/4 -> 243662.34 | O6: =SUM('Monthly EOP Balance'!AO6:'Monthly EOP Balance'!AR6)/4 -> 243786.72
A7: Consumer banking | B7: 79000 | C7: 77699 | D7: 77154 | E7: 76224 | F7: 75091 | G7: 75386 | H7: 76182 | I7: 77231 | J7: 78480 | K7: 80095 | L7: =SUM('Monthly EOP Balance'!AF7:'Monthly EOP Balance'!AI7)/4 -> 92926.536 | M7: =SUM('Monthly EOP Balance'!AI7:'Monthly EOP Balance'!AL7)/4 -> 92877.078 | N7: =SUM('Monthly EOP Balance'!AL7:'Monthly EOP Balance'!AO7)/4 -> 92827.619 | O7: =SUM('Monthly EOP Balance'!AO7:'Monthly EOP Balance'!AR7)/4 -> 92778.16
A8: Commercial banking | B8: 94446 | C8: 93874 | D8: 92254 | E8: 91385 | F8: 90423 | G8: 89571 | H8: 88373 | I8: 87672 | J8: 87884 | K8: 88749 | L8: =SUM('Monthly EOP Balance'!AF8:'Monthly EOP Balance'!AI8)/4 -> 103020.66 | M8: =SUM('Monthly EOP Balance'!AI8:'Monthly EOP Balance'!AL8)/4 -> 103073.31 | N8: =SUM('Monthly EOP Balance'!AL8:'Monthly EOP Balance'!AO8)/4 -> 103125.95 | O8: =SUM('Monthly EOP Balance'!AO8:'Monthly EOP Balance'!AR8)/4 -> 103178.59
A9: Total loans (incl. HFS) | B9: 308115 | C9: 310335 | D9: 313461 | E9: 316721 | F9: 315563 | G9: 315823 | H9: 318715 | I9: 322263 | J9: 322772 | K9: 378537 | L9: =SUM('Monthly EOP Balance'!AF9:'Monthly EOP Balance'!AI9)/4 -> 439360.78 | M9: =SUM('Monthly EOP Balance'!AI9:'Monthly EOP Balance'!AL9)/4 -> 439488.34 | N9: =SUM('Monthly EOP Balance'!AL9:'Monthly EOP Balance'!AO9)/4 -> 439615.91 | O9: =SUM('Monthly EOP Balance'!AO9:'Monthly EOP Balance'!AR9)/4 -> 439743.47
A10: Investment securities | B10: 89960 | C10: 89994 | D10: 87845 | E10: 88643 | F10: 88581 | G10: 89501 | H10: 90644 | I10: 92260 | J10: 92659 | K10: 93024 | L10: =SUM('Monthly EOP Balance'!AF10:'Monthly EOP Balance'!AI10)/4 -> 87196 | M10: =SUM('Monthly EOP Balance'!AI10:'Monthly EOP Balance'!AL10)/4 -> 87196 | N10: =SUM('Monthly EOP Balance'!AL10:'Monthly EOP Balance'!AO10)/4 -> 87196 | O10: =SUM('Monthly EOP Balance'!AO10:'Monthly EOP Balance'!AR10)/4 -> 87196
A11: Cash equivalents and other | B11: 37124 | C11: 38810 | D11: 42226 | E11: 41625 | F11: 43659 | G11: 45584 | H11: 45125 | I11: 46167 | J11: 47340 | K11: 53368 | L11: =SUM('Monthly EOP Balance'!AF11:'Monthly EOP Balance'!AI11)/4 -> 61593.737 | M11: =SUM('Monthly EOP Balance'!AI11:'Monthly EOP Balance'!AL11)/4 -> 61625.21 | N11: =SUM('Monthly EOP Balance'!AL11:'Monthly EOP Balance'!AO11)/4 -> 61656.683 | O11: =SUM('Monthly EOP Balance'!AO11:'Monthly EOP Balance'!AR11)/4 -> 61688.156
A12: Total interest-earning assets | B12: 435199 | C12: 439139 | D12: 443532 | E12: 446989 | F12: 447803 | G12: 450908 | H12: 454484 | I12: 460690 | J12: 462771 | K12: 524929 | L12: =SUM('Monthly EOP Balance'!AF12:'Monthly EOP Balance'!AI12)/4 -> 588150.52 | M12: =SUM('Monthly EOP Balance'!AI12:'Monthly EOP Balance'!AL12)/4 -> 588309.55 | N12: =SUM('Monthly EOP Balance'!AL12:'Monthly EOP Balance'!AO12)/4 -> 588468.59 | O12: =SUM('Monthly EOP Balance'!AO12:'Monthly EOP Balance'!AR12)/4 -> 588627.63
A14: INTEREST-BEARING LIABILITIES
A15: Interest-bearing deposits | B15: 308788 | C15: 313207 | D15: 316032 | E15: 316842 | F15: 318450 | G15: 322581 | H15: 324509 | I15: 331620 | J15: 337840 | K15: 387139 | L15: =SUM('Monthly EOP Balance'!AF15:'Monthly EOP Balance'!AI15)/4 -> 440343.5 | M15: =SUM('Monthly EOP Balance'!AI15:'Monthly EOP Balance'!AL15)/4 -> 440568.51 | N15: =SUM('Monthly EOP Balance'!AL15:'Monthly EOP Balance'!AO15)/4 -> 440793.52 | O15: =SUM('Monthly EOP Balance'!AO15:'Monthly EOP Balance'!AR15)/4 -> 441018.53
A16: Securitized debt obligations | B16: 17251 | C16: 17771 | D16: 17649 | E16: 18026 | F16: 17836 | G16: 17452 | H16: 15833 | I16: 14920 | J16: 13731 | K16: 13043 | L16: =SUM('Monthly EOP Balance'!AF16:'Monthly EOP Balance'!AI16)/4 -> 14639.71 | M16: =SUM('Monthly EOP Balance'!AI16:'Monthly EOP Balance'!AL16)/4 -> 14421.211 | N16: =SUM('Monthly EOP Balance'!AL16:'Monthly EOP Balance'!AO16)/4 -> 14205.973 | O16: =SUM('Monthly EOP Balance'!AO16:'Monthly EOP Balance'!AR16)/4 -> 13993.947
A17: Senior and subordinated notes | B17: 30136 | C17: 30161 | D17: 31522 | E17: 32603 | F17: 32211 | G17: 30978 | H17: 32041 | I17: 30884 | J17: 30331 | K17: 32872 | L17: =SUM('Monthly EOP Balance'!AF17:'Monthly EOP Balance'!AI17)/4 -> 37174.033 | M17: =SUM('Monthly EOP Balance'!AI17:'Monthly EOP Balance'!AL17)/4 -> 37174.033 | N17: =SUM('Monthly EOP Balance'!AL17:'Monthly EOP Balance'!AO17)/4 -> 37174.033 | O17: =SUM('Monthly EOP Balance'!AO17:'Monthly EOP Balance'!AR17)/4 -> 37174.033
A18: Other borrowings | B18: 2335 | C18: 2419 | D18: 2473 | E18: 2346 | F18: 2373 | G18: 2502 | H18: 2389 | I18: 2430 | J18: 2312 | K18: 2872 | L18: =SUM('Monthly EOP Balance'!AF18:'Monthly EOP Balance'!AI18)/4 -> 1302 | M18: =SUM('Monthly EOP Balance'!AI18:'Monthly EOP Balance'!AL18)/4 -> 1302 | N18: =SUM('Monthly EOP Balance'!AL18:'Monthly EOP Balance'!AO18)/4 -> 1302 | O18: =SUM('Monthly EOP Balance'!AO18:'Monthly EOP Balance'!AR18)/4 -> 1302
A19: Total interest-bearing liabilities | B19: 358510 | C19: 363558 | D19: 367676 | E19: 369817 | F19: 370870 | G19: 373513 | H19: 374772 | I19: 379854 | J19: 384214 | K19: 435926 | L19: =SUM('Monthly EOP Balance'!AF19:'Monthly EOP Balance'!AI19)/4 -> 493459.25 | M19: =SUM('Monthly EOP Balance'!AI19:'Monthly EOP Balance'!AL19)/4 -> 493465.76 | N19: =SUM('Monthly EOP Balance'!AL19:'Monthly EOP Balance'!AO19)/4 -> 493475.52 | O19: =SUM('Monthly EOP Balance'!AO19:'Monthly EOP Balance'!AR19)/4 -> 493488.51
A21: Net earning assets (assets − liabilities) | B21: =B12-B19 -> 76689 | C21: =C12-C19 -> 75581 | D21: =D12-D19 -> 75856 | E21: =E12-E19 -> 77172 | F21: =F12-F19 -> 76933 | G21: =G12-G19 -> 77395 | H21: =H12-H19 -> 79712 | I21: =I12-I19 -> 80836 | ... K21: =K12-K19 -> 89003 | L21: =SUM('Monthly EOP Balance'!AF21:'Monthly EOP Balance'!AI21)/4 -> 94691.271 | M21: =SUM('Monthly EOP Balance'!AI21:'Monthly EOP Balance'!AL21)/4 -> 94843.799 | N21: =SUM('Monthly EOP Balance'!AL21:'Monthly EOP Balance'!AO21)/4 -> 94993.066 | O21: =SUM('Monthly EOP Balance'!AO21:'Monthly EOP Balance'!AR21)/4 -> 95139.121

Sheet Rate
A1: Capital One — Average Yield / Rate by line item (annualised)
A2: Annualised yield on assets and cost of funds on liabilities. Actuals through Q2:25; forecast rates retain June 2025 benchmark spreads or betas.
A4: Line item (as disclosed) | B4: 2023-03-31 | C4: 2023-06-30 | D4: 2023-09-30 | E4: 2023-12-31 (D) | F4: 2024-03-31 | G4: 2024-06-30 | H4: 2024-09-30 | I4: 2024-12-31 (D) | J4: 2025-03-31 | K4: 2025-06-30 | L4: 2025-09-30 (F) | M4: 2025-12-31 (F) | N4: 2026-03-31 (F) | O4: 2026-06-30 (F)
A5: INTEREST-EARNING ASSETS
A6: Credit card | B6: 0.1798 | C6: 0.1817 | D6: 0.1902 | E6: 0.1894 | F6: 0.1884 | G6: 0.1879 | H6: 0.1966 | I6: 0.1905 | J6: 0.1854 | K6: 0.1794 | L6: =IF(Balance!L6=0,"",'Net Interest Income'!L6*4/Balance!L6) -> 0.17615904 | M6: =IF(Balance!M6=0,"",'Net Interest Income'!M6*4/Balance!M6) -> 0.17528404 | N6: =IF(Balance!N6=0,"",'Net Interest Income'!N6*4/Balance!N6) -> 0.17440904 | O6: =IF(Balance!O6=0,"",'Net Interest Income'!O6*4/Balance!O6) -> 0.17353404
A7: Consumer banking | B7: 0.074 | C7: 0.0765 | D7: 0.0797 | E7: 0.0817 | F7: 0.0833 | G7: 0.0854 | H7: 0.0888 | I7: 0.0904 | J7: 0.0903 | K7: 0.093 | L7: =IF(Balance!L7=0,"",'Net Interest Income'!L7*4/Balance!L7) -> 0.095173115 | M7: =IF(Balance!M7=0,"",'Net Interest Income'!M7*4/Balance!M7) -> 0.095123115 | N7: =IF(Balance!N7=0,"",'Net Interest Income'!N7*4/Balance!N7) -> 0.095073115 | O7: =IF(Balance!O7=0,"",'Net Interest Income'!O7*4/Balance!O7) -> 0.095023115
A8: Commercial banking | B8: 0.063 | C8: 0.0674 | D8: 0.0712 | E8: 0.0724 | F8: 0.0713 | G8: 0.0722 | H8: 0.0724 | I8: 0.0672 | J8: 0.0629 | K8: 0.064 | L8: =IF(Balance!L8=0,"",'Net Interest Income'!L8*4/Balance!L8) -> 0.065225042 | M8: =IF(Balance!M8=0,"",'Net Interest Income'!M8*4/Balance!M8) -> 0.064475042 | N8: =IF(Balance!N8=0,"",'Net Interest Income'!N8*4/Balance!N8) -> 0.063725042 | O8: =IF(Balance!O8=0,"",'Net Interest Income'!O8*4/Balance!O8) -> 0.062975042
A9: Total loans (incl. HFS) | B9: 0.1132 | C9: 0.1167 | D9: 0.1237 | E9: 0.1255 | F9: 0.1257 | G9: 0.1266 | H9: 0.1324 | I9: 0.1295 | J9: 0.1259 | K9: 0.1315 | L9: =IF(Balance!L9=0,"",'Net Interest Income'!L9*4/Balance!L9) -> 0.13301856 | M9: =IF(Balance!M9=0,"",'Net Interest Income'!M9*4/Balance!M9) -> 0.13235557 | N9: =IF(Balance!N9=0,"",'Net Interest Income'!N9*4/Balance!N9) -> 0.1316923 | O9: =IF(Balance!O9=0,"",'Net Interest Income'!O9*4/Balance!O9) -> 0.13102876
A10: Investment securities | B10: 0.0273 | C10: 0.0284 | D10: 0.0286 | E10: 0.0302 | F10: 0.031 | G10: 0.0313 | H10: 0.0324 | I10: 0.0326 | J10: 0.0332 | K10: 0.0337 | L10: =IF(Balance!L10=0,"",'Net Interest Income'!L10*4/Balance!L10) -> 0.031892018 | M10: =IF(Balance!M10=0,"",'Net Interest Income'!M10*4/Balance!M10) -> 0.030442018 | N10: =IF(Balance!N10=0,"",'Net Interest Income'!N10*4/Balance!N10) -> 0.028992018 | O10: =IF(Balance!O10=0,"",'Net Interest Income'!O10*4/Balance!O10) -> 0.027542018
A11: Cash equivalents and other | B11: 0.0449 | C11: 0.0484 | D11: 0.0521 | E11: 0.0521 | F11: 0.0521 | G11: 0.0516 | H11: 0.0514 | I11: 0.0459 | J11: 0.0414 | K11: 0.0446 | L11: =IF(Balance!L11=0,"",'Net Interest Income'!L11*4/Balance!L11) -> 0.044632572 | M11: =IF(Balance!M11=0,"",'Net Interest Income'!M11*4/Balance!M11) -> 0.043882572 | N11: =IF(Balance!N11=0,"",'Net Interest Income'!N11*4/Balance!N11) -> 0.043132572 | O11: =IF(Balance!O11=0,"",'Net Interest Income'!O11*4/Balance!O11) -> 0.042382572
A12: Total interest-earning assets | B12: 0.0896 | C12: 0.0926 | D12: 0.0981 | E12: 0.0997 | F12: 0.0998 | G12: 0.1001 | H12: 0.1044 | I12: 0.1017 | J12: 0.0987 | K12: 0.1054 | L12: =IF(Balance!L12=0,"",'Net Interest Income'!L12*4/Balance!L12) -> 0.10876991 | M12: =IF(Balance!M12=0,"",'Net Interest Income'!M12*4/Balance!M12) -> 0.10798299 | N12: =IF(Balance!N12=0,"",'Net Interest Income'!N12*4/Balance!N12) -> 0.10719592 | O12: =IF(Balance!O12=0,"",'Net Interest Income'!O12*4/Balance!O12) -> 0.10640869
A14: INTEREST-BEARING LIABILITIES
A15: Interest-bearing deposits | B15: 0.024 | C15: 0.0291 | D15: 0.033 | E15: 0.0347 | F15: 0.0353 | G15: 0.0356 | H15: 0.0363 | I15: 0.0345 | J15: 0.0322 | K15: 0.0322 | L15: =IF(Balance!L15=0,"",'Net Interest Income'!L15*4/Balance!L15) -> 0.031959386 | M15: =IF(Balance!M15=0,"",'Net Interest Income'!M15*4/Balance!M15) -> 0.03139935 | N15: =IF(Balance!N15=0,"",'Net Interest Income'!N15*4/Balance!N15) -> 0.030839314 | O15: =IF(Balance!O15=0,"",'Net Interest Income'!O15*4/Balance!O15) -> 0.030279277
A16: Securitized debt obligations | B16: 0.049 | C16: 0.0531 | D16: 0.0563 | E16: 0.0584 | F16: 0.0585 | G16: 0.0591 | H16: 0.0593 | I16: 0.055 | J16: 0.0511 | K16: 0.0506 | L16: =IF(Balance!L16=0,"",'Net Interest Income'!L16*4/Balance!L16) -> 0.050314841 | M16: =IF(Balance!M16=0,"",'Net Interest Income'!M16*4/Balance!M16) -> 0.048864847 | N16: =IF(Balance!N16=0,"",'Net Interest Income'!N16*4/Balance!N16) -> 0.047414853 | O16: =IF(Balance!O16=0,"",'Net Interest Income'!O16*4/Balance!O16) -> 0.045964859
A17: Senior and subordinated notes | B17: 0.0649 | C17: 0.07 | D17: 0.0736 | E17: 0.0746 | F17: 0.0752 | G17: 0.0764 | H17: 0.0743 | I17: 0.0699 | J17: 0.0666 | K17: 0.0651 | L17: =IF(Balance!L17=0,"",'Net Interest Income'!L17*4/Balance!L17) -> 0.064401724 | M17: =IF(Balance!M17=0,"",'Net Interest Income'!M17*4/Balance!M17) -> 0.063456224 | N17: =IF(Balance!N17=0,"",'Net Interest Income'!N17*4/Balance!N17) -> 0.062510724 | O17: =IF(Balance!O17=0,"",'Net Interest Income'!O17*4/Balance!O17) -> 0.061565224
A18: Other borrowings | B18: 0.0208 | C18: 0.0195 | D18: 0.0179 | E18: 0.0171 | F18: 0.0178 | G18: 0.0173 | H18: 0.015 | I18: 0.0198 | J18: 0.0157 | K18: 0.0185 | L18: =IF(Balance!L18=0,"",'Net Interest Income'!L18*4/Balance!L18) -> 0.015442304 | M18: =IF(Balance!M18=0,"",'Net Interest Income'!M18*4/Balance!M18) -> 0.014692304 | N18: =IF(Balance!N18=0,"",'Net Interest Income'!N18*4/Balance!N18) -> 0.013942304 | O18: =IF(Balance!O18=0,"",'Net Interest Income'!O18*4/Balance!O18) -> 0.013192304
A19: Total interest-bearing liabilities | B19: 0.0287 | C19: 0.0336 | D19: 0.0375 | E19: 0.0392 | F19: 0.0398 | G19: 0.04 | H19: 0.0404 | I19: 0.0381 | J19: 0.0354 | K19: 0.0352 | L19: =IF(Balance!L19=0,"",'Net Interest Income'!L19*4/Balance!L19) -> 0.034904363 | M19: =IF(Balance!M19=0,"",'Net Interest Income'!M19*4/Balance!M19) -> 0.034280612 | N19: =IF(Balance!N19=0,"",'Net Interest Income'!N19*4/Balance!N19) -> 0.033657743 | O19: =IF(Balance!O19=0,"",'Net Interest Income'!O19*4/Balance!O19) -> 0.033035736
A21: Net interest spread (asset yield − funding cost) | B21: =B12-B19 -> 0.0609 | C21: =C12-C19 -> 0.059 | D21: =D12-D19 -> 0.0606 | E21: =E12-E19 -> 0.0605 | F21: =F12-F19 -> 0.06 | G21: =G12-G19 -> 0.0601 | H21: =H12-H19 -> 0.064 | I21: =I12-I19 -> 0.0636 | ... O21: =O12-O19 -> 0.073372956
A22: Net interest margin (NII / avg earning assets) | B22: =IFERROR(('Net Interest Income'!B21*4)/Balance!B12,"") -> 0.066047946 | C22: =IFERROR(('Net Interest Income'!C21*4)/Balance!C12,"") -> 0.064790419 | D22: =IFERROR(('Net Interest Income'!D21*4)/Balance!D12,"") -> 0.066944437 | E22: =IFERROR(('Net Interest Income'!E21*4)/Balance!E12,"") -> 0.067285772 | F22: =IFERROR(('Net Interest Income'!F21*4)/Balance!F12,"") -> 0.066886555 | G22: =IFERROR(('Net Interest Income'!G21*4)/Balance!G12,"") -> 0.066940485 | H22: =IFERROR(('Net Interest Income'!H21*4)/Balance!H12,"") -> 0.07107841 | I22: =IFERROR(('Net Interest Income'!I21*4)/Balance!I12,"") -> 0.070311923 | ... K22: =IFERROR(('Net Interest Income'!K21*4)/Balance!K12,"") -> 0.076162681 | L22: ='Net Interest Income'!L21*4/Balance!L12 -> 0.079485095 | M22: ='Net Interest Income'!M21*4/Balance!M12 -> 0.079228896 | N22: ='Net Interest Income'!N21*4/Balance!N12 -> 0.078971347 | O22: ='Net Interest Income'!O21*4/Balance!O12 -> 0.07871248

Sheet Net Interest Income
A1: Capital One — Interest Income / Expense by line item ($mm, quarterly)
A2: Interest income on assets and interest expense on liabilities. Actuals through Q2:25; forecast quarters sum the macro-driven monthly schedule.
A4: Line item (as disclosed) | B4: 2023-03-31 | C4: 2023-06-30 | D4: 2023-09-30 | E4: 2023-12-31 (D) | F4: 2024-03-31 | G4: 2024-06-30 | H4: 2024-09-30 | I4: 2024-12-31 (D) | J4: 2025-03-31 | K4: 2025-06-30 | L4: 2025-09-30 (F) | M4: 2025-12-31 (F) | N4: 2026-03-31 (F) | O4: 2026-06-30 (F)
A5: INTEREST-EARNING ASSETS
A6: Credit card | B6: 6053 | C6: 6302 | D6: 6850 | E6: 7062 | F6: 7067 | G6: 7088 | H6: 7578 | I6: 7493 | J6: 7248 | K6: 9407 | L6: =SUM('Monthly NII'!AF6:'Monthly NII'!AH6) -> 10719.876 | M6: =SUM('Monthly NII'!AI6:'Monthly NII'!AK6) -> 10672.079 | N6: =SUM('Monthly NII'!AL6:'Monthly NII'!AN6) -> 10624.229 | O6: =SUM('Monthly NII'!AO6:'Monthly NII'!AQ6) -> 10576.323
A7: Consumer banking | B7: 1461 | C7: 1486 | D7: 1537 | E7: 1557 | F7: 1564 | G7: 1611 | H7: 1692 | I7: 1745 | J7: 1773 | K7: 1861 | L7: =SUM('Monthly NII'!AF7:'Monthly NII'!AH7) -> 2211.027 | M7: =SUM('Monthly NII'!AI7:'Monthly NII'!AK7) -> 2208.6892 | N7: =SUM('Monthly NII'!AL7:'Monthly NII'!AN7) -> 2206.3527 | O7: =SUM('Monthly NII'!AO7:'Monthly NII'!AQ7) -> 2204.0174
A8: Commercial banking | B8: 1488 | C8: 1580 | D8: 1642 | E8: 1653 | F8: 1612 | G8: 1616 | H8: 1601 | I8: 1472 | J8: 1382 | K8: 1421 | L8: =SUM('Monthly NII'!AF8:'Monthly NII'!AH8) -> 1679.8818 | M8: =SUM('Monthly NII'!AI8:'Monthly NII'!AK8) -> 1661.4139 | N8: =SUM('Monthly NII'!AL8:'Monthly NII'!AN8) -> 1642.9263 | O8: =SUM('Monthly NII'!AO8:'Monthly NII'!AQ8) -> 1624.419
A9: Total loans (incl. HFS) | B9: 8723 | C9: 9057 | D9: 9696 | E9: 9934 | F9: 9920 | G9: 9993 | H9: 10547 | I9: 10434 | J9: 10157 | K9: 12449 | L9: =SUM('Monthly NII'!AF9:'Monthly NII'!AH9) -> 14610.784 | M9: =SUM('Monthly NII'!AI9:'Monthly NII'!AK9) -> 14542.182 | N9: =SUM('Monthly NII'!AL9:'Monthly NII'!AN9) -> 14473.508 | O9: =SUM('Monthly NII'!AO9:'Monthly NII'!AQ9) -> 14404.76
A10: Investment securities | B10: 615 | C10: 639 | D10: 627 | E10: 669 | F10: 687 | G10: 700 | H10: 733 | I10: 753 | J10: 770 | K10: 784 | L10: =SUM('Monthly NII'!AF10:'Monthly NII'!AH10) -> 695.2141 | M10: =SUM('Monthly NII'!AI10:'Monthly NII'!AK10) -> 663.60555 | N10: =SUM('Monthly NII'!AL10:'Monthly NII'!AN10) -> 631.997 | O10: =SUM('Monthly NII'!AO10:'Monthly NII'!AQ10) -> 600.38845
A11: Cash equivalents and other | B11: 416 | C11: 470 | D11: 550 | E11: 542 | F11: 570 | G11: 587 | H11: 580 | I11: 530 | J11: 491 | K11: 595 | L11: =SUM('Monthly NII'!AF11:'Monthly NII'!AH11) -> 687.27173 | M11: =SUM('Monthly NII'!AI11:'Monthly NII'!AK11) -> 676.06818 | N11: =SUM('Monthly NII'!AL11:'Monthly NII'!AN11) -> 664.85284 | O11: =SUM('Monthly NII'!AO11:'Monthly NII'!AQ11) -> 653.62569
A12: Total interest-earning assets | B12: 9754 | C12: 10166 | D12: 10873 | E12: 11145 | F12: 11177 | G12: 11280 | H12: 11860 | I12: 11717 | J12: 11418 | K12: 13828 | L12: =SUM('Monthly NII'!AF12:'Monthly NII'!AH12) -> 15993.27 | M12: =SUM('Monthly NII'!AI12:'Monthly NII'!AK12) -> 15881.856 | N12: =SUM('Monthly NII'!AL12:'Monthly NII'!AN12) -> 15770.357 | O12: =SUM('Monthly NII'!AO12:'Monthly NII'!AQ12) -> 15658.774
A14: INTEREST-BEARING LIABILITIES
A15: Interest-bearing deposits | B15: 1856 | C15: 2277 | D15: 2611 | E15: 2745 | F15: 2812 | G15: 2874 | H15: 2945 | I15: 2862 | J15: 2715 | K15: 3120 | L15: =SUM('Monthly NII'!AF15:'Monthly NII'!AH15) -> 3518.277 | M15: =SUM('Monthly NII'!AI15:'Monthly NII'!AK15) -> 3458.3912 | N15: =SUM('Monthly NII'!AL15:'Monthly NII'!AN15) -> 3398.4424 | O15: =SUM('Monthly NII'!AO15:'Monthly NII'!AQ15) -> 3338.4305
A16: Securitized debt obligations | B16: 211 | C16: 236 | D16: 249 | E16: 263 | F16: 261 | G16: 258 | H16: 234 | I16: 205 | J16: 176 | K16: 164 | L16: =SUM('Monthly NII'!AF16:'Monthly NII'!AH16) -> 184.14868 | M16: =SUM('Monthly NII'!AI16:'Monthly NII'!AK16) -> 176.17257 | N16: =SUM('Monthly NII'!AL16:'Monthly NII'!AN16) -> 168.39353 | O16: =SUM('Monthly NII'!AO16:'Monthly NII'!AQ16) -> 160.80745
A17: Senior and subordinated notes | B17: 489 | C17: 528 | D17: 579 | E17: 608 | F17: 606 | G17: 591 | H17: 596 | I17: 540 | J17: 505 | K17: 535 | L17: =SUM('Monthly NII'!AF17:'Monthly NII'!AH17) -> 598.51796 | M17: =SUM('Monthly NII'!AI17:'Monthly NII'!AK17) -> 589.73095 | N17: =SUM('Monthly NII'!AL17:'Monthly NII'!AN17) -> 580.94393 | O17: =SUM('Monthly NII'!AO17:'Monthly NII'!AQ17) -> 572.15692
A18: Other borrowings | B18: 12 | C18: 12 | D18: 11 | E18: 10 | F18: 10 | G18: 11 | H18: 9 | I18: 12 | J18: 9 | K18: 14 | L18: =SUM('Monthly NII'!AF18:'Monthly NII'!AH18) -> 5.02647 | M18: =SUM('Monthly NII'!AI18:'Monthly NII'!AK18) -> 4.782345 | N18: =SUM('Monthly NII'!AL18:'Monthly NII'!AN18) -> 4.53822 | O18: =SUM('Monthly NII'!AO18:'Monthly NII'!AQ18) -> 4.294095
A19: Total interest-bearing liabilities | B19: 2568 | C19: 3053 | D19: 3450 | E19: 3626 | F19: 3689 | G19: 3734 | H19: 3784 | I19: 3619 | J19: 3405 | K19: 3833 | L19: =SUM('Monthly NII'!AF19:'Monthly NII'!AH19) -> 4305.9701 | M19: =SUM('Monthly NII'!AI19:'Monthly NII'!AK19) -> 4229.0771 | N19: =SUM('Monthly NII'!AL19:'Monthly NII'!AN19) -> 4152.3181 | O19: =SUM('Monthly NII'!AO19:'Monthly NII'!AQ19) -> 4075.689
A21: NET INTEREST INCOME | B21: =B12-B19 -> 7186 | C21: =C12-C19 -> 7113 | D21: =D12-D19 -> 7423 | E21: =E12-E19 -> 7519 | F21: =F12-F19 -> 7488 | G21: =G12-G19 -> 7546 | H21: =H12-H19 -> 8076 | I21: =I12-I19 -> 8098 | ... K21: =K12-K19 -> 9995 | L21: =SUM('Monthly NII'!AF21:'Monthly NII'!AH21) -> 11687.3 | M21: =SUM('Monthly NII'!AI21:'Monthly NII'!AK21) -> 11652.779 | N21: =SUM('Monthly NII'!AL21:'Monthly NII'!AN21) -> 11618.039 | O21: =SUM('Monthly NII'!AO21:'Monthly NII'!AQ21) -> 11583.085
A23: CHECK: NII vs income statement (flows.csv)
A24: Income statement NII (XBRL) | B24: 7186 | C24: 7113 | D24: 7423 | E24: 7519 | F24: 7488 | G24: 7546 | H24: 8076 | I24: 8098 | J24: 8013 | K24: 9995
A25: Difference | B25: =IF(B24="","",B21-B24) -> 0 | C25: =IF(C24="","",C21-C24) -> 0 | D25: =IF(D24="","",D21-D24) -> 0 | E25: =IF(E24="","",E21-E24) -> 0 | F25: =IF(F24="","",F21-F24) -> 0 | G25: =IF(G24="","",G21-G24) -> 0 | H25: =IF(H24="","",H21-H24) -> 0 | I25: =IF(I24="","",I21-I24) -> 0 | ... K25: =IF(K24="","",K21-K24) -> 0
A27: Blue = as disclosed. Green = from the XBRL income statement (independent source). Black = formula. Difference should be zero: the MD&A average-balance table and the income statement must agree on NII.
J28: 6month NII | K28: =SUM(J21:K21) -> 18008 | O28: =SUM(N21:O21) -> 23201.124

Sheet Notes & Sources
A1: Balance / Rate / Net Interest Income — Capital One
A3: ON "GL ACCOUNTS"
A4: SEC filings do not expose a general ledger. These rows are the line items Capital One discloses in its average-balance table — the finest account-level granularity available externally. They are groupings, not GL account numbers.
A6: WHAT EACH TABLE HOLDS
A7: Balance — AVERAGE balance over the quarter, in $mm. Not period-end; it will not tie to the balance sheet.
A8: Rate — annualised yield (assets) and cost of funds (liabilities), stored as fractions and displayed as percentages.
A9: Net Interest Income — interest income on assets and interest expense on liabilities, with NII computed as the difference of the totals.
A11: SOURCE
A12: Capital One Financial Corp (CIK 0000927628), Forms 10-Q and 10-K, MD&A table 'Average Balances, Net Interest Income and Net Interest Margin'. These MD&A tables are NOT XBRL-tagged, so values are parsed from the rendered HTML.
A14: Q4 DERIVATION, AND WHY IT IS SOUND
A15: No 3-month Q4 average-balance table is published: the 10-K table is annual and the 10-Q tables are 3/6/9-month. Q4 columns are marked (D).
A16: Two identities were tested against the actual data, both passing 48 of 48 cases: interest is additive (6M = Q1 + Q2), and average balances weight by months (6M avg = (Q1 avg x3 + Q2 avg x3) / 6).
... A42: Macro inputs and calibration values are shown on Forecast Drivers.

Sheet Quarter-End Anchors
A1: Quarter-End Balance Anchors ($mm)
A2: Reported balance-sheet controls through Jun-25. Forecast quarter ends thereafter link to the monthly balance forecast; filing source controls are intentionally blank.
A4: Line item / source control | B4: 44926 | C4: 45016 | D4: 45107 | E4: 45199 | F4: 45291 | G4: 45382 | H4: 45473 | I4: 45565 | J4: 45657 | K4: 45747 | L4: 45838 | M4: 45930 | N4: 46022 | O4: 46112 | P4: 46203
A5: INTEREST-EARNING ASSETS
A6: Credit card | C6: =IF(ISNUMBER(C9),C9*Balance!B6/Balance!B9,"") | D6: =IF(ISNUMBER(D9),D9*Balance!C6/Balance!C9,"") | E6: =IF(ISNUMBER(E9),E9*Balance!D6/Balance!D9,"") | F6: =IF(ISNUMBER(F9),F9*Balance!E6/Balance!E9,"") -> 150877.97 | G6: =IF(ISNUMBER(G9),G9*Balance!F6/Balance!F9,"") -> 149854.52 | H6: =IF(ISNUMBER(H9),H9*Balance!G6/Balance!G9,"") -> 151994.79 | I6: =IF(ISNUMBER(I9),I9*Balance!H6/Balance!H9,"") -> 154899.08 | J6: =IF(ISNUMBER(J9),J9*Balance!I6/Balance!I9,"") -> 160051.49 | ... L6: =IF(ISNUMBER(L9),L9*Balance!K6/Balance!K9,"") -> 243351.39 | M6: ='Monthly EOP Balance'!AI6 -> 243475.77 | N6: ='Monthly EOP Balance'!AL6 -> 243600.15 | O6: ='Monthly EOP Balance'!AO6 -> 243724.53 | P6: ='Monthly EOP Balance'!AR6 -> 243848.91
A7: Consumer banking | C7: =IF(ISNUMBER(C9),C9*Balance!B7/Balance!B9,"") | D7: =IF(ISNUMBER(D9),D9*Balance!C7/Balance!C9,"") | E7: =IF(ISNUMBER(E9),E9*Balance!D7/Balance!D9,"") | F7: =IF(ISNUMBER(F9),F9*Balance!E7/Balance!E9,"") -> 77126.738 | G7: =IF(ISNUMBER(G9),G9*Balance!F7/Balance!F9,"") -> 74993.675 | H7: =IF(ISNUMBER(H9),H9*Balance!G7/Balance!G9,"") -> 75950.041 | I7: =IF(ISNUMBER(I9),I9*Balance!H7/Balance!H9,"") -> 76547.236 | J7: =IF(ISNUMBER(J9),J9*Balance!I7/Balance!I9,"") -> 78551.962 | ... L7: =IF(ISNUMBER(L9),L9*Balance!K7/Balance!K9,"") -> 92951.266 | M7: ='Monthly EOP Balance'!AI7 -> 92901.807 | N7: ='Monthly EOP Balance'!AL7 -> 92852.348 | O7: ='Monthly EOP Balance'!AO7 -> 92802.89 | P7: ='Monthly EOP Balance'!AR7 -> 92753.431
A8: Commercial banking | C8: =IF(ISNUMBER(C9),C9*Balance!B8/Balance!B9,"") | D8: =IF(ISNUMBER(D9),D9*Balance!C8/Balance!C9,"") | E8: =IF(ISNUMBER(E9),E9*Balance!D8/Balance!D9,"") | F8: =IF(ISNUMBER(F9),F9*Balance!E8/Balance!E9,"") -> 92467.294 | G8: =IF(ISNUMBER(G9),G9*Balance!F8/Balance!F9,"") -> 90305.803 | H8: =IF(ISNUMBER(H9),H9*Balance!G8/Balance!G9,"") -> 90241.174 | I8: =IF(ISNUMBER(I9),I9*Balance!H8/Balance!H9,"") -> 88796.682 | J8: =IF(ISNUMBER(J9),J9*Balance!I8/Balance!I9,"") -> 89171.546 | ... L8: =IF(ISNUMBER(L9),L9*Balance!K8/Balance!K9,"") -> 102994.34 | M8: ='Monthly EOP Balance'!AI8 -> 103046.98 | N8: ='Monthly EOP Balance'!AL8 -> 103099.63 | O8: ='Monthly EOP Balance'!AO8 -> 103152.27 | P8: ='Monthly EOP Balance'!AR8 -> 103204.91
A9: Total loans (incl. HFS) | B9: =IF(ISNUMBER(B24),B24,"") | C9: =IF(ISNUMBER(C24),C24,"") | D9: =IF(ISNUMBER(D24),D24,"") | E9: =IF(ISNUMBER(E24),E24,"") | F9: =IF(ISNUMBER(F24),F24,"") -> 320472 | G9: =IF(ISNUMBER(G24),G24,"") -> 315154 | H9: =IF(ISNUMBER(H24),H24,"") -> 318186 | I9: =IF(ISNUMBER(I24),I24,"") -> 320243 | ... L9: =IF(ISNUMBER(L24),L24,"") -> 439297 | M9: ='Monthly EOP Balance'!AI9 -> 439424.56 | N9: ='Monthly EOP Balance'!AL9 -> 439552.13 | O9: ='Monthly EOP Balance'!AO9 -> 439679.69 | P9: ='Monthly EOP Balance'!AR9 -> 439807.25
A10: Investment securities | B10: =IF(COUNT(B25:B26)=0,"",SUM(B25:B26)) | C10: =IF(COUNT(C25:C26)=0,"",SUM(C25:C26)) | D10: =IF(COUNT(D25:D26)=0,"",SUM(D25:D26)) | E10: =IF(COUNT(E25:E26)=0,"",SUM(E25:E26)) | F10: =IF(COUNT(F25:F26)=0,"",SUM(F25:F26)) -> 79117 | G10: =IF(COUNT(G25:G26)=0,"",SUM(G25:G26)) -> 78398 | H10: =IF(COUNT(H25:H26)=0,"",SUM(H25:H26)) -> 79250 | I10: =IF(COUNT(I25:I26)=0,"",SUM(I25:I26)) -> 83500 | ... L10: =IF(COUNT(L25:L26)=0,"",SUM(L25:L26)) -> 87196 | M10: ='Monthly EOP Balance'!AI10 -> 87196 | N10: ='Monthly EOP Balance'!AL10 -> 87196 | O10: ='Monthly EOP Balance'!AO10 -> 87196 | P10: ='Monthly EOP Balance'!AR10 -> 87196
A11: Cash equivalents and other | B11: =IF(ISNUMBER(B27),B27,"") -> 31256 | C11: =IF(ISNUMBER(C27),C27,"") -> 46973 | D11: =IF(ISNUMBER(D27),D27,"") -> 42048 | E11: =IF(ISNUMBER(E27),E27,"") -> 45304 | F11: =IF(ISNUMBER(F27),F27,"") -> 43755 | G11: =IF(ISNUMBER(G27),G27,"") -> 51502 | H11: =IF(ISNUMBER(H27),H27,"") -> 47829 | I11: =IF(ISNUMBER(I27),I27,"") -> 49719 | ... L11: =IF(ISNUMBER(L27),L27,"") -> 61578 | M11: ='Monthly EOP Balance'!AI11 -> 61609.473 | N11: ='Monthly EOP Balance'!AL11 -> 61640.947 | O11: ='Monthly EOP Balance'!AO11 -> 61672.42 | P11: ='Monthly EOP Balance'!AR11 -> 61703.893
A12: Total interest-earning assets | B12: =IF(COUNT(B9:B11)<3,"",SUM(B9:B11)) | C12: =IF(COUNT(C9:C11)<3,"",SUM(C9:C11)) | D12: =IF(COUNT(D9:D11)<3,"",SUM(D9:D11)) | E12: =IF(COUNT(E9:E11)<3,"",SUM(E9:E11)) | F12: =IF(COUNT(F9:F11)<3,"",SUM(F9:F11)) -> 443344 | G12: =IF(COUNT(G9:G11)<3,"",SUM(G9:G11)) -> 445054 | H12: =IF(COUNT(H9:H11)<3,"",SUM(H9:H11)) -> 445265 | I12: =IF(COUNT(I9:I11)<3,"",SUM(I9:I11)) -> 453462 | ... L12: =IF(COUNT(L9:L11)<3,"",SUM(L9:L11)) -> 588071 | M12: ='Monthly EOP Balance'!AI12 -> 588230.04 | N12: ='Monthly EOP Balance'!AL12 -> 588389.07 | O12: ='Monthly EOP Balance'!AO12 -> 588548.11 | P12: ='Monthly EOP Balance'!AR12 -> 588707.14
A14: INTEREST-BEARING LIABILITIES
A15: Interest-bearing deposits | B15: =IF(ISNUMBER(B28),B28,"") | C15: =IF(ISNUMBER(C28),C28,"") | D15: =IF(ISNUMBER(D28),D28,"") | E15: =IF(ISNUMBER(E28),E28,"") | F15: =IF(ISNUMBER(F28),F28,"") -> 320389 | G15: =IF(ISNUMBER(G28),G28,"") -> 323352 | H15: =IF(ISNUMBER(H28),H28,"") -> 324437 | I15: =IF(ISNUMBER(I28),I28,"") -> 327253 | ... L15: =IF(ISNUMBER(L28),L28,"") -> 440231 | M15: ='Monthly EOP Balance'!AI15 -> 440456.01 | N15: ='Monthly EOP Balance'!AL15 -> 440681.01 | O15: ='Monthly EOP Balance'!AO15 -> 440906.02 | P15: ='Monthly EOP Balance'!AR15 -> 441131.03
A16: Securitized debt obligations | C16: =IF(ISNUMBER(C29),C29*Balance!B16/SUM(Balance!B16:'Balance'!B17),"") | D16: =IF(ISNUMBER(D29),D29*Balance!C16/SUM(Balance!C16:'Balance'!C17),"") | E16: =IF(ISNUMBER(E29),E29*Balance!D16/SUM(Balance!D16:'Balance'!D17),"") | F16: =IF(ISNUMBER(F29),F29*Balance!E16/SUM(Balance!E16:'Balance'!E17),"") -> 17559.23 | G16: =IF(ISNUMBER(G29),G29*Balance!F16/SUM(Balance!F16:'Balance'!F17),"") -> 17745.478 | H16: =IF(ISNUMBER(H29),H29*Balance!G16/SUM(Balance!G16:'Balance'!G17),"") -> 17023.538 | I16: =IF(ISNUMBER(I29),I29*Balance!H16/SUM(Balance!H16:'Balance'!H17),"") -> 16144.54 | J16: =IF(ISNUMBER(J29),J29*Balance!I16/SUM(Balance!I16:'Balance'!I17),"") -> 14654.525 | ... L16: =IF(ISNUMBER(L29),L29*Balance!K16/SUM(Balance!K16:'Balance'!K17),"") -> 14749.967 | M16: ='Monthly EOP Balance'!AI16 -> 14529.822 | N16: ='Monthly EOP Balance'!AL16 -> 14312.962 | O16: ='Monthly EOP Balance'!AO16 -> 14099.34 | P16: ='Monthly EOP Balance'!AR16 -> 13888.905
A17: Senior and subordinated notes | C17: =IF(ISNUMBER(C29),C29*Balance!B17/SUM(Balance!B16:'Balance'!B17),"") | D17: =IF(ISNUMBER(D29),D29*Balance!C17/SUM(Balance!C16:'Balance'!C17),"") | E17: =IF(ISNUMBER(E29),E29*Balance!D17/SUM(Balance!D16:'Balance'!D17),"") | F17: =IF(ISNUMBER(F29),F29*Balance!E17/SUM(Balance!E16:'Balance'!E17),"") -> 31758.77 | G17: =IF(ISNUMBER(G29),G29*Balance!F17/SUM(Balance!F16:'Balance'!F17),"") -> 32047.522 | H17: =IF(ISNUMBER(H29),H29*Balance!G17/SUM(Balance!G16:'Balance'!G17),"") -> 30217.462 | I17: =IF(ISNUMBER(I29),I29*Balance!H17/SUM(Balance!H16:'Balance'!H17),"") -> 32671.46 | J17: =IF(ISNUMBER(J29),J29*Balance!I17/SUM(Balance!I16:'Balance'!I17),"") -> 30334.475 | ... L17: =IF(ISNUMBER(L29),L29*Balance!K17/SUM(Balance!K16:'Balance'!K17),"") -> 37174.033 | M17: ='Monthly EOP Balance'!AI17 -> 37174.033 | N17: ='Monthly EOP Balance'!AL17 -> 37174.033 | O17: ='Monthly EOP Balance'!AO17 -> 37174.033 | P17: ='Monthly EOP Balance'!AR17 -> 37174.033
A18: Other borrowings | B18: =IF(COUNT(B30:B31)<2,"",SUM(B30:B31)) | C18: =IF(COUNT(C30:C31)<2,"",SUM(C30:C31)) | D18: =IF(COUNT(D30:D31)<2,"",SUM(D30:D31)) | E18: =IF(COUNT(E30:E31)<2,"",SUM(E30:E31)) | F18: =IF(COUNT(F30:F31)<2,"",SUM(F30:F31)) -> 565 | G18: =IF(COUNT(G30:G31)<2,"",SUM(G30:G31)) -> 592 | H18: =IF(COUNT(H30:H31)<2,"",SUM(H30:H31)) -> 740 | I18: =IF(COUNT(I30:I31)<2,"",SUM(I30:I31)) -> 544 | ... L18: =IF(COUNT(L30:L31)<2,"",SUM(L30:L31)) -> 1302 | M18: ='Monthly EOP Balance'!AI18 -> 1302 | N18: ='Monthly EOP Balance'!AL18 -> 1302 | O18: ='Monthly EOP Balance'!AO18 -> 1302 | P18: ='Monthly EOP Balance'!AR18 -> 1302
A19: Total interest-bearing liabilities | B19: =IF(COUNT(B15:B18)<4,"",SUM(B15:B18)) | C19: =IF(COUNT(C15:C18)<4,"",SUM(C15:C18)) | D19: =IF(COUNT(D15:D18)<4,"",SUM(D15:D18)) | E19: =IF(COUNT(E15:E18)<4,"",SUM(E15:E18)) | F19: =IF(COUNT(F15:F18)<4,"",SUM(F15:F18)) -> 370272 | G19: =IF(COUNT(G15:G18)<4,"",SUM(G15:G18)) -> 373737 | H19: =IF(COUNT(H15:H18)<4,"",SUM(H15:H18)) -> 372418 | I19: =IF(COUNT(I15:I18)<4,"",SUM(I15:I18)) -> 376613 | ... L19: =IF(COUNT(L15:L18)<4,"",SUM(L15:L18)) -> 493457 | M19: ='Monthly EOP Balance'!AI19 -> 493461.86 | N19: ='Monthly EOP Balance'!AL19 -> 493470.01 | O19: ='Monthly EOP Balance'!AO19 -> 493481.39 | P19: ='Monthly EOP Balance'!AR19 -> 493495.97
A21: Net earning assets (assets − liabilities) | B21: =IF(COUNT(B12,B19)<2,"",B12-B19) | C21: =IF(COUNT(C12,C19)<2,"",C12-C19) | D21: =IF(COUNT(D12,D19)<2,"",D12-D19) | E21: =IF(COUNT(E12,E19)<2,"",E12-E19) | F21: =IF(COUNT(F12,F19)<2,"",F12-F19) -> 73072 | G21: =IF(COUNT(G12,G19)<2,"",G12-G19) -> 71317 | H21: =IF(COUNT(H12,H19)<2,"",H12-H19) -> 72847 | I21: =IF(COUNT(I12,I19)<2,"",I12-I19) -> 76849 | ... L21: =IF(COUNT(L12,L19)<2,"",L12-L19) -> 94614 | M21: ='Monthly EOP Balance'!AI21 -> 94768.174 | N21: ='Monthly EOP Balance'!AL21 -> 94919.062 | O21: ='Monthly EOP Balance'!AO21 -> 95066.713 | P21: ='Monthly EOP Balance'!AR21 -> 95211.177
A23: SOURCE CONTROLS
A24: Loans HFI, gross | F24: 320472 | G24: 315154 | H24: 318186 | I24: 320243 | J24: 327775 | K24: 323598 | L24: 439297
A25: Securities AFS | F25: 79117 | G25: 78398 | H25: 79250 | I25: 83500 | J25: 83013 | K25: 84362 | L25: 87196
A26: Securities HTM
A27: Cash and cash equivalents | B27: 31256 | C27: 46973 | D27: 42048 | E27: 45304 | F27: 43755 | G27: 51502 | H27: 47829 | I27: 49719 | J27: 43671 | K27: 48965 | L27: 61578
A28: Interest-bearing deposits | F28: 320389 | G28: 323352 | H28: 324437 | I28: 327253 | J28: 336585 | K28: 340964 | L28: 440231
A29: Long-term debt | F29: 49318 | G29: 49793 | H29: 47241 | I29: 48816 | J29: 44989 | K29: 41200 | L29: 51924
A30: Short-term borrowings | F30: 538 | G30: 568 | H30: 715 | I30: 520 | J30: 562 | K30: 573 | L30: 742
A31: Other borrowings | F31: 27 | G31: 24 | H31: 25 | I31: 24 | J31: 29 | K31: 25 | L31: 560

Sheet Monthly EOP Balance
A1: Capital One - Imputed Monthly End-of-Period Balance by line item ($mm)
A2: Reported and controlled month ends through Jun-25. Jul-25 through Jun-26 is a macro-driven balance forecast.
A4: Line item (as disclosed) | B4: 44926 | C4: 44957 | D4: 44985 | E4: 45016 | F4: 45046 | G4: 45077 | H4: 45107 | I4: 45138 | J4: 45169 | K4: 45199 | L4: 45230 | M4: 45260 | N4: 45291 | O4: 45322 | P4: 45351 | Q4: 45382 | R4: 45412 | S4: 45443 | T4: 45473 | U4: 45504 | V4: 45535 | W4: 45565 | X4: 45596 | Y4: 45626 | Z4: 45657 | AA4: 45688 | AB4: 45716 | AC4: 45747 | AD4: 45777 | AE4: 45808 | AF4: 45838 | AG4: 45869 | AH4: 45900 | AI4: 45930 | AJ4: 45961 | AK4: 45991 | AL4: 46022 | AM4: 46053 | AN4: 46081 | AO4: 46112 | AP4: 46142 | AQ4: 46173 | AR4: 46203
A5: INTEREST-EARNING ASSETS
A6: Credit card | B6: =IF(ISNUMBER('Quarter-End Anchors'!B6),'Quarter-End Anchors'!B6,Balance!B6) -> 134669 | C6: =B6+(E6-B6)/3+(2*Balance!B6-B6-E6) -> 134669 | D6: =B6+2*(E6-B6)/3+(2*Balance!B6-B6-E6) -> 134669 | E6: =IF(ISNUMBER('Quarter-End Anchors'!C6),'Quarter-End Anchors'!C6,2*Balance!B6-B6) -> 134669 | F6: =E6+(H6-E6)/3+(2*Balance!C6-E6-H6) -> 137397.67 | G6: =E6+2*(H6-E6)/3+(2*Balance!C6-E6-H6) -> 140126.33 | H6: =IF(ISNUMBER('Quarter-End Anchors'!D6),'Quarter-End Anchors'!D6,2*Balance!C6-E6) -> 142855 | I6: =H6+(K6-H6)/3+(2*Balance!D6-H6-K6) -> 143653.67 | J6: =H6+2*(K6-H6)/3+(2*Balance!D6-H6-K6) -> 144452.33 | K6: =IF(ISNUMBER('Quarter-End Anchors'!E6),'Quarter-End Anchors'!E6,2*Balance!D6-H6) -> 145251 | L6: =K6+(N6-K6)/3+(2*Balance!E6-K6-N6) -> 149221.69 | M6: =K6+2*(N6-K6)/3+(2*Balance!E6-K6-N6) -> 151097.34 | N6: =IF(ISNUMBER('Quarter-End Anchors'!F6),'Quarter-End Anchors'!F6,2*Balance!E6-K6) -> 150877.97 | O6: =N6+(Q6-N6)/3+(2*Balance!F6-N6-Q6) -> 149902.33 | P6: =N6+2*(Q6-N6)/3+(2*Balance!F6-N6-Q6) -> 149561.18 | Q6: =IF(ISNUMBER('Quarter-End Anchors'!G6),'Quarter-End Anchors'!G6,2*Balance!F6-N6) -> 149854.52 | R6: =Q6+(T6-Q6)/3+(2*Balance!G6-Q6-T6) -> 150450.64 | S6: =Q6+2*(T6-Q6)/3+(2*Balance!G6-Q6-T6) -> 151164.06 | T6: =IF(ISNUMBER('Quarter-End Anchors'!H6),'Quarter-End Anchors'!H6,2*Balance!G6-Q6) -> 151994.79 | U6: =T6+(W6-T6)/3+(2*Balance!H6-T6-W6) -> 154389.02 | V6: =T6+2*(W6-T6)/3+(2*Balance!H6-T6-W6) -> 155357.12 | W6: =IF(ISNUMBER('Quarter-End Anchors'!I6),'Quarter-End Anchors'!I6,2*Balance!H6-T6) -> 154899.08 | X6: =W6+(Z6-W6)/3+(2*Balance!I6-W6-Z6) -> 156385.98 | Y6: =W6+2*(Z6-W6)/3+(2*Balance!I6-W6-Z6) -> 158103.45 | Z6: =IF(ISNUMBER('Quarter-End Anchors'!J6),'Quarter-End Anchors'!J6,2*Balance!I6-W6) -> 160051.49 | AA6: =Z6+(AC6-Z6)/3+(2*Balance!J6-Z6-AC6) -> 154926.66 | AB6: =Z6+2*(AC6-Z6)/3+(2*Balance!J6-Z6-AC6) -> 153845.58 | AC6: =IF(ISNUMBER('Quarter-End Anchors'!K6),'Quarter-End Anchors'!K6,2*Balance!J6-Z6) -> 156808.26 | AD6: =AC6+(AF6-AC6)/3+(2*Balance!K6-AC6-AF6) -> 204882.32 | AE6: =AC6+2*(AF6-AC6)/3+(2*Balance!K6-AC6-AF6) -> 233730.03 | AF6: =IF(ISNUMBER('Quarter-End Anchors'!L6),'Quarter-End Anchors'!L6,2*Balance!K6-AC6) -> 243351.39 | AG6: =AF6*('Forecast Drivers'!C12/'Forecast Drivers'!B12)*((1-'Forecast Drivers'!C11/100)/(1-'Forecast Drivers'!B11/100)) -> 243392.85 | AH6: =AG6*('Forecast Drivers'!D12/'Forecast Drivers'!C12)*((1-'Forecast Drivers'!D11/100)/(1-'Forecast Drivers'!C11/100)) -> 243434.31 | AI6: =AH6*('Forecast Drivers'!E12/'Forecast Drivers'!D12)*((1-'Forecast Drivers'!E11/100)/(1-'Forecast Drivers'!D11/100)) -> 243475.77 | AJ6: =AI6*('Forecast Drivers'!F12/'Forecast Drivers'!E12)*((1-'Forecast Drivers'!F11/100)/(1-'Forecast Drivers'!E11/100)) -> 243517.23 | AK6: =AJ6*('Forecast Drivers'!G12/'Forecast Drivers'!F12)*((1-'Forecast Drivers'!G11/100)/(1-'Forecast Drivers'!F11/100)) -> 243558.69 | AL6: =AK6*('Forecast Drivers'!H12/'Forecast Drivers'!G12)*((1-'Forecast Drivers'!H11/100)/(1-'Forecast Drivers'!G11/100)) -> 243600.15 | AM6: =AL6*('Forecast Drivers'!I12/'Forecast Drivers'!H12)*((1-'Forecast Drivers'!I11/100)/(1-'Forecast Drivers'!H11/100)) -> 243641.61 | AN6: =AM6*('Forecast Drivers'!J12/'Forecast Drivers'!I12)*((1-'Forecast Drivers'!J11/100)/(1-'Forecast Drivers'!I11/100)) -> 243683.07 | ... AR6: =AQ6*('Forecast Drivers'!N12/'Forecast Drivers'!M12)*((1-'Forecast Drivers'!N11/100)/(1-'Forecast Drivers'!M11/100)) -> 243848.91
A7: Consumer banking | B7: =IF(ISNUMBER('Quarter-End Anchors'!B7),'Quarter-End Anchors'!B7,Balance!B7) -> 79000 | C7: =B7+(E7-B7)/3+(2*Balance!B7-B7-E7) -> 79000 | D7: =B7+2*(E7-B7)/3+(2*Balance!B7-B7-E7) -> 79000 | E7: =IF(ISNUMBER('Quarter-End Anchors'!C7),'Quarter-End Anchors'!C7,2*Balance!B7-B7) -> 79000 | F7: =E7+(H7-E7)/3+(2*Balance!C7-E7-H7) -> 78132.667 | G7: =E7+2*(H7-E7)/3+(2*Balance!C7-E7-H7) -> 77265.333 | H7: =IF(ISNUMBER('Quarter-End Anchors'!D7),'Quarter-End Anchors'!D7,2*Balance!C7-E7) -> 76398 | I7: =H7+(K7-H7)/3+(2*Balance!D7-H7-K7) -> 76902 | J7: =H7+2*(K7-H7)/3+(2*Balance!D7-H7-K7) -> 77406 | K7: =IF(ISNUMBER('Quarter-End Anchors'!E7),'Quarter-End Anchors'!E7,2*Balance!D7-H7) -> 77910 | L7: =K7+(N7-K7)/3+(2*Balance!E7-K7-N7) -> 75060.174 | M7: =K7+2*(N7-K7)/3+(2*Balance!E7-K7-N7) -> 74799.087 | N7: =IF(ISNUMBER('Quarter-End Anchors'!F7),'Quarter-End Anchors'!F7,2*Balance!E7-K7) -> 77126.738 | O7: =N7+(Q7-N7)/3+(2*Balance!F7-N7-Q7) -> 74477.304 | P7: =N7+2*(Q7-N7)/3+(2*Balance!F7-N7-Q7) -> 73766.283 | Q7: =IF(ISNUMBER('Quarter-End Anchors'!G7),'Quarter-End Anchors'!G7,2*Balance!F7-N7) -> 74993.675 | R7: =Q7+(T7-Q7)/3+(2*Balance!G7-Q7-T7) -> 75140.748 | S7: =Q7+2*(T7-Q7)/3+(2*Balance!G7-Q7-T7) -> 75459.536 | T7: =IF(ISNUMBER('Quarter-End Anchors'!H7),'Quarter-End Anchors'!H7,2*Balance!G7-Q7) -> 75950.041 | U7: =T7+(W7-T7)/3+(2*Balance!H7-T7-W7) -> 76015.829 | V7: =T7+2*(W7-T7)/3+(2*Balance!H7-T7-W7) -> 76214.894 | W7: =IF(ISNUMBER('Quarter-End Anchors'!I7),'Quarter-End Anchors'!I7,2*Balance!H7-T7) -> 76547.236 | X7: =W7+(Z7-W7)/3+(2*Balance!I7-W7-Z7) -> 76578.28 | Y7: =W7+2*(Z7-W7)/3+(2*Balance!I7-W7-Z7) -> 77246.522 | Z7: =IF(ISNUMBER('Quarter-End Anchors'!J7),'Quarter-End Anchors'!J7,2*Balance!I7-W7) -> 78551.962 | AA7: =Z7+(AC7-Z7)/3+(2*Balance!J7-Z7-AC7) -> 78322.121 | AB7: =Z7+2*(AC7-Z7)/3+(2*Balance!J7-Z7-AC7) -> 78365.08 | AC7: =IF(ISNUMBER('Quarter-End Anchors'!K7),'Quarter-End Anchors'!K7,2*Balance!J7-Z7) -> 78680.837 | AD7: =AC7+(AF7-AC7)/3+(2*Balance!K7-AC7-AF7) -> 71995.544 | AE7: =AC7+2*(AF7-AC7)/3+(2*Balance!K7-AC7-AF7) -> 76752.354 | AF7: =IF(ISNUMBER('Quarter-End Anchors'!L7),'Quarter-End Anchors'!L7,2*Balance!K7-AC7) -> 92951.266 | AG7: =AF7*('Forecast Drivers'!C9/'Forecast Drivers'!B9) -> 92934.779 | AH7: =AG7*('Forecast Drivers'!D9/'Forecast Drivers'!C9) -> 92918.293 | AI7: =AH7*('Forecast Drivers'!E9/'Forecast Drivers'!D9) -> 92901.807 | AJ7: =AI7*('Forecast Drivers'!F9/'Forecast Drivers'!E9) -> 92885.321 | AK7: =AJ7*('Forecast Drivers'!G9/'Forecast Drivers'!F9) -> 92868.834 | AL7: =AK7*('Forecast Drivers'!H9/'Forecast Drivers'!G9) -> 92852.348 | AM7: =AL7*('Forecast Drivers'!I9/'Forecast Drivers'!H9) -> 92835.862 | AN7: =AM7*('Forecast Drivers'!J9/'Forecast Drivers'!I9) -> 92819.376 | ... AR7: =AQ7*('Forecast Drivers'!N9/'Forecast Drivers'!M9) -> 92753.431
A8: Commercial banking | B8: =IF(ISNUMBER('Quarter-End Anchors'!B8),'Quarter-End Anchors'!B8,Balance!B8) -> 94446 | C8: =B8+(E8-B8)/3+(2*Balance!B8-B8-E8) -> 94446 | D8: =B8+2*(E8-B8)/3+(2*Balance!B8-B8-E8) -> 94446 | E8: =IF(ISNUMBER('Quarter-End Anchors'!C8),'Quarter-End Anchors'!C8,2*Balance!B8-B8) -> 94446 | F8: =E8+(H8-E8)/3+(2*Balance!C8-E8-H8) -> 94064.667 | G8: =E8+2*(H8-E8)/3+(2*Balance!C8-E8-H8) -> 93683.333 | H8: =IF(ISNUMBER('Quarter-End Anchors'!D8),'Quarter-End Anchors'!D8,2*Balance!C8-E8) -> 93302 | I8: =H8+(K8-H8)/3+(2*Balance!D8-H8-K8) -> 92603.333 | J8: =H8+2*(K8-H8)/3+(2*Balance!D8-H8-K8) -> 91904.667 | K8: =IF(ISNUMBER('Quarter-End Anchors'!E8),'Quarter-End Anchors'!E8,2*Balance!D8-H8) -> 91206 | L8: =K8+(N8-K8)/3+(2*Balance!E8-K8-N8) -> 90723.138 | M8: =K8+2*(N8-K8)/3+(2*Balance!E8-K8-N8) -> 91143.569 | N8: =IF(ISNUMBER('Quarter-End Anchors'!F8),'Quarter-End Anchors'!F8,2*Balance!E8-K8) -> 92467.294 | O8: =N8+(Q8-N8)/3+(2*Balance!F8-N8-Q8) -> 89819.7 | P8: =N8+2*(Q8-N8)/3+(2*Balance!F8-N8-Q8) -> 89099.203 | Q8: =IF(ISNUMBER('Quarter-End Anchors'!G8),'Quarter-End Anchors'!G8,2*Balance!F8-N8) -> 90305.803 | R8: =Q8+(T8-Q8)/3+(2*Balance!G8-Q8-T8) -> 88879.283 | S8: =Q8+2*(T8-Q8)/3+(2*Balance!G8-Q8-T8) -> 88857.74 | T8: =IF(ISNUMBER('Quarter-End Anchors'!H8),'Quarter-End Anchors'!H8,2*Balance!G8-Q8) -> 90241.174 | U8: =T8+(W8-T8)/3+(2*Balance!H8-T8-W8) -> 87467.82 | V8: =T8+2*(W8-T8)/3+(2*Balance!H8-T8-W8) -> 86986.323 | W8: =IF(ISNUMBER('Quarter-End Anchors'!I8),'Quarter-End Anchors'!I8,2*Balance!H8-T8) -> 88796.682 | X8: =W8+(Z8-W8)/3+(2*Balance!I8-W8-Z8) -> 86297.409 | Y8: =W8+2*(Z8-W8)/3+(2*Balance!I8-W8-Z8) -> 86422.363 | Z8: =IF(ISNUMBER('Quarter-End Anchors'!J8),'Quarter-End Anchors'!J8,2*Balance!I8-W8) -> 89171.546 | AA8: =Z8+(AC8-Z8)/3+(2*Balance!J8-Z8-AC8) -> 87304.883 | AB8: =Z8+2*(AC8-Z8)/3+(2*Balance!J8-Z8-AC8) -> 86950.669 | AC8: =IF(ISNUMBER('Quarter-End Anchors'!K8),'Quarter-End Anchors'!K8,2*Balance!J8-Z8) -> 88108.902 | AD8: =AC8+(AF8-AC8)/3+(2*Balance!K8-AC8-AF8) -> 79465.471 | AE8: =AC8+2*(AF8-AC8)/3+(2*Balance!K8-AC8-AF8) -> 84427.284 | AF8: =IF(ISNUMBER('Quarter-End Anchors'!L8),'Quarter-End Anchors'!L8,2*Balance!K8-AC8) -> 102994.34 | AG8: =AF8*('Forecast Drivers'!C12/'Forecast Drivers'!B12) -> 103011.89 | AH8: =AG8*('Forecast Drivers'!D12/'Forecast Drivers'!C12) -> 103029.44 | AI8: =AH8*('Forecast Drivers'!E12/'Forecast Drivers'!D12) -> 103046.98 | AJ8: =AI8*('Forecast Drivers'!F12/'Forecast Drivers'!E12) -> 103064.53 | AK8: =AJ8*('Forecast Drivers'!G12/'Forecast Drivers'!F12) -> 103082.08 | AL8: =AK8*('Forecast Drivers'!H12/'Forecast Drivers'!G12) -> 103099.63 | AM8: =AL8*('Forecast Drivers'!I12/'Forecast Drivers'!H12) -> 103117.17 | AN8: =AM8*('Forecast Drivers'!J12/'Forecast Drivers'!I12) -> 103134.72 | ... AR8: =AQ8*('Forecast Drivers'!N12/'Forecast Drivers'!M12) -> 103204.91
A9: Total loans (incl. HFS) | B9: =SUM(B6:B8) -> 308115 | C9: =SUM(C6:C8) -> 308115 | D9: =SUM(D6:D8) -> 308115 | E9: =SUM(E6:E8) -> 308115 | F9: =SUM(F6:F8) -> 309595 | G9: =SUM(G6:G8) -> 311075 | H9: =SUM(H6:H8) -> 312555 | I9: =SUM(I6:I8) -> 313159 | ... AR9: =SUM(AR6:AR8) -> 439807.25
A10: Investment securities | B10: =IF(ISNUMBER('Quarter-End Anchors'!B10),'Quarter-End Anchors'!B10,Balance!B10) -> 89960 | C10: =B10+(E10-B10)/3+(2*Balance!B10-B10-E10) -> 89960 | D10: =B10+2*(E10-B10)/3+(2*Balance!B10-B10-E10) -> 89960 | E10: =IF(ISNUMBER('Quarter-End Anchors'!C10),'Quarter-End Anchors'!C10,2*Balance!B10-B10) -> 89960 | F10: =E10+(H10-E10)/3+(2*Balance!C10-E10-H10) -> 89982.667 | G10: =E10+2*(H10-E10)/3+(2*Balance!C10-E10-H10) -> 90005.333 | H10: =IF(ISNUMBER('Quarter-End Anchors'!D10),'Quarter-End Anchors'!D10,2*Balance!C10-E10) -> 90028 | I10: =H10+(K10-H10)/3+(2*Balance!D10-H10-K10) -> 88572.667 | J10: =H10+2*(K10-H10)/3+(2*Balance!D10-H10-K10) -> 87117.333 | K10: =IF(ISNUMBER('Quarter-End Anchors'!E10),'Quarter-End Anchors'!E10,2*Balance!D10-H10) -> 85662 | L10: =K10+(N10-K10)/3+(2*Balance!E10-K10-N10) -> 95987.333 | M10: =K10+2*(N10-K10)/3+(2*Balance!E10-K10-N10) -> 93805.667 | N10: =IF(ISNUMBER('Quarter-End Anchors'!F10),'Quarter-End Anchors'!F10,2*Balance!E10-K10) -> 79117 | O10: =N10+(Q10-N10)/3+(2*Balance!F10-N10-Q10) -> 98524.333 | P10: =N10+2*(Q10-N10)/3+(2*Balance!F10-N10-Q10) -> 98284.667 | Q10: =IF(ISNUMBER('Quarter-End Anchors'!G10),'Quarter-End Anchors'!G10,2*Balance!F10-N10) -> 78398 | R10: =Q10+(T10-Q10)/3+(2*Balance!G10-Q10-T10) -> 100036 | S10: =Q10+2*(T10-Q10)/3+(2*Balance!G10-Q10-T10) -> 100320 | T10: =IF(ISNUMBER('Quarter-End Anchors'!H10),'Quarter-End Anchors'!H10,2*Balance!G10-Q10) -> 79250 | U10: =T10+(W10-T10)/3+(2*Balance!H10-T10-W10) -> 99204.667 | V10: =T10+2*(W10-T10)/3+(2*Balance!H10-T10-W10) -> 100621.33 | W10: =IF(ISNUMBER('Quarter-End Anchors'!I10),'Quarter-End Anchors'!I10,2*Balance!H10-T10) -> 83500 | X10: =W10+(Z10-W10)/3+(2*Balance!I10-W10-Z10) -> 101344.67 | Y10: =W10+2*(Z10-W10)/3+(2*Balance!I10-W10-Z10) -> 101182.33 | Z10: =IF(ISNUMBER('Quarter-End Anchors'!J10),'Quarter-End Anchors'!J10,2*Balance!I10-W10) -> 83013 | AA10: =Z10+(AC10-Z10)/3+(2*Balance!J10-Z10-AC10) -> 101405.67 | AB10: =Z10+2*(AC10-Z10)/3+(2*Balance!J10-Z10-AC10) -> 101855.33 | AC10: =IF(ISNUMBER('Quarter-End Anchors'!K10),'Quarter-End Anchors'!K10,2*Balance!J10-Z10) -> 84362 | AD10: =AC10+(AF10-AC10)/3+(2*Balance!K10-AC10-AF10) -> 99796.667 | AE10: =AC10+2*(AF10-AC10)/3+(2*Balance!K10-AC10-AF10) -> 100741.33 | AF10: =IF(ISNUMBER('Quarter-End Anchors'!L10),'Quarter-End Anchors'!L10,2*Balance!K10-AC10) -> 87196 | AG10: =AF10 -> 87196 | AH10: =AG10 -> 87196 | AI10: =AH10 -> 87196 | AJ10: =AI10 -> 87196 | AK10: =AJ10 -> 87196 | AL10: =AK10 -> 87196 | AM10: =AL10 -> 87196 | AN10: =AM10 -> 87196 | ... AR10: =AQ10 -> 87196
A11: Cash equivalents and other | B11: =IF(ISNUMBER('Quarter-End Anchors'!B11),'Quarter-End Anchors'!B11,Balance!B11) -> 31256 | C11: =B11+(E11-B11)/3+(2*Balance!B11-B11-E11) -> 32514 | D11: =B11+2*(E11-B11)/3+(2*Balance!B11-B11-E11) -> 37753 | E11: =IF(ISNUMBER('Quarter-End Anchors'!C11),'Quarter-End Anchors'!C11,2*Balance!B11-B11) -> 46973 | F11: =E11+(H11-E11)/3+(2*Balance!C11-E11-H11) -> 33930.333 | G11: =E11+2*(H11-E11)/3+(2*Balance!C11-E11-H11) -> 32288.667 | H11: =IF(ISNUMBER('Quarter-End Anchors'!D11),'Quarter-End Anchors'!D11,2*Balance!C11-E11) -> 42048 | I11: =H11+(K11-H11)/3+(2*Balance!D11-H11-K11) -> 40233.333 | J11: =H11+2*(K11-H11)/3+(2*Balance!D11-H11-K11) -> 41318.667 | K11: =IF(ISNUMBER('Quarter-End Anchors'!E11),'Quarter-End Anchors'!E11,2*Balance!D11-H11) -> 45304 | L11: =K11+(N11-K11)/3+(2*Balance!E11-K11-N11) -> 38978.667 | M11: =K11+2*(N11-K11)/3+(2*Balance!E11-K11-N11) -> 38462.333 | N11: =IF(ISNUMBER('Quarter-End Anchors'!F11),'Quarter-End Anchors'!F11,2*Balance!E11-K11) -> 43755 | O11: =N11+(Q11-N11)/3+(2*Balance!F11-N11-Q11) -> 38398.333 | P11: =N11+2*(Q11-N11)/3+(2*Balance!F11-N11-Q11) -> 40980.667 | Q11: =IF(ISNUMBER('Quarter-End Anchors'!G11),'Quarter-End Anchors'!G11,2*Balance!F11-N11) -> 51502 | R11: =Q11+(T11-Q11)/3+(2*Balance!G11-Q11-T11) -> 42114.667 | S11: =Q11+2*(T11-Q11)/3+(2*Balance!G11-Q11-T11) -> 40890.333 | T11: =IF(ISNUMBER('Quarter-End Anchors'!H11),'Quarter-End Anchors'!H11,2*Balance!G11-Q11) -> 47829 | U11: =T11+(W11-T11)/3+(2*Balance!H11-T11-W11) -> 41161 | V11: =T11+2*(W11-T11)/3+(2*Balance!H11-T11-W11) -> 41791 | W11: =IF(ISNUMBER('Quarter-End Anchors'!I11),'Quarter-End Anchors'!I11,2*Balance!H11-T11) -> 49719 | X11: =W11+(Z11-W11)/3+(2*Balance!I11-W11-Z11) -> 46647 | Y11: =W11+2*(Z11-W11)/3+(2*Balance!I11-W11-Z11) -> 44631 | Z11: =IF(ISNUMBER('Quarter-End Anchors'!J11),'Quarter-End Anchors'!J11,2*Balance!I11-W11) -> 43671 | AA11: =Z11+(AC11-Z11)/3+(2*Balance!J11-Z11-AC11) -> 47479.667 | AB11: =Z11+2*(AC11-Z11)/3+(2*Balance!J11-Z11-AC11) -> 49244.333 | AC11: =IF(ISNUMBER('Quarter-End Anchors'!K11),'Quarter-End Anchors'!K11,2*Balance!J11-Z11) -> 48965 | AD11: =AC11+(AF11-AC11)/3+(2*Balance!K11-AC11-AF11) -> 49362.333 | AE11: =AC11+2*(AF11-AC11)/3+(2*Balance!K11-AC11-AF11) -> 53566.667 | AF11: =IF(ISNUMBER('Quarter-End Anchors'!L11),'Quarter-End Anchors'!L11,2*Balance!K11-AC11) -> 61578 | AG11: =AG15*'Forecast Drivers'!$B$18 -> 61588.491 | AH11: =AH15*'Forecast Drivers'!$B$18 -> 61598.982 | AI11: =AI15*'Forecast Drivers'!$B$18 -> 61609.473 | AJ11: =AJ15*'Forecast Drivers'!$B$18 -> 61619.964 | AK11: =AK15*'Forecast Drivers'!$B$18 -> 61630.455 | AL11: =AL15*'Forecast Drivers'!$B$18 -> 61640.947 | AM11: =AM15*'Forecast Drivers'!$B$18 -> 61651.438 | AN11: =AN15*'Forecast Drivers'!$B$18 -> 61661.929 | ... AR11: =AR15*'Forecast Drivers'!$B$18 -> 61703.893
A12: Total interest-earning assets | B12: =SUM(B9:B11) -> 429331 | C12: =SUM(C9:C11) -> 430589 | D12: =SUM(D9:D11) -> 435828 | E12: =SUM(E9:E11) -> 445048 | F12: =SUM(F9:F11) -> 433508 | G12: =SUM(G9:G11) -> 433369 | H12: =SUM(H9:H11) -> 444631 | I12: =SUM(I9:I11) -> 441965 | ... AR12: =SUM(AR9:AR11) -> 588707.14
A14: INTEREST-BEARING LIABILITIES
A15: Interest-bearing deposits | B15: =IF(ISNUMBER('Quarter-End Anchors'!B15),'Quarter-End Anchors'!B15,Balance!B15) -> 308788 | C15: =B15+(E15-B15)/3+(2*Balance!B15-B15-E15) -> 308788 | D15: =B15+2*(E15-B15)/3+(2*Balance!B15-B15-E15) -> 308788 | E15: =IF(ISNUMBER('Quarter-End Anchors'!C15),'Quarter-End Anchors'!C15,2*Balance!B15-B15) -> 308788 | F15: =E15+(H15-E15)/3+(2*Balance!C15-E15-H15) -> 311734 | G15: =E15+2*(H15-E15)/3+(2*Balance!C15-E15-H15) -> 314680 | H15: =IF(ISNUMBER('Quarter-End Anchors'!D15),'Quarter-End Anchors'!D15,2*Balance!C15-E15) -> 317626 | I15: =H15+(K15-H15)/3+(2*Balance!D15-H15-K15) -> 316563.33 | J15: =H15+2*(K15-H15)/3+(2*Balance!D15-H15-K15) -> 315500.67 | K15: =IF(ISNUMBER('Quarter-End Anchors'!E15),'Quarter-End Anchors'!E15,2*Balance!D15-H15) -> 314438 | L15: =K15+(N15-K15)/3+(2*Balance!E15-K15-N15) -> 315278.67 | M15: =K15+2*(N15-K15)/3+(2*Balance!E15-K15-N15) -> 317262.33 | N15: =IF(ISNUMBER('Quarter-End Anchors'!F15),'Quarter-End Anchors'!F15,2*Balance!E15-K15) -> 320389 | O15: =N15+(Q15-N15)/3+(2*Balance!F15-N15-Q15) -> 314535.67 | P15: =N15+2*(Q15-N15)/3+(2*Balance!F15-N15-Q15) -> 315523.33 | Q15: =IF(ISNUMBER('Quarter-End Anchors'!G15),'Quarter-End Anchors'!G15,2*Balance!F15-N15) -> 323352 | R15: =Q15+(T15-Q15)/3+(2*Balance!G15-Q15-T15) -> 321086.67 | S15: =Q15+2*(T15-Q15)/3+(2*Balance!G15-Q15-T15) -> 321448.33 | T15: =IF(ISNUMBER('Quarter-End Anchors'!H15),'Quarter-End Anchors'!H15,2*Balance!G15-Q15) -> 324437 | U15: =T15+(W15-T15)/3+(2*Balance!H15-T15-W15) -> 322703.67 | V15: =T15+2*(W15-T15)/3+(2*Balance!H15-T15-W15) -> 323642.33 | W15: =IF(ISNUMBER('Quarter-End Anchors'!I15),'Quarter-End Anchors'!I15,2*Balance!H15-T15) -> 327253 | X15: =W15+(Z15-W15)/3+(2*Balance!I15-W15-Z15) -> 329765.67 | Y15: =W15+2*(Z15-W15)/3+(2*Balance!I15-W15-Z15) -> 332876.33 | Z15: =IF(ISNUMBER('Quarter-End Anchors'!J15),'Quarter-End Anchors'!J15,2*Balance!I15-W15) -> 336585 | AA15: =Z15+(AC15-Z15)/3+(2*Balance!J15-Z15-AC15) -> 336175.67 | AB15: =Z15+2*(AC15-Z15)/3+(2*Balance!J15-Z15-AC15) -> 337635.33 | AC15: =IF(ISNUMBER('Quarter-End Anchors'!K15),'Quarter-End Anchors'!K15,2*Balance!J15-Z15) -> 340964 | AD15: =AC15+(AF15-AC15)/3+(2*Balance!K15-AC15-AF15) -> 367136 | AE15: =AC15+2*(AF15-AC15)/3+(2*Balance!K15-AC15-AF15) -> 400225 | AF15: =IF(ISNUMBER('Quarter-End Anchors'!L15),'Quarter-End Anchors'!L15,2*Balance!K15-AC15) -> 440231 | AG15: =AF15*('Forecast Drivers'!C12/'Forecast Drivers'!B12) -> 440306 | AH15: =AG15*('Forecast Drivers'!D12/'Forecast Drivers'!C12) -> 440381 | AI15: =AH15*('Forecast Drivers'!E12/'Forecast Drivers'!D12) -> 440456.01 | AJ15: =AI15*('Forecast Drivers'!F12/'Forecast Drivers'!E12) -> 440531.01 | AK15: =AJ15*('Forecast Drivers'!G12/'Forecast Drivers'!F12) -> 440606.01 | AL15: =AK15*('Forecast Drivers'!H12/'Forecast Drivers'!G12) -> 440681.01 | AM15: =AL15*('Forecast Drivers'!I12/'Forecast Drivers'!H12) -> 440756.02 | AN15: =AM15*('Forecast Drivers'!J12/'Forecast Drivers'!I12) -> 440831.02 | ... AR15: =AQ15*('Forecast Drivers'!N12/'Forecast Drivers'!M12) -> 441131.03
A16: Securitized debt obligations | B16: =IF(ISNUMBER('Quarter-End Anchors'!B16),'Quarter-End Anchors'!B16,Balance!B16) -> 17251 | C16: =B16+(E16-B16)/3+(2*Balance!B16-B16-E16) -> 17251 | D16: =B16+2*(E16-B16)/3+(2*Balance!B16-B16-E16) -> 17251 | E16: =IF(ISNUMBER('Quarter-End Anchors'!C16),'Quarter-End Anchors'!C16,2*Balance!B16-B16) -> 17251 | F16: =E16+(H16-E16)/3+(2*Balance!C16-E16-H16) -> 17597.667 | G16: =E16+2*(H16-E16)/3+(2*Balance!C16-E16-H16) -> 17944.333 | H16: =IF(ISNUMBER('Quarter-End Anchors'!D16),'Quarter-End Anchors'!D16,2*Balance!C16-E16) -> 18291 | I16: =H16+(K16-H16)/3+(2*Balance!D16-H16-K16) -> 17863 | J16: =H16+2*(K16-H16)/3+(2*Balance!D16-H16-K16) -> 17435 | K16: =IF(ISNUMBER('Quarter-End Anchors'!E16),'Quarter-End Anchors'!E16,2*Balance!D16-H16) -> 17007 | L16: =K16+(N16-K16)/3+(2*Balance!E16-K16-N16) -> 18676.847 | M16: =K16+2*(N16-K16)/3+(2*Balance!E16-K16-N16) -> 18860.923 | N16: =IF(ISNUMBER('Quarter-End Anchors'!F16),'Quarter-End Anchors'!F16,2*Balance!E16-K16) -> 17559.23 | O16: =N16+(Q16-N16)/3+(2*Balance!F16-N16-Q16) -> 17988.604 | P16: =N16+2*(Q16-N16)/3+(2*Balance!F16-N16-Q16) -> 18050.687 | Q16: =IF(ISNUMBER('Quarter-End Anchors'!G16),'Quarter-End Anchors'!G16,2*Balance!F16-N16) -> 17745.478 | R16: =Q16+(T16-Q16)/3+(2*Balance!G16-Q16-T16) -> 17639.815 | S16: =Q16+2*(T16-Q16)/3+(2*Balance!G16-Q16-T16) -> 17399.169 | T16: =IF(ISNUMBER('Quarter-End Anchors'!H16),'Quarter-End Anchors'!H16,2*Balance!G16-Q16) -> 17023.538 | U16: =T16+(W16-T16)/3+(2*Balance!H16-T16-W16) -> 15228.46 | V16: =T16+2*(W16-T16)/3+(2*Balance!H16-T16-W16) -> 14935.461 | W16: =IF(ISNUMBER('Quarter-End Anchors'!I16),'Quarter-End Anchors'!I16,2*Balance!H16-T16) -> 16144.54 | X16: =W16+(Z16-W16)/3+(2*Balance!I16-W16-Z16) -> 14688.803 | Y16: =W16+2*(Z16-W16)/3+(2*Balance!I16-W16-Z16) -> 14192.131 | Z16: =IF(ISNUMBER('Quarter-End Anchors'!J16),'Quarter-End Anchors'!J16,2*Balance!I16-W16) -> 14654.525 | AA16: =Z16+(AC16-Z16)/3+(2*Balance!J16-Z16-AC16) -> 14017.746 | AB16: =Z16+2*(AC16-Z16)/3+(2*Balance!J16-Z16-AC16) -> 13412.611 | AC16: =IF(ISNUMBER('Quarter-End Anchors'!K16),'Quarter-End Anchors'!K16,2*Balance!J16-Z16) -> 12839.118 | AD16: =AC16+(AF16-AC16)/3+(2*Balance!K16-AC16-AF16) -> 11972.983 | AE16: =AC16+2*(AF16-AC16)/3+(2*Balance!K16-AC16-AF16) -> 12609.933 | AF16: =IF(ISNUMBER('Quarter-End Anchors'!L16),'Quarter-End Anchors'!L16,2*Balance!K16-AC16) -> 14749.967 | AG16: =AF16*(1-'Forecast Drivers'!$B$19) -> 14676.217 | AH16: =AG16*(1-'Forecast Drivers'!$B$19) -> 14602.836 | AI16: =AH16*(1-'Forecast Drivers'!$B$19) -> 14529.822 | AJ16: =AI16*(1-'Forecast Drivers'!$B$19) -> 14457.173 | AK16: =AJ16*(1-'Forecast Drivers'!$B$19) -> 14384.887 | AL16: =AK16*(1-'Forecast Drivers'!$B$19) -> 14312.962 | AM16: =AL16*(1-'Forecast Drivers'!$B$19) -> 14241.398 | AN16: =AM16*(1-'Forecast Drivers'!$B$19) -> 14170.191 | ... AR16: =AQ16*(1-'Forecast Drivers'!$B$19) -> 13888.905
A17: Senior and subordinated notes | B17: =IF(ISNUMBER('Quarter-End Anchors'!B17),'Quarter-End Anchors'!B17,Balance!B17) -> 30136 | C17: =B17+(E17-B17)/3+(2*Balance!B17-B17-E17) -> 30136 | D17: =B17+2*(E17-B17)/3+(2*Balance!B17-B17-E17) -> 30136 | E17: =IF(ISNUMBER('Quarter-End Anchors'!C17),'Quarter-End Anchors'!C17,2*Balance!B17-B17) -> 30136 | F17: =E17+(H17-E17)/3+(2*Balance!C17-E17-H17) -> 30152.667 | G17: =E17+2*(H17-E17)/3+(2*Balance!C17-E17-H17) -> 30169.333 | H17: =IF(ISNUMBER('Quarter-End Anchors'!D17),'Quarter-End Anchors'!D17,2*Balance!C17-E17) -> 30186 | I17: =H17+(K17-H17)/3+(2*Balance!D17-H17-K17) -> 31076.667 | J17: =H17+2*(K17-H17)/3+(2*Balance!D17-H17-K17) -> 31967.333 | K17: =IF(ISNUMBER('Quarter-End Anchors'!E17),'Quarter-End Anchors'!E17,2*Balance!D17-H17) -> 32858 | L17: =K17+(N17-K17)/3+(2*Balance!E17-K17-N17) -> 33080.82 | M17: =K17+2*(N17-K17)/3+(2*Balance!E17-K17-N17) -> 32714.41 | N17: =IF(ISNUMBER('Quarter-End Anchors'!F17),'Quarter-End Anchors'!F17,2*Balance!E17-K17) -> 31758.77 | O17: =N17+(Q17-N17)/3+(2*Balance!F17-N17-Q17) -> 32470.729 | P17: =N17+2*(Q17-N17)/3+(2*Balance!F17-N17-Q17) -> 32566.98 | Q17: =IF(ISNUMBER('Quarter-End Anchors'!G17),'Quarter-End Anchors'!G17,2*Balance!F17-N17) -> 32047.522 | R17: =Q17+(T17-Q17)/3+(2*Balance!G17-Q17-T17) -> 31128.518 | S17: =Q17+2*(T17-Q17)/3+(2*Balance!G17-Q17-T17) -> 30518.498 | T17: =IF(ISNUMBER('Quarter-End Anchors'!H17),'Quarter-End Anchors'!H17,2*Balance!G17-Q17) -> 30217.462 | U17: =T17+(W17-T17)/3+(2*Balance!H17-T17-W17) -> 32228.54 | V17: =T17+2*(W17-T17)/3+(2*Balance!H17-T17-W17) -> 33046.539 | W17: =IF(ISNUMBER('Quarter-End Anchors'!I17),'Quarter-End Anchors'!I17,2*Balance!H17-T17) -> 32671.46 | X17: =W17+(Z17-W17)/3+(2*Balance!I17-W17-Z17) -> 30654.53 | Y17: =W17+2*(Z17-W17)/3+(2*Balance!I17-W17-Z17) -> 29875.535 | Z17: =IF(ISNUMBER('Quarter-End Anchors'!J17),'Quarter-End Anchors'!J17,2*Balance!I17-W17) -> 30334.475 | AA17: =Z17+(AC17-Z17)/3+(2*Balance!J17-Z17-AC17) -> 31643.254 | AB17: =Z17+2*(AC17-Z17)/3+(2*Balance!J17-Z17-AC17) -> 30985.389 | AC17: =IF(ISNUMBER('Quarter-End Anchors'!K17),'Quarter-End Anchors'!K17,2*Balance!J17-Z17) -> 28360.882 | AD17: =AC17+(AF17-AC17)/3+(2*Balance!K17-AC17-AF17) -> 31507.684 | AE17: =AC17+2*(AF17-AC17)/3+(2*Balance!K17-AC17-AF17) -> 34445.401 | AF17: =IF(ISNUMBER('Quarter-End Anchors'!L17),'Quarter-End Anchors'!L17,2*Balance!K17-AC17) -> 37174.033 | AG17: =AF17 -> 37174.033 | AH17: =AG17 -> 37174.033 | AI17: =AH17 -> 37174.033 | AJ17: =AI17 -> 37174.033 | AK17: =AJ17 -> 37174.033 | AL17: =AK17 -> 37174.033 | AM17: =AL17 -> 37174.033 | AN17: =AM17 -> 37174.033 | ... AR17: =AQ17 -> 37174.033
A18: Other borrowings | B18: =IF(ISNUMBER('Quarter-End Anchors'!B18),'Quarter-End Anchors'!B18,Balance!B18) -> 2335 | C18: =B18+(E18-B18)/3+(2*Balance!B18-B18-E18) -> 2335 | D18: =B18+2*(E18-B18)/3+(2*Balance!B18-B18-E18) -> 2335 | E18: =IF(ISNUMBER('Quarter-End Anchors'!C18),'Quarter-End Anchors'!C18,2*Balance!B18-B18) -> 2335 | F18: =E18+(H18-E18)/3+(2*Balance!C18-E18-H18) -> 2391 | G18: =E18+2*(H18-E18)/3+(2*Balance!C18-E18-H18) -> 2447 | H18: =IF(ISNUMBER('Quarter-End Anchors'!D18),'Quarter-End Anchors'!D18,2*Balance!C18-E18) -> 2503 | I18: =H18+(K18-H18)/3+(2*Balance!D18-H18-K18) -> 2483 | J18: =H18+2*(K18-H18)/3+(2*Balance!D18-H18-K18) -> 2463 | K18: =IF(ISNUMBER('Quarter-End Anchors'!E18),'Quarter-End Anchors'!E18,2*Balance!D18-H18) -> 2443 | L18: =K18+(N18-K18)/3+(2*Balance!E18-K18-N18) -> 3501 | M18: =K18+2*(N18-K18)/3+(2*Balance!E18-K18-N18) -> 2875 | N18: =IF(ISNUMBER('Quarter-End Anchors'!F18),'Quarter-End Anchors'!F18,2*Balance!E18-K18) -> 565 | O18: =N18+(Q18-N18)/3+(2*Balance!F18-N18-Q18) -> 4163 | P18: =N18+2*(Q18-N18)/3+(2*Balance!F18-N18-Q18) -> 4172 | Q18: =IF(ISNUMBER('Quarter-End Anchors'!G18),'Quarter-End Anchors'!G18,2*Balance!F18-N18) -> 592 | R18: =Q18+(T18-Q18)/3+(2*Balance!G18-Q18-T18) -> 4313.3333 | S18: =Q18+2*(T18-Q18)/3+(2*Balance!G18-Q18-T18) -> 4362.6667 | T18: =IF(ISNUMBER('Quarter-End Anchors'!H18),'Quarter-End Anchors'!H18,2*Balance!G18-Q18) -> 740 | U18: =T18+(W18-T18)/3+(2*Balance!H18-T18-W18) -> 4168.6667 | V18: =T18+2*(W18-T18)/3+(2*Balance!H18-T18-W18) -> 4103.3333 | W18: =IF(ISNUMBER('Quarter-End Anchors'!I18),'Quarter-End Anchors'!I18,2*Balance!H18-T18) -> 544 | X18: =W18+(Z18-W18)/3+(2*Balance!I18-W18-Z18) -> 4284.6667 | Y18: =W18+2*(Z18-W18)/3+(2*Balance!I18-W18-Z18) -> 4300.3333 | Z18: =IF(ISNUMBER('Quarter-End Anchors'!J18),'Quarter-End Anchors'!J18,2*Balance!I18-W18) -> 591 | AA18: =Z18+(AC18-Z18)/3+(2*Balance!J18-Z18-AC18) -> 4028.3333 | AB18: =Z18+2*(AC18-Z18)/3+(2*Balance!J18-Z18-AC18) -> 4030.6667 | AC18: =IF(ISNUMBER('Quarter-End Anchors'!K18),'Quarter-End Anchors'!K18,2*Balance!J18-Z18) -> 598 | AD18: =AC18+(AF18-AC18)/3+(2*Balance!K18-AC18-AF18) -> 4676.6667 | AE18: =AC18+2*(AF18-AC18)/3+(2*Balance!K18-AC18-AF18) -> 4911.3333 | AF18: =IF(ISNUMBER('Quarter-End Anchors'!L18),'Quarter-End Anchors'!L18,2*Balance!K18-AC18) -> 1302 | AG18: =AF18 -> 1302 | AH18: =AG18 -> 1302 | AI18: =AH18 -> 1302 | AJ18: =AI18 -> 1302 | AK18: =AJ18 -> 1302 | AL18: =AK18 -> 1302 | AM18: =AL18 -> 1302 | AN18: =AM18 -> 1302 | ... AR18: =AQ18 -> 1302
A19: Total interest-bearing liabilities | B19: =SUM(B15:B18) -> 358510 | C19: =SUM(C15:C18) -> 358510 | D19: =SUM(D15:D18) -> 358510 | E19: =SUM(E15:E18) -> 358510 | F19: =SUM(F15:F18) -> 361875.33 | G19: =SUM(G15:G18) -> 365240.67 | H19: =SUM(H15:H18) -> 368606 | I19: =SUM(I15:I18) -> 367986 | ... AR19: =SUM(AR15:AR18) -> 493495.97
A21: Net earning assets (assets − liabilities) | B21: =B12-B19 -> 70821 | C21: =C12-C19 -> 72079 | D21: =D12-D19 -> 77318 | E21: =E12-E19 -> 86538 | F21: =F12-F19 -> 71632.667 | G21: =G12-G19 -> 68128.333 | H21: =H12-H19 -> 76025 | I21: =I12-I19 -> 73979 | ... AR21: =AR12-AR19 -> 95211.177

Sheet Monthly Avg Balance
A1: Capital One - Imputed Monthly Average Balance by line item ($mm)
A2: Monthly average balance is the average of prior and current month end. Forecast months begin Jul-25.
A4: Line item (as disclosed) | B4: 44957 | C4: 44985 | D4: 45016 | E4: 45046 | F4: 45077 | G4: 45107 | H4: 45138 | I4: 45169 | J4: 45199 | K4: 45230 | L4: 45260 | M4: 45291 | N4: 45322 | O4: 45351 | P4: 45382 | Q4: 45412 | R4: 45443 | S4: 45473 | T4: 45504 | U4: 45535 | V4: 45565 | W4: 45596 | X4: 45626 | Y4: 45657 | Z4: 45688 | AA4: 45716 | AB4: 45747 | AC4: 45777 | AD4: 45808 | AE4: 45838 | AF4: 45869 | AG4: 45900 | AH4: 45930 | AI4: 45961 | AJ4: 45991 | AK4: 46022 | AL4: 46053 | AM4: 46081 | AN4: 46112 | AO4: 46142 | AP4: 46173 | AQ4: 46203
A5: INTEREST-EARNING ASSETS
A6: Credit card | B6: =AVERAGE('Monthly EOP Balance'!B6,'Monthly EOP Balance'!C6) -> 134669 | C6: =AVERAGE('Monthly EOP Balance'!C6,'Monthly EOP Balance'!D6) -> 134669 | D6: =AVERAGE('Monthly EOP Balance'!D6,'Monthly EOP Balance'!E6) -> 134669 | E6: =AVERAGE('Monthly EOP Balance'!E6,'Monthly EOP Balance'!F6) -> 136033.33 | F6: =AVERAGE('Monthly EOP Balance'!F6,'Monthly EOP Balance'!G6) -> 138762 | G6: =AVERAGE('Monthly EOP Balance'!G6,'Monthly EOP Balance'!H6) -> 141490.67 | H6: =AVERAGE('Monthly EOP Balance'!H6,'Monthly EOP Balance'!I6) -> 143254.33 | I6: =AVERAGE('Monthly EOP Balance'!I6,'Monthly EOP Balance'!J6) -> 144053 | ... AQ6: =AVERAGE('Monthly EOP Balance'!AQ6,'Monthly EOP Balance'!AR6) -> 243828.18
A7: Consumer banking | B7: =AVERAGE('Monthly EOP Balance'!B7,'Monthly EOP Balance'!C7) -> 79000 | C7: =AVERAGE('Monthly EOP Balance'!C7,'Monthly EOP Balance'!D7) -> 79000 | D7: =AVERAGE('Monthly EOP Balance'!D7,'Monthly EOP Balance'!E7) -> 79000 | E7: =AVERAGE('Monthly EOP Balance'!E7,'Monthly EOP Balance'!F7) -> 78566.333 | F7: =AVERAGE('Monthly EOP Balance'!F7,'Monthly EOP Balance'!G7) -> 77699 | G7: =AVERAGE('Monthly EOP Balance'!G7,'Monthly EOP Balance'!H7) -> 76831.667 | H7: =AVERAGE('Monthly EOP Balance'!H7,'Monthly EOP Balance'!I7) -> 76650 | I7: =AVERAGE('Monthly EOP Balance'!I7,'Monthly EOP Balance'!J7) -> 77154 | ... AQ7: =AVERAGE('Monthly EOP Balance'!AQ7,'Monthly EOP Balance'!AR7) -> 92761.674
A8: Commercial banking | B8: =AVERAGE('Monthly EOP Balance'!B8,'Monthly EOP Balance'!C8) -> 94446 | C8: =AVERAGE('Monthly EOP Balance'!C8,'Monthly EOP Balance'!D8) -> 94446 | D8: =AVERAGE('Monthly EOP Balance'!D8,'Monthly EOP Balance'!E8) -> 94446 | E8: =AVERAGE('Monthly EOP Balance'!E8,'Monthly EOP Balance'!F8) -> 94255.333 | F8: =AVERAGE('Monthly EOP Balance'!F8,'Monthly EOP Balance'!G8) -> 93874 | G8: =AVERAGE('Monthly EOP Balance'!G8,'Monthly EOP Balance'!H8) -> 93492.667 | H8: =AVERAGE('Monthly EOP Balance'!H8,'Monthly EOP Balance'!I8) -> 92952.667 | I8: =AVERAGE('Monthly EOP Balance'!I8,'Monthly EOP Balance'!J8) -> 92254 | ... AQ8: =AVERAGE('Monthly EOP Balance'!AQ8,'Monthly EOP Balance'!AR8) -> 103196.14
A9: Total loans (incl. HFS) | B9: =AVERAGE('Monthly EOP Balance'!B9,'Monthly EOP Balance'!C9) -> 308115 | C9: =AVERAGE('Monthly EOP Balance'!C9,'Monthly EOP Balance'!D9) -> 308115 | D9: =AVERAGE('Monthly EOP Balance'!D9,'Monthly EOP Balance'!E9) -> 308115 | E9: =AVERAGE('Monthly EOP Balance'!E9,'Monthly EOP Balance'!F9) -> 308855 | F9: =AVERAGE('Monthly EOP Balance'!F9,'Monthly EOP Balance'!G9) -> 310335 | G9: =AVERAGE('Monthly EOP Balance'!G9,'Monthly EOP Balance'!H9) -> 311815 | H9: =AVERAGE('Monthly EOP Balance'!H9,'Monthly EOP Balance'!I9) -> 312857 | I9: =AVERAGE('Monthly EOP Balance'!I9,'Monthly EOP Balance'!J9) -> 313461 | ... AE9: =AVERAGE('Monthly EOP Balance'!AE9,'Monthly EOP Balance'!AF9) -> 417103.33 | AF9: =SUM(AF6:AF8) -> 439318.26 | AG9: =SUM(AG6:AG8) -> 439360.78 | AH9: =SUM(AH6:AH8) -> 439403.3 | AI9: =SUM(AI6:AI8) -> 439445.82 | AJ9: =SUM(AJ6:AJ8) -> 439488.34 | AK9: =SUM(AK6:AK8) -> 439530.87 | AL9: =SUM(AL6:AL8) -> 439573.39 | AM9: =SUM(AM6:AM8) -> 439615.91 | ... AQ9: =SUM(AQ6:AQ8) -> 439785.99
A10: Investment securities | B10: =AVERAGE('Monthly EOP Balance'!B10,'Monthly EOP Balance'!C10) -> 89960 | C10: =AVERAGE('Monthly EOP Balance'!C10,'Monthly EOP Balance'!D10) -> 89960 | D10: =AVERAGE('Monthly EOP Balance'!D10,'Monthly EOP Balance'!E10) -> 89960 | E10: =AVERAGE('Monthly EOP Balance'!E10,'Monthly EOP Balance'!F10) -> 89971.333 | F10: =AVERAGE('Monthly EOP Balance'!F10,'Monthly EOP Balance'!G10) -> 89994 | G10: =AVERAGE('Monthly EOP Balance'!G10,'Monthly EOP Balance'!H10) -> 90016.667 | H10: =AVERAGE('Monthly EOP Balance'!H10,'Monthly EOP Balance'!I10) -> 89300.333 | I10: =AVERAGE('Monthly EOP Balance'!I10,'Monthly EOP Balance'!J10) -> 87845 | ... AQ10: =AVERAGE('Monthly EOP Balance'!AQ10,'Monthly EOP Balance'!AR10) -> 87196
A11: Cash equivalents and other | B11: =AVERAGE('Monthly EOP Balance'!B11,'Monthly EOP Balance'!C11) -> 31885 | C11: =AVERAGE('Monthly EOP Balance'!C11,'Monthly EOP Balance'!D11) -> 35133.5 | D11: =AVERAGE('Monthly EOP Balance'!D11,'Monthly EOP Balance'!E11) -> 42363 | E11: =AVERAGE('Monthly EOP Balance'!E11,'Monthly EOP Balance'!F11) -> 40451.667 | F11: =AVERAGE('Monthly EOP Balance'!F11,'Monthly EOP Balance'!G11) -> 33109.5 | G11: =AVERAGE('Monthly EOP Balance'!G11,'Monthly EOP Balance'!H11) -> 37168.333 | H11: =AVERAGE('Monthly EOP Balance'!H11,'Monthly EOP Balance'!I11) -> 41140.667 | I11: =AVERAGE('Monthly EOP Balance'!I11,'Monthly EOP Balance'!J11) -> 40776 | ... AQ11: =AVERAGE('Monthly EOP Balance'!AQ11,'Monthly EOP Balance'!AR11) -> 61698.647
A12: Total interest-earning assets | B12: =AVERAGE('Monthly EOP Balance'!B12,'Monthly EOP Balance'!C12) -> 429960 | C12: =AVERAGE('Monthly EOP Balance'!C12,'Monthly EOP Balance'!D12) -> 433208.5 | D12: =AVERAGE('Monthly EOP Balance'!D12,'Monthly EOP Balance'!E12) -> 440438 | E12: =AVERAGE('Monthly EOP Balance'!E12,'Monthly EOP Balance'!F12) -> 439278 | F12: =AVERAGE('Monthly EOP Balance'!F12,'Monthly EOP Balance'!G12) -> 433438.5 | G12: =AVERAGE('Monthly EOP Balance'!G12,'Monthly EOP Balance'!H12) -> 439000 | H12: =AVERAGE('Monthly EOP Balance'!H12,'Monthly EOP Balance'!I12) -> 443298 | I12: =AVERAGE('Monthly EOP Balance'!I12,'Monthly EOP Balance'!J12) -> 442082 | ... AE12: =AVERAGE('Monthly EOP Balance'!AE12,'Monthly EOP Balance'!AF12) -> 568644.33 | AF12: =SUM(AF9:AF11) -> 588097.51 | AG12: =SUM(AG9:AG11) -> 588150.52 | AH12: =SUM(AH9:AH11) -> 588203.53 | AI12: =SUM(AI9:AI11) -> 588256.54 | AJ12: =SUM(AJ9:AJ11) -> 588309.55 | AK12: =SUM(AK9:AK11) -> 588362.57 | AL12: =SUM(AL9:AL11) -> 588415.58 | AM12: =SUM(AM9:AM11) -> 588468.59 | ... AQ12: =SUM(AQ9:AQ11) -> 588680.64
A14: INTEREST-BEARING LIABILITIES
A15: Interest-bearing deposits | B15: =AVERAGE('Monthly EOP Balance'!B15,'Monthly EOP Balance'!C15) -> 308788 | C15: =AVERAGE('Monthly EOP Balance'!C15,'Monthly EOP Balance'!D15) -> 308788 | D15: =AVERAGE('Monthly EOP Balance'!D15,'Monthly EOP Balance'!E15) -> 308788 | E15: =AVERAGE('Monthly EOP Balance'!E15,'Monthly EOP Balance'!F15) -> 310261 | F15: =AVERAGE('Monthly EOP Balance'!F15,'Monthly EOP Balance'!G15) -> 313207 | G15: =AVERAGE('Monthly EOP Balance'!G15,'Monthly EOP Balance'!H15) -> 316153 | H15: =AVERAGE('Monthly EOP Balance'!H15,'Monthly EOP Balance'!I15) -> 317094.67 | I15: =AVERAGE('Monthly EOP Balance'!I15,'Monthly EOP Balance'!J15) -> 316032 | ... AQ15: =AVERAGE('Monthly EOP Balance'!AQ15,'Monthly EOP Balance'!AR15) -> 441093.53
A16: Securitized debt obligations | B16: =AVERAGE('Monthly EOP Balance'!B16,'Monthly EOP Balance'!C16) -> 17251 | C16: =AVERAGE('Monthly EOP Balance'!C16,'Monthly EOP Balance'!D16) -> 17251 | D16: =AVERAGE('Monthly EOP Balance'!D16,'Monthly EOP Balance'!E16) -> 17251 | E16: =AVERAGE('Monthly EOP Balance'!E16,'Monthly EOP Balance'!F16) -> 17424.333 | F16: =AVERAGE('Monthly EOP Balance'!F16,'Monthly EOP Balance'!G16) -> 17771 | G16: =AVERAGE('Monthly EOP Balance'!G16,'Monthly EOP Balance'!H16) -> 18117.667 | H16: =AVERAGE('Monthly EOP Balance'!H16,'Monthly EOP Balance'!I16) -> 18077 | I16: =AVERAGE('Monthly EOP Balance'!I16,'Monthly EOP Balance'!J16) -> 17649 | ... AQ16: =AVERAGE('Monthly EOP Balance'!AQ16,'Monthly EOP Balance'!AR16) -> 13923.802
A17: Senior and subordinated notes | B17: =AVERAGE('Monthly EOP Balance'!B17,'Monthly EOP Balance'!C17) -> 30136 | C17: =AVERAGE('Monthly EOP Balance'!C17,'Monthly EOP Balance'!D17) -> 30136 | D17: =AVERAGE('Monthly EOP Balance'!D17,'Monthly EOP Balance'!E17) -> 30136 | E17: =AVERAGE('Monthly EOP Balance'!E17,'Monthly EOP Balance'!F17) -> 30144.333 | F17: =AVERAGE('Monthly EOP Balance'!F17,'Monthly EOP Balance'!G17) -> 30161 | G17: =AVERAGE('Monthly EOP Balance'!G17,'Monthly EOP Balance'!H17) -> 30177.667 | H17: =AVERAGE('Monthly EOP Balance'!H17,'Monthly EOP Balance'!I17) -> 30631.333 | I17: =AVERAGE('Monthly EOP Balance'!I17,'Monthly EOP Balance'!J17) -> 31522 | ... AQ17: =AVERAGE('Monthly EOP Balance'!AQ17,'Monthly EOP Balance'!AR17) -> 37174.033
A18: Other borrowings | B18: =AVERAGE('Monthly EOP Balance'!B18,'Monthly EOP Balance'!C18) -> 2335 | C18: =AVERAGE('Monthly EOP Balance'!C18,'Monthly EOP Balance'!D18) -> 2335 | D18: =AVERAGE('Monthly EOP Balance'!D18,'Monthly EOP Balance'!E18) -> 2335 | E18: =AVERAGE('Monthly EOP Balance'!E18,'Monthly EOP Balance'!F18) -> 2363 | F18: =AVERAGE('Monthly EOP Balance'!F18,'Monthly EOP Balance'!G18) -> 2419 | G18: =AVERAGE('Monthly EOP Balance'!G18,'Monthly EOP Balance'!H18) -> 2475 | H18: =AVERAGE('Monthly EOP Balance'!H18,'Monthly EOP Balance'!I18) -> 2493 | I18: =AVERAGE('Monthly EOP Balance'!I18,'Monthly EOP Balance'!J18) -> 2473 | ... AQ18: =AVERAGE('Monthly EOP Balance'!AQ18,'Monthly EOP Balance'!AR18) -> 1302
A19: Total interest-bearing liabilities | B19: =AVERAGE('Monthly EOP Balance'!B19,'Monthly EOP Balance'!C19) -> 358510 | C19: =AVERAGE('Monthly EOP Balance'!C19,'Monthly EOP Balance'!D19) -> 358510 | D19: =AVERAGE('Monthly EOP Balance'!D19,'Monthly EOP Balance'!E19) -> 358510 | E19: =AVERAGE('Monthly EOP Balance'!E19,'Monthly EOP Balance'!F19) -> 360192.67 | F19: =AVERAGE('Monthly EOP Balance'!F19,'Monthly EOP Balance'!G19) -> 363558 | G19: =AVERAGE('Monthly EOP Balance'!G19,'Monthly EOP Balance'!H19) -> 366923.33 | H19: =AVERAGE('Monthly EOP Balance'!H19,'Monthly EOP Balance'!I19) -> 368296 | I19: =AVERAGE('Monthly EOP Balance'!I19,'Monthly EOP Balance'!J19) -> 367676 | ... AE19: =AVERAGE('Monthly EOP Balance'!AE19,'Monthly EOP Balance'!AF19) -> 472824.33 | AF19: =SUM(AF15:AF18) -> 493457.63 | AG19: =SUM(AG15:AG18) -> 493459.06 | AH19: =SUM(AH15:AH18) -> 493460.87 | AI19: =SUM(AI15:AI18) -> 493463.04 | AJ19: =SUM(AJ15:AJ18) -> 493465.57 | AK19: =SUM(AK15:AK18) -> 493468.47 | AL19: =SUM(AL15:AL18) -> 493471.73 | AM19: =SUM(AM15:AM18) -> 493475.35 | ... AQ19: =SUM(AQ15:AQ18) -> 493493.36
A21: Net earning assets (assets − liabilities) | B21: =B12-B19 -> 71450 | C21: =C12-C19 -> 74698.5 | D21: =D12-D19 -> 81928 | E21: =E12-E19 -> 79085.333 | F21: =F12-F19 -> 69880.5 | G21: =G12-G19 -> 72076.667 | H21: =H12-H19 -> 75002 | I21: =I12-I19 -> 74406 | ... AQ21: =AQ12-AQ19 -> 95187.275

Sheet Monthly NII
A1: Capital One - Imputed Monthly Interest Income / Expense by line item ($mm)
A2: Monthly interest income or expense equals monthly average balance times annualized forecast rate divided by 12.
A4: Line item (as disclosed) | B4: 44957 | C4: 44985 | D4: 45016 | E4: 45046 | F4: 45077 | G4: 45107 | H4: 45138 | I4: 45169 | J4: 45199 | K4: 45230 | L4: 45260 | M4: 45291 | N4: 45322 | O4: 45351 | P4: 45382 | Q4: 45412 | R4: 45443 | S4: 45473 | T4: 45504 | U4: 45535 | V4: 45565 | W4: 45596 | X4: 45626 | Y4: 45657 | Z4: 45688 | AA4: 45716 | AB4: 45747 | AC4: 45777 | AD4: 45808 | AE4: 45838 | AF4: 45869 | AG4: 45900 | AH4: 45930 | AI4: 45961 | AJ4: 45991 | AK4: 46022 | AL4: 46053 | AM4: 46081 | AN4: 46112 | AO4: 46142 | AP4: 46173 | AQ4: 46203
A5: INTEREST-EARNING ASSETS
A6: Credit card | B6: =IF(SUM('Monthly Avg Balance'!B6:'Monthly Avg Balance'!D6)=0,"",'Monthly Avg Balance'!B6*Rate!B6/12+('Net Interest Income'!B6-SUM('Monthly Avg Balance'!B6:'Monthly Avg Balance'!D6)*Rate!B6/12)*'Monthly Avg Balance'!B6/SUM('Monthly Avg Balance'!B6:'Monthly Avg Balance'!D6)) -> 2017.6667 | C6: =IF(SUM('Monthly Avg Balance'!B6:'Monthly Avg Balance'!D6)=0,"",'Monthly Avg Balance'!C6*Rate!B6/12+('Net Interest Income'!B6-SUM('Monthly Avg Balance'!B6:'Monthly Avg Balance'!D6)*Rate!B6/12)*'Monthly Avg Balance'!C6/SUM('Monthly Avg Balance'!B6:'Monthly Avg Balance'!D6)) -> 2017.6667 | D6: =IF(SUM('Monthly Avg Balance'!B6:'Monthly Avg Balance'!D6)=0,"",'Monthly Avg Balance'!D6*Rate!B6/12+('Net Interest Income'!B6-SUM('Monthly Avg Balance'!B6:'Monthly Avg Balance'!D6)*Rate!B6/12)*'Monthly Avg Balance'!D6/SUM('Monthly Avg Balance'!B6:'Monthly Avg Balance'!D6)) -> 2017.6667 | E6: =IF(SUM('Monthly Avg Balance'!E6:'Monthly Avg Balance'!G6)=0,"",'Monthly Avg Balance'!E6*Rate!C6/12+('Net Interest Income'!C6-SUM('Monthly Avg Balance'!E6:'Monthly Avg Balance'!G6)*Rate!C6/12)*'Monthly Avg Balance'!E6/SUM('Monthly Avg Balance'!E6:'Monthly Avg Balance'!G6)) -> 2059.3584 | F6: =IF(SUM('Monthly Avg Balance'!E6:'Monthly Avg Balance'!G6)=0,"",'Monthly Avg Balance'!F6*Rate!C6/12+('Net Interest Income'!C6-SUM('Monthly Avg Balance'!E6:'Monthly Avg Balance'!G6)*Rate!C6/12)*'Monthly Avg Balance'!F6/SUM('Monthly Avg Balance'!E6:'Monthly Avg Balance'!G6)) -> 2100.6667 | G6: =IF(SUM('Monthly Avg Balance'!E6:'Monthly Avg Balance'!G6)=0,"",'Monthly Avg Balance'!G6*Rate!C6/12+('Net Interest Income'!C6-SUM('Monthly Avg Balance'!E6:'Monthly Avg Balance'!G6)*Rate!C6/12)*'Monthly Avg Balance'!G6/SUM('Monthly Avg Balance'!E6:'Monthly Avg Balance'!G6)) -> 2141.9749 | H6: =IF(SUM('Monthly Avg Balance'!H6:'Monthly Avg Balance'!J6)=0,"",'Monthly Avg Balance'!H6*Rate!D6/12+('Net Interest Income'!D6-SUM('Monthly Avg Balance'!H6:'Monthly Avg Balance'!J6)*Rate!D6/12)*'Monthly Avg Balance'!H6/SUM('Monthly Avg Balance'!H6:'Monthly Avg Balance'!J6)) -> 2270.6739 | I6: =IF(SUM('Monthly Avg Balance'!H6:'Monthly Avg Balance'!J6)=0,"",'Monthly Avg Balance'!I6*Rate!D6/12+('Net Interest Income'!D6-SUM('Monthly Avg Balance'!H6:'Monthly Avg Balance'!J6)*Rate!D6/12)*'Monthly Avg Balance'!I6/SUM('Monthly Avg Balance'!H6:'Monthly Avg Balance'!J6)) -> 2283.3333 | J6: =IF(SUM('Monthly Avg Balance'!H6:'Monthly Avg Balance'!J6)=0,"",'Monthly Avg Balance'!J6*Rate!D6/12+('Net Interest Income'!D6-SUM('Monthly Avg Balance'!H6:'Monthly Avg Balance'!J6)*Rate!D6/12)*'Monthly Avg Balance'!J6/SUM('Monthly Avg Balance'!H6:'Monthly Avg Balance'!J6)) -> 2295.9927 | K6: =IF(SUM('Monthly Avg Balance'!K6:'Monthly Avg Balance'!M6)=0,"",'Monthly Avg Balance'!K6*Rate!E6/12+('Net Interest Income'!E6-SUM('Monthly Avg Balance'!K6:'Monthly Avg Balance'!M6)*Rate!E6/12)*'Monthly Avg Balance'!K6/SUM('Monthly Avg Balance'!K6:'Monthly Avg Balance'!M6)) -> 2318.9592 | L6: =IF(SUM('Monthly Avg Balance'!K6:'Monthly Avg Balance'!M6)=0,"",'Monthly Avg Balance'!L6*Rate!E6/12+('Net Interest Income'!E6-SUM('Monthly Avg Balance'!K6:'Monthly Avg Balance'!M6)*Rate!E6/12)*'Monthly Avg Balance'!L6/SUM('Monthly Avg Balance'!K6:'Monthly Avg Balance'!M6)) -> 2364.9989 | M6: =IF(SUM('Monthly Avg Balance'!K6:'Monthly Avg Balance'!M6)=0,"",'Monthly Avg Balance'!M6*Rate!E6/12+('Net Interest Income'!E6-SUM('Monthly Avg Balance'!K6:'Monthly Avg Balance'!M6)*Rate!E6/12)*'Monthly Avg Balance'!M6/SUM('Monthly Avg Balance'!K6:'Monthly Avg Balance'!M6)) -> 2378.042 | N6: =IF(SUM('Monthly Avg Balance'!N6:'Monthly Avg Balance'!P6)=0,"",'Monthly Avg Balance'!N6*Rate!F6/12+('Net Interest Income'!F6-SUM('Monthly Avg Balance'!N6:'Monthly Avg Balance'!P6)*Rate!F6/12)*'Monthly Avg Balance'!N6/SUM('Monthly Avg Balance'!N6:'Monthly Avg Balance'!P6)) -> 2362.6876 | O6: =IF(SUM('Monthly Avg Balance'!N6:'Monthly Avg Balance'!P6)=0,"",'Monthly Avg Balance'!O6*Rate!F6/12+('Net Interest Income'!F6-SUM('Monthly Avg Balance'!N6:'Monthly Avg Balance'!P6)*Rate!F6/12)*'Monthly Avg Balance'!O6/SUM('Monthly Avg Balance'!N6:'Monthly Avg Balance'!P6)) -> 2352.344 | P6: =IF(SUM('Monthly Avg Balance'!N6:'Monthly Avg Balance'!P6)=0,"",'Monthly Avg Balance'!P6*Rate!F6/12+('Net Interest Income'!F6-SUM('Monthly Avg Balance'!N6:'Monthly Avg Balance'!P6)*Rate!F6/12)*'Monthly Avg Balance'!P6/SUM('Monthly Avg Balance'!N6:'Monthly Avg Balance'!P6)) -> 2351.9684 | Q6: =IF(SUM('Monthly Avg Balance'!Q6:'Monthly Avg Balance'!S6)=0,"",'Monthly Avg Balance'!Q6*Rate!G6/12+('Net Interest Income'!G6-SUM('Monthly Avg Balance'!Q6:'Monthly Avg Balance'!S6)*Rate!G6/12)*'Monthly Avg Balance'!Q6/SUM('Monthly Avg Balance'!Q6:'Monthly Avg Balance'!S6)) -> 2351.7988 | R6: =IF(SUM('Monthly Avg Balance'!Q6:'Monthly Avg Balance'!S6)=0,"",'Monthly Avg Balance'!R6*Rate!G6/12+('Net Interest Income'!G6-SUM('Monthly Avg Balance'!Q6:'Monthly Avg Balance'!S6)*Rate!G6/12)*'Monthly Avg Balance'!R6/SUM('Monthly Avg Balance'!Q6:'Monthly Avg Balance'!S6)) -> 2362.0542 | S6: =IF(SUM('Monthly Avg Balance'!Q6:'Monthly Avg Balance'!S6)=0,"",'Monthly Avg Balance'!S6*Rate!G6/12+('Net Interest Income'!G6-SUM('Monthly Avg Balance'!Q6:'Monthly Avg Balance'!S6)*Rate!G6/12)*'Monthly Avg Balance'!S6/SUM('Monthly Avg Balance'!Q6:'Monthly Avg Balance'!S6)) -> 2374.147 | T6: =IF(SUM('Monthly Avg Balance'!T6:'Monthly Avg Balance'!V6)=0,"",'Monthly Avg Balance'!T6*Rate!H6/12+('Net Interest Income'!H6-SUM('Monthly Avg Balance'!T6:'Monthly Avg Balance'!V6)*Rate!H6/12)*'Monthly Avg Balance'!T6/SUM('Monthly Avg Balance'!T6:'Monthly Avg Balance'!V6)) -> 2506.2729 | U6: =IF(SUM('Monthly Avg Balance'!T6:'Monthly Avg Balance'!V6)=0,"",'Monthly Avg Balance'!U6*Rate!H6/12+('Net Interest Income'!H6-SUM('Monthly Avg Balance'!T6:'Monthly Avg Balance'!V6)*Rate!H6/12)*'Monthly Avg Balance'!U6/SUM('Monthly Avg Balance'!T6:'Monthly Avg Balance'!V6)) -> 2533.7773 | V6: =IF(SUM('Monthly Avg Balance'!T6:'Monthly Avg Balance'!V6)=0,"",'Monthly Avg Balance'!V6*Rate!H6/12+('Net Interest Income'!H6-SUM('Monthly Avg Balance'!T6:'Monthly Avg Balance'!V6)*Rate!H6/12)*'Monthly Avg Balance'!V6/SUM('Monthly Avg Balance'!T6:'Monthly Avg Balance'!V6)) -> 2537.9498 | W6: =IF(SUM('Monthly Avg Balance'!W6:'Monthly Avg Balance'!Y6)=0,"",'Monthly Avg Balance'!W6*Rate!I6/12+('Net Interest Income'!I6-SUM('Monthly Avg Balance'!W6:'Monthly Avg Balance'!Y6)*Rate!I6/12)*'Monthly Avg Balance'!W6/SUM('Monthly Avg Balance'!W6:'Monthly Avg Balance'!Y6)) -> 2471.0099 | X6: =IF(SUM('Monthly Avg Balance'!W6:'Monthly Avg Balance'!Y6)=0,"",'Monthly Avg Balance'!X6*Rate!I6/12+('Net Interest Income'!I6-SUM('Monthly Avg Balance'!W6:'Monthly Avg Balance'!Y6)*Rate!I6/12)*'Monthly Avg Balance'!X6/SUM('Monthly Avg Balance'!W6:'Monthly Avg Balance'!Y6)) -> 2496.4465 | Y6: =IF(SUM('Monthly Avg Balance'!W6:'Monthly Avg Balance'!Y6)=0,"",'Monthly Avg Balance'!Y6*Rate!I6/12+('Net Interest Income'!I6-SUM('Monthly Avg Balance'!W6:'Monthly Avg Balance'!Y6)*Rate!I6/12)*'Monthly Avg Balance'!Y6/SUM('Monthly Avg Balance'!W6:'Monthly Avg Balance'!Y6)) -> 2525.5436 | Z6: =IF(SUM('Monthly Avg Balance'!Z6:'Monthly Avg Balance'!AB6)=0,"",'Monthly Avg Balance'!Z6*Rate!J6/12+('Net Interest Income'!J6-SUM('Monthly Avg Balance'!Z6:'Monthly Avg Balance'!AB6)*Rate!J6/12)*'Monthly Avg Balance'!Z6/SUM('Monthly Avg Balance'!Z6:'Monthly Avg Balance'!AB6)) -> 2443.227 | AA6: =IF(SUM('Monthly Avg Balance'!Z6:'Monthly Avg Balance'!AB6)=0,"",'Monthly Avg Balance'!AA6*Rate!J6/12+('Net Interest Income'!J6-SUM('Monthly Avg Balance'!Z6:'Monthly Avg Balance'!AB6)*Rate!J6/12)*'Monthly Avg Balance'!AA6/SUM('Monthly Avg Balance'!Z6:'Monthly Avg Balance'!AB6)) -> 2395.0889 | AB6: =IF(SUM('Monthly Avg Balance'!Z6:'Monthly Avg Balance'!AB6)=0,"",'Monthly Avg Balance'!AB6*Rate!J6/12+('Net Interest Income'!J6-SUM('Monthly Avg Balance'!Z6:'Monthly Avg Balance'!AB6)*Rate!J6/12)*'Monthly Avg Balance'!AB6/SUM('Monthly Avg Balance'!Z6:'Monthly Avg Balance'!AB6)) -> 2409.6841 | AC6: =IF(SUM('Monthly Avg Balance'!AC6:'Monthly Avg Balance'!AE6)=0,"",'Monthly Avg Balance'!AC6*Rate!K6/12+('Net Interest Income'!K6-SUM('Monthly Avg Balance'!AC6:'Monthly Avg Balance'!AE6)*Rate!K6/12)*'Monthly Avg Balance'!AC6/SUM('Monthly Avg Balance'!AC6:'Monthly Avg Balance'!AE6)) -> 2663.5862 | AD6: =IF(SUM('Monthly Avg Balance'!AC6:'Monthly Avg Balance'!AE6)=0,"",'Monthly Avg Balance'!AD6*Rate!K6/12+('Net Interest Income'!K6-SUM('Monthly Avg Balance'!AC6:'Monthly Avg Balance'!AE6)*Rate!K6/12)*'Monthly Avg Balance'!AD6/SUM('Monthly Avg Balance'!AC6:'Monthly Avg Balance'!AE6)) -> 3230.0586 | AE6: =IF(SUM('Monthly Avg Balance'!AC6:'Monthly Avg Balance'!AE6)=0,"",'Monthly Avg Balance'!AE6*Rate!K6/12+('Net Interest Income'!K6-SUM('Monthly Avg Balance'!AC6:'Monthly Avg Balance'!AE6)*Rate!K6/12)*'Monthly Avg Balance'!AE6/SUM('Monthly Avg Balance'!AC6:'Monthly Avg Balance'!AE6)) -> 3513.3552 | AF6: ='Monthly Avg Balance'!AF6*'Monthly Rate'!AF6/12 -> 3584.5148 | AG6: ='Monthly Avg Balance'!AG6*'Monthly Rate'!AG6/12 -> 3567.3765 | AH6: ='Monthly Avg Balance'!AH6*'Monthly Rate'!AH6/12 -> 3567.9842 | AI6: ='Monthly Avg Balance'!AI6*'Monthly Rate'!AI6/12 -> 3568.5918 | AJ6: ='Monthly Avg Balance'!AJ6*'Monthly Rate'!AJ6/12 -> 3551.4414 | AK6: ='Monthly Avg Balance'!AK6*'Monthly Rate'!AK6/12 -> 3552.046 | AL6: ='Monthly Avg Balance'!AL6*'Monthly Rate'!AL6/12 -> 3552.6506 | AM6: ='Monthly Avg Balance'!AM6*'Monthly Rate'!AM6/12 -> 3535.4882 | ... AQ6: ='Monthly Avg Balance'!AQ6*'Monthly Rate'!AQ6/12 -> 3520.1153
A7: Consumer banking | B7: =IF(SUM('Monthly Avg Balance'!B7:'Monthly Avg Balance'!D7)=0,"",'Monthly Avg Balance'!B7*Rate!B7/12+('Net Interest Income'!B7-SUM('Monthly Avg Balance'!B7:'Monthly Avg Balance'!D7)*Rate!B7/12)*'Monthly Avg Balance'!B7/SUM('Monthly Avg Balance'!B7:'Monthly Avg Balance'!D7)) -> 487 | C7: =IF(SUM('Monthly Avg Balance'!B7:'Monthly Avg Balance'!D7)=0,"",'Monthly Avg Balance'!C7*Rate!B7/12+('Net Interest Income'!B7-SUM('Monthly Avg Balance'!B7:'Monthly Avg Balance'!D7)*Rate!B7/12)*'Monthly Avg Balance'!C7/SUM('Monthly Avg Balance'!B7:'Monthly Avg Balance'!D7)) -> 487 | D7: =IF(SUM('Monthly Avg Balance'!B7:'Monthly Avg Balance'!D7)=0,"",'Monthly Avg Balance'!D7*Rate!B7/12+('Net Interest Income'!B7-SUM('Monthly Avg Balance'!B7:'Monthly Avg Balance'!D7)*Rate!B7/12)*'Monthly Avg Balance'!D7/SUM('Monthly Avg Balance'!B7:'Monthly Avg Balance'!D7)) -> 487 | E7: =IF(SUM('Monthly Avg Balance'!E7:'Monthly Avg Balance'!G7)=0,"",'Monthly Avg Balance'!E7*Rate!C7/12+('Net Interest Income'!C7-SUM('Monthly Avg Balance'!E7:'Monthly Avg Balance'!G7)*Rate!C7/12)*'Monthly Avg Balance'!E7/SUM('Monthly Avg Balance'!E7:'Monthly Avg Balance'!G7)) -> 500.86261 | F7: =IF(SUM('Monthly Avg Balance'!E7:'Monthly Avg Balance'!G7)=0,"",'Monthly Avg Balance'!F7*Rate!C7/12+('Net Interest Income'!C7-SUM('Monthly Avg Balance'!E7:'Monthly Avg Balance'!G7)*Rate!C7/12)*'Monthly Avg Balance'!F7/SUM('Monthly Avg Balance'!E7:'Monthly Avg Balance'!G7)) -> 495.33333 | G7: =IF(SUM('Monthly Avg Balance'!E7:'Monthly Avg Balance'!G7)=0,"",'Monthly Avg Balance'!G7*Rate!C7/12+('Net Interest Income'!C7-SUM('Monthly Avg Balance'!E7:'Monthly Avg Balance'!G7)*Rate!C7/12)*'Monthly Avg Balance'!G7/SUM('Monthly Avg Balance'!E7:'Monthly Avg Balance'!G7)) -> 489.80406 | H7: =IF(SUM('Monthly Avg Balance'!H7:'Monthly Avg Balance'!J7)=0,"",'Monthly Avg Balance'!H7*Rate!D7/12+('Net Interest Income'!D7-SUM('Monthly Avg Balance'!H7:'Monthly Avg Balance'!J7)*Rate!D7/12)*'Monthly Avg Balance'!H7/SUM('Monthly Avg Balance'!H7:'Monthly Avg Balance'!J7)) -> 508.98657 | I7: =IF(SUM('Monthly Avg Balance'!H7:'Monthly Avg Balance'!J7)=0,"",'Monthly Avg Balance'!I7*Rate!D7/12+('Net Interest Income'!D7-SUM('Monthly Avg Balance'!H7:'Monthly Avg Balance'!J7)*Rate!D7/12)*'Monthly Avg Balance'!I7/SUM('Monthly Avg Balance'!H7:'Monthly Avg Balance'!J7)) -> 512.33333 | J7: =IF(SUM('Monthly Avg Balance'!H7:'Monthly Avg Balance'!J7)=0,"",'Monthly Avg Balance'!J7*Rate!D7/12+('Net Interest Income'!D7-SUM('Monthly Avg Balance'!H7:'Monthly Avg Balance'!J7)*Rate!D7/12)*'Monthly Avg Balance'!J7/SUM('Monthly Avg Balance'!H7:'Monthly Avg Balance'!J7)) -> 515.68009 | K7: =IF(SUM('Monthly Avg Balance'!K7:'Monthly Avg Balance'!M7)=0,"",'Monthly Avg Balance'!K7*Rate!E7/12+('Net Interest Income'!E7-SUM('Monthly Avg Balance'!K7:'Monthly Avg Balance'!M7)*Rate!E7/12)*'Monthly Avg Balance'!K7/SUM('Monthly Avg Balance'!K7:'Monthly Avg Balance'!M7)) -> 523.74229 | L7: =IF(SUM('Monthly Avg Balance'!K7:'Monthly Avg Balance'!M7)=0,"",'Monthly Avg Balance'!L7*Rate!E7/12+('Net Interest Income'!E7-SUM('Monthly Avg Balance'!K7:'Monthly Avg Balance'!M7)*Rate!E7/12)*'Monthly Avg Balance'!L7/SUM('Monthly Avg Balance'!K7:'Monthly Avg Balance'!M7)) -> 513.09108 | M7: =IF(SUM('Monthly Avg Balance'!K7:'Monthly Avg Balance'!M7)=0,"",'Monthly Avg Balance'!M7*Rate!E7/12+('Net Interest Income'!E7-SUM('Monthly Avg Balance'!K7:'Monthly Avg Balance'!M7)*Rate!E7/12)*'Monthly Avg Balance'!M7/SUM('Monthly Avg Balance'!K7:'Monthly Avg Balance'!M7)) -> 520.16663 | N7: =IF(SUM('Monthly Avg Balance'!N7:'Monthly Avg Balance'!P7)=0,"",'Monthly Avg Balance'!N7*Rate!F7/12+('Net Interest Income'!F7-SUM('Monthly Avg Balance'!N7:'Monthly Avg Balance'!P7)*Rate!F7/12)*'Monthly Avg Balance'!N7/SUM('Monthly Avg Balance'!N7:'Monthly Avg Balance'!P7)) -> 528.54372 | O7: =IF(SUM('Monthly Avg Balance'!N7:'Monthly Avg Balance'!P7)=0,"",'Monthly Avg Balance'!O7*Rate!F7/12+('Net Interest Income'!F7-SUM('Monthly Avg Balance'!N7:'Monthly Avg Balance'!P7)*Rate!F7/12)*'Monthly Avg Balance'!O7/SUM('Monthly Avg Balance'!N7:'Monthly Avg Balance'!P7)) -> 516.82802 | P7: =IF(SUM('Monthly Avg Balance'!N7:'Monthly Avg Balance'!P7)=0,"",'Monthly Avg Balance'!P7*Rate!F7/12+('Net Interest Income'!F7-SUM('Monthly Avg Balance'!N7:'Monthly Avg Balance'!P7)*Rate!F7/12)*'Monthly Avg Balance'!P7/SUM('Monthly Avg Balance'!N7:'Monthly Avg Balance'!P7)) -> 518.62826 | Q7: =IF(SUM('Monthly Avg Balance'!Q7:'Monthly Avg Balance'!S7)=0,"",'Monthly Avg Balance'!Q7*Rate!G7/12+('Net Interest Income'!G7-SUM('Monthly Avg Balance'!Q7:'Monthly Avg Balance'!S7)*Rate!G7/12)*'Monthly Avg Balance'!Q7/SUM('Monthly Avg Balance'!Q7:'Monthly Avg Balance'!S7)) -> 534.93224 | R7: =IF(SUM('Monthly Avg Balance'!Q7:'Monthly Avg Balance'!S7)=0,"",'Monthly Avg Balance'!R7*Rate!G7/12+('Net Interest Income'!G7-SUM('Monthly Avg Balance'!Q7:'Monthly Avg Balance'!S7)*Rate!G7/12)*'Monthly Avg Balance'!R7/SUM('Monthly Avg Balance'!Q7:'Monthly Avg Balance'!S7)) -> 536.59212 | S7: =IF(SUM('Monthly Avg Balance'!Q7:'Monthly Avg Balance'!S7)=0,"",'Monthly Avg Balance'!S7*Rate!G7/12+('Net Interest Income'!G7-SUM('Monthly Avg Balance'!Q7:'Monthly Avg Balance'!S7)*Rate!G7/12)*'Monthly Avg Balance'!S7/SUM('Monthly Avg Balance'!Q7:'Monthly Avg Balance'!S7)) -> 539.47564 | T7: =IF(SUM('Monthly Avg Balance'!T7:'Monthly Avg Balance'!V7)=0,"",'Monthly Avg Balance'!T7*Rate!H7/12+('Net Interest Income'!H7-SUM('Monthly Avg Balance'!T7:'Monthly Avg Balance'!V7)*Rate!H7/12)*'Monthly Avg Balance'!T7/SUM('Monthly Avg Balance'!T7:'Monthly Avg Balance'!V7)) -> 562.69032 | U7: =IF(SUM('Monthly Avg Balance'!T7:'Monthly Avg Balance'!V7)=0,"",'Monthly Avg Balance'!U7*Rate!H7/12+('Net Interest Income'!H7-SUM('Monthly Avg Balance'!T7:'Monthly Avg Balance'!V7)*Rate!H7/12)*'Monthly Avg Balance'!U7/SUM('Monthly Avg Balance'!T7:'Monthly Avg Balance'!V7)) -> 563.67101 | V7: =IF(SUM('Monthly Avg Balance'!T7:'Monthly Avg Balance'!V7)=0,"",'Monthly Avg Balance'!V7*Rate!H7/12+('Net Interest Income'!H7-SUM('Monthly Avg Balance'!T7:'Monthly Avg Balance'!V7)*Rate!H7/12)*'Monthly Avg Balance'!V7/SUM('Monthly Avg Balance'!T7:'Monthly Avg Balance'!V7)) -> 565.63867 | W7: =IF(SUM('Monthly Avg Balance'!W7:'Monthly Avg Balance'!Y7)=0,"",'Monthly Avg Balance'!W7*Rate!I7/12+('Net Interest Income'!I7-SUM('Monthly Avg Balance'!W7:'Monthly Avg Balance'!Y7)*Rate!I7/12)*'Monthly Avg Balance'!W7/SUM('Monthly Avg Balance'!W7:'Monthly Avg Balance'!Y7)) -> 577.4278 | X7: =IF(SUM('Monthly Avg Balance'!W7:'Monthly Avg Balance'!Y7)=0,"",'Monthly Avg Balance'!X7*Rate!I7/12+('Net Interest Income'!I7-SUM('Monthly Avg Balance'!W7:'Monthly Avg Balance'!Y7)*Rate!I7/12)*'Monthly Avg Balance'!X7/SUM('Monthly Avg Balance'!W7:'Monthly Avg Balance'!Y7)) -> 580.06477 | Y7: =IF(SUM('Monthly Avg Balance'!W7:'Monthly Avg Balance'!Y7)=0,"",'Monthly Avg Balance'!Y7*Rate!I7/12+('Net Interest Income'!I7-SUM('Monthly Avg Balance'!W7:'Monthly Avg Balance'!Y7)*Rate!I7/12)*'Monthly Avg Balance'!Y7/SUM('Monthly Avg Balance'!W7:'Monthly Avg Balance'!Y7)) -> 587.50742 | Z7: =IF(SUM('Monthly Avg Balance'!Z7:'Monthly Avg Balance'!AB7)=0,"",'Monthly Avg Balance'!Z7*Rate!J7/12+('Net Interest Income'!J7-SUM('Monthly Avg Balance'!Z7:'Monthly Avg Balance'!AB7)*Rate!J7/12)*'Monthly Avg Balance'!Z7/SUM('Monthly Avg Balance'!Z7:'Monthly Avg Balance'!AB7)) -> 591.0189 | AA7: =IF(SUM('Monthly Avg Balance'!Z7:'Monthly Avg Balance'!AB7)=0,"",'Monthly Avg Balance'!AA7*Rate!J7/12+('Net Interest Income'!J7-SUM('Monthly Avg Balance'!Z7:'Monthly Avg Balance'!AB7)*Rate!J7/12)*'Monthly Avg Balance'!AA7/SUM('Monthly Avg Balance'!Z7:'Monthly Avg Balance'!AB7)) -> 590.31482 | AB7: =IF(SUM('Monthly Avg Balance'!Z7:'Monthly Avg Balance'!AB7)=0,"",'Monthly Avg Balance'!AB7*Rate!J7/12+('Net Interest Income'!J7-SUM('Monthly Avg Balance'!Z7:'Monthly Avg Balance'!AB7)*Rate!J7/12)*'Monthly Avg Balance'!AB7/SUM('Monthly Avg Balance'!Z7:'Monthly Avg Balance'!AB7)) -> 591.66628 | AC7: =IF(SUM('Monthly Avg Balance'!AC7:'Monthly Avg Balance'!AE7)=0,"",'Monthly Avg Balance'!AC7*Rate!K7/12+('Net Interest Income'!K7-SUM('Monthly Avg Balance'!AC7:'Monthly Avg Balance'!AE7)*Rate!K7/12)*'Monthly Avg Balance'!AC7/SUM('Monthly Avg Balance'!AC7:'Monthly Avg Balance'!AE7)) -> 597.72345 | AD7: =IF(SUM('Monthly Avg Balance'!AC7:'Monthly Avg Balance'!AE7)=0,"",'Monthly Avg Balance'!AD7*Rate!K7/12+('Net Interest Income'!K7-SUM('Monthly Avg Balance'!AC7:'Monthly Avg Balance'!AE7)*Rate!K7/12)*'Monthly Avg Balance'!AD7/SUM('Monthly Avg Balance'!AC7:'Monthly Avg Balance'!AE7)) -> 590.07328 | AE7: =IF(SUM('Monthly Avg Balance'!AC7:'Monthly Avg Balance'!AE7)=0,"",'Monthly Avg Balance'!AE7*Rate!K7/12+('Net Interest Income'!K7-SUM('Monthly Avg Balance'!AC7:'Monthly Avg Balance'!AE7)*Rate!K7/12)*'Monthly Avg Balance'!AE7/SUM('Monthly Avg Balance'!AC7:'Monthly Avg Balance'!AE7)) -> 673.20327 | AF7: ='Monthly Avg Balance'!AF7*'Monthly Rate'!AF7/12 -> 737.26882 | AG7: ='Monthly Avg Balance'!AG7*'Monthly Rate'!AG7/12 -> 737.00898 | AH7: ='Monthly Avg Balance'!AH7*'Monthly Rate'!AH7/12 -> 736.74918 | AI7: ='Monthly Avg Balance'!AI7*'Monthly Rate'!AI7/12 -> 736.48943 | AJ7: ='Monthly Avg Balance'!AJ7*'Monthly Rate'!AJ7/12 -> 736.22973 | AK7: ='Monthly Avg Balance'!AK7*'Monthly Rate'!AK7/12 -> 735.97007 | AL7: ='Monthly Avg Balance'!AL7*'Monthly Rate'!AL7/12 -> 735.71046 | AM7: ='Monthly Avg Balance'!AM7*'Monthly Rate'!AM7/12 -> 735.45089 | ... AQ7: ='Monthly Avg Balance'!AQ7*'Monthly Rate'!AQ7/12 -> 734.41308
A8: Commercial banking | B8: =IF(SUM('Monthly Avg Balance'!B8:'Monthly Avg Balance'!D8)=0,"",'Monthly Avg Balance'!B8*Rate!B8/12+('Net Interest Income'!B8-SUM('Monthly Avg Balance'!B8:'Monthly Avg Balance'!D8)*Rate!B8/12)*'Monthly Avg Balance'!B8/SUM('Monthly Avg Balance'!B8:'Monthly Avg Balance'!D8)) -> 496 | C8: =IF(SUM('Monthly Avg Balance'!B8:'Monthly Avg Balance'!D8)=0,"",'Monthly Avg Balance'!C8*Rate!B8/12+('Net Interest Income'!B8-SUM('Monthly Avg Balance'!B8:'Monthly Avg Balance'!D8)*Rate!B8/12)*'Monthly Avg Balance'!C8/SUM('Monthly Avg Balance'!B8:'Monthly Avg Balance'!D8)) -> 496 | D8: =IF(SUM('Monthly Avg Balance'!B8:'Monthly Avg Balance'!D8)=0,"",'Monthly Avg Balance'!D8*Rate!B8/12+('Net Interest Income'!B8-SUM('Monthly Avg Balance'!B8:'Monthly Avg Balance'!D8)*Rate!B8/12)*'Monthly Avg Balance'!D8/SUM('Monthly Avg Balance'!B8:'Monthly Avg Balance'!D8)) -> 496 | E8: =IF(SUM('Monthly Avg Balance'!E8:'Monthly Avg Balance'!G8)=0,"",'Monthly Avg Balance'!E8*Rate!C8/12+('Net Interest Income'!C8-SUM('Monthly Avg Balance'!E8:'Monthly Avg Balance'!G8)*Rate!C8/12)*'Monthly Avg Balance'!E8/SUM('Monthly Avg Balance'!E8:'Monthly Avg Balance'!G8)) -> 528.80608 | F8: =IF(SUM('Monthly Avg Balance'!E8:'Monthly Avg Balance'!G8)=0,"",'Monthly Avg Balance'!F8*Rate!C8/12+('Net Interest Income'!C8-SUM('Monthly Avg Balance'!E8:'Monthly Avg Balance'!G8)*Rate!C8/12)*'Monthly Avg Balance'!F8/SUM('Monthly Avg Balance'!E8:'Monthly Avg Balance'!G8)) -> 526.66667 | G8: =IF(SUM('Monthly Avg Balance'!E8:'Monthly Avg Balance'!G8)=0,"",'Monthly Avg Balance'!G8*Rate!C8/12+('Net Interest Income'!C8-SUM('Monthly Avg Balance'!E8:'Monthly Avg Balance'!G8)*Rate!C8/12)*'Monthly Avg Balance'!G8/SUM('Monthly Avg Balance'!E8:'Monthly Avg Balance'!G8)) -> 524.52725 | H8: =IF(SUM('Monthly Avg Balance'!H8:'Monthly Avg Balance'!J8)=0,"",'Monthly Avg Balance'!H8*Rate!D8/12+('Net Interest Income'!D8-SUM('Monthly Avg Balance'!H8:'Monthly Avg Balance'!J8)*Rate!D8/12)*'Monthly Avg Balance'!H8/SUM('Monthly Avg Balance'!H8:'Monthly Avg Balance'!J8)) -> 551.47845 | I8: =IF(SUM('Monthly Avg Balance'!H8:'Monthly Avg Balance'!J8)=0,"",'Monthly Avg Balance'!I8*Rate!D8/12+('Net Interest Income'!D8-SUM('Monthly Avg Balance'!H8:'Monthly Avg Balance'!J8)*Rate!D8/12)*'Monthly Avg Balance'!I8/SUM('Monthly Avg Balance'!H8:'Monthly Avg Balance'!J8)) -> 547.33333 | J8: =IF(SUM('Monthly Avg Balance'!H8:'Monthly Avg Balance'!J8)=0,"",'Monthly Avg Balance'!J8*Rate!D8/12+('Net Interest Income'!D8-SUM('Monthly Avg Balance'!H8:'Monthly Avg Balance'!J8)*Rate!D8/12)*'Monthly Avg Balance'!J8/SUM('Monthly Avg Balance'!H8:'Monthly Avg Balance'!J8)) -> 543.18822 | K8: =IF(SUM('Monthly Avg Balance'!K8:'Monthly Avg Balance'!M8)=0,"",'Monthly Avg Balance'!K8*Rate!E8/12+('Net Interest Income'!E8-SUM('Monthly Avg Balance'!K8:'Monthly Avg Balance'!M8)*Rate!E8/12)*'Monthly Avg Balance'!K8/SUM('Monthly Avg Balance'!K8:'Monthly Avg Balance'!M8)) -> 549.37008 | L8: =IF(SUM('Monthly Avg Balance'!K8:'Monthly Avg Balance'!M8)=0,"",'Monthly Avg Balance'!L8*Rate!E8/12+('Net Interest Income'!E8-SUM('Monthly Avg Balance'!K8:'Monthly Avg Balance'!M8)*Rate!E8/12)*'Monthly Avg Balance'!L8/SUM('Monthly Avg Balance'!K8:'Monthly Avg Balance'!M8)) -> 549.18155 | M8: =IF(SUM('Monthly Avg Balance'!K8:'Monthly Avg Balance'!M8)=0,"",'Monthly Avg Balance'!M8*Rate!E8/12+('Net Interest Income'!E8-SUM('Monthly Avg Balance'!K8:'Monthly Avg Balance'!M8)*Rate!E8/12)*'Monthly Avg Balance'!M8/SUM('Monthly Avg Balance'!K8:'Monthly Avg Balance'!M8)) -> 554.44837 | N8: =IF(SUM('Monthly Avg Balance'!N8:'Monthly Avg Balance'!P8)=0,"",'Monthly Avg Balance'!N8*Rate!F8/12+('Net Interest Income'!F8-SUM('Monthly Avg Balance'!N8:'Monthly Avg Balance'!P8)*Rate!F8/12)*'Monthly Avg Balance'!N8/SUM('Monthly Avg Balance'!N8:'Monthly Avg Balance'!P8)) -> 543.54552 | O8: =IF(SUM('Monthly Avg Balance'!N8:'Monthly Avg Balance'!P8)=0,"",'Monthly Avg Balance'!O8*Rate!F8/12+('Net Interest Income'!F8-SUM('Monthly Avg Balance'!N8:'Monthly Avg Balance'!P8)*Rate!F8/12)*'Monthly Avg Balance'!O8/SUM('Monthly Avg Balance'!N8:'Monthly Avg Balance'!P8)) -> 533.50251 | P8: =IF(SUM('Monthly Avg Balance'!N8:'Monthly Avg Balance'!P8)=0,"",'Monthly Avg Balance'!P8*Rate!F8/12+('Net Interest Income'!F8-SUM('Monthly Avg Balance'!N8:'Monthly Avg Balance'!P8)*Rate!F8/12)*'Monthly Avg Balance'!P8/SUM('Monthly Avg Balance'!N8:'Monthly Avg Balance'!P8)) -> 534.95197 | Q8: =IF(SUM('Monthly Avg Balance'!Q8:'Monthly Avg Balance'!S8)=0,"",'Monthly Avg Balance'!Q8*Rate!G8/12+('Net Interest Income'!G8-SUM('Monthly Avg Balance'!Q8:'Monthly Avg Balance'!S8)*Rate!G8/12)*'Monthly Avg Balance'!Q8/SUM('Monthly Avg Balance'!Q8:'Monthly Avg Balance'!S8)) -> 540.20847 | R8: =IF(SUM('Monthly Avg Balance'!Q8:'Monthly Avg Balance'!S8)=0,"",'Monthly Avg Balance'!R8*Rate!G8/12+('Net Interest Income'!G8-SUM('Monthly Avg Balance'!Q8:'Monthly Avg Balance'!S8)*Rate!G8/12)*'Monthly Avg Balance'!R8/SUM('Monthly Avg Balance'!Q8:'Monthly Avg Balance'!S8)) -> 535.84284 | S8: =IF(SUM('Monthly Avg Balance'!Q8:'Monthly Avg Balance'!S8)=0,"",'Monthly Avg Balance'!S8*Rate!G8/12+('Net Interest Income'!G8-SUM('Monthly Avg Balance'!Q8:'Monthly Avg Balance'!S8)*Rate!G8/12)*'Monthly Avg Balance'!S8/SUM('Monthly Avg Balance'!Q8:'Monthly Avg Balance'!S8)) -> 539.94868 | T8: =IF(SUM('Monthly Avg Balance'!T8:'Monthly Avg Balance'!V8)=0,"",'Monthly Avg Balance'!T8*Rate!H8/12+('Net Interest Income'!H8-SUM('Monthly Avg Balance'!T8:'Monthly Avg Balance'!V8)*Rate!H8/12)*'Monthly Avg Balance'!T8/SUM('Monthly Avg Balance'!T8:'Monthly Avg Balance'!V8)) -> 538.90364 | U8: =IF(SUM('Monthly Avg Balance'!T8:'Monthly Avg Balance'!V8)=0,"",'Monthly Avg Balance'!U8*Rate!H8/12+('Net Interest Income'!H8-SUM('Monthly Avg Balance'!T8:'Monthly Avg Balance'!V8)*Rate!H8/12)*'Monthly Avg Balance'!U8/SUM('Monthly Avg Balance'!T8:'Monthly Avg Balance'!V8)) -> 529.03329 | V8: =IF(SUM('Monthly Avg Balance'!T8:'Monthly Avg Balance'!V8)=0,"",'Monthly Avg Balance'!V8*Rate!H8/12+('Net Interest Income'!H8-SUM('Monthly Avg Balance'!T8:'Monthly Avg Balance'!V8)*Rate!H8/12)*'Monthly Avg Balance'!V8/SUM('Monthly Avg Balance'!T8:'Monthly Avg Balance'!V8)) -> 533.06307 | W8: =IF(SUM('Monthly Avg Balance'!W8:'Monthly Avg Balance'!Y8)=0,"",'Monthly Avg Balance'!W8*Rate!I8/12+('Net Interest Income'!I8-SUM('Monthly Avg Balance'!W8:'Monthly Avg Balance'!Y8)*Rate!I8/12)*'Monthly Avg Balance'!W8/SUM('Monthly Avg Balance'!W8:'Monthly Avg Balance'!Y8)) -> 492.42391 | X8: =IF(SUM('Monthly Avg Balance'!W8:'Monthly Avg Balance'!Y8)=0,"",'Monthly Avg Balance'!X8*Rate!I8/12+('Net Interest Income'!I8-SUM('Monthly Avg Balance'!W8:'Monthly Avg Balance'!Y8)*Rate!I8/12)*'Monthly Avg Balance'!X8/SUM('Monthly Avg Balance'!W8:'Monthly Avg Balance'!Y8)) -> 485.74652 | Y8: =IF(SUM('Monthly Avg Balance'!W8:'Monthly Avg Balance'!Y8)=0,"",'Monthly Avg Balance'!Y8*Rate!I8/12+('Net Interest Income'!I8-SUM('Monthly Avg Balance'!W8:'Monthly Avg Balance'!Y8)*Rate!I8/12)*'Monthly Avg Balance'!Y8/SUM('Monthly Avg Balance'!W8:'Monthly Avg Balance'!Y8)) -> 493.82957 | Z8: =IF(SUM('Monthly Avg Balance'!Z8:'Monthly Avg Balance'!AB8)=0,"",'Monthly Avg Balance'!Z8*Rate!J8/12+('Net Interest Income'!J8-SUM('Monthly Avg Balance'!Z8:'Monthly Avg Balance'!AB8)*Rate!J8/12)*'Monthly Avg Balance'!Z8/SUM('Monthly Avg Balance'!Z8:'Monthly Avg Balance'!AB8)) -> 463.85383 | AA8: =IF(SUM('Monthly Avg Balance'!Z8:'Monthly Avg Balance'!AB8)=0,"",'Monthly Avg Balance'!AA8*Rate!J8/12+('Net Interest Income'!J8-SUM('Monthly Avg Balance'!Z8:'Monthly Avg Balance'!AB8)*Rate!J8/12)*'Monthly Avg Balance'!AA8/SUM('Monthly Avg Balance'!Z8:'Monthly Avg Balance'!AB8)) -> 458.01644 | AB8: =IF(SUM('Monthly Avg Balance'!Z8:'Monthly Avg Balance'!AB8)=0,"",'Monthly Avg Balance'!AB8*Rate!J8/12+('Net Interest Income'!J8-SUM('Monthly Avg Balance'!Z8:'Monthly Avg Balance'!AB8)*Rate!J8/12)*'Monthly Avg Balance'!AB8/SUM('Monthly Avg Balance'!Z8:'Monthly Avg Balance'!AB8)) -> 460.12973 | AC8: =IF(SUM('Monthly Avg Balance'!AC8:'Monthly Avg Balance'!AE8)=0,"",'Monthly Avg Balance'!AC8*Rate!K8/12+('Net Interest Income'!K8-SUM('Monthly Avg Balance'!AC8:'Monthly Avg Balance'!AE8)*Rate!K8/12)*'Monthly Avg Balance'!AC8/SUM('Monthly Avg Balance'!AC8:'Monthly Avg Balance'!AE8)) -> 458.9099 | AD8: =IF(SUM('Monthly Avg Balance'!AC8:'Monthly Avg Balance'!AE8)=0,"",'Monthly Avg Balance'!AD8*Rate!K8/12+('Net Interest Income'!K8-SUM('Monthly Avg Balance'!AC8:'Monthly Avg Balance'!AE8)*Rate!K8/12)*'Monthly Avg Balance'!AD8/SUM('Monthly Avg Balance'!AC8:'Monthly Avg Balance'!AE8)) -> 448.82762 | AE8: =IF(SUM('Monthly Avg Balance'!AC8:'Monthly Avg Balance'!AE8)=0,"",'Monthly Avg Balance'!AE8*Rate!K8/12+('Net Interest Income'!K8-SUM('Monthly Avg Balance'!AC8:'Monthly Avg Balance'!AE8)*Rate!K8/12)*'Monthly Avg Balance'!AE8/SUM('Monthly Avg Balance'!AC8:'Monthly Avg Balance'!AE8)) -> 513.26248 | AF8: ='Monthly Avg Balance'!AF8*'Monthly Rate'!AF8/12 -> 562.01136 | AG8: ='Monthly Avg Balance'!AG8*'Monthly Rate'!AG8/12 -> 559.96084 | AH8: ='Monthly Avg Balance'!AH8*'Monthly Rate'!AH8/12 -> 557.90958 | AI8: ='Monthly Avg Balance'!AI8*'Monthly Rate'!AI8/12 -> 555.8576 | AJ8: ='Monthly Avg Balance'!AJ8*'Monthly Rate'!AJ8/12 -> 553.80488 | AK8: ='Monthly Avg Balance'!AK8*'Monthly Rate'!AK8/12 -> 551.75144 | AL8: ='Monthly Avg Balance'!AL8*'Monthly Rate'!AL8/12 -> 549.69726 | AM8: ='Monthly Avg Balance'!AM8*'Monthly Rate'!AM8/12 -> 547.64235 | ... AQ8: ='Monthly Avg Balance'!AQ8*'Monthly Rate'!AQ8/12 -> 539.41541
A9: Total loans (incl. HFS) | B9: =IF(SUM('Monthly Avg Balance'!B9:'Monthly Avg Balance'!D9)=0,"",'Monthly Avg Balance'!B9*Rate!B9/12+('Net Interest Income'!B9-SUM('Monthly Avg Balance'!B9:'Monthly Avg Balance'!D9)*Rate!B9/12)*'Monthly Avg Balance'!B9/SUM('Monthly Avg Balance'!B9:'Monthly Avg Balance'!D9)) -> 2907.6667 | C9: =IF(SUM('Monthly Avg Balance'!B9:'Monthly Avg Balance'!D9)=0,"",'Monthly Avg Balance'!C9*Rate!B9/12+('Net Interest Income'!B9-SUM('Monthly Avg Balance'!B9:'Monthly Avg Balance'!D9)*Rate!B9/12)*'Monthly Avg Balance'!C9/SUM('Monthly Avg Balance'!B9:'Monthly Avg Balance'!D9)) -> 2907.6667 | D9: =IF(SUM('Monthly Avg Balance'!B9:'Monthly Avg Balance'!D9)=0,"",'Monthly Avg Balance'!D9*Rate!B9/12+('Net Interest Income'!B9-SUM('Monthly Avg Balance'!B9:'Monthly Avg Balance'!D9)*Rate!B9/12)*'Monthly Avg Balance'!D9/SUM('Monthly Avg Balance'!B9:'Monthly Avg Balance'!D9)) -> 2907.6667 | E9: =IF(SUM('Monthly Avg Balance'!E9:'Monthly Avg Balance'!G9)=0,"",'Monthly Avg Balance'!E9*Rate!C9/12+('Net Interest Income'!C9-SUM('Monthly Avg Balance'!E9:'Monthly Avg Balance'!G9)*Rate!C9/12)*'Monthly Avg Balance'!E9/SUM('Monthly Avg Balance'!E9:'Monthly Avg Balance'!G9)) -> 3004.6023 | F9: =IF(SUM('Monthly Avg Balance'!E9:'Monthly Avg Balance'!G9)=0,"",'Monthly Avg Balance'!F9*Rate!C9/12+('Net Interest Income'!C9-SUM('Monthly Avg Balance'!E9:'Monthly Avg Balance'!G9)*Rate!C9/12)*'Monthly Avg Balance'!F9/SUM('Monthly Avg Balance'!E9:'Monthly Avg Balance'!G9)) -> 3019 | G9: =IF(SUM('Monthly Avg Balance'!E9:'Monthly Avg Balance'!G9)=0,"",'Monthly Avg Balance'!G9*Rate!C9/12+('Net Interest Income'!C9-SUM('Monthly Avg Balance'!E9:'Monthly Avg Balance'!G9)*Rate!C9/12)*'Monthly Avg Balance'!G9/SUM('Monthly Avg Balance'!E9:'Monthly Avg Balance'!G9)) -> 3033.3977 | H9: =IF(SUM('Monthly Avg Balance'!H9:'Monthly Avg Balance'!J9)=0,"",'Monthly Avg Balance'!H9*Rate!D9/12+('Net Interest Income'!D9-SUM('Monthly Avg Balance'!H9:'Monthly Avg Balance'!J9)*Rate!D9/12)*'Monthly Avg Balance'!H9/SUM('Monthly Avg Balance'!H9:'Monthly Avg Balance'!J9)) -> 3225.7723 | I9: =IF(SUM('Monthly Avg Balance'!H9:'Monthly Avg Balance'!J9)=0,"",'Monthly Avg Balance'!I9*Rate!D9/12+('Net Interest Income'!D9-SUM('Monthly Avg Balance'!H9:'Monthly Avg Balance'!J9)*Rate!D9/12)*'Monthly Avg Balance'!I9/SUM('Monthly Avg Balance'!H9:'Monthly Avg Balance'!J9)) -> 3232 | J9: =IF(SUM('Monthly Avg Balance'!H9:'Monthly Avg Balance'!J9)=0,"",'Monthly Avg Balance'!J9*Rate!D9/12+('Net Interest Income'!D9-SUM('Monthly Avg Balance'!H9:'Monthly Avg Balance'!J9)*Rate!D9/12)*'Monthly Avg Balance'!J9/SUM('Monthly Avg Balance'!H9:'Monthly Avg Balance'!J9)) -> 3238.2277 | K9: =IF(SUM('Monthly Avg Balance'!K9:'Monthly Avg Balance'!M9)=0,"",'Monthly Avg Balance'!K9*Rate!E9/12+('Net Interest Income'!E9-SUM('Monthly Avg Balance'!K9:'Monthly Avg Balance'!M9)*Rate!E9/12)*'Monthly Avg Balance'!K9/SUM('Monthly Avg Balance'!K9:'Monthly Avg Balance'!M9)) -> 3292.4777 | L9: =IF(SUM('Monthly Avg Balance'!K9:'Monthly Avg Balance'!M9)=0,"",'Monthly Avg Balance'!L9*Rate!E9/12+('Net Interest Income'!E9-SUM('Monthly Avg Balance'!K9:'Monthly Avg Balance'!M9)*Rate!E9/12)*'Monthly Avg Balance'!L9/SUM('Monthly Avg Balance'!K9:'Monthly Avg Balance'!M9)) -> 3306.4612 | M9: =IF(SUM('Monthly Avg Balance'!K9:'Monthly Avg Balance'!M9)=0,"",'Monthly Avg Balance'!M9*Rate!E9/12+('Net Interest Income'!E9-SUM('Monthly Avg Balance'!K9:'Monthly Avg Balance'!M9)*Rate!E9/12)*'Monthly Avg Balance'!M9/SUM('Monthly Avg Balance'!K9:'Monthly Avg Balance'!M9)) -> 3335.0611 | N9: =IF(SUM('Monthly Avg Balance'!N9:'Monthly Avg Balance'!P9)=0,"",'Monthly Avg Balance'!N9*Rate!F9/12+('Net Interest Income'!F9-SUM('Monthly Avg Balance'!N9:'Monthly Avg Balance'!P9)*Rate!F9/12)*'Monthly Avg Balance'!N9/SUM('Monthly Avg Balance'!N9:'Monthly Avg Balance'!P9)) -> 3333.1637 | O9: =IF(SUM('Monthly Avg Balance'!N9:'Monthly Avg Balance'!P9)=0,"",'Monthly Avg Balance'!O9*Rate!F9/12+('Net Interest Income'!F9-SUM('Monthly Avg Balance'!N9:'Monthly Avg Balance'!P9)*Rate!F9/12)*'Monthly Avg Balance'!O9/SUM('Monthly Avg Balance'!N9:'Monthly Avg Balance'!P9)) -> 3290.9113 | P9: =IF(SUM('Monthly Avg Balance'!N9:'Monthly Avg Balance'!P9)=0,"",'Monthly Avg Balance'!P9*Rate!F9/12+('Net Interest Income'!F9-SUM('Monthly Avg Balance'!N9:'Monthly Avg Balance'!P9)*Rate!F9/12)*'Monthly Avg Balance'!P9/SUM('Monthly Avg Balance'!N9:'Monthly Avg Balance'!P9)) -> 3295.925 | Q9: =IF(SUM('Monthly Avg Balance'!Q9:'Monthly Avg Balance'!S9)=0,"",'Monthly Avg Balance'!Q9*Rate!G9/12+('Net Interest Income'!G9-SUM('Monthly Avg Balance'!Q9:'Monthly Avg Balance'!S9)*Rate!G9/12)*'Monthly Avg Balance'!Q9/SUM('Monthly Avg Balance'!Q9:'Monthly Avg Balance'!S9)) -> 3323.3114 | R9: =IF(SUM('Monthly Avg Balance'!Q9:'Monthly Avg Balance'!S9)=0,"",'Monthly Avg Balance'!R9*Rate!G9/12+('Net Interest Income'!G9-SUM('Monthly Avg Balance'!Q9:'Monthly Avg Balance'!S9)*Rate!G9/12)*'Monthly Avg Balance'!R9/SUM('Monthly Avg Balance'!Q9:'Monthly Avg Balance'!S9)) -> 3325.0391 | S9: =IF(SUM('Monthly Avg Balance'!Q9:'Monthly Avg Balance'!S9)=0,"",'Monthly Avg Balance'!S9*Rate!G9/12+('Net Interest Income'!G9-SUM('Monthly Avg Balance'!Q9:'Monthly Avg Balance'!S9)*Rate!G9/12)*'Monthly Avg Balance'!S9/SUM('Monthly Avg Balance'!Q9:'Monthly Avg Balance'!S9)) -> 3344.6495 | T9: =IF(SUM('Monthly Avg Balance'!T9:'Monthly Avg Balance'!V9)=0,"",'Monthly Avg Balance'!T9*Rate!H9/12+('Net Interest Income'!H9-SUM('Monthly Avg Balance'!T9:'Monthly Avg Balance'!V9)*Rate!H9/12)*'Monthly Avg Balance'!T9/SUM('Monthly Avg Balance'!T9:'Monthly Avg Balance'!V9)) -> 3509.9369 | U9: =IF(SUM('Monthly Avg Balance'!T9:'Monthly Avg Balance'!V9)=0,"",'Monthly Avg Balance'!U9*Rate!H9/12+('Net Interest Income'!H9-SUM('Monthly Avg Balance'!T9:'Monthly Avg Balance'!V9)*Rate!H9/12)*'Monthly Avg Balance'!U9/SUM('Monthly Avg Balance'!T9:'Monthly Avg Balance'!V9)) -> 3511.9915 | V9: =IF(SUM('Monthly Avg Balance'!T9:'Monthly Avg Balance'!V9)=0,"",'Monthly Avg Balance'!V9*Rate!H9/12+('Net Interest Income'!H9-SUM('Monthly Avg Balance'!T9:'Monthly Avg Balance'!V9)*Rate!H9/12)*'Monthly Avg Balance'!V9/SUM('Monthly Avg Balance'!T9:'Monthly Avg Balance'!V9)) -> 3525.0716 | W9: =IF(SUM('Monthly Avg Balance'!W9:'Monthly Avg Balance'!Y9)=0,"",'Monthly Avg Balance'!W9*Rate!I9/12+('Net Interest Income'!I9-SUM('Monthly Avg Balance'!W9:'Monthly Avg Balance'!Y9)*Rate!I9/12)*'Monthly Avg Balance'!W9/SUM('Monthly Avg Balance'!W9:'Monthly Avg Balance'!Y9)) -> 3457.1473 | X9: =IF(SUM('Monthly Avg Balance'!W9:'Monthly Avg Balance'!Y9)=0,"",'Monthly Avg Balance'!X9*Rate!I9/12+('Net Interest Income'!I9-SUM('Monthly Avg Balance'!W9:'Monthly Avg Balance'!Y9)*Rate!I9/12)*'Monthly Avg Balance'!X9/SUM('Monthly Avg Balance'!W9:'Monthly Avg Balance'!Y9)) -> 3465.4149 | Y9: =IF(SUM('Monthly Avg Balance'!W9:'Monthly Avg Balance'!Y9)=0,"",'Monthly Avg Balance'!Y9*Rate!I9/12+('Net Interest Income'!I9-SUM('Monthly Avg Balance'!W9:'Monthly Avg Balance'!Y9)*Rate!I9/12)*'Monthly Avg Balance'!Y9/SUM('Monthly Avg Balance'!W9:'Monthly Avg Balance'!Y9)) -> 3511.4378 | Z9: =IF(SUM('Monthly Avg Balance'!Z9:'Monthly Avg Balance'!AB9)=0,"",'Monthly Avg Balance'!Z9*Rate!J9/12+('Net Interest Income'!J9-SUM('Monthly Avg Balance'!Z9:'Monthly Avg Balance'!AB9)*Rate!J9/12)*'Monthly Avg Balance'!Z9/SUM('Monthly Avg Balance'!Z9:'Monthly Avg Balance'!AB9)) -> 3410.5366 | AA9: =IF(SUM('Monthly Avg Balance'!Z9:'Monthly Avg Balance'!AB9)=0,"",'Monthly Avg Balance'!AA9*Rate!J9/12+('Net Interest Income'!J9-SUM('Monthly Avg Balance'!Z9:'Monthly Avg Balance'!AB9)*Rate!J9/12)*'Monthly Avg Balance'!AA9/SUM('Monthly Avg Balance'!Z9:'Monthly Avg Balance'!AB9)) -> 3365.2243 | AB9: =IF(SUM('Monthly Avg Balance'!Z9:'Monthly Avg Balance'!AB9)=0,"",'Monthly Avg Balance'!AB9*Rate!J9/12+('Net Interest Income'!J9-SUM('Monthly Avg Balance'!Z9:'Monthly Avg Balance'!AB9)*Rate!J9/12)*'Monthly Avg Balance'!AB9/SUM('Monthly Avg Balance'!Z9:'Monthly Avg Balance'!AB9)) -> 3381.2391 | AC9: =IF(SUM('Monthly Avg Balance'!AC9:'Monthly Avg Balance'!AE9)=0,"",'Monthly Avg Balance'!AC9*Rate!K9/12+('Net Interest Income'!K9-SUM('Monthly Avg Balance'!AC9:'Monthly Avg Balance'!AE9)*Rate!K9/12)*'Monthly Avg Balance'!AC9/SUM('Monthly Avg Balance'!AC9:'Monthly Avg Balance'!AE9)) -> 3736.4642 | AD9: =IF(SUM('Monthly Avg Balance'!AC9:'Monthly Avg Balance'!AE9)=0,"",'Monthly Avg Balance'!AD9*Rate!K9/12+('Net Interest Income'!K9-SUM('Monthly Avg Balance'!AC9:'Monthly Avg Balance'!AE9)*Rate!K9/12)*'Monthly Avg Balance'!AD9/SUM('Monthly Avg Balance'!AC9:'Monthly Avg Balance'!AE9)) -> 4128.3413 | AE9: =IF(SUM('Monthly Avg Balance'!AC9:'Monthly Avg Balance'!AE9)=0,"",'Monthly Avg Balance'!AE9*Rate!K9/12+('Net Interest Income'!K9-SUM('Monthly Avg Balance'!AC9:'Monthly Avg Balance'!AE9)*Rate!K9/12)*'Monthly Avg Balance'!AE9/SUM('Monthly Avg Balance'!AC9:'Monthly Avg Balance'!AE9)) -> 4584.1945 | AF9: =SUM(AF6:AF8) -> 4883.795 | AG9: =SUM(AG6:AG8) -> 4864.3464 | AH9: =SUM(AH6:AH8) -> 4862.6429 | AI9: =SUM(AI6:AI8) -> 4860.9388 | AJ9: =SUM(AJ6:AJ8) -> 4841.476 | AK9: =SUM(AK6:AK8) -> 4839.7675 | AL9: =SUM(AL6:AL8) -> 4838.0583 | AM9: =SUM(AM6:AM8) -> 4818.5814 | ... AQ9: =SUM(AQ6:AQ8) -> 4793.9438
A10: Investment securities | B10: =IF(SUM('Monthly Avg Balance'!B10:'Monthly Avg Balance'!D10)=0,"",'Monthly Avg Balance'!B10*Rate!B10/12+('Net Interest Income'!B10-SUM('Monthly Avg Balance'!B10:'Monthly Avg Balance'!D10)*Rate!B10/12)*'Monthly Avg Balance'!B10/SUM('Monthly Avg Balance'!B10:'Monthly Avg Balance'!D10)) -> 205 | C10: =IF(SUM('Monthly Avg Balance'!B10:'Monthly Avg Balance'!D10)=0,"",'Monthly Avg Balance'!C10*Rate!B10/12+('Net Interest Income'!B10-SUM('Monthly Avg Balance'!B10:'Monthly Avg Balance'!D10)*Rate!B10/12)*'Monthly Avg Balance'!C10/SUM('Monthly Avg Balance'!B10:'Monthly Avg Balance'!D10)) -> 205 | D10: =IF(SUM('Monthly Avg Balance'!B10:'Monthly Avg Balance'!D10)=0,"",'Monthly Avg Balance'!D10*Rate!B10/12+('Net Interest Income'!B10-SUM('Monthly Avg Balance'!B10:'Monthly Avg Balance'!D10)*Rate!B10/12)*'Monthly Avg Balance'!D10/SUM('Monthly Avg Balance'!B10:'Monthly Avg Balance'!D10)) -> 205 | E10: =IF(SUM('Monthly Avg Balance'!E10:'Monthly Avg Balance'!G10)=0,"",'Monthly Avg Balance'!E10*Rate!C10/12+('Net Interest Income'!C10-SUM('Monthly Avg Balance'!E10:'Monthly Avg Balance'!G10)*Rate!C10/12)*'Monthly Avg Balance'!E10/SUM('Monthly Avg Balance'!E10:'Monthly Avg Balance'!G10)) -> 212.94635 | F10: =IF(SUM('Monthly Avg Balance'!E10:'Monthly Avg Balance'!G10)=0,"",'Monthly Avg Balance'!F10*Rate!C10/12+('Net Interest Income'!C10-SUM('Monthly Avg Balance'!E10:'Monthly Avg Balance'!G10)*Rate!C10/12)*'Monthly Avg Balance'!F10/SUM('Monthly Avg Balance'!E10:'Monthly Avg Balance'!G10)) -> 213 | G10: =IF(SUM('Monthly Avg Balance'!E10:'Monthly Avg Balance'!G10)=0,"",'Monthly Avg Balance'!G10*Rate!C10/12+('Net Interest Income'!C10-SUM('Monthly Avg Balance'!E10:'Monthly Avg Balance'!G10)*Rate!C10/12)*'Monthly Avg Balance'!G10/SUM('Monthly Avg Balance'!E10:'Monthly Avg Balance'!G10)) -> 213.05365 | H10: =IF(SUM('Monthly Avg Balance'!H10:'Monthly Avg Balance'!J10)=0,"",'Monthly Avg Balance'!H10*Rate!D10/12+('Net Interest Income'!D10-SUM('Monthly Avg Balance'!H10:'Monthly Avg Balance'!J10)*Rate!D10/12)*'Monthly Avg Balance'!H10/SUM('Monthly Avg Balance'!H10:'Monthly Avg Balance'!J10)) -> 212.46252 | I10: =IF(SUM('Monthly Avg Balance'!H10:'Monthly Avg Balance'!J10)=0,"",'Monthly Avg Balance'!I10*Rate!D10/12+('Net Interest Income'!D10-SUM('Monthly Avg Balance'!H10:'Monthly Avg Balance'!J10)*Rate!D10/12)*'Monthly Avg Balance'!I10/SUM('Monthly Avg Balance'!H10:'Monthly Avg Balance'!J10)) -> 209 | J10: =IF(SUM('Monthly Avg Balance'!H10:'Monthly Avg Balance'!J10)=0,"",'Monthly Avg Balance'!J10*Rate!D10/12+('Net Interest Income'!D10-SUM('Monthly Avg Balance'!H10:'Monthly Avg Balance'!J10)*Rate!D10/12)*'Monthly Avg Balance'!J10/SUM('Monthly Avg Balance'!H10:'Monthly Avg Balance'!J10)) -> 205.53748 | K10: =IF(SUM('Monthly Avg Balance'!K10:'Monthly Avg Balance'!M10)=0,"",'Monthly Avg Balance'!K10*Rate!E10/12+('Net Interest Income'!E10-SUM('Monthly Avg Balance'!K10:'Monthly Avg Balance'!M10)*Rate!E10/12)*'Monthly Avg Balance'!K10/SUM('Monthly Avg Balance'!K10:'Monthly Avg Balance'!M10)) -> 223.23883 | L10: =IF(SUM('Monthly Avg Balance'!K10:'Monthly Avg Balance'!M10)=0,"",'Monthly Avg Balance'!L10*Rate!E10/12+('Net Interest Income'!E10-SUM('Monthly Avg Balance'!K10:'Monthly Avg Balance'!M10)*Rate!E10/12)*'Monthly Avg Balance'!L10/SUM('Monthly Avg Balance'!K10:'Monthly Avg Balance'!M10)) -> 233.24703 | M10: =IF(SUM('Monthly Avg Balance'!K10:'Monthly Avg Balance'!M10)=0,"",'Monthly Avg Balance'!M10*Rate!E10/12+('Net Interest Income'!E10-SUM('Monthly Avg Balance'!K10:'Monthly Avg Balance'!M10)*Rate!E10/12)*'Monthly Avg Balance'!M10/SUM('Monthly Avg Balance'!K10:'Monthly Avg Balance'!M10)) -> 212.51415 | N10: =IF(SUM('Monthly Avg Balance'!N10:'Monthly Avg Balance'!P10)=0,"",'Monthly Avg Balance'!N10*Rate!F10/12+('Net Interest Income'!F10-SUM('Monthly Avg Balance'!N10:'Monthly Avg Balance'!P10)*Rate!F10/12)*'Monthly Avg Balance'!N10/SUM('Monthly Avg Balance'!N10:'Monthly Avg Balance'!P10)) -> 221.43402 | O10: =IF(SUM('Monthly Avg Balance'!N10:'Monthly Avg Balance'!P10)=0,"",'Monthly Avg Balance'!O10*Rate!F10/12+('Net Interest Income'!F10-SUM('Monthly Avg Balance'!N10:'Monthly Avg Balance'!P10)*Rate!F10/12)*'Monthly Avg Balance'!O10/SUM('Monthly Avg Balance'!N10:'Monthly Avg Balance'!P10)) -> 245.32696 | P10: =IF(SUM('Monthly Avg Balance'!N10:'Monthly Avg Balance'!P10)=0,"",'Monthly Avg Balance'!P10*Rate!F10/12+('Net Interest Income'!F10-SUM('Monthly Avg Balance'!N10:'Monthly Avg Balance'!P10)*Rate!F10/12)*'Monthly Avg Balance'!P10/SUM('Monthly Avg Balance'!N10:'Monthly Avg Balance'!P10)) -> 220.23902 | Q10: =IF(SUM('Monthly Avg Balance'!Q10:'Monthly Avg Balance'!S10)=0,"",'Monthly Avg Balance'!Q10*Rate!G10/12+('Net Interest Income'!G10-SUM('Monthly Avg Balance'!Q10:'Monthly Avg Balance'!S10)*Rate!G10/12)*'Monthly Avg Balance'!Q10/SUM('Monthly Avg Balance'!Q10:'Monthly Avg Balance'!S10)) -> 223.69761 | R10: =IF(SUM('Monthly Avg Balance'!Q10:'Monthly Avg Balance'!S10)=0,"",'Monthly Avg Balance'!R10*Rate!G10/12+('Net Interest Income'!G10-SUM('Monthly Avg Balance'!Q10:'Monthly Avg Balance'!S10)*Rate!G10/12)*'Monthly Avg Balance'!R10/SUM('Monthly Avg Balance'!Q10:'Monthly Avg Balance'!S10)) -> 251.1806 | S10: =IF(SUM('Monthly Avg Balance'!Q10:'Monthly Avg Balance'!S10)=0,"",'Monthly Avg Balance'!S10*Rate!G10/12+('Net Interest Income'!G10-SUM('Monthly Avg Balance'!Q10:'Monthly Avg Balance'!S10)*Rate!G10/12)*'Monthly Avg Balance'!S10/SUM('Monthly Avg Balance'!Q10:'Monthly Avg Balance'!S10)) -> 225.12179 | T10: =IF(SUM('Monthly Avg Balance'!T10:'Monthly Avg Balance'!V10)=0,"",'Monthly Avg Balance'!T10*Rate!H10/12+('Net Interest Income'!H10-SUM('Monthly Avg Balance'!T10:'Monthly Avg Balance'!V10)*Rate!H10/12)*'Monthly Avg Balance'!T10/SUM('Monthly Avg Balance'!T10:'Monthly Avg Balance'!V10)) -> 232.58678 | U10: =IF(SUM('Monthly Avg Balance'!T10:'Monthly Avg Balance'!V10)=0,"",'Monthly Avg Balance'!U10*Rate!H10/12+('Net Interest Income'!H10-SUM('Monthly Avg Balance'!T10:'Monthly Avg Balance'!V10)*Rate!H10/12)*'Monthly Avg Balance'!U10/SUM('Monthly Avg Balance'!T10:'Monthly Avg Balance'!V10)) -> 260.44086 | V10: =IF(SUM('Monthly Avg Balance'!T10:'Monthly Avg Balance'!V10)=0,"",'Monthly Avg Balance'!V10*Rate!H10/12+('Net Interest Income'!H10-SUM('Monthly Avg Balance'!T10:'Monthly Avg Balance'!V10)*Rate!H10/12)*'Monthly Avg Balance'!V10/SUM('Monthly Avg Balance'!T10:'Monthly Avg Balance'!V10)) -> 239.97236 | W10: =IF(SUM('Monthly Avg Balance'!W10:'Monthly Avg Balance'!Y10)=0,"",'Monthly Avg Balance'!W10*Rate!I10/12+('Net Interest Income'!I10-SUM('Monthly Avg Balance'!W10:'Monthly Avg Balance'!Y10)*Rate!I10/12)*'Monthly Avg Balance'!W10/SUM('Monthly Avg Balance'!W10:'Monthly Avg Balance'!Y10)) -> 243.52007 | X10: =IF(SUM('Monthly Avg Balance'!W10:'Monthly Avg Balance'!Y10)=0,"",'Monthly Avg Balance'!X10*Rate!I10/12+('Net Interest Income'!I10-SUM('Monthly Avg Balance'!W10:'Monthly Avg Balance'!Y10)*Rate!I10/12)*'Monthly Avg Balance'!X10/SUM('Monthly Avg Balance'!W10:'Monthly Avg Balance'!Y10)) -> 266.81532 | Y10: =IF(SUM('Monthly Avg Balance'!W10:'Monthly Avg Balance'!Y10)=0,"",'Monthly Avg Balance'!Y10*Rate!I10/12+('Net Interest Income'!I10-SUM('Monthly Avg Balance'!W10:'Monthly Avg Balance'!Y10)*Rate!I10/12)*'Monthly Avg Balance'!Y10/SUM('Monthly Avg Balance'!W10:'Monthly Avg Balance'!Y10)) -> 242.66461 | Z10: =IF(SUM('Monthly Avg Balance'!Z10:'Monthly Avg Balance'!AB10)=0,"",'Monthly Avg Balance'!Z10*Rate!J10/12+('Net Interest Income'!J10-SUM('Monthly Avg Balance'!Z10:'Monthly Avg Balance'!AB10)*Rate!J10/12)*'Monthly Avg Balance'!Z10/SUM('Monthly Avg Balance'!Z10:'Monthly Avg Balance'!AB10)) -> 247.43529 | AA10: =IF(SUM('Monthly Avg Balance'!Z10:'Monthly Avg Balance'!AB10)=0,"",'Monthly Avg Balance'!AA10*Rate!J10/12+('Net Interest Income'!J10-SUM('Monthly Avg Balance'!Z10:'Monthly Avg Balance'!AB10)*Rate!J10/12)*'Monthly Avg Balance'!AA10/SUM('Monthly Avg Balance'!Z10:'Monthly Avg Balance'!AB10)) -> 272.71613 | AB10: =IF(SUM('Monthly Avg Balance'!Z10:'Monthly Avg Balance'!AB10)=0,"",'Monthly Avg Balance'!AB10*Rate!J10/12+('Net Interest Income'!J10-SUM('Monthly Avg Balance'!Z10:'Monthly Avg Balance'!AB10)*Rate!J10/12)*'Monthly Avg Balance'!AB10/SUM('Monthly Avg Balance'!Z10:'Monthly Avg Balance'!AB10)) -> 249.84857 | AC10: =IF(SUM('Monthly Avg Balance'!AC10:'Monthly Avg Balance'!AE10)=0,"",'Monthly Avg Balance'!AC10*Rate!K10/12+('Net Interest Income'!K10-SUM('Monthly Avg Balance'!AC10:'Monthly Avg Balance'!AE10)*Rate!K10/12)*'Monthly Avg Balance'!AC10/SUM('Monthly Avg Balance'!AC10:'Monthly Avg Balance'!AE10)) -> 252.13381 | AD10: =IF(SUM('Monthly Avg Balance'!AC10:'Monthly Avg Balance'!AE10)=0,"",'Monthly Avg Balance'!AD10*Rate!K10/12+('Net Interest Income'!K10-SUM('Monthly Avg Balance'!AC10:'Monthly Avg Balance'!AE10)*Rate!K10/12)*'Monthly Avg Balance'!AD10/SUM('Monthly Avg Balance'!AC10:'Monthly Avg Balance'!AE10)) -> 274.55895 | AE10: =IF(SUM('Monthly Avg Balance'!AC10:'Monthly Avg Balance'!AE10)=0,"",'Monthly Avg Balance'!AE10*Rate!K10/12+('Net Interest Income'!K10-SUM('Monthly Avg Balance'!AC10:'Monthly Avg Balance'!AE10)*Rate!K10/12)*'Monthly Avg Balance'!AE10/SUM('Monthly Avg Balance'!AC10:'Monthly Avg Balance'!AE10)) -> 257.30723 | AF10: ='Monthly Avg Balance'!AF10*'Monthly Rate'!AF10/12 -> 235.25009 | AG10: ='Monthly Avg Balance'!AG10*'Monthly Rate'!AG10/12 -> 231.73803 | AH10: ='Monthly Avg Balance'!AH10*'Monthly Rate'!AH10/12 -> 228.22597 | AI10: ='Monthly Avg Balance'!AI10*'Monthly Rate'!AI10/12 -> 224.71391 | AJ10: ='Monthly Avg Balance'!AJ10*'Monthly Rate'!AJ10/12 -> 221.20185 | AK10: ='Monthly Avg Balance'!AK10*'Monthly Rate'!AK10/12 -> 217.68979 | AL10: ='Monthly Avg Balance'!AL10*'Monthly Rate'!AL10/12 -> 214.17773 | AM10: ='Monthly Avg Balance'!AM10*'Monthly Rate'!AM10/12 -> 210.66567 | ... AQ10: ='Monthly Avg Balance'!AQ10*'Monthly Rate'!AQ10/12 -> 196.61742
A11: Cash equivalents and other | B11: =IF(SUM('Monthly Avg Balance'!B11:'Monthly Avg Balance'!D11)=0,"",'Monthly Avg Balance'!B11*Rate!B11/12+('Net Interest Income'!B11-SUM('Monthly Avg Balance'!B11:'Monthly Avg Balance'!D11)*Rate!B11/12)*'Monthly Avg Balance'!B11/SUM('Monthly Avg Balance'!B11:'Monthly Avg Balance'!D11)) -> 121.26511 | C11: =IF(SUM('Monthly Avg Balance'!B11:'Monthly Avg Balance'!D11)=0,"",'Monthly Avg Balance'!C11*Rate!B11/12+('Net Interest Income'!B11-SUM('Monthly Avg Balance'!B11:'Monthly Avg Balance'!D11)*Rate!B11/12)*'Monthly Avg Balance'!C11/SUM('Monthly Avg Balance'!B11:'Monthly Avg Balance'!D11)) -> 133.61982 | D11: =IF(SUM('Monthly Avg Balance'!B11:'Monthly Avg Balance'!D11)=0,"",'Monthly Avg Balance'!D11*Rate!B11/12+('Net Interest Income'!B11-SUM('Monthly Avg Balance'!B11:'Monthly Avg Balance'!D11)*Rate!B11/12)*'Monthly Avg Balance'!D11/SUM('Monthly Avg Balance'!B11:'Monthly Avg Balance'!D11)) -> 161.11507 | E11: =IF(SUM('Monthly Avg Balance'!E11:'Monthly Avg Balance'!G11)=0,"",'Monthly Avg Balance'!E11*Rate!C11/12+('Net Interest Income'!C11-SUM('Monthly Avg Balance'!E11:'Monthly Avg Balance'!G11)*Rate!C11/12)*'Monthly Avg Balance'!E11/SUM('Monthly Avg Balance'!E11:'Monthly Avg Balance'!G11)) -> 171.70025 | F11: =IF(SUM('Monthly Avg Balance'!E11:'Monthly Avg Balance'!G11)=0,"",'Monthly Avg Balance'!F11*Rate!C11/12+('Net Interest Income'!C11-SUM('Monthly Avg Balance'!E11:'Monthly Avg Balance'!G11)*Rate!C11/12)*'Monthly Avg Balance'!F11/SUM('Monthly Avg Balance'!E11:'Monthly Avg Balance'!G11)) -> 140.53586 | G11: =IF(SUM('Monthly Avg Balance'!E11:'Monthly Avg Balance'!G11)=0,"",'Monthly Avg Balance'!G11*Rate!C11/12+('Net Interest Income'!C11-SUM('Monthly Avg Balance'!E11:'Monthly Avg Balance'!G11)*Rate!C11/12)*'Monthly Avg Balance'!G11/SUM('Monthly Avg Balance'!E11:'Monthly Avg Balance'!G11)) -> 157.76389 | H11: =IF(SUM('Monthly Avg Balance'!H11:'Monthly Avg Balance'!J11)=0,"",'Monthly Avg Balance'!H11*Rate!D11/12+('Net Interest Income'!D11-SUM('Monthly Avg Balance'!H11:'Monthly Avg Balance'!J11)*Rate!D11/12)*'Monthly Avg Balance'!H11/SUM('Monthly Avg Balance'!H11:'Monthly Avg Balance'!J11)) -> 180.68936 | I11: =IF(SUM('Monthly Avg Balance'!H11:'Monthly Avg Balance'!J11)=0,"",'Monthly Avg Balance'!I11*Rate!D11/12+('Net Interest Income'!D11-SUM('Monthly Avg Balance'!H11:'Monthly Avg Balance'!J11)*Rate!D11/12)*'Monthly Avg Balance'!I11/SUM('Monthly Avg Balance'!H11:'Monthly Avg Balance'!J11)) -> 179.08774 | J11: =IF(SUM('Monthly Avg Balance'!H11:'Monthly Avg Balance'!J11)=0,"",'Monthly Avg Balance'!J11*Rate!D11/12+('Net Interest Income'!D11-SUM('Monthly Avg Balance'!H11:'Monthly Avg Balance'!J11)*Rate!D11/12)*'Monthly Avg Balance'!J11/SUM('Monthly Avg Balance'!H11:'Monthly Avg Balance'!J11)) -> 190.2229 | K11: =IF(SUM('Monthly Avg Balance'!K11:'Monthly Avg Balance'!M11)=0,"",'Monthly Avg Balance'!K11*Rate!E11/12+('Net Interest Income'!E11-SUM('Monthly Avg Balance'!K11:'Monthly Avg Balance'!M11)*Rate!E11/12)*'Monthly Avg Balance'!K11/SUM('Monthly Avg Balance'!K11:'Monthly Avg Balance'!M11)) -> 187.26334 | L11: =IF(SUM('Monthly Avg Balance'!K11:'Monthly Avg Balance'!M11)=0,"",'Monthly Avg Balance'!L11*Rate!E11/12+('Net Interest Income'!E11-SUM('Monthly Avg Balance'!K11:'Monthly Avg Balance'!M11)*Rate!E11/12)*'Monthly Avg Balance'!L11/SUM('Monthly Avg Balance'!K11:'Monthly Avg Balance'!M11)) -> 172.06219 | M11: =IF(SUM('Monthly Avg Balance'!K11:'Monthly Avg Balance'!M11)=0,"",'Monthly Avg Balance'!M11*Rate!E11/12+('Net Interest Income'!E11-SUM('Monthly Avg Balance'!K11:'Monthly Avg Balance'!M11)*Rate!E11/12)*'Monthly Avg Balance'!M11/SUM('Monthly Avg Balance'!K11:'Monthly Avg Balance'!M11)) -> 182.67448 | N11: =IF(SUM('Monthly Avg Balance'!N11:'Monthly Avg Balance'!P11)=0,"",'Monthly Avg Balance'!N11*Rate!F11/12+('Net Interest Income'!F11-SUM('Monthly Avg Balance'!N11:'Monthly Avg Balance'!P11)*Rate!F11/12)*'Monthly Avg Balance'!N11/SUM('Monthly Avg Balance'!N11:'Monthly Avg Balance'!P11)) -> 184.34896 | O11: =IF(SUM('Monthly Avg Balance'!N11:'Monthly Avg Balance'!P11)=0,"",'Monthly Avg Balance'!O11*Rate!F11/12+('Net Interest Income'!F11-SUM('Monthly Avg Balance'!N11:'Monthly Avg Balance'!P11)*Rate!F11/12)*'Monthly Avg Balance'!O11/SUM('Monthly Avg Balance'!N11:'Monthly Avg Balance'!P11)) -> 178.12346 | P11: =IF(SUM('Monthly Avg Balance'!N11:'Monthly Avg Balance'!P11)=0,"",'Monthly Avg Balance'!P11*Rate!F11/12+('Net Interest Income'!F11-SUM('Monthly Avg Balance'!N11:'Monthly Avg Balance'!P11)*Rate!F11/12)*'Monthly Avg Balance'!P11/SUM('Monthly Avg Balance'!N11:'Monthly Avg Balance'!P11)) -> 207.52759 | Q11: =IF(SUM('Monthly Avg Balance'!Q11:'Monthly Avg Balance'!S11)=0,"",'Monthly Avg Balance'!Q11*Rate!G11/12+('Net Interest Income'!G11-SUM('Monthly Avg Balance'!Q11:'Monthly Avg Balance'!S11)*Rate!G11/12)*'Monthly Avg Balance'!Q11/SUM('Monthly Avg Balance'!Q11:'Monthly Avg Balance'!S11)) -> 207.10325 | R11: =IF(SUM('Monthly Avg Balance'!Q11:'Monthly Avg Balance'!S11)=0,"",'Monthly Avg Balance'!R11*Rate!G11/12+('Net Interest Income'!G11-SUM('Monthly Avg Balance'!Q11:'Monthly Avg Balance'!S11)*Rate!G11/12)*'Monthly Avg Balance'!R11/SUM('Monthly Avg Balance'!Q11:'Monthly Avg Balance'!S11)) -> 183.62762 | S11: =IF(SUM('Monthly Avg Balance'!Q11:'Monthly Avg Balance'!S11)=0,"",'Monthly Avg Balance'!S11*Rate!G11/12+('Net Interest Income'!G11-SUM('Monthly Avg Balance'!Q11:'Monthly Avg Balance'!S11)*Rate!G11/12)*'Monthly Avg Balance'!S11/SUM('Monthly Avg Balance'!Q11:'Monthly Avg Balance'!S11)) -> 196.26914 | T11: =IF(SUM('Monthly Avg Balance'!T11:'Monthly Avg Balance'!V11)=0,"",'Monthly Avg Balance'!T11*Rate!H11/12+('Net Interest Income'!H11-SUM('Monthly Avg Balance'!T11:'Monthly Avg Balance'!V11)*Rate!H11/12)*'Monthly Avg Balance'!T11/SUM('Monthly Avg Balance'!T11:'Monthly Avg Balance'!V11)) -> 195.91501 | U11: =IF(SUM('Monthly Avg Balance'!T11:'Monthly Avg Balance'!V11)=0,"",'Monthly Avg Balance'!U11*Rate!H11/12+('Net Interest Income'!H11-SUM('Monthly Avg Balance'!T11:'Monthly Avg Balance'!V11)*Rate!H11/12)*'Monthly Avg Balance'!U11/SUM('Monthly Avg Balance'!T11:'Monthly Avg Balance'!V11)) -> 182.62211 | V11: =IF(SUM('Monthly Avg Balance'!T11:'Monthly Avg Balance'!V11)=0,"",'Monthly Avg Balance'!V11*Rate!H11/12+('Net Interest Income'!H11-SUM('Monthly Avg Balance'!T11:'Monthly Avg Balance'!V11)*Rate!H11/12)*'Monthly Avg Balance'!V11/SUM('Monthly Avg Balance'!T11:'Monthly Avg Balance'!V11)) -> 201.46289 | W11: =IF(SUM('Monthly Avg Balance'!W11:'Monthly Avg Balance'!Y11)=0,"",'Monthly Avg Balance'!W11*Rate!I11/12+('Net Interest Income'!I11-SUM('Monthly Avg Balance'!W11:'Monthly Avg Balance'!Y11)*Rate!I11/12)*'Monthly Avg Balance'!W11/SUM('Monthly Avg Balance'!W11:'Monthly Avg Balance'!Y11)) -> 185.08686 | X11: =IF(SUM('Monthly Avg Balance'!W11:'Monthly Avg Balance'!Y11)=0,"",'Monthly Avg Balance'!X11*Rate!I11/12+('Net Interest Income'!I11-SUM('Monthly Avg Balance'!W11:'Monthly Avg Balance'!Y11)*Rate!I11/12)*'Monthly Avg Balance'!X11/SUM('Monthly Avg Balance'!W11:'Monthly Avg Balance'!Y11)) -> 175.31452 | Y11: =IF(SUM('Monthly Avg Balance'!W11:'Monthly Avg Balance'!Y11)=0,"",'Monthly Avg Balance'!Y11*Rate!I11/12+('Net Interest Income'!I11-SUM('Monthly Avg Balance'!W11:'Monthly Avg Balance'!Y11)*Rate!I11/12)*'Monthly Avg Balance'!Y11/SUM('Monthly Avg Balance'!W11:'Monthly Avg Balance'!Y11)) -> 169.59862 | Z11: =IF(SUM('Monthly Avg Balance'!Z11:'Monthly Avg Balance'!AB11)=0,"",'Monthly Avg Balance'!Z11*Rate!J11/12+('Net Interest Income'!J11-SUM('Monthly Avg Balance'!Z11:'Monthly Avg Balance'!AB11)*Rate!J11/12)*'Monthly Avg Balance'!Z11/SUM('Monthly Avg Balance'!Z11:'Monthly Avg Balance'!AB11)) -> 156.43999 | AA11: =IF(SUM('Monthly Avg Balance'!Z11:'Monthly Avg Balance'!AB11)=0,"",'Monthly Avg Balance'!AA11*Rate!J11/12+('Net Interest Income'!J11-SUM('Monthly Avg Balance'!Z11:'Monthly Avg Balance'!AB11)*Rate!J11/12)*'Monthly Avg Balance'!AA11/SUM('Monthly Avg Balance'!Z11:'Monthly Avg Balance'!AB11)) -> 166.00538 | AB11: =IF(SUM('Monthly Avg Balance'!Z11:'Monthly Avg Balance'!AB11)=0,"",'Monthly Avg Balance'!AB11*Rate!J11/12+('Net Interest Income'!J11-SUM('Monthly Avg Balance'!Z11:'Monthly Avg Balance'!AB11)*Rate!J11/12)*'Monthly Avg Balance'!AB11/SUM('Monthly Avg Balance'!Z11:'Monthly Avg Balance'!AB11)) -> 168.55463 | AC11: =IF(SUM('Monthly Avg Balance'!AC11:'Monthly Avg Balance'!AE11)=0,"",'Monthly Avg Balance'!AC11*Rate!K11/12+('Net Interest Income'!K11-SUM('Monthly Avg Balance'!AC11:'Monthly Avg Balance'!AE11)*Rate!K11/12)*'Monthly Avg Balance'!AC11/SUM('Monthly Avg Balance'!AC11:'Monthly Avg Balance'!AE11)) -> 184.90701 | AD11: =IF(SUM('Monthly Avg Balance'!AC11:'Monthly Avg Balance'!AE11)=0,"",'Monthly Avg Balance'!AD11*Rate!K11/12+('Net Interest Income'!K11-SUM('Monthly Avg Balance'!AC11:'Monthly Avg Balance'!AE11)*Rate!K11/12)*'Monthly Avg Balance'!AD11/SUM('Monthly Avg Balance'!AC11:'Monthly Avg Balance'!AE11)) -> 193.56056 | AE11: =IF(SUM('Monthly Avg Balance'!AC11:'Monthly Avg Balance'!AE11)=0,"",'Monthly Avg Balance'!AE11*Rate!K11/12+('Net Interest Income'!K11-SUM('Monthly Avg Balance'!AC11:'Monthly Avg Balance'!AE11)*Rate!K11/12)*'Monthly Avg Balance'!AE11/SUM('Monthly Avg Balance'!AC11:'Monthly Avg Balance'!AE11)) -> 216.53243 | AF11: ='Monthly Avg Balance'!AF11*'Monthly Rate'!AF11/12 -> 230.33469 | AG11: ='Monthly Avg Balance'!AG11*'Monthly Rate'!AG11/12 -> 229.09072 | AH11: ='Monthly Avg Balance'!AH11*'Monthly Rate'!AH11/12 -> 227.84632 | AI11: ='Monthly Avg Balance'!AI11*'Monthly Rate'!AI11/12 -> 226.60148 | AJ11: ='Monthly Avg Balance'!AJ11*'Monthly Rate'!AJ11/12 -> 225.35621 | AK11: ='Monthly Avg Balance'!AK11*'Monthly Rate'!AK11/12 -> 224.11049 | AL11: ='Monthly Avg Balance'!AL11*'Monthly Rate'!AL11/12 -> 222.86434 | AM11: ='Monthly Avg Balance'!AM11*'Monthly Rate'!AM11/12 -> 221.61776 | ... AQ11: ='Monthly Avg Balance'!AQ11*'Monthly Rate'!AQ11/12 -> 216.62704
A12: Total interest-earning assets | B12: =SUM(B9:B11) -> 3233.9318 | C12: =SUM(C9:C11) -> 3246.2865 | D12: =SUM(D9:D11) -> 3273.7817 | E12: =SUM(E9:E11) -> 3389.2489 | F12: =SUM(F9:F11) -> 3372.5359 | G12: =SUM(G9:G11) -> 3404.2153 | H12: =SUM(H9:H11) -> 3618.9242 | I12: =SUM(I9:I11) -> 3620.0877 | ... AQ12: =SUM(AQ9:AQ11) -> 5207.1883
A14: INTEREST-BEARING LIABILITIES
A15: Interest-bearing deposits | B15: =IF(SUM('Monthly Avg Balance'!B15:'Monthly Avg Balance'!D15)=0,"",'Monthly Avg Balance'!B15*Rate!B15/12+('Net Interest Income'!B15-SUM('Monthly Avg Balance'!B15:'Monthly Avg Balance'!D15)*Rate!B15/12)*'Monthly Avg Balance'!B15/SUM('Monthly Avg Balance'!B15:'Monthly Avg Balance'!D15)) -> 618.66667 | C15: =IF(SUM('Monthly Avg Balance'!B15:'Monthly Avg Balance'!D15)=0,"",'Monthly Avg Balance'!C15*Rate!B15/12+('Net Interest Income'!B15-SUM('Monthly Avg Balance'!B15:'Monthly Avg Balance'!D15)*Rate!B15/12)*'Monthly Avg Balance'!C15/SUM('Monthly Avg Balance'!B15:'Monthly Avg Balance'!D15)) -> 618.66667 | D15: =IF(SUM('Monthly Avg Balance'!B15:'Monthly Avg Balance'!D15)=0,"",'Monthly Avg Balance'!D15*Rate!B15/12+('Net Interest Income'!B15-SUM('Monthly Avg Balance'!B15:'Monthly Avg Balance'!D15)*Rate!B15/12)*'Monthly Avg Balance'!D15/SUM('Monthly Avg Balance'!B15:'Monthly Avg Balance'!D15)) -> 618.66667 | E15: =IF(SUM('Monthly Avg Balance'!E15:'Monthly Avg Balance'!G15)=0,"",'Monthly Avg Balance'!E15*Rate!C15/12+('Net Interest Income'!C15-SUM('Monthly Avg Balance'!E15:'Monthly Avg Balance'!G15)*Rate!C15/12)*'Monthly Avg Balance'!E15/SUM('Monthly Avg Balance'!E15:'Monthly Avg Balance'!G15)) -> 751.86091 | F15: =IF(SUM('Monthly Avg Balance'!E15:'Monthly Avg Balance'!G15)=0,"",'Monthly Avg Balance'!F15*Rate!C15/12+('Net Interest Income'!C15-SUM('Monthly Avg Balance'!E15:'Monthly Avg Balance'!G15)*Rate!C15/12)*'Monthly Avg Balance'!F15/SUM('Monthly Avg Balance'!E15:'Monthly Avg Balance'!G15)) -> 759 | G15: =IF(SUM('Monthly Avg Balance'!E15:'Monthly Avg Balance'!G15)=0,"",'Monthly Avg Balance'!G15*Rate!C15/12+('Net Interest Income'!C15-SUM('Monthly Avg Balance'!E15:'Monthly Avg Balance'!G15)*Rate!C15/12)*'Monthly Avg Balance'!G15/SUM('Monthly Avg Balance'!E15:'Monthly Avg Balance'!G15)) -> 766.13909 | H15: =IF(SUM('Monthly Avg Balance'!H15:'Monthly Avg Balance'!J15)=0,"",'Monthly Avg Balance'!H15*Rate!D15/12+('Net Interest Income'!D15-SUM('Monthly Avg Balance'!H15:'Monthly Avg Balance'!J15)*Rate!D15/12)*'Monthly Avg Balance'!H15/SUM('Monthly Avg Balance'!H15:'Monthly Avg Balance'!J15)) -> 873.25985 | I15: =IF(SUM('Monthly Avg Balance'!H15:'Monthly Avg Balance'!J15)=0,"",'Monthly Avg Balance'!I15*Rate!D15/12+('Net Interest Income'!D15-SUM('Monthly Avg Balance'!H15:'Monthly Avg Balance'!J15)*Rate!D15/12)*'Monthly Avg Balance'!I15/SUM('Monthly Avg Balance'!H15:'Monthly Avg Balance'!J15)) -> 870.33333 | J15: =IF(SUM('Monthly Avg Balance'!H15:'Monthly Avg Balance'!J15)=0,"",'Monthly Avg Balance'!J15*Rate!D15/12+('Net Interest Income'!D15-SUM('Monthly Avg Balance'!H15:'Monthly Avg Balance'!J15)*Rate!D15/12)*'Monthly Avg Balance'!J15/SUM('Monthly Avg Balance'!H15:'Monthly Avg Balance'!J15)) -> 867.40681 | K15: =IF(SUM('Monthly Avg Balance'!K15:'Monthly Avg Balance'!M15)=0,"",'Monthly Avg Balance'!K15*Rate!E15/12+('Net Interest Income'!E15-SUM('Monthly Avg Balance'!K15:'Monthly Avg Balance'!M15)*Rate!E15/12)*'Monthly Avg Balance'!K15/SUM('Monthly Avg Balance'!K15:'Monthly Avg Balance'!M15)) -> 909.81844 | L15: =IF(SUM('Monthly Avg Balance'!K15:'Monthly Avg Balance'!M15)=0,"",'Monthly Avg Balance'!L15*Rate!E15/12+('Net Interest Income'!E15-SUM('Monthly Avg Balance'!K15:'Monthly Avg Balance'!M15)*Rate!E15/12)*'Monthly Avg Balance'!L15/SUM('Monthly Avg Balance'!K15:'Monthly Avg Balance'!M15)) -> 913.89906 | M15: =IF(SUM('Monthly Avg Balance'!K15:'Monthly Avg Balance'!M15)=0,"",'Monthly Avg Balance'!M15*Rate!E15/12+('Net Interest Income'!E15-SUM('Monthly Avg Balance'!K15:'Monthly Avg Balance'!M15)*Rate!E15/12)*'Monthly Avg Balance'!M15/SUM('Monthly Avg Balance'!K15:'Monthly Avg Balance'!M15)) -> 921.2825 | N15: =IF(SUM('Monthly Avg Balance'!N15:'Monthly Avg Balance'!P15)=0,"",'Monthly Avg Balance'!N15*Rate!F15/12+('Net Interest Income'!F15-SUM('Monthly Avg Balance'!N15:'Monthly Avg Balance'!P15)*Rate!F15/12)*'Monthly Avg Balance'!N15/SUM('Monthly Avg Balance'!N15:'Monthly Avg Balance'!P15)) -> 937.78382 | O15: =IF(SUM('Monthly Avg Balance'!N15:'Monthly Avg Balance'!P15)=0,"",'Monthly Avg Balance'!O15*Rate!F15/12+('Net Interest Income'!F15-SUM('Monthly Avg Balance'!N15:'Monthly Avg Balance'!P15)*Rate!F15/12)*'Monthly Avg Balance'!O15/SUM('Monthly Avg Balance'!N15:'Monthly Avg Balance'!P15)) -> 930.59723 | P15: =IF(SUM('Monthly Avg Balance'!N15:'Monthly Avg Balance'!P15)=0,"",'Monthly Avg Balance'!P15*Rate!F15/12+('Net Interest Income'!F15-SUM('Monthly Avg Balance'!N15:'Monthly Avg Balance'!P15)*Rate!F15/12)*'Monthly Avg Balance'!P15/SUM('Monthly Avg Balance'!N15:'Monthly Avg Balance'!P15)) -> 943.61895 | Q15: =IF(SUM('Monthly Avg Balance'!Q15:'Monthly Avg Balance'!S15)=0,"",'Monthly Avg Balance'!Q15*Rate!G15/12+('Net Interest Income'!G15-SUM('Monthly Avg Balance'!Q15:'Monthly Avg Balance'!S15)*Rate!G15/12)*'Monthly Avg Balance'!Q15/SUM('Monthly Avg Balance'!Q15:'Monthly Avg Balance'!S15)) -> 958.22651 | R15: =IF(SUM('Monthly Avg Balance'!Q15:'Monthly Avg Balance'!S15)=0,"",'Monthly Avg Balance'!R15*Rate!G15/12+('Net Interest Income'!G15-SUM('Monthly Avg Balance'!Q15:'Monthly Avg Balance'!S15)*Rate!G15/12)*'Monthly Avg Balance'!R15/SUM('Monthly Avg Balance'!Q15:'Monthly Avg Balance'!S15)) -> 955.39591 | S15: =IF(SUM('Monthly Avg Balance'!Q15:'Monthly Avg Balance'!S15)=0,"",'Monthly Avg Balance'!S15*Rate!G15/12+('Net Interest Income'!G15-SUM('Monthly Avg Balance'!Q15:'Monthly Avg Balance'!S15)*Rate!G15/12)*'Monthly Avg Balance'!S15/SUM('Monthly Avg Balance'!Q15:'Monthly Avg Balance'!S15)) -> 960.37758 | T15: =IF(SUM('Monthly Avg Balance'!T15:'Monthly Avg Balance'!V15)=0,"",'Monthly Avg Balance'!T15*Rate!H15/12+('Net Interest Income'!H15-SUM('Monthly Avg Balance'!T15:'Monthly Avg Balance'!V15)*Rate!H15/12)*'Monthly Avg Balance'!T15/SUM('Monthly Avg Balance'!T15:'Monthly Avg Balance'!V15)) -> 980.17224 | U15: =IF(SUM('Monthly Avg Balance'!T15:'Monthly Avg Balance'!V15)=0,"",'Monthly Avg Balance'!U15*Rate!H15/12+('Net Interest Income'!H15-SUM('Monthly Avg Balance'!T15:'Monthly Avg Balance'!V15)*Rate!H15/12)*'Monthly Avg Balance'!U15/SUM('Monthly Avg Balance'!T15:'Monthly Avg Balance'!V15)) -> 978.96862 | V15: =IF(SUM('Monthly Avg Balance'!T15:'Monthly Avg Balance'!V15)=0,"",'Monthly Avg Balance'!V15*Rate!H15/12+('Net Interest Income'!H15-SUM('Monthly Avg Balance'!T15:'Monthly Avg Balance'!V15)*Rate!H15/12)*'Monthly Avg Balance'!V15/SUM('Monthly Avg Balance'!T15:'Monthly Avg Balance'!V15)) -> 985.85914 | W15: =IF(SUM('Monthly Avg Balance'!W15:'Monthly Avg Balance'!Y15)=0,"",'Monthly Avg Balance'!W15*Rate!I15/12+('Net Interest Income'!I15-SUM('Monthly Avg Balance'!W15:'Monthly Avg Balance'!Y15)*Rate!I15/12)*'Monthly Avg Balance'!W15/SUM('Monthly Avg Balance'!W15:'Monthly Avg Balance'!Y15)) -> 945.33539 | X15: =IF(SUM('Monthly Avg Balance'!W15:'Monthly Avg Balance'!Y15)=0,"",'Monthly Avg Balance'!X15*Rate!I15/12+('Net Interest Income'!I15-SUM('Monthly Avg Balance'!W15:'Monthly Avg Balance'!Y15)*Rate!I15/12)*'Monthly Avg Balance'!X15/SUM('Monthly Avg Balance'!W15:'Monthly Avg Balance'!Y15)) -> 953.42639 | Y15: =IF(SUM('Monthly Avg Balance'!W15:'Monthly Avg Balance'!Y15)=0,"",'Monthly Avg Balance'!Y15*Rate!I15/12+('Net Interest Income'!I15-SUM('Monthly Avg Balance'!W15:'Monthly Avg Balance'!Y15)*Rate!I15/12)*'Monthly Avg Balance'!Y15/SUM('Monthly Avg Balance'!W15:'Monthly Avg Balance'!Y15)) -> 963.23822 | Z15: =IF(SUM('Monthly Avg Balance'!Z15:'Monthly Avg Balance'!AB15)=0,"",'Monthly Avg Balance'!Z15*Rate!J15/12+('Net Interest Income'!J15-SUM('Monthly Avg Balance'!Z15:'Monthly Avg Balance'!AB15)*Rate!J15/12)*'Monthly Avg Balance'!Z15/SUM('Monthly Avg Balance'!Z15:'Monthly Avg Balance'!AB15)) -> 901.92147 | AA15: =IF(SUM('Monthly Avg Balance'!Z15:'Monthly Avg Balance'!AB15)=0,"",'Monthly Avg Balance'!AA15*Rate!J15/12+('Net Interest Income'!J15-SUM('Monthly Avg Balance'!Z15:'Monthly Avg Balance'!AB15)*Rate!J15/12)*'Monthly Avg Balance'!AA15/SUM('Monthly Avg Balance'!Z15:'Monthly Avg Balance'!AB15)) -> 903.32958 | AB15: =IF(SUM('Monthly Avg Balance'!Z15:'Monthly Avg Balance'!AB15)=0,"",'Monthly Avg Balance'!AB15*Rate!J15/12+('Net Interest Income'!J15-SUM('Monthly Avg Balance'!Z15:'Monthly Avg Balance'!AB15)*Rate!J15/12)*'Monthly Avg Balance'!AB15/SUM('Monthly Avg Balance'!Z15:'Monthly Avg Balance'!AB15)) -> 909.74895 | AC15: =IF(SUM('Monthly Avg Balance'!AC15:'Monthly Avg Balance'!AE15)=0,"",'Monthly Avg Balance'!AC15*Rate!K15/12+('Net Interest Income'!K15-SUM('Monthly Avg Balance'!AC15:'Monthly Avg Balance'!AE15)*Rate!K15/12)*'Monthly Avg Balance'!AC15/SUM('Monthly Avg Balance'!AC15:'Monthly Avg Balance'!AE15)) -> 953.95129 | AD15: =IF(SUM('Monthly Avg Balance'!AC15:'Monthly Avg Balance'!AE15)=0,"",'Monthly Avg Balance'!AD15*Rate!K15/12+('Net Interest Income'!K15-SUM('Monthly Avg Balance'!AC15:'Monthly Avg Balance'!AE15)*Rate!K15/12)*'Monthly Avg Balance'!AD15/SUM('Monthly Avg Balance'!AC15:'Monthly Avg Balance'!AE15)) -> 1033.7876 | AE15: =IF(SUM('Monthly Avg Balance'!AC15:'Monthly Avg Balance'!AE15)=0,"",'Monthly Avg Balance'!AE15*Rate!K15/12+('Net Interest Income'!K15-SUM('Monthly Avg Balance'!AC15:'Monthly Avg Balance'!AE15)*Rate!K15/12)*'Monthly Avg Balance'!AE15/SUM('Monthly Avg Balance'!AC15:'Monthly Avg Balance'!AE15)) -> 1132.2611 | AF15: ='Monthly Avg Balance'!AF15*'Monthly Rate'!AF15/12 -> 1179.4091 | AG15: ='Monthly Avg Balance'!AG15*'Monthly Rate'!AG15/12 -> 1172.7598 | AH15: ='Monthly Avg Balance'!AH15*'Monthly Rate'!AH15/12 -> 1166.1081 | AI15: ='Monthly Avg Balance'!AI15*'Monthly Rate'!AI15/12 -> 1159.4542 | AJ15: ='Monthly Avg Balance'!AJ15*'Monthly Rate'!AJ15/12 -> 1152.7978 | AK15: ='Monthly Avg Balance'!AK15*'Monthly Rate'!AK15/12 -> 1146.1392 | AL15: ='Monthly Avg Balance'!AL15*'Monthly Rate'!AL15/12 -> 1139.4782 | AM15: ='Monthly Avg Balance'!AM15*'Monthly Rate'!AM15/12 -> 1132.8149 | ... AQ15: ='Monthly Avg Balance'!AQ15*'Monthly Rate'!AQ15/12 -> 1106.1383
A16: Securitized debt obligations | B16: =IF(SUM('Monthly Avg Balance'!B16:'Monthly Avg Balance'!D16)=0,"",'Monthly Avg Balance'!B16*Rate!B16/12+('Net Interest Income'!B16-SUM('Monthly Avg Balance'!B16:'Monthly Avg Balance'!D16)*Rate!B16/12)*'Monthly Avg Balance'!B16/SUM('Monthly Avg Balance'!B16:'Monthly Avg Balance'!D16)) -> 70.333333 | C16: =IF(SUM('Monthly Avg Balance'!B16:'Monthly Avg Balance'!D16)=0,"",'Monthly Avg Balance'!C16*Rate!B16/12+('Net Interest Income'!B16-SUM('Monthly Avg Balance'!B16:'Monthly Avg Balance'!D16)*Rate!B16/12)*'Monthly Avg Balance'!C16/SUM('Monthly Avg Balance'!B16:'Monthly Avg Balance'!D16)) -> 70.333333 | D16: =IF(SUM('Monthly Avg Balance'!B16:'Monthly Avg Balance'!D16)=0,"",'Monthly Avg Balance'!D16*Rate!B16/12+('Net Interest Income'!B16-SUM('Monthly Avg Balance'!B16:'Monthly Avg Balance'!D16)*Rate!B16/12)*'Monthly Avg Balance'!D16/SUM('Monthly Avg Balance'!B16:'Monthly Avg Balance'!D16)) -> 70.333333 | E16: =IF(SUM('Monthly Avg Balance'!E16:'Monthly Avg Balance'!G16)=0,"",'Monthly Avg Balance'!E16*Rate!C16/12+('Net Interest Income'!C16-SUM('Monthly Avg Balance'!E16:'Monthly Avg Balance'!G16)*Rate!C16/12)*'Monthly Avg Balance'!E16/SUM('Monthly Avg Balance'!E16:'Monthly Avg Balance'!G16)) -> 77.132082 | F16: =IF(SUM('Monthly Avg Balance'!E16:'Monthly Avg Balance'!G16)=0,"",'Monthly Avg Balance'!F16*Rate!C16/12+('Net Interest Income'!C16-SUM('Monthly Avg Balance'!E16:'Monthly Avg Balance'!G16)*Rate!C16/12)*'Monthly Avg Balance'!F16/SUM('Monthly Avg Balance'!E16:'Monthly Avg Balance'!G16)) -> 78.666667 | G16: =IF(SUM('Monthly Avg Balance'!E16:'Monthly Avg Balance'!G16)=0,"",'Monthly Avg Balance'!G16*Rate!C16/12+('Net Interest Income'!C16-SUM('Monthly Avg Balance'!E16:'Monthly Avg Balance'!G16)*Rate!C16/12)*'Monthly Avg Balance'!G16/SUM('Monthly Avg Balance'!E16:'Monthly Avg Balance'!G16)) -> 80.201252 | H16: =IF(SUM('Monthly Avg Balance'!H16:'Monthly Avg Balance'!J16)=0,"",'Monthly Avg Balance'!H16*Rate!D16/12+('Net Interest Income'!D16-SUM('Monthly Avg Balance'!H16:'Monthly Avg Balance'!J16)*Rate!D16/12)*'Monthly Avg Balance'!H16/SUM('Monthly Avg Balance'!H16:'Monthly Avg Balance'!J16)) -> 85.012805 | I16: =IF(SUM('Monthly Avg Balance'!H16:'Monthly Avg Balance'!J16)=0,"",'Monthly Avg Balance'!I16*Rate!D16/12+('Net Interest Income'!D16-SUM('Monthly Avg Balance'!H16:'Monthly Avg Balance'!J16)*Rate!D16/12)*'Monthly Avg Balance'!I16/SUM('Monthly Avg Balance'!H16:'Monthly Avg Balance'!J16)) -> 83 | J16: =IF(SUM('Monthly Avg Balance'!H16:'Monthly Avg Balance'!J16)=0,"",'Monthly Avg Balance'!J16*Rate!D16/12+('Net Interest Income'!D16-SUM('Monthly Avg Balance'!H16:'Monthly Avg Balance'!J16)*Rate!D16/12)*'Monthly Avg Balance'!J16/SUM('Monthly Avg Balance'!H16:'Monthly Avg Balance'!J16)) -> 80.987195 | K16: =IF(SUM('Monthly Avg Balance'!K16:'Monthly Avg Balance'!M16)=0,"",'Monthly Avg Balance'!K16*Rate!E16/12+('Net Interest Income'!E16-SUM('Monthly Avg Balance'!K16:'Monthly Avg Balance'!M16)*Rate!E16/12)*'Monthly Avg Balance'!K16/SUM('Monthly Avg Balance'!K16:'Monthly Avg Balance'!M16)) -> 85.595587 | L16: =IF(SUM('Monthly Avg Balance'!K16:'Monthly Avg Balance'!M16)=0,"",'Monthly Avg Balance'!L16*Rate!E16/12+('Net Interest Income'!E16-SUM('Monthly Avg Balance'!K16:'Monthly Avg Balance'!M16)*Rate!E16/12)*'Monthly Avg Balance'!L16/SUM('Monthly Avg Balance'!K16:'Monthly Avg Balance'!M16)) -> 90.042631 | M16: =IF(SUM('Monthly Avg Balance'!K16:'Monthly Avg Balance'!M16)=0,"",'Monthly Avg Balance'!M16*Rate!E16/12+('Net Interest Income'!E16-SUM('Monthly Avg Balance'!K16:'Monthly Avg Balance'!M16)*Rate!E16/12)*'Monthly Avg Balance'!M16/SUM('Monthly Avg Balance'!K16:'Monthly Avg Balance'!M16)) -> 87.361782 | N16: =IF(SUM('Monthly Avg Balance'!N16:'Monthly Avg Balance'!P16)=0,"",'Monthly Avg Balance'!N16*Rate!F16/12+('Net Interest Income'!F16-SUM('Monthly Avg Balance'!N16:'Monthly Avg Balance'!P16)*Rate!F16/12)*'Monthly Avg Balance'!N16/SUM('Monthly Avg Balance'!N16:'Monthly Avg Balance'!P16)) -> 86.400638 | O16: =IF(SUM('Monthly Avg Balance'!N16:'Monthly Avg Balance'!P16)=0,"",'Monthly Avg Balance'!O16*Rate!F16/12+('Net Interest Income'!F16-SUM('Monthly Avg Balance'!N16:'Monthly Avg Balance'!P16)*Rate!F16/12)*'Monthly Avg Balance'!O16/SUM('Monthly Avg Balance'!N16:'Monthly Avg Balance'!P16)) -> 87.595146 | P16: =IF(SUM('Monthly Avg Balance'!N16:'Monthly Avg Balance'!P16)=0,"",'Monthly Avg Balance'!P16*Rate!F16/12+('Net Interest Income'!F16-SUM('Monthly Avg Balance'!N16:'Monthly Avg Balance'!P16)*Rate!F16/12)*'Monthly Avg Balance'!P16/SUM('Monthly Avg Balance'!N16:'Monthly Avg Balance'!P16)) -> 87.004217 | Q16: =IF(SUM('Monthly Avg Balance'!Q16:'Monthly Avg Balance'!S16)=0,"",'Monthly Avg Balance'!Q16*Rate!G16/12+('Net Interest Income'!G16-SUM('Monthly Avg Balance'!Q16:'Monthly Avg Balance'!S16)*Rate!G16/12)*'Monthly Avg Balance'!Q16/SUM('Monthly Avg Balance'!Q16:'Monthly Avg Balance'!S16)) -> 87.073613 | R16: =IF(SUM('Monthly Avg Balance'!Q16:'Monthly Avg Balance'!S16)=0,"",'Monthly Avg Balance'!R16*Rate!G16/12+('Net Interest Income'!G16-SUM('Monthly Avg Balance'!Q16:'Monthly Avg Balance'!S16)*Rate!G16/12)*'Monthly Avg Balance'!R16/SUM('Monthly Avg Balance'!Q16:'Monthly Avg Balance'!S16)) -> 86.221439 | S16: =IF(SUM('Monthly Avg Balance'!Q16:'Monthly Avg Balance'!S16)=0,"",'Monthly Avg Balance'!S16*Rate!G16/12+('Net Interest Income'!G16-SUM('Monthly Avg Balance'!Q16:'Monthly Avg Balance'!S16)*Rate!G16/12)*'Monthly Avg Balance'!S16/SUM('Monthly Avg Balance'!Q16:'Monthly Avg Balance'!S16)) -> 84.704947 | T16: =IF(SUM('Monthly Avg Balance'!T16:'Monthly Avg Balance'!V16)=0,"",'Monthly Avg Balance'!T16*Rate!H16/12+('Net Interest Income'!H16-SUM('Monthly Avg Balance'!T16:'Monthly Avg Balance'!V16)*Rate!H16/12)*'Monthly Avg Balance'!T16/SUM('Monthly Avg Balance'!T16:'Monthly Avg Balance'!V16)) -> 80.719752 | U16: =IF(SUM('Monthly Avg Balance'!T16:'Monthly Avg Balance'!V16)=0,"",'Monthly Avg Balance'!U16*Rate!H16/12+('Net Interest Income'!H16-SUM('Monthly Avg Balance'!T16:'Monthly Avg Balance'!V16)*Rate!H16/12)*'Monthly Avg Balance'!U16/SUM('Monthly Avg Balance'!T16:'Monthly Avg Balance'!V16)) -> 75.49375 | V16: =IF(SUM('Monthly Avg Balance'!T16:'Monthly Avg Balance'!V16)=0,"",'Monthly Avg Balance'!V16*Rate!H16/12+('Net Interest Income'!H16-SUM('Monthly Avg Balance'!T16:'Monthly Avg Balance'!V16)*Rate!H16/12)*'Monthly Avg Balance'!V16/SUM('Monthly Avg Balance'!T16:'Monthly Avg Balance'!V16)) -> 77.786499 | W16: =IF(SUM('Monthly Avg Balance'!W16:'Monthly Avg Balance'!Y16)=0,"",'Monthly Avg Balance'!W16*Rate!I16/12+('Net Interest Income'!I16-SUM('Monthly Avg Balance'!W16:'Monthly Avg Balance'!Y16)*Rate!I16/12)*'Monthly Avg Balance'!W16/SUM('Monthly Avg Balance'!W16:'Monthly Avg Balance'!Y16)) -> 71.372727 | X16: =IF(SUM('Monthly Avg Balance'!W16:'Monthly Avg Balance'!Y16)=0,"",'Monthly Avg Balance'!X16*Rate!I16/12+('Net Interest Income'!I16-SUM('Monthly Avg Balance'!W16:'Monthly Avg Balance'!Y16)*Rate!I16/12)*'Monthly Avg Balance'!X16/SUM('Monthly Avg Balance'!W16:'Monthly Avg Balance'!Y16)) -> 66.853309 | Y16: =IF(SUM('Monthly Avg Balance'!W16:'Monthly Avg Balance'!Y16)=0,"",'Monthly Avg Balance'!Y16*Rate!I16/12+('Net Interest Income'!I16-SUM('Monthly Avg Balance'!W16:'Monthly Avg Balance'!Y16)*Rate!I16/12)*'Monthly Avg Balance'!Y16/SUM('Monthly Avg Balance'!W16:'Monthly Avg Balance'!Y16)) -> 66.773964 | Z16: =IF(SUM('Monthly Avg Balance'!Z16:'Monthly Avg Balance'!AB16)=0,"",'Monthly Avg Balance'!Z16*Rate!J16/12+('Net Interest Income'!J16-SUM('Monthly Avg Balance'!Z16:'Monthly Avg Balance'!AB16)*Rate!J16/12)*'Monthly Avg Balance'!Z16/SUM('Monthly Avg Balance'!Z16:'Monthly Avg Balance'!AB16)) -> 61.275687 | AA16: =IF(SUM('Monthly Avg Balance'!Z16:'Monthly Avg Balance'!AB16)=0,"",'Monthly Avg Balance'!AA16*Rate!J16/12+('Net Interest Income'!J16-SUM('Monthly Avg Balance'!Z16:'Monthly Avg Balance'!AB16)*Rate!J16/12)*'Monthly Avg Balance'!AA16/SUM('Monthly Avg Balance'!Z16:'Monthly Avg Balance'!AB16)) -> 58.621584 | AB16: =IF(SUM('Monthly Avg Balance'!Z16:'Monthly Avg Balance'!AB16)=0,"",'Monthly Avg Balance'!AB16*Rate!J16/12+('Net Interest Income'!J16-SUM('Monthly Avg Balance'!Z16:'Monthly Avg Balance'!AB16)*Rate!J16/12)*'Monthly Avg Balance'!AB16/SUM('Monthly Avg Balance'!Z16:'Monthly Avg Balance'!AB16)) -> 56.102729 | AC16: =IF(SUM('Monthly Avg Balance'!AC16:'Monthly Avg Balance'!AE16)=0,"",'Monthly Avg Balance'!AC16*Rate!K16/12+('Net Interest Income'!K16-SUM('Monthly Avg Balance'!AC16:'Monthly Avg Balance'!AE16)*Rate!K16/12)*'Monthly Avg Balance'!AC16/SUM('Monthly Avg Balance'!AC16:'Monthly Avg Balance'!AE16)) -> 53.015295 | AD16: =IF(SUM('Monthly Avg Balance'!AC16:'Monthly Avg Balance'!AE16)=0,"",'Monthly Avg Balance'!AD16*Rate!K16/12+('Net Interest Income'!K16-SUM('Monthly Avg Balance'!AC16:'Monthly Avg Balance'!AE16)*Rate!K16/12)*'Monthly Avg Balance'!AD16/SUM('Monthly Avg Balance'!AC16:'Monthly Avg Balance'!AE16)) -> 52.525602 | AE16: =IF(SUM('Monthly Avg Balance'!AC16:'Monthly Avg Balance'!AE16)=0,"",'Monthly Avg Balance'!AE16*Rate!K16/12+('Net Interest Income'!K16-SUM('Monthly Avg Balance'!AC16:'Monthly Avg Balance'!AE16)*Rate!K16/12)*'Monthly Avg Balance'!AE16/SUM('Monthly Avg Balance'!AC16:'Monthly Avg Balance'!AE16)) -> 58.459103 | AF16: ='Monthly Avg Balance'!AF16*'Monthly Rate'!AF16/12 -> 62.281463 | AG16: ='Monthly Avg Balance'!AG16*'Monthly Rate'!AG16/12 -> 61.380408 | AH16: ='Monthly Avg Balance'!AH16*'Monthly Rate'!AH16/12 -> 60.486806 | AI16: ='Monthly Avg Balance'!AI16*'Monthly Rate'!AI16/12 -> 59.600606 | AJ16: ='Monthly Avg Balance'!AJ16*'Monthly Rate'!AJ16/12 -> 58.721756 | AK16: ='Monthly Avg Balance'!AK16*'Monthly Rate'!AK16/12 -> 57.850205 | AL16: ='Monthly Avg Balance'!AL16*'Monthly Rate'!AL16/12 -> 56.985901 | AM16: ='Monthly Avg Balance'!AM16*'Monthly Rate'!AM16/12 -> 56.128793 | ... AQ16: ='Monthly Avg Balance'!AQ16*'Monthly Rate'!AQ16/12 -> 52.77133
A17: Senior and subordinated notes | B17: =IF(SUM('Monthly Avg Balance'!B17:'Monthly Avg Balance'!D17)=0,"",'Monthly Avg Balance'!B17*Rate!B17/12+('Net Interest Income'!B17-SUM('Monthly Avg Balance'!B17:'Monthly Avg Balance'!D17)*Rate!B17/12)*'Monthly Avg Balance'!B17/SUM('Monthly Avg Balance'!B17:'Monthly Avg Balance'!D17)) -> 163 | C17: =IF(SUM('Monthly Avg Balance'!B17:'Monthly Avg Balance'!D17)=0,"",'Monthly Avg Balance'!C17*Rate!B17/12+('Net Interest Income'!B17-SUM('Monthly Avg Balance'!B17:'Monthly Avg Balance'!D17)*Rate!B17/12)*'Monthly Avg Balance'!C17/SUM('Monthly Avg Balance'!B17:'Monthly Avg Balance'!D17)) -> 163 | D17: =IF(SUM('Monthly Avg Balance'!B17:'Monthly Avg Balance'!D17)=0,"",'Monthly Avg Balance'!D17*Rate!B17/12+('Net Interest Income'!B17-SUM('Monthly Avg Balance'!B17:'Monthly Avg Balance'!D17)*Rate!B17/12)*'Monthly Avg Balance'!D17/SUM('Monthly Avg Balance'!B17:'Monthly Avg Balance'!D17)) -> 163 | E17: =IF(SUM('Monthly Avg Balance'!E17:'Monthly Avg Balance'!G17)=0,"",'Monthly Avg Balance'!E17*Rate!C17/12+('Net Interest Income'!C17-SUM('Monthly Avg Balance'!E17:'Monthly Avg Balance'!G17)*Rate!C17/12)*'Monthly Avg Balance'!E17/SUM('Monthly Avg Balance'!E17:'Monthly Avg Balance'!G17)) -> 175.90274 | F17: =IF(SUM('Monthly Avg Balance'!E17:'Monthly Avg Balance'!G17)=0,"",'Monthly Avg Balance'!F17*Rate!C17/12+('Net Interest Income'!C17-SUM('Monthly Avg Balance'!E17:'Monthly Avg Balance'!G17)*Rate!C17/12)*'Monthly Avg Balance'!F17/SUM('Monthly Avg Balance'!E17:'Monthly Avg Balance'!G17)) -> 176 | G17: =IF(SUM('Monthly Avg Balance'!E17:'Monthly Avg Balance'!G17)=0,"",'Monthly Avg Balance'!G17*Rate!C17/12+('Net Interest Income'!C17-SUM('Monthly Avg Balance'!E17:'Monthly Avg Balance'!G17)*Rate!C17/12)*'Monthly Avg Balance'!G17/SUM('Monthly Avg Balance'!E17:'Monthly Avg Balance'!G17)) -> 176.09726 | H17: =IF(SUM('Monthly Avg Balance'!H17:'Monthly Avg Balance'!J17)=0,"",'Monthly Avg Balance'!H17*Rate!D17/12+('Net Interest Income'!D17-SUM('Monthly Avg Balance'!H17:'Monthly Avg Balance'!J17)*Rate!D17/12)*'Monthly Avg Balance'!H17/SUM('Monthly Avg Balance'!H17:'Monthly Avg Balance'!J17)) -> 187.54671 | I17: =IF(SUM('Monthly Avg Balance'!H17:'Monthly Avg Balance'!J17)=0,"",'Monthly Avg Balance'!I17*Rate!D17/12+('Net Interest Income'!D17-SUM('Monthly Avg Balance'!H17:'Monthly Avg Balance'!J17)*Rate!D17/12)*'Monthly Avg Balance'!I17/SUM('Monthly Avg Balance'!H17:'Monthly Avg Balance'!J17)) -> 193 | J17: =IF(SUM('Monthly Avg Balance'!H17:'Monthly Avg Balance'!J17)=0,"",'Monthly Avg Balance'!J17*Rate!D17/12+('Net Interest Income'!D17-SUM('Monthly Avg Balance'!H17:'Monthly Avg Balance'!J17)*Rate!D17/12)*'Monthly Avg Balance'!J17/SUM('Monthly Avg Balance'!H17:'Monthly Avg Balance'!J17)) -> 198.45329 | K17: =IF(SUM('Monthly Avg Balance'!K17:'Monthly Avg Balance'!M17)=0,"",'Monthly Avg Balance'!K17*Rate!E17/12+('Net Interest Income'!E17-SUM('Monthly Avg Balance'!K17:'Monthly Avg Balance'!M17)*Rate!E17/12)*'Monthly Avg Balance'!K17/SUM('Monthly Avg Balance'!K17:'Monthly Avg Balance'!M17)) -> 204.32888 | L17: =IF(SUM('Monthly Avg Balance'!K17:'Monthly Avg Balance'!M17)=0,"",'Monthly Avg Balance'!L17*Rate!E17/12+('Net Interest Income'!E17-SUM('Monthly Avg Balance'!K17:'Monthly Avg Balance'!M17)*Rate!E17/12)*'Monthly Avg Balance'!L17/SUM('Monthly Avg Balance'!K17:'Monthly Avg Balance'!M17)) -> 203.88392 | M17: =IF(SUM('Monthly Avg Balance'!K17:'Monthly Avg Balance'!M17)=0,"",'Monthly Avg Balance'!M17*Rate!E17/12+('Net Interest Income'!E17-SUM('Monthly Avg Balance'!K17:'Monthly Avg Balance'!M17)*Rate!E17/12)*'Monthly Avg Balance'!M17/SUM('Monthly Avg Balance'!K17:'Monthly Avg Balance'!M17)) -> 199.7872 | N17: =IF(SUM('Monthly Avg Balance'!N17:'Monthly Avg Balance'!P17)=0,"",'Monthly Avg Balance'!N17*Rate!F17/12+('Net Interest Income'!F17-SUM('Monthly Avg Balance'!N17:'Monthly Avg Balance'!P17)*Rate!F17/12)*'Monthly Avg Balance'!N17/SUM('Monthly Avg Balance'!N17:'Monthly Avg Balance'!P17)) -> 200.75682 | O17: =IF(SUM('Monthly Avg Balance'!N17:'Monthly Avg Balance'!P17)=0,"",'Monthly Avg Balance'!O17*Rate!F17/12+('Net Interest Income'!F17-SUM('Monthly Avg Balance'!N17:'Monthly Avg Balance'!P17)*Rate!F17/12)*'Monthly Avg Balance'!O17/SUM('Monthly Avg Balance'!N17:'Monthly Avg Balance'!P17)) -> 203.28298 | P17: =IF(SUM('Monthly Avg Balance'!N17:'Monthly Avg Balance'!P17)=0,"",'Monthly Avg Balance'!P17*Rate!F17/12+('Net Interest Income'!F17-SUM('Monthly Avg Balance'!N17:'Monthly Avg Balance'!P17)*Rate!F17/12)*'Monthly Avg Balance'!P17/SUM('Monthly Avg Balance'!N17:'Monthly Avg Balance'!P17)) -> 201.9602 | Q17: =IF(SUM('Monthly Avg Balance'!Q17:'Monthly Avg Balance'!S17)=0,"",'Monthly Avg Balance'!Q17*Rate!G17/12+('Net Interest Income'!G17-SUM('Monthly Avg Balance'!Q17:'Monthly Avg Balance'!S17)*Rate!G17/12)*'Monthly Avg Balance'!Q17/SUM('Monthly Avg Balance'!Q17:'Monthly Avg Balance'!S17)) -> 201.21383 | R17: =IF(SUM('Monthly Avg Balance'!Q17:'Monthly Avg Balance'!S17)=0,"",'Monthly Avg Balance'!R17*Rate!G17/12+('Net Interest Income'!G17-SUM('Monthly Avg Balance'!Q17:'Monthly Avg Balance'!S17)*Rate!G17/12)*'Monthly Avg Balance'!R17/SUM('Monthly Avg Balance'!Q17:'Monthly Avg Balance'!S17)) -> 196.34393 | S17: =IF(SUM('Monthly Avg Balance'!Q17:'Monthly Avg Balance'!S17)=0,"",'Monthly Avg Balance'!S17*Rate!G17/12+('Net Interest Income'!G17-SUM('Monthly Avg Balance'!Q17:'Monthly Avg Balance'!S17)*Rate!G17/12)*'Monthly Avg Balance'!S17/SUM('Monthly Avg Balance'!Q17:'Monthly Avg Balance'!S17)) -> 193.44224 | T17: =IF(SUM('Monthly Avg Balance'!T17:'Monthly Avg Balance'!V17)=0,"",'Monthly Avg Balance'!T17*Rate!H17/12+('Net Interest Income'!H17-SUM('Monthly Avg Balance'!T17:'Monthly Avg Balance'!V17)*Rate!H17/12)*'Monthly Avg Balance'!T17/SUM('Monthly Avg Balance'!T17:'Monthly Avg Balance'!V17)) -> 192.40072 | U17: =IF(SUM('Monthly Avg Balance'!T17:'Monthly Avg Balance'!V17)=0,"",'Monthly Avg Balance'!U17*Rate!H17/12+('Net Interest Income'!H17-SUM('Monthly Avg Balance'!T17:'Monthly Avg Balance'!V17)*Rate!H17/12)*'Monthly Avg Balance'!U17/SUM('Monthly Avg Balance'!T17:'Monthly Avg Balance'!V17)) -> 201.11731 | V17: =IF(SUM('Monthly Avg Balance'!T17:'Monthly Avg Balance'!V17)=0,"",'Monthly Avg Balance'!V17*Rate!H17/12+('Net Interest Income'!H17-SUM('Monthly Avg Balance'!T17:'Monthly Avg Balance'!V17)*Rate!H17/12)*'Monthly Avg Balance'!V17/SUM('Monthly Avg Balance'!T17:'Monthly Avg Balance'!V17)) -> 202.48198 | W17: =IF(SUM('Monthly Avg Balance'!W17:'Monthly Avg Balance'!Y17)=0,"",'Monthly Avg Balance'!W17*Rate!I17/12+('Net Interest Income'!I17-SUM('Monthly Avg Balance'!W17:'Monthly Avg Balance'!Y17)*Rate!I17/12)*'Monthly Avg Balance'!W17/SUM('Monthly Avg Balance'!W17:'Monthly Avg Balance'!Y17)) -> 185.78131 | X17: =IF(SUM('Monthly Avg Balance'!W17:'Monthly Avg Balance'!Y17)=0,"",'Monthly Avg Balance'!X17*Rate!I17/12+('Net Interest Income'!I17-SUM('Monthly Avg Balance'!W17:'Monthly Avg Balance'!Y17)*Rate!I17/12)*'Monthly Avg Balance'!X17/SUM('Monthly Avg Balance'!W17:'Monthly Avg Balance'!Y17)) -> 177.57882 | Y17: =IF(SUM('Monthly Avg Balance'!W17:'Monthly Avg Balance'!Y17)=0,"",'Monthly Avg Balance'!Y17*Rate!I17/12+('Net Interest Income'!I17-SUM('Monthly Avg Balance'!W17:'Monthly Avg Balance'!Y17)*Rate!I17/12)*'Monthly Avg Balance'!Y17/SUM('Monthly Avg Balance'!W17:'Monthly Avg Balance'!Y17)) -> 176.63987 | Z17: =IF(SUM('Monthly Avg Balance'!Z17:'Monthly Avg Balance'!AB17)=0,"",'Monthly Avg Balance'!Z17*Rate!J17/12+('Net Interest Income'!J17-SUM('Monthly Avg Balance'!Z17:'Monthly Avg Balance'!AB17)*Rate!J17/12)*'Monthly Avg Balance'!Z17/SUM('Monthly Avg Balance'!Z17:'Monthly Avg Balance'!AB17)) -> 170.14571 | AA17: =IF(SUM('Monthly Avg Balance'!Z17:'Monthly Avg Balance'!AB17)=0,"",'Monthly Avg Balance'!AA17*Rate!J17/12+('Net Interest Income'!J17-SUM('Monthly Avg Balance'!Z17:'Monthly Avg Balance'!AB17)*Rate!J17/12)*'Monthly Avg Balance'!AA17/SUM('Monthly Avg Balance'!Z17:'Monthly Avg Balance'!AB17)) -> 171.93265 | AB17: =IF(SUM('Monthly Avg Balance'!Z17:'Monthly Avg Balance'!AB17)=0,"",'Monthly Avg Balance'!AB17*Rate!J17/12+('Net Interest Income'!J17-SUM('Monthly Avg Balance'!Z17:'Monthly Avg Balance'!AB17)*Rate!J17/12)*'Monthly Avg Balance'!AB17/SUM('Monthly Avg Balance'!Z17:'Monthly Avg Balance'!AB17)) -> 162.92165 | AC17: =IF(SUM('Monthly Avg Balance'!AC17:'Monthly Avg Balance'!AE17)=0,"",'Monthly Avg Balance'!AC17*Rate!K17/12+('Net Interest Income'!K17-SUM('Monthly Avg Balance'!AC17:'Monthly Avg Balance'!AE17)*Rate!K17/12)*'Monthly Avg Balance'!AC17/SUM('Monthly Avg Balance'!AC17:'Monthly Avg Balance'!AE17)) -> 162.224 | AD17: =IF(SUM('Monthly Avg Balance'!AC17:'Monthly Avg Balance'!AE17)=0,"",'Monthly Avg Balance'!AD17*Rate!K17/12+('Net Interest Income'!K17-SUM('Monthly Avg Balance'!AC17:'Monthly Avg Balance'!AE17)*Rate!K17/12)*'Monthly Avg Balance'!AD17/SUM('Monthly Avg Balance'!AC17:'Monthly Avg Balance'!AE17)) -> 178.71103 | AE17: =IF(SUM('Monthly Avg Balance'!AC17:'Monthly Avg Balance'!AE17)=0,"",'Monthly Avg Balance'!AE17*Rate!K17/12+('Net Interest Income'!K17-SUM('Monthly Avg Balance'!AC17:'Monthly Avg Balance'!AE17)*Rate!K17/12)*'Monthly Avg Balance'!AE17/SUM('Monthly Avg Balance'!AC17:'Monthly Avg Balance'!AE17)) -> 194.06496 | AF17: ='Monthly Avg Balance'!AF17*'Monthly Rate'!AF17/12 -> 200.48232 | AG17: ='Monthly Avg Balance'!AG17*'Monthly Rate'!AG17/12 -> 199.50599 | AH17: ='Monthly Avg Balance'!AH17*'Monthly Rate'!AH17/12 -> 198.52965 | AI17: ='Monthly Avg Balance'!AI17*'Monthly Rate'!AI17/12 -> 197.55332 | AJ17: ='Monthly Avg Balance'!AJ17*'Monthly Rate'!AJ17/12 -> 196.57698 | AK17: ='Monthly Avg Balance'!AK17*'Monthly Rate'!AK17/12 -> 195.60065 | AL17: ='Monthly Avg Balance'!AL17*'Monthly Rate'!AL17/12 -> 194.62431 | AM17: ='Monthly Avg Balance'!AM17*'Monthly Rate'!AM17/12 -> 193.64798 | ... AQ17: ='Monthly Avg Balance'!AQ17*'Monthly Rate'!AQ17/12 -> 189.74264
A18: Other borrowings | B18: =IF(SUM('Monthly Avg Balance'!B18:'Monthly Avg Balance'!D18)=0,"",'Monthly Avg Balance'!B18*Rate!B18/12+('Net Interest Income'!B18-SUM('Monthly Avg Balance'!B18:'Monthly Avg Balance'!D18)*Rate!B18/12)*'Monthly Avg Balance'!B18/SUM('Monthly Avg Balance'!B18:'Monthly Avg Balance'!D18)) -> 4 | C18: =IF(SUM('Monthly Avg Balance'!B18:'Monthly Avg Balance'!D18)=0,"",'Monthly Avg Balance'!C18*Rate!B18/12+('Net Interest Income'!B18-SUM('Monthly Avg Balance'!B18:'Monthly Avg Balance'!D18)*Rate!B18/12)*'Monthly Avg Balance'!C18/SUM('Monthly Avg Balance'!B18:'Monthly Avg Balance'!D18)) -> 4 | D18: =IF(SUM('Monthly Avg Balance'!B18:'Monthly Avg Balance'!D18)=0,"",'Monthly Avg Balance'!D18*Rate!B18/12+('Net Interest Income'!B18-SUM('Monthly Avg Balance'!B18:'Monthly Avg Balance'!D18)*Rate!B18/12)*'Monthly Avg Balance'!D18/SUM('Monthly Avg Balance'!B18:'Monthly Avg Balance'!D18)) -> 4 | E18: =IF(SUM('Monthly Avg Balance'!E18:'Monthly Avg Balance'!G18)=0,"",'Monthly Avg Balance'!E18*Rate!C18/12+('Net Interest Income'!C18-SUM('Monthly Avg Balance'!E18:'Monthly Avg Balance'!G18)*Rate!C18/12)*'Monthly Avg Balance'!E18/SUM('Monthly Avg Balance'!E18:'Monthly Avg Balance'!G18)) -> 3.9073998 | F18: =IF(SUM('Monthly Avg Balance'!E18:'Monthly Avg Balance'!G18)=0,"",'Monthly Avg Balance'!F18*Rate!C18/12+('Net Interest Income'!C18-SUM('Monthly Avg Balance'!E18:'Monthly Avg Balance'!G18)*Rate!C18/12)*'Monthly Avg Balance'!F18/SUM('Monthly Avg Balance'!E18:'Monthly Avg Balance'!G18)) -> 4 | G18: =IF(SUM('Monthly Avg Balance'!E18:'Monthly Avg Balance'!G18)=0,"",'Monthly Avg Balance'!G18*Rate!C18/12+('Net Interest Income'!C18-SUM('Monthly Avg Balance'!E18:'Monthly Avg Balance'!G18)*Rate!C18/12)*'Monthly Avg Balance'!G18/SUM('Monthly Avg Balance'!E18:'Monthly Avg Balance'!G18)) -> 4.0926002 | H18: =IF(SUM('Monthly Avg Balance'!H18:'Monthly Avg Balance'!J18)=0,"",'Monthly Avg Balance'!H18*Rate!D18/12+('Net Interest Income'!D18-SUM('Monthly Avg Balance'!H18:'Monthly Avg Balance'!J18)*Rate!D18/12)*'Monthly Avg Balance'!H18/SUM('Monthly Avg Balance'!H18:'Monthly Avg Balance'!J18)) -> 3.6963203 | I18: =IF(SUM('Monthly Avg Balance'!H18:'Monthly Avg Balance'!J18)=0,"",'Monthly Avg Balance'!I18*Rate!D18/12+('Net Interest Income'!D18-SUM('Monthly Avg Balance'!H18:'Monthly Avg Balance'!J18)*Rate!D18/12)*'Monthly Avg Balance'!I18/SUM('Monthly Avg Balance'!H18:'Monthly Avg Balance'!J18)) -> 3.6666667 | J18: =IF(SUM('Monthly Avg Balance'!H18:'Monthly Avg Balance'!J18)=0,"",'Monthly Avg Balance'!J18*Rate!D18/12+('Net Interest Income'!D18-SUM('Monthly Avg Balance'!H18:'Monthly Avg Balance'!J18)*Rate!D18/12)*'Monthly Avg Balance'!J18/SUM('Monthly Avg Balance'!H18:'Monthly Avg Balance'!J18)) -> 3.6370131 | K18: =IF(SUM('Monthly Avg Balance'!K18:'Monthly Avg Balance'!M18)=0,"",'Monthly Avg Balance'!K18*Rate!E18/12+('Net Interest Income'!E18-SUM('Monthly Avg Balance'!K18:'Monthly Avg Balance'!M18)*Rate!E18/12)*'Monthly Avg Balance'!K18/SUM('Monthly Avg Balance'!K18:'Monthly Avg Balance'!M18)) -> 3.7715736 | L18: =IF(SUM('Monthly Avg Balance'!K18:'Monthly Avg Balance'!M18)=0,"",'Monthly Avg Balance'!L18*Rate!E18/12+('Net Interest Income'!E18-SUM('Monthly Avg Balance'!K18:'Monthly Avg Balance'!M18)*Rate!E18/12)*'Monthly Avg Balance'!L18/SUM('Monthly Avg Balance'!K18:'Monthly Avg Balance'!M18)) -> 4.0456853 | M18: =IF(SUM('Monthly Avg Balance'!K18:'Monthly Avg Balance'!M18)=0,"",'Monthly Avg Balance'!M18*Rate!E18/12+('Net Interest Income'!E18-SUM('Monthly Avg Balance'!K18:'Monthly Avg Balance'!M18)*Rate!E18/12)*'Monthly Avg Balance'!M18/SUM('Monthly Avg Balance'!K18:'Monthly Avg Balance'!M18)) -> 2.1827411 | N18: =IF(SUM('Monthly Avg Balance'!N18:'Monthly Avg Balance'!P18)=0,"",'Monthly Avg Balance'!N18*Rate!F18/12+('Net Interest Income'!F18-SUM('Monthly Avg Balance'!N18:'Monthly Avg Balance'!P18)*Rate!F18/12)*'Monthly Avg Balance'!N18/SUM('Monthly Avg Balance'!N18:'Monthly Avg Balance'!P18)) -> 2.6521568 | O18: =IF(SUM('Monthly Avg Balance'!N18:'Monthly Avg Balance'!P18)=0,"",'Monthly Avg Balance'!O18*Rate!F18/12+('Net Interest Income'!F18-SUM('Monthly Avg Balance'!N18:'Monthly Avg Balance'!P18)*Rate!F18/12)*'Monthly Avg Balance'!O18/SUM('Monthly Avg Balance'!N18:'Monthly Avg Balance'!P18)) -> 4.6754922 | P18: =IF(SUM('Monthly Avg Balance'!N18:'Monthly Avg Balance'!P18)=0,"",'Monthly Avg Balance'!P18*Rate!F18/12+('Net Interest Income'!F18-SUM('Monthly Avg Balance'!N18:'Monthly Avg Balance'!P18)*Rate!F18/12)*'Monthly Avg Balance'!P18/SUM('Monthly Avg Balance'!N18:'Monthly Avg Balance'!P18)) -> 2.6723509 | Q18: =IF(SUM('Monthly Avg Balance'!Q18:'Monthly Avg Balance'!S18)=0,"",'Monthly Avg Balance'!Q18*Rate!G18/12+('Net Interest Income'!G18-SUM('Monthly Avg Balance'!Q18:'Monthly Avg Balance'!S18)*Rate!G18/12)*'Monthly Avg Balance'!Q18/SUM('Monthly Avg Balance'!Q18:'Monthly Avg Balance'!S18)) -> 2.8879612 | R18: =IF(SUM('Monthly Avg Balance'!Q18:'Monthly Avg Balance'!S18)=0,"",'Monthly Avg Balance'!R18*Rate!G18/12+('Net Interest Income'!G18-SUM('Monthly Avg Balance'!Q18:'Monthly Avg Balance'!S18)*Rate!G18/12)*'Monthly Avg Balance'!R18/SUM('Monthly Avg Balance'!Q18:'Monthly Avg Balance'!S18)) -> 5.1078998 | S18: =IF(SUM('Monthly Avg Balance'!Q18:'Monthly Avg Balance'!S18)=0,"",'Monthly Avg Balance'!S18*Rate!G18/12+('Net Interest Income'!G18-SUM('Monthly Avg Balance'!Q18:'Monthly Avg Balance'!S18)*Rate!G18/12)*'Monthly Avg Balance'!S18/SUM('Monthly Avg Balance'!Q18:'Monthly Avg Balance'!S18)) -> 3.004139 | T18: =IF(SUM('Monthly Avg Balance'!T18:'Monthly Avg Balance'!V18)=0,"",'Monthly Avg Balance'!T18*Rate!H18/12+('Net Interest Income'!H18-SUM('Monthly Avg Balance'!T18:'Monthly Avg Balance'!V18)*Rate!H18/12)*'Monthly Avg Balance'!T18/SUM('Monthly Avg Balance'!T18:'Monthly Avg Balance'!V18)) -> 2.4780121 | U18: =IF(SUM('Monthly Avg Balance'!T18:'Monthly Avg Balance'!V18)=0,"",'Monthly Avg Balance'!U18*Rate!H18/12+('Net Interest Income'!H18-SUM('Monthly Avg Balance'!T18:'Monthly Avg Balance'!V18)*Rate!H18/12)*'Monthly Avg Balance'!U18/SUM('Monthly Avg Balance'!T18:'Monthly Avg Balance'!V18)) -> 4.1759031 | V18: =IF(SUM('Monthly Avg Balance'!T18:'Monthly Avg Balance'!V18)=0,"",'Monthly Avg Balance'!V18*Rate!H18/12+('Net Interest Income'!H18-SUM('Monthly Avg Balance'!T18:'Monthly Avg Balance'!V18)*Rate!H18/12)*'Monthly Avg Balance'!V18/SUM('Monthly Avg Balance'!T18:'Monthly Avg Balance'!V18)) -> 2.3460848 | W18: =IF(SUM('Monthly Avg Balance'!W18:'Monthly Avg Balance'!Y18)=0,"",'Monthly Avg Balance'!W18*Rate!I18/12+('Net Interest Income'!I18-SUM('Monthly Avg Balance'!W18:'Monthly Avg Balance'!Y18)*Rate!I18/12)*'Monthly Avg Balance'!W18/SUM('Monthly Avg Balance'!W18:'Monthly Avg Balance'!Y18)) -> 3.1654739 | X18: =IF(SUM('Monthly Avg Balance'!W18:'Monthly Avg Balance'!Y18)=0,"",'Monthly Avg Balance'!X18*Rate!I18/12+('Net Interest Income'!I18-SUM('Monthly Avg Balance'!W18:'Monthly Avg Balance'!Y18)*Rate!I18/12)*'Monthly Avg Balance'!X18/SUM('Monthly Avg Balance'!W18:'Monthly Avg Balance'!Y18)) -> 5.6279705 | Y18: =IF(SUM('Monthly Avg Balance'!W18:'Monthly Avg Balance'!Y18)=0,"",'Monthly Avg Balance'!Y18*Rate!I18/12+('Net Interest Income'!I18-SUM('Monthly Avg Balance'!W18:'Monthly Avg Balance'!Y18)*Rate!I18/12)*'Monthly Avg Balance'!Y18/SUM('Monthly Avg Balance'!W18:'Monthly Avg Balance'!Y18)) -> 3.2065556 | Z18: =IF(SUM('Monthly Avg Balance'!Z18:'Monthly Avg Balance'!AB18)=0,"",'Monthly Avg Balance'!Z18*Rate!J18/12+('Net Interest Income'!J18-SUM('Monthly Avg Balance'!Z18:'Monthly Avg Balance'!AB18)*Rate!J18/12)*'Monthly Avg Balance'!Z18/SUM('Monthly Avg Balance'!Z18:'Monthly Avg Balance'!AB18)) -> 2.4021494 | AA18: =IF(SUM('Monthly Avg Balance'!Z18:'Monthly Avg Balance'!AB18)=0,"",'Monthly Avg Balance'!AA18*Rate!J18/12+('Net Interest Income'!J18-SUM('Monthly Avg Balance'!Z18:'Monthly Avg Balance'!AB18)*Rate!J18/12)*'Monthly Avg Balance'!AA18/SUM('Monthly Avg Balance'!Z18:'Monthly Avg Balance'!AB18)) -> 4.1908476 | AB18: =IF(SUM('Monthly Avg Balance'!Z18:'Monthly Avg Balance'!AB18)=0,"",'Monthly Avg Balance'!AB18*Rate!J18/12+('Net Interest Income'!J18-SUM('Monthly Avg Balance'!Z18:'Monthly Avg Balance'!AB18)*Rate!J18/12)*'Monthly Avg Balance'!AB18/SUM('Monthly Avg Balance'!Z18:'Monthly Avg Balance'!AB18)) -> 2.4070029 | AC18: =IF(SUM('Monthly Avg Balance'!AC18:'Monthly Avg Balance'!AE18)=0,"",'Monthly Avg Balance'!AC18*Rate!K18/12+('Net Interest Income'!K18-SUM('Monthly Avg Balance'!AC18:'Monthly Avg Balance'!AE18)*Rate!K18/12)*'Monthly Avg Balance'!AC18/SUM('Monthly Avg Balance'!AC18:'Monthly Avg Balance'!AE18)) -> 3.5037642 | AD18: =IF(SUM('Monthly Avg Balance'!AC18:'Monthly Avg Balance'!AE18)=0,"",'Monthly Avg Balance'!AD18*Rate!K18/12+('Net Interest Income'!K18-SUM('Monthly Avg Balance'!AC18:'Monthly Avg Balance'!AE18)*Rate!K18/12)*'Monthly Avg Balance'!AD18/SUM('Monthly Avg Balance'!AC18:'Monthly Avg Balance'!AE18)) -> 6.3689505 | AE18: =IF(SUM('Monthly Avg Balance'!AC18:'Monthly Avg Balance'!AE18)=0,"",'Monthly Avg Balance'!AE18*Rate!K18/12+('Net Interest Income'!K18-SUM('Monthly Avg Balance'!AC18:'Monthly Avg Balance'!AE18)*Rate!K18/12)*'Monthly Avg Balance'!AE18/SUM('Monthly Avg Balance'!AC18:'Monthly Avg Balance'!AE18)) -> 4.1272854 | AF18: ='Monthly Avg Balance'!AF18*'Monthly Rate'!AF18/12 -> 1.702615 | AG18: ='Monthly Avg Balance'!AG18*'Monthly Rate'!AG18/12 -> 1.67549 | AH18: ='Monthly Avg Balance'!AH18*'Monthly Rate'!AH18/12 -> 1.648365 | AI18: ='Monthly Avg Balance'!AI18*'Monthly Rate'!AI18/12 -> 1.62124 | AJ18: ='Monthly Avg Balance'!AJ18*'Monthly Rate'!AJ18/12 -> 1.594115 | AK18: ='Monthly Avg Balance'!AK18*'Monthly Rate'!AK18/12 -> 1.56699 | AL18: ='Monthly Avg Balance'!AL18*'Monthly Rate'!AL18/12 -> 1.539865 | AM18: ='Monthly Avg Balance'!AM18*'Monthly Rate'!AM18/12 -> 1.51274 | ... AQ18: ='Monthly Avg Balance'!AQ18*'Monthly Rate'!AQ18/12 -> 1.40424
A19: Total interest-bearing liabilities | B19: =SUM(B15:B18) -> 856 | C19: =SUM(C15:C18) -> 856 | D19: =SUM(D15:D18) -> 856 | E19: =SUM(E15:E18) -> 1008.8031 | F19: =SUM(F15:F18) -> 1017.6667 | G19: =SUM(G15:G18) -> 1026.5302 | H19: =SUM(H15:H18) -> 1149.5157 | I19: =SUM(I15:I18) -> 1150 | ... AQ19: =SUM(AQ15:AQ18) -> 1350.0565
A21: NET INTEREST INCOME | B21: =B12-B19 -> 2377.9318 | C21: =C12-C19 -> 2390.2865 | D21: =D12-D19 -> 2417.7817 | E21: =E12-E19 -> 2380.4457 | F21: =F12-F19 -> 2354.8692 | G21: =G12-G19 -> 2377.6851 | H21: =H12-H19 -> 2469.4085 | I21: =I12-I19 -> 2470.0877 | ... AQ21: =AQ12-AQ19 -> 3857.1318

Sheet Monthly Rate
A1: Capital One - Imputed Monthly Yield / Rate by line item (annualized)
A2: Actual yields through Jun-25. Forecast yields use the Macro Drivers benchmark path plus June 2025 product spreads or betas.
A4: Line item (as disclosed) | B4: 44957 | C4: 44985 | D4: 45016 | E4: 45046 | F4: 45077 | G4: 45107 | H4: 45138 | I4: 45169 | J4: 45199 | K4: 45230 | L4: 45260 | M4: 45291 | N4: 45322 | O4: 45351 | P4: 45382 | Q4: 45412 | R4: 45443 | S4: 45473 | T4: 45504 | U4: 45535 | V4: 45565 | W4: 45596 | X4: 45626 | Y4: 45657 | Z4: 45688 | AA4: 45716 | AB4: 45747 | AC4: 45777 | AD4: 45808 | AE4: 45838 | AF4: 45869 | AG4: 45900 | AH4: 45930 | AI4: 45961 | AJ4: 45991 | AK4: 46022 | AL4: 46053 | AM4: 46081 | AN4: 46112 | AO4: 46142 | AP4: 46173 | AQ4: 46203
A5: INTEREST-EARNING ASSETS
A6: Credit card | B6: =IF('Monthly Avg Balance'!B6=0,"",'Monthly NII'!B6*12/'Monthly Avg Balance'!B6) -> 0.17978896 | C6: =IF('Monthly Avg Balance'!C6=0,"",'Monthly NII'!C6*12/'Monthly Avg Balance'!C6) -> 0.17978896 | D6: =IF('Monthly Avg Balance'!D6=0,"",'Monthly NII'!D6*12/'Monthly Avg Balance'!D6) -> 0.17978896 | E6: =IF('Monthly Avg Balance'!E6=0,"",'Monthly NII'!E6*12/'Monthly Avg Balance'!E6) -> 0.18166357 | F6: =IF('Monthly Avg Balance'!F6=0,"",'Monthly NII'!F6*12/'Monthly Avg Balance'!F6) -> 0.18166357 | G6: =IF('Monthly Avg Balance'!G6=0,"",'Monthly NII'!G6*12/'Monthly Avg Balance'!G6) -> 0.18166357 | H6: =IF('Monthly Avg Balance'!H6=0,"",'Monthly NII'!H6*12/'Monthly Avg Balance'!H6) -> 0.19020777 | I6: =IF('Monthly Avg Balance'!I6=0,"",'Monthly NII'!I6*12/'Monthly Avg Balance'!I6) -> 0.19020777 | ... AE6: =IF('Monthly Avg Balance'!AE6=0,"",'Monthly NII'!AE6*12/'Monthly Avg Balance'!AE6) -> 0.17674242 | AF6: =MAX(0,'Forecast Drivers'!C15/100+'Forecast Drivers'!$B$21) -> 0.17674242 | AG6: =MAX(0,'Forecast Drivers'!D15/100+'Forecast Drivers'!$B$21) -> 0.17586742 | AH6: =MAX(0,'Forecast Drivers'!E15/100+'Forecast Drivers'!$B$21) -> 0.17586742 | AI6: =MAX(0,'Forecast Drivers'!F15/100+'Forecast Drivers'!$B$21) -> 0.17586742 | AJ6: =MAX(0,'Forecast Drivers'!G15/100+'Forecast Drivers'!$B$21) -> 0.17499242 | AK6: =MAX(0,'Forecast Drivers'!H15/100+'Forecast Drivers'!$B$21) -> 0.17499242 | AL6: =MAX(0,'Forecast Drivers'!I15/100+'Forecast Drivers'!$B$21) -> 0.17499242 | AM6: =MAX(0,'Forecast Drivers'!J15/100+'Forecast Drivers'!$B$21) -> 0.17411742 | ... AQ6: =MAX(0,'Forecast Drivers'!N15/100+'Forecast Drivers'!$B$21) -> 0.17324242
A7: Consumer banking | B7: =IF('Monthly Avg Balance'!B7=0,"",'Monthly NII'!B7*12/'Monthly Avg Balance'!B7) -> 0.073974684 | C7: =IF('Monthly Avg Balance'!C7=0,"",'Monthly NII'!C7*12/'Monthly Avg Balance'!C7) -> 0.073974684 | D7: =IF('Monthly Avg Balance'!D7=0,"",'Monthly NII'!D7*12/'Monthly Avg Balance'!D7) -> 0.073974684 | E7: =IF('Monthly Avg Balance'!E7=0,"",'Monthly NII'!E7*12/'Monthly Avg Balance'!E7) -> 0.076500341 | F7: =IF('Monthly Avg Balance'!F7=0,"",'Monthly NII'!F7*12/'Monthly Avg Balance'!F7) -> 0.076500341 | G7: =IF('Monthly Avg Balance'!G7=0,"",'Monthly NII'!G7*12/'Monthly Avg Balance'!G7) -> 0.076500341 | H7: =IF('Monthly Avg Balance'!H7=0,"",'Monthly NII'!H7*12/'Monthly Avg Balance'!H7) -> 0.079684786 | I7: =IF('Monthly Avg Balance'!I7=0,"",'Monthly NII'!I7*12/'Monthly Avg Balance'!I7) -> 0.079684786 | ... AE7: =IF('Monthly Avg Balance'!AE7=0,"",'Monthly NII'!AE7*12/'Monthly Avg Balance'!AE7) -> 0.095206446 | AF7: =MAX(0,'Forecast Drivers'!C10/100+'Forecast Drivers'!$B$22) -> 0.09518978 | AG7: =MAX(0,'Forecast Drivers'!D10/100+'Forecast Drivers'!$B$22) -> 0.095173113 | AH7: =MAX(0,'Forecast Drivers'!E10/100+'Forecast Drivers'!$B$22) -> 0.095156446 | AI7: =MAX(0,'Forecast Drivers'!F10/100+'Forecast Drivers'!$B$22) -> 0.09513978 | AJ7: =MAX(0,'Forecast Drivers'!G10/100+'Forecast Drivers'!$B$22) -> 0.095123113 | AK7: =MAX(0,'Forecast Drivers'!H10/100+'Forecast Drivers'!$B$22) -> 0.095106446 | AL7: =MAX(0,'Forecast Drivers'!I10/100+'Forecast Drivers'!$B$22) -> 0.09508978 | AM7: =MAX(0,'Forecast Drivers'!J10/100+'Forecast Drivers'!$B$22) -> 0.095073113 | ... AQ7: =MAX(0,'Forecast Drivers'!N10/100+'Forecast Drivers'!$B$22) -> 0.095006446
A8: Commercial banking | B8: =IF('Monthly Avg Balance'!B8=0,"",'Monthly NII'!B8*12/'Monthly Avg Balance'!B8) -> 0.063020138 | C8: =IF('Monthly Avg Balance'!C8=0,"",'Monthly NII'!C8*12/'Monthly Avg Balance'!C8) -> 0.063020138 | D8: =IF('Monthly Avg Balance'!D8=0,"",'Monthly NII'!D8*12/'Monthly Avg Balance'!D8) -> 0.063020138 | E8: =IF('Monthly Avg Balance'!E8=0,"",'Monthly NII'!E8*12/'Monthly Avg Balance'!E8) -> 0.067324286 | F8: =IF('Monthly Avg Balance'!F8=0,"",'Monthly NII'!F8*12/'Monthly Avg Balance'!F8) -> 0.067324286 | G8: =IF('Monthly Avg Balance'!G8=0,"",'Monthly NII'!G8*12/'Monthly Avg Balance'!G8) -> 0.067324286 | H8: =IF('Monthly Avg Balance'!H8=0,"",'Monthly NII'!H8*12/'Monthly Avg Balance'!H8) -> 0.071194745 | I8: =IF('Monthly Avg Balance'!I8=0,"",'Monthly NII'!I8*12/'Monthly Avg Balance'!I8) -> 0.071194745 | ... AE8: =IF('Monthly Avg Balance'!AE8=0,"",'Monthly NII'!AE8*12/'Monthly Avg Balance'!AE8) -> 0.06572507 | AF8: =MAX(0,'Forecast Drivers'!C8/100+'Forecast Drivers'!$B$23) -> 0.06547507 | AG8: =MAX(0,'Forecast Drivers'!D8/100+'Forecast Drivers'!$B$23) -> 0.06522507 | AH8: =MAX(0,'Forecast Drivers'!E8/100+'Forecast Drivers'!$B$23) -> 0.06497507 | AI8: =MAX(0,'Forecast Drivers'!F8/100+'Forecast Drivers'!$B$23) -> 0.06472507 | AJ8: =MAX(0,'Forecast Drivers'!G8/100+'Forecast Drivers'!$B$23) -> 0.06447507 | AK8: =MAX(0,'Forecast Drivers'!H8/100+'Forecast Drivers'!$B$23) -> 0.06422507 | AL8: =MAX(0,'Forecast Drivers'!I8/100+'Forecast Drivers'!$B$23) -> 0.06397507 | AM8: =MAX(0,'Forecast Drivers'!J8/100+'Forecast Drivers'!$B$23) -> 0.06372507 | ... AQ8: =MAX(0,'Forecast Drivers'!N8/100+'Forecast Drivers'!$B$23) -> 0.06272507
A9: Total loans (incl. HFS) | B9: =IF('Monthly Avg Balance'!B9=0,"",'Monthly NII'!B9*12/'Monthly Avg Balance'!B9) -> 0.11324343 | C9: =IF('Monthly Avg Balance'!C9=0,"",'Monthly NII'!C9*12/'Monthly Avg Balance'!C9) -> 0.11324343 | D9: =IF('Monthly Avg Balance'!D9=0,"",'Monthly NII'!D9*12/'Monthly Avg Balance'!D9) -> 0.11324343 | E9: =IF('Monthly Avg Balance'!E9=0,"",'Monthly NII'!E9*12/'Monthly Avg Balance'!E9) -> 0.11673836 | F9: =IF('Monthly Avg Balance'!F9=0,"",'Monthly NII'!F9*12/'Monthly Avg Balance'!F9) -> 0.11673836 | G9: =IF('Monthly Avg Balance'!G9=0,"",'Monthly NII'!G9*12/'Monthly Avg Balance'!G9) -> 0.11673836 | H9: =IF('Monthly Avg Balance'!H9=0,"",'Monthly NII'!H9*12/'Monthly Avg Balance'!H9) -> 0.12372831 | I9: =IF('Monthly Avg Balance'!I9=0,"",'Monthly NII'!I9*12/'Monthly Avg Balance'!I9) -> 0.12372831 | ... AE9: =IF('Monthly Avg Balance'!AE9=0,"",'Monthly NII'!AE9*12/'Monthly Avg Balance'!AE9) -> 0.13188658 | AF9: =('Monthly Avg Balance'!AF6*AF6+'Monthly Avg Balance'!AF7*AF7+'Monthly Avg Balance'!AF8*AF8)/'Monthly Avg Balance'!AF9 -> 0.1334011 | AG9: =('Monthly Avg Balance'!AG6*AG6+'Monthly Avg Balance'!AG7*AG7+'Monthly Avg Balance'!AG8*AG8)/'Monthly Avg Balance'!AG9 -> 0.132857 | AH9: =('Monthly Avg Balance'!AH6*AH6+'Monthly Avg Balance'!AH7*AH7+'Monthly Avg Balance'!AH8*AH8)/'Monthly Avg Balance'!AH9 -> 0.13279763 | AI9: =('Monthly Avg Balance'!AI6*AI6+'Monthly Avg Balance'!AI7*AI7+'Monthly Avg Balance'!AI8*AI8)/'Monthly Avg Balance'!AI9 -> 0.13273824 | AJ9: =('Monthly Avg Balance'!AJ6*AJ6+'Monthly Avg Balance'!AJ7*AJ7+'Monthly Avg Balance'!AJ8*AJ8)/'Monthly Avg Balance'!AJ9 -> 0.13219398 | AK9: =('Monthly Avg Balance'!AK6*AK6+'Monthly Avg Balance'!AK7*AK7+'Monthly Avg Balance'!AK8*AK8)/'Monthly Avg Balance'!AK9 -> 0.13213454 | AL9: =('Monthly Avg Balance'!AL6*AL6+'Monthly Avg Balance'!AL7*AL7+'Monthly Avg Balance'!AL8*AL8)/'Monthly Avg Balance'!AL9 -> 0.1320751 | AM9: =('Monthly Avg Balance'!AM6*AM6+'Monthly Avg Balance'!AM7*AM7+'Monthly Avg Balance'!AM8*AM8)/'Monthly Avg Balance'!AM9 -> 0.13153068 | ... AQ9: =('Monthly Avg Balance'!AQ6*AQ6+'Monthly Avg Balance'!AQ7*AQ7+'Monthly Avg Balance'!AQ8*AQ8)/'Monthly Avg Balance'!AQ9 -> 0.13080755
A10: Investment securities | B10: =IF('Monthly Avg Balance'!B10=0,"",'Monthly NII'!B10*12/'Monthly Avg Balance'!B10) -> 0.027345487 | C10: =IF('Monthly Avg Balance'!C10=0,"",'Monthly NII'!C10*12/'Monthly Avg Balance'!C10) -> 0.027345487 | D10: =IF('Monthly Avg Balance'!D10=0,"",'Monthly NII'!D10*12/'Monthly Avg Balance'!D10) -> 0.027345487 | E10: =IF('Monthly Avg Balance'!E10=0,"",'Monthly NII'!E10*12/'Monthly Avg Balance'!E10) -> 0.028401893 | F10: =IF('Monthly Avg Balance'!F10=0,"",'Monthly NII'!F10*12/'Monthly Avg Balance'!F10) -> 0.028401893 | G10: =IF('Monthly Avg Balance'!G10=0,"",'Monthly NII'!G10*12/'Monthly Avg Balance'!G10) -> 0.028401893 | H10: =IF('Monthly Avg Balance'!H10=0,"",'Monthly NII'!H10*12/'Monthly Avg Balance'!H10) -> 0.028550287 | I10: =IF('Monthly Avg Balance'!I10=0,"",'Monthly NII'!I10*12/'Monthly Avg Balance'!I10) -> 0.028550287 | ... AE10: =IF('Monthly Avg Balance'!AE10=0,"",'Monthly NII'!AE10*12/'Monthly Avg Balance'!AE10) -> 0.032858685 | AF10: =MAX(0,'Forecast Drivers'!C6/100+'Forecast Drivers'!$B$24) -> 0.032375351 | AG10: =MAX(0,'Forecast Drivers'!D6/100+'Forecast Drivers'!$B$24) -> 0.031892018 | AH10: =MAX(0,'Forecast Drivers'!E6/100+'Forecast Drivers'!$B$24) -> 0.031408685 | AI10: =MAX(0,'Forecast Drivers'!F6/100+'Forecast Drivers'!$B$24) -> 0.030925351 | AJ10: =MAX(0,'Forecast Drivers'!G6/100+'Forecast Drivers'!$B$24) -> 0.030442018 | AK10: =MAX(0,'Forecast Drivers'!H6/100+'Forecast Drivers'!$B$24) -> 0.029958685 | AL10: =MAX(0,'Forecast Drivers'!I6/100+'Forecast Drivers'!$B$24) -> 0.029475351 | AM10: =MAX(0,'Forecast Drivers'!J6/100+'Forecast Drivers'!$B$24) -> 0.028992018 | ... AQ10: =MAX(0,'Forecast Drivers'!N6/100+'Forecast Drivers'!$B$24) -> 0.027058685
A11: Cash equivalents and other | B11: =IF('Monthly Avg Balance'!B11=0,"",'Monthly NII'!B11*12/'Monthly Avg Balance'!B11) -> 0.045638431 | C11: =IF('Monthly Avg Balance'!C11=0,"",'Monthly NII'!C11*12/'Monthly Avg Balance'!C11) -> 0.045638431 | D11: =IF('Monthly Avg Balance'!D11=0,"",'Monthly NII'!D11*12/'Monthly Avg Balance'!D11) -> 0.045638431 | E11: =IF('Monthly Avg Balance'!E11=0,"",'Monthly NII'!E11*12/'Monthly Avg Balance'!E11) -> 0.050934936 | F11: =IF('Monthly Avg Balance'!F11=0,"",'Monthly NII'!F11*12/'Monthly Avg Balance'!F11) -> 0.050934936 | G11: =IF('Monthly Avg Balance'!G11=0,"",'Monthly NII'!G11*12/'Monthly Avg Balance'!G11) -> 0.050934936 | H11: =IF('Monthly Avg Balance'!H11=0,"",'Monthly NII'!H11*12/'Monthly Avg Balance'!H11) -> 0.052703868 | I11: =IF('Monthly Avg Balance'!I11=0,"",'Monthly NII'!I11*12/'Monthly Avg Balance'!I11) -> 0.052703868 | ... AE11: =IF('Monthly Avg Balance'!AE11=0,"",'Monthly NII'!AE11*12/'Monthly Avg Balance'!AE11) -> 0.045132601 | AF11: =MAX(0,'Forecast Drivers'!C5/100+'Forecast Drivers'!$B$25) -> 0.044882601 | AG11: =MAX(0,'Forecast Drivers'!D5/100+'Forecast Drivers'!$B$25) -> 0.044632601 | AH11: =MAX(0,'Forecast Drivers'!E5/100+'Forecast Drivers'!$B$25) -> 0.044382601 | AI11: =MAX(0,'Forecast Drivers'!F5/100+'Forecast Drivers'!$B$25) -> 0.044132601 | AJ11: =MAX(0,'Forecast Drivers'!G5/100+'Forecast Drivers'!$B$25) -> 0.043882601 | AK11: =MAX(0,'Forecast Drivers'!H5/100+'Forecast Drivers'!$B$25) -> 0.043632601 | AL11: =MAX(0,'Forecast Drivers'!I5/100+'Forecast Drivers'!$B$25) -> 0.043382601 | AM11: =MAX(0,'Forecast Drivers'!J5/100+'Forecast Drivers'!$B$25) -> 0.043132601 | ... AQ11: =MAX(0,'Forecast Drivers'!N5/100+'Forecast Drivers'!$B$25) -> 0.042132601
A12: Total interest-earning assets | B12: =IF('Monthly Avg Balance'!B12=0,"",'Monthly NII'!B12*12/'Monthly Avg Balance'!B12) -> 0.090257655 | C12: =IF('Monthly Avg Balance'!C12=0,"",'Monthly NII'!C12*12/'Monthly Avg Balance'!C12) -> 0.089923069 | D12: =IF('Monthly Avg Balance'!D12=0,"",'Monthly NII'!D12*12/'Monthly Avg Balance'!D12) -> 0.089196166 | E12: =IF('Monthly Avg Balance'!E12=0,"",'Monthly NII'!E12*12/'Monthly Avg Balance'!E12) -> 0.092585985 | F12: =IF('Monthly Avg Balance'!F12=0,"",'Monthly NII'!F12*12/'Monthly Avg Balance'!F12) -> 0.09337064 | G12: =IF('Monthly Avg Balance'!G12=0,"",'Monthly NII'!G12*12/'Monthly Avg Balance'!G12) -> 0.09305372 | H12: =IF('Monthly Avg Balance'!H12=0,"",'Monthly NII'!H12*12/'Monthly Avg Balance'!H12) -> 0.097963651 | I12: =IF('Monthly Avg Balance'!I12=0,"",'Monthly NII'!I12*12/'Monthly Avg Balance'!I12) -> 0.098264695 | ... AE12: =IF('Monthly Avg Balance'!AE12=0,"",'Monthly NII'!AE12*12/'Monthly Avg Balance'!AE12) -> 0.10673879 | AF12: =('Monthly Avg Balance'!AF9*AF9+'Monthly Avg Balance'!AF10*AF10+'Monthly Avg Balance'!AF11*AF11)/'Monthly Avg Balance'!AF12 -> 0.10915292 | AG12: =('Monthly Avg Balance'!AG9*AG9+'Monthly Avg Balance'!AG10*AG10+'Monthly Avg Balance'!AG11*AG11)/'Monthly Avg Balance'!AG12 -> 0.10864923 | AH12: =('Monthly Avg Balance'!AH9*AH9+'Monthly Avg Balance'!AH10*AH10+'Monthly Avg Balance'!AH11*AH11)/'Monthly Avg Balance'!AH12 -> 0.10850765 | AI12: =('Monthly Avg Balance'!AI9*AI9+'Monthly Avg Balance'!AI10*AI10+'Monthly Avg Balance'!AI11*AI11)/'Monthly Avg Balance'!AI12 -> 0.10836607 | AJ12: =('Monthly Avg Balance'!AJ9*AJ9+'Monthly Avg Balance'!AJ10*AJ10+'Monthly Avg Balance'!AJ11*AJ11)/'Monthly Avg Balance'!AJ12 -> 0.10786228 | AK12: =('Monthly Avg Balance'!AK9*AK9+'Monthly Avg Balance'!AK10*AK10+'Monthly Avg Balance'!AK11*AK11)/'Monthly Avg Balance'!AK12 -> 0.10772068 | AL12: =('Monthly Avg Balance'!AL9*AL9+'Monthly Avg Balance'!AL10*AL10+'Monthly Avg Balance'!AL11*AL11)/'Monthly Avg Balance'!AL12 -> 0.10757908 | AM12: =('Monthly Avg Balance'!AM9*AM9+'Monthly Avg Balance'!AM10*AM10+'Monthly Avg Balance'!AM11*AM11)/'Monthly Avg Balance'!AM12 -> 0.10707518 | ... AQ12: =('Monthly Avg Balance'!AQ9*AQ9+'Monthly Avg Balance'!AQ10*AQ10+'Monthly Avg Balance'!AQ11*AQ11)/'Monthly Avg Balance'!AQ12 -> 0.10614628
A14: INTEREST-BEARING LIABILITIES
A15: Interest-bearing deposits | B15: =IF('Monthly Avg Balance'!B15=0,"",'Monthly NII'!B15*12/'Monthly Avg Balance'!B15) -> 0.024042385 | C15: =IF('Monthly Avg Balance'!C15=0,"",'Monthly NII'!C15*12/'Monthly Avg Balance'!C15) -> 0.024042385 | D15: =IF('Monthly Avg Balance'!D15=0,"",'Monthly NII'!D15*12/'Monthly Avg Balance'!D15) -> 0.024042385 | E15: =IF('Monthly Avg Balance'!E15=0,"",'Monthly NII'!E15*12/'Monthly Avg Balance'!E15) -> 0.02907981 | F15: =IF('Monthly Avg Balance'!F15=0,"",'Monthly NII'!F15*12/'Monthly Avg Balance'!F15) -> 0.02907981 | G15: =IF('Monthly Avg Balance'!G15=0,"",'Monthly NII'!G15*12/'Monthly Avg Balance'!G15) -> 0.02907981 | H15: =IF('Monthly Avg Balance'!H15=0,"",'Monthly NII'!H15*12/'Monthly Avg Balance'!H15) -> 0.033047286 | I15: =IF('Monthly Avg Balance'!I15=0,"",'Monthly NII'!I15*12/'Monthly Avg Balance'!I15) -> 0.033047286 | ... AE15: =IF('Monthly Avg Balance'!AE15=0,"",'Monthly NII'!AE15*12/'Monthly Avg Balance'!AE15) -> 0.032332765 | AF15: =MAX(0,'Forecast Drivers'!C5/100*'Forecast Drivers'!$B$20) -> 0.032146086 | AG15: =MAX(0,'Forecast Drivers'!D5/100*'Forecast Drivers'!$B$20) -> 0.031959407 | AH15: =MAX(0,'Forecast Drivers'!E5/100*'Forecast Drivers'!$B$20) -> 0.031772729 | AI15: =MAX(0,'Forecast Drivers'!F5/100*'Forecast Drivers'!$B$20) -> 0.03158605 | AJ15: =MAX(0,'Forecast Drivers'!G5/100*'Forecast Drivers'!$B$20) -> 0.031399371 | AK15: =MAX(0,'Forecast Drivers'!H5/100*'Forecast Drivers'!$B$20) -> 0.031212692 | AL15: =MAX(0,'Forecast Drivers'!I5/100*'Forecast Drivers'!$B$20) -> 0.031026013 | AM15: =MAX(0,'Forecast Drivers'!J5/100*'Forecast Drivers'!$B$20) -> 0.030839335 | ... AQ15: =MAX(0,'Forecast Drivers'!N5/100*'Forecast Drivers'!$B$20) -> 0.03009262
A16: Securitized debt obligations | B16: =IF('Monthly Avg Balance'!B16=0,"",'Monthly NII'!B16*12/'Monthly Avg Balance'!B16) -> 0.0489247 | C16: =IF('Monthly Avg Balance'!C16=0,"",'Monthly NII'!C16*12/'Monthly Avg Balance'!C16) -> 0.0489247 | D16: =IF('Monthly Avg Balance'!D16=0,"",'Monthly NII'!D16*12/'Monthly Avg Balance'!D16) -> 0.0489247 | E16: =IF('Monthly Avg Balance'!E16=0,"",'Monthly NII'!E16*12/'Monthly Avg Balance'!E16) -> 0.053120252 | F16: =IF('Monthly Avg Balance'!F16=0,"",'Monthly NII'!F16*12/'Monthly Avg Balance'!F16) -> 0.053120252 | G16: =IF('Monthly Avg Balance'!G16=0,"",'Monthly NII'!G16*12/'Monthly Avg Balance'!G16) -> 0.053120252 | H16: =IF('Monthly Avg Balance'!H16=0,"",'Monthly NII'!H16*12/'Monthly Avg Balance'!H16) -> 0.056433792 | I16: =IF('Monthly Avg Balance'!I16=0,"",'Monthly NII'!I16*12/'Monthly Avg Balance'!I16) -> 0.056433792 | ... AE16: =IF('Monthly Avg Balance'!AE16=0,"",'Monthly NII'!AE16*12/'Monthly Avg Balance'!AE16) -> 0.051280103 | AF16: =MAX(0,'Forecast Drivers'!C6/100+'Forecast Drivers'!$B$26) -> 0.05079677 | AG16: =MAX(0,'Forecast Drivers'!D6/100+'Forecast Drivers'!$B$26) -> 0.050313437 | AH16: =MAX(0,'Forecast Drivers'!E6/100+'Forecast Drivers'!$B$26) -> 0.049830103 | AI16: =MAX(0,'Forecast Drivers'!F6/100+'Forecast Drivers'!$B$26) -> 0.04934677 | AJ16: =MAX(0,'Forecast Drivers'!G6/100+'Forecast Drivers'!$B$26) -> 0.048863437 | AK16: =MAX(0,'Forecast Drivers'!H6/100+'Forecast Drivers'!$B$26) -> 0.048380103 | AL16: =MAX(0,'Forecast Drivers'!I6/100+'Forecast Drivers'!$B$26) -> 0.04789677 | AM16: =MAX(0,'Forecast Drivers'!J6/100+'Forecast Drivers'!$B$26) -> 0.047413437 | ... AQ16: =MAX(0,'Forecast Drivers'!N6/100+'Forecast Drivers'!$B$26) -> 0.045480103
A17: Senior and subordinated notes | B17: =IF('Monthly Avg Balance'!B17=0,"",'Monthly NII'!B17*12/'Monthly Avg Balance'!B17) -> 0.064905761 | C17: =IF('Monthly Avg Balance'!C17=0,"",'Monthly NII'!C17*12/'Monthly Avg Balance'!C17) -> 0.064905761 | D17: =IF('Monthly Avg Balance'!D17=0,"",'Monthly NII'!D17*12/'Monthly Avg Balance'!D17) -> 0.064905761 | E17: =IF('Monthly Avg Balance'!E17=0,"",'Monthly NII'!E17*12/'Monthly Avg Balance'!E17) -> 0.070024203 | F17: =IF('Monthly Avg Balance'!F17=0,"",'Monthly NII'!F17*12/'Monthly Avg Balance'!F17) -> 0.070024203 | G17: =IF('Monthly Avg Balance'!G17=0,"",'Monthly NII'!G17*12/'Monthly Avg Balance'!G17) -> 0.070024203 | H17: =IF('Monthly Avg Balance'!H17=0,"",'Monthly NII'!H17*12/'Monthly Avg Balance'!H17) -> 0.073472495 | I17: =IF('Monthly Avg Balance'!I17=0,"",'Monthly NII'!I17*12/'Monthly Avg Balance'!I17) -> 0.073472495 | ... AE17: =IF('Monthly Avg Balance'!AE17=0,"",'Monthly NII'!AE17*12/'Monthly Avg Balance'!AE17) -> 0.065032058 | AF17: =MAX(0,'Forecast Drivers'!C6/100+'Forecast Drivers'!C13/100+'Forecast Drivers'!$B$27) -> 0.064716891 | AG17: =MAX(0,'Forecast Drivers'!D6/100+'Forecast Drivers'!D13/100+'Forecast Drivers'!$B$27) -> 0.064401724 | AH17: =MAX(0,'Forecast Drivers'!E6/100+'Forecast Drivers'!E13/100+'Forecast Drivers'!$B$27) -> 0.064086558 | AI17: =MAX(0,'Forecast Drivers'!F6/100+'Forecast Drivers'!F13/100+'Forecast Drivers'!$B$27) -> 0.063771391 | AJ17: =MAX(0,'Forecast Drivers'!G6/100+'Forecast Drivers'!G13/100+'Forecast Drivers'!$B$27) -> 0.063456224 | AK17: =MAX(0,'Forecast Drivers'!H6/100+'Forecast Drivers'!H13/100+'Forecast Drivers'!$B$27) -> 0.063141058 | AL17: =MAX(0,'Forecast Drivers'!I6/100+'Forecast Drivers'!I13/100+'Forecast Drivers'!$B$27) -> 0.062825891 | AM17: =MAX(0,'Forecast Drivers'!J6/100+'Forecast Drivers'!J13/100+'Forecast Drivers'!$B$27) -> 0.062510724 | ... AQ17: =MAX(0,'Forecast Drivers'!N6/100+'Forecast Drivers'!N13/100+'Forecast Drivers'!$B$27) -> 0.061250058
A18: Other borrowings | B18: =IF('Monthly Avg Balance'!B18=0,"",'Monthly NII'!B18*12/'Monthly Avg Balance'!B18) -> 0.020556745 | C18: =IF('Monthly Avg Balance'!C18=0,"",'Monthly NII'!C18*12/'Monthly Avg Balance'!C18) -> 0.020556745 | D18: =IF('Monthly Avg Balance'!D18=0,"",'Monthly NII'!D18*12/'Monthly Avg Balance'!D18) -> 0.020556745 | E18: =IF('Monthly Avg Balance'!E18=0,"",'Monthly NII'!E18*12/'Monthly Avg Balance'!E18) -> 0.01984291 | F18: =IF('Monthly Avg Balance'!F18=0,"",'Monthly NII'!F18*12/'Monthly Avg Balance'!F18) -> 0.01984291 | G18: =IF('Monthly Avg Balance'!G18=0,"",'Monthly NII'!G18*12/'Monthly Avg Balance'!G18) -> 0.01984291 | H18: =IF('Monthly Avg Balance'!H18=0,"",'Monthly NII'!H18*12/'Monthly Avg Balance'!H18) -> 0.017792155 | I18: =IF('Monthly Avg Balance'!I18=0,"",'Monthly NII'!I18*12/'Monthly Avg Balance'!I18) -> 0.017792155 | ... AE18: =IF('Monthly Avg Balance'!AE18=0,"",'Monthly NII'!AE18*12/'Monthly Avg Balance'!AE18) -> 0.015942304 | AF18: =MAX(0,'Forecast Drivers'!C5/100+'Forecast Drivers'!$B$28) -> 0.015692304 | AG18: =MAX(0,'Forecast Drivers'!D5/100+'Forecast Drivers'!$B$28) -> 0.015442304 | AH18: =MAX(0,'Forecast Drivers'!E5/100+'Forecast Drivers'!$B$28) -> 0.015192304 | AI18: =MAX(0,'Forecast Drivers'!F5/100+'Forecast Drivers'!$B$28) -> 0.014942304 | AJ18: =MAX(0,'Forecast Drivers'!G5/100+'Forecast Drivers'!$B$28) -> 0.014692304 | AK18: =MAX(0,'Forecast Drivers'!H5/100+'Forecast Drivers'!$B$28) -> 0.014442304 | AL18: =MAX(0,'Forecast Drivers'!I5/100+'Forecast Drivers'!$B$28) -> 0.014192304 | AM18: =MAX(0,'Forecast Drivers'!J5/100+'Forecast Drivers'!$B$28) -> 0.013942304 | ... AQ18: =MAX(0,'Forecast Drivers'!N5/100+'Forecast Drivers'!$B$28) -> 0.012942304
A19: Total interest-bearing liabilities | B19: =IF('Monthly Avg Balance'!B19=0,"",'Monthly NII'!B19*12/'Monthly Avg Balance'!B19) -> 0.02865192 | C19: =IF('Monthly Avg Balance'!C19=0,"",'Monthly NII'!C19*12/'Monthly Avg Balance'!C19) -> 0.02865192 | D19: =IF('Monthly Avg Balance'!D19=0,"",'Monthly NII'!D19*12/'Monthly Avg Balance'!D19) -> 0.02865192 | E19: =IF('Monthly Avg Balance'!E19=0,"",'Monthly NII'!E19*12/'Monthly Avg Balance'!E19) -> 0.033608784 | F19: =IF('Monthly Avg Balance'!F19=0,"",'Monthly NII'!F19*12/'Monthly Avg Balance'!F19) -> 0.033590239 | G19: =IF('Monthly Avg Balance'!G19=0,"",'Monthly NII'!G19*12/'Monthly Avg Balance'!G19) -> 0.033572033 | H19: =IF('Monthly Avg Balance'!H19=0,"",'Monthly NII'!H19*12/'Monthly Avg Balance'!H19) -> 0.037454081 | I19: =IF('Monthly Avg Balance'!I19=0,"",'Monthly NII'!I19*12/'Monthly Avg Balance'!I19) -> 0.037533045 | ... AE19: =IF('Monthly Avg Balance'!AE19=0,"",'Monthly NII'!AE19*12/'Monthly Avg Balance'!AE19) -> 0.035249771 | AF19: =('Monthly Avg Balance'!AF15*AF15+'Monthly Avg Balance'!AF16*AF16+'Monthly Avg Balance'!AF17*AF17+'Monthly Avg Balance'!AF18*AF18)/'Monthly Avg Balance'!AF19 -> 0.035112449 | AG19: =('Monthly Avg Balance'!AG15*AG15+'Monthly Avg Balance'!AG16*AG16+'Monthly Avg Balance'!AG17*AG17+'Monthly Avg Balance'!AG18*AG18)/'Monthly Avg Balance'!AG19 -> 0.034904334 | AH19: =('Monthly Avg Balance'!AH15*AH15+'Monthly Avg Balance'!AH16*AH16+'Monthly Avg Balance'!AH17*AH17+'Monthly Avg Balance'!AH18*AH18)/'Monthly Avg Balance'!AH19 -> 0.034696319 | AI19: =('Monthly Avg Balance'!AI15*AI15+'Monthly Avg Balance'!AI16*AI16+'Monthly Avg Balance'!AI17*AI17+'Monthly Avg Balance'!AI18*AI18)/'Monthly Avg Balance'!AI19 -> 0.034488402 | AJ19: =('Monthly Avg Balance'!AJ15*AJ15+'Monthly Avg Balance'!AJ16*AJ16+'Monthly Avg Balance'!AJ17*AJ17+'Monthly Avg Balance'!AJ18*AJ18)/'Monthly Avg Balance'!AJ19 -> 0.034280585 | AK19: =('Monthly Avg Balance'!AK15*AK15+'Monthly Avg Balance'!AK16*AK16+'Monthly Avg Balance'!AK17*AK17+'Monthly Avg Balance'!AK18*AK18)/'Monthly Avg Balance'!AK19 -> 0.034072865 | AL19: =('Monthly Avg Balance'!AL15*AL15+'Monthly Avg Balance'!AL16*AL16+'Monthly Avg Balance'!AL17*AL17+'Monthly Avg Balance'!AL18*AL18)/'Monthly Avg Balance'!AL19 -> 0.033865242 | AM19: =('Monthly Avg Balance'!AM15*AM15+'Monthly Avg Balance'!AM16*AM16+'Monthly Avg Balance'!AM17*AM17+'Monthly Avg Balance'!AM18*AM18)/'Monthly Avg Balance'!AM19 -> 0.033657716 | ... AQ19: =('Monthly Avg Balance'!AQ15*AQ15+'Monthly Avg Balance'!AQ16*AQ16+'Monthly Avg Balance'!AQ17*AQ17+'Monthly Avg Balance'!AQ18*AQ18)/'Monthly Avg Balance'!AQ19 -> 0.032828564
A21: Net interest spread (asset yield − funding cost) | B21: =B12-B19 -> 0.061605735 | C21: =C12-C19 -> 0.061271148 | D21: =D12-D19 -> 0.060544245 | E21: =E12-E19 -> 0.058977201 | F21: =F12-F19 -> 0.059780402 | G21: =G12-G19 -> 0.059481687 | H21: =H12-H19 -> 0.06050957 | I21: =I12-I19 -> 0.06073165 | ... AQ21: =AQ12-AQ19 -> 0.073317716
A22: Net interest margin (NII / avg earning assets) | B22: =IF('Monthly Avg Balance'!B12=0,"",'Monthly NII'!B21*12/'Monthly Avg Balance'!B12) -> 0.066367061 | C22: =IF('Monthly Avg Balance'!C12=0,"",'Monthly NII'!C21*12/'Monthly Avg Balance'!C12) -> 0.066211623 | D22: =IF('Monthly Avg Balance'!D12=0,"",'Monthly NII'!D21*12/'Monthly Avg Balance'!D12) -> 0.065873927 | E22: =IF('Monthly Avg Balance'!E12=0,"",'Monthly NII'!E21*12/'Monthly Avg Balance'!E12) -> 0.065027952 | F22: =IF('Monthly Avg Balance'!F12=0,"",'Monthly NII'!F21*12/'Monthly Avg Balance'!F12) -> 0.06519594 | G22: =IF('Monthly Avg Balance'!G12=0,"",'Monthly NII'!G21*12/'Monthly Avg Balance'!G12) -> 0.064993669 | H22: =IF('Monthly Avg Balance'!H12=0,"",'Monthly NII'!H21*12/'Monthly Avg Balance'!H12) -> 0.066846461 | I22: =IF('Monthly Avg Balance'!I12=0,"",'Monthly NII'!I21*12/'Monthly Avg Balance'!I12) -> 0.067048767 | ... AE22: =IF('Monthly Avg Balance'!AE12=0,"",'Monthly NII'!AE21*12/'Monthly Avg Balance'!AE12) -> 0.077428821 | AF22: ='Monthly NII'!AF21*12/'Monthly Avg Balance'!AF12 -> 0.079690954 | AG22: ='Monthly NII'!AG21*12/'Monthly Avg Balance'!AG12 -> 0.079364448 | AH22: ='Monthly NII'!AH21*12/'Monthly Avg Balance'!AH12 -> 0.07939991 | AI22: ='Monthly NII'!AI21*12/'Monthly Avg Balance'!AI12 -> 0.079435238 | AJ22: ='Monthly NII'!AJ21*12/'Monthly Avg Balance'!AJ12 -> 0.079108218 | AK22: ='Monthly NII'!AK21*12/'Monthly Avg Balance'!AK12 -> 0.079143256 | AL22: ='Monthly NII'!AL21*12/'Monthly Avg Balance'!AL12 -> 0.079178164 | AM22: ='Monthly NII'!AM21*12/'Monthly Avg Balance'!AM12 -> 0.07885064 | ... AQ22: ='Monthly NII'!AQ21*12/'Monthly Avg Balance'!AQ12 -> 0.078625961

Sheet Monthly Checks
A1: Controlled Monthly Imputation Checks
A2: Actual controls run through Q2:25. Forecast columns thereafter verify quarter-end links, four-point averages and monthly NII sums.
A4: Line item | B4: Q1:23 | C4: Q2:23 | D4: Q3:23 | E4: Q4:23 | F4: Q1:24 | G4: Q2:24 | H4: Q3:24 | I4: Q4:24 | J4: Q1:25 | K4: Q2:25 | L4: Q3:25 | M4: Q4:25 | N4: Q1:26 | O4: Q2:26
A5: QUARTER-END ANCHOR DIFFERENCE
A6: Credit card | B6: =IF(ISNUMBER('Quarter-End Anchors'!C6),ROUND('Monthly EOP Balance'!E6-'Quarter-End Anchors'!C6,2),"") | C6: =IF(ISNUMBER('Quarter-End Anchors'!D6),ROUND('Monthly EOP Balance'!H6-'Quarter-End Anchors'!D6,2),"") | D6: =IF(ISNUMBER('Quarter-End Anchors'!E6),ROUND('Monthly EOP Balance'!K6-'Quarter-End Anchors'!E6,2),"") | E6: =IF(ISNUMBER('Quarter-End Anchors'!F6),ROUND('Monthly EOP Balance'!N6-'Quarter-End Anchors'!F6,2),"") -> 0 | F6: =IF(ISNUMBER('Quarter-End Anchors'!G6),ROUND('Monthly EOP Balance'!Q6-'Quarter-End Anchors'!G6,2),"") -> 0 | G6: =IF(ISNUMBER('Quarter-End Anchors'!H6),ROUND('Monthly EOP Balance'!T6-'Quarter-End Anchors'!H6,2),"") -> 0 | H6: =IF(ISNUMBER('Quarter-End Anchors'!I6),ROUND('Monthly EOP Balance'!W6-'Quarter-End Anchors'!I6,2),"") -> 0 | I6: =IF(ISNUMBER('Quarter-End Anchors'!J6),ROUND('Monthly EOP Balance'!Z6-'Quarter-End Anchors'!J6,2),"") -> 0 | J6: =IF(ISNUMBER('Quarter-End Anchors'!K6),ROUND('Monthly EOP Balance'!AC6-'Quarter-End Anchors'!K6,2),"") -> 0 | K6: =IF(ISNUMBER('Quarter-End Anchors'!L6),ROUND('Monthly EOP Balance'!AF6-'Quarter-End Anchors'!L6,2),"") -> 0 | L6: =IF(ISNUMBER('Quarter-End Anchors'!M6),ROUND('Monthly EOP Balance'!AI6-'Quarter-End Anchors'!M6,2),"") -> 0 | M6: =IF(ISNUMBER('Quarter-End Anchors'!N6),ROUND('Monthly EOP Balance'!AL6-'Quarter-End Anchors'!N6,2),"") -> 0 | N6: =IF(ISNUMBER('Quarter-End Anchors'!O6),ROUND('Monthly EOP Balance'!AO6-'Quarter-End Anchors'!O6,2),"") -> 0 | O6: =IF(ISNUMBER('Quarter-End Anchors'!P6),ROUND('Monthly EOP Balance'!AR6-'Quarter-End Anchors'!P6,2),"") -> 0
A7: Consumer banking | B7: =IF(ISNUMBER('Quarter-End Anchors'!C7),ROUND('Monthly EOP Balance'!E7-'Quarter-End Anchors'!C7,2),"") | C7: =IF(ISNUMBER('Quarter-End Anchors'!D7),ROUND('Monthly EOP Balance'!H7-'Quarter-End Anchors'!D7,2),"") | D7: =IF(ISNUMBER('Quarter-End Anchors'!E7),ROUND('Monthly EOP Balance'!K7-'Quarter-End Anchors'!E7,2),"") | E7: =IF(ISNUMBER('Quarter-End Anchors'!F7),ROUND('Monthly EOP Balance'!N7-'Quarter-End Anchors'!F7,2),"") -> 0 | F7: =IF(ISNUMBER('Quarter-End Anchors'!G7),ROUND('Monthly EOP Balance'!Q7-'Quarter-End Anchors'!G7,2),"") -> 0 | G7: =IF(ISNUMBER('Quarter-End Anchors'!H7),ROUND('Monthly EOP Balance'!T7-'Quarter-End Anchors'!H7,2),"") -> 0 | H7: =IF(ISNUMBER('Quarter-End Anchors'!I7),ROUND('Monthly EOP Balance'!W7-'Quarter-End Anchors'!I7,2),"") -> 0 | I7: =IF(ISNUMBER('Quarter-End Anchors'!J7),ROUND('Monthly EOP Balance'!Z7-'Quarter-End Anchors'!J7,2),"") -> 0 | J7: =IF(ISNUMBER('Quarter-End Anchors'!K7),ROUND('Monthly EOP Balance'!AC7-'Quarter-End Anchors'!K7,2),"") -> 0 | K7: =IF(ISNUMBER('Quarter-End Anchors'!L7),ROUND('Monthly EOP Balance'!AF7-'Quarter-End Anchors'!L7,2),"") -> 0 | L7: =IF(ISNUMBER('Quarter-End Anchors'!M7),ROUND('Monthly EOP Balance'!AI7-'Quarter-End Anchors'!M7,2),"") -> 0 | M7: =IF(ISNUMBER('Quarter-End Anchors'!N7),ROUND('Monthly EOP Balance'!AL7-'Quarter-End Anchors'!N7,2),"") -> 0 | N7: =IF(ISNUMBER('Quarter-End Anchors'!O7),ROUND('Monthly EOP Balance'!AO7-'Quarter-End Anchors'!O7,2),"") -> 0 | O7: =IF(ISNUMBER('Quarter-End Anchors'!P7),ROUND('Monthly EOP Balance'!AR7-'Quarter-End Anchors'!P7,2),"") -> 0
