Workbook

Sheet Deposit Actuals
A2: Capital One deposit rate and balance actuals
A3: Monthly actuals from Jan-2024 through Jun-2026. Balances and monthly interest expense are in $ millions; rates are annualized.
A5: Period | B5: Start Month | C5: Through Month | D5: Checking Avg Balance | E5: Savings Avg Balance | F5: Time Deposits Avg Balance | G5: Total IB Avg Balance | H5: NIB Avg Balance | I5: Total Deposits Avg Balance | J5: IB Average Rate | K5: Total Deposit Cost
A6: 2024 | B6: 45322 | C6: 45657 | D6: =SUMIFS($F$13:$F$192,$D$13:$D$192,"Checking",$A$13:$A$192,">="&$B6,$A$13:$A$192,"<="&$C6)/COUNTIFS($D$13:$D$192,"Checking",$A$13:$A$192,">="&$B6,$A$13:$A$192,"<="&$C6) -> 34848.68 | E6: =SUMIFS($F$13:$F$192,$D$13:$D$192,"Savings",$A$13:$A$192,">="&$B6,$A$13:$A$192,"<="&$C6)/COUNTIFS($D$13:$D$192,"Savings",$A$13:$A$192,">="&$B6,$A$13:$A$192,"<="&$C6) -> 210768.01 | F6: =SUMIFS($F$13:$F$192,$D$13:$D$192,"Time deposits",$A$13:$A$192,">="&$B6,$A$13:$A$192,"<="&$C6)/COUNTIFS($D$13:$D$192,"Time deposits",$A$13:$A$192,">="&$B6,$A$13:$A$192,"<="&$C6) -> 78142.559 | G6: =SUMIFS($F$13:$F$192,$D$13:$D$192,"Total interest-bearing deposits",$A$13:$A$192,">="&$B6,$A$13:$A$192,"<="&$C6)/COUNTIFS($D$13:$D$192,"Total interest-bearing deposits",$A$13:$A$192,">="&$B6,$A$13:$A$192,"<="&$C6) -> 323759.25 | H6: =SUMIFS($F$13:$F$192,$D$13:$D$192,"Non-interest-bearing deposits",$A$13:$A$192,">="&$B6,$A$13:$A$192,"<="&$C6)/COUNTIFS($D$13:$D$192,"Non-interest-bearing deposits",$A$13:$A$192,">="&$B6,$A$13:$A$192,"<="&$C6) -> 26822.917 | I6: =SUMIFS($F$13:$F$192,$D$13:$D$192,"Total deposits",$A$13:$A$192,">="&$B6,$A$13:$A$192,"<="&$C6)/COUNTIFS($D$13:$D$192,"Total deposits",$A$13:$A$192,">="&$B6,$A$13:$A$192,"<="&$C6) -> 350582.17 | J6: =SUMIFS($H$13:$H$192,$D$13:$D$192,"Total interest-bearing deposits",$A$13:$A$192,">="&$B6,$A$13:$A$192,"<="&$C6)*12/SUMIFS($F$13:$F$192,$D$13:$D$192,"Total interest-bearing deposits",$A$13:$A$192,">="&$B6,$A$13:$A$192,"<="&$C6) -> 0.0354986 | K6: =SUMIFS($H$13:$H$192,$D$13:$D$192,"Total deposits",$A$13:$A$192,">="&$B6,$A$13:$A$192,"<="&$C6)*12/SUMIFS($F$13:$F$192,$D$13:$D$192,"Total deposits",$A$13:$A$192,">="&$B6,$A$13:$A$192,"<="&$C6) -> 0.032782614
A7: 2025 | B7: 45688 | C7: 46022 | D7: =SUMIFS($F$13:$F$192,$D$13:$D$192,"Checking",$A$13:$A$192,">="&$B7,$A$13:$A$192,"<="&$C7)/COUNTIFS($D$13:$D$192,"Checking",$A$13:$A$192,">="&$B7,$A$13:$A$192,"<="&$C7) -> 35892.669 | E7: =SUMIFS($F$13:$F$192,$D$13:$D$192,"Savings",$A$13:$A$192,">="&$B7,$A$13:$A$192,"<="&$C7)/COUNTIFS($D$13:$D$192,"Savings",$A$13:$A$192,">="&$B7,$A$13:$A$192,"<="&$C7) -> 273526.51 | F7: =SUMIFS($F$13:$F$192,$D$13:$D$192,"Time deposits",$A$13:$A$192,">="&$B7,$A$13:$A$192,"<="&$C7)/COUNTIFS($D$13:$D$192,"Time deposits",$A$13:$A$192,">="&$B7,$A$13:$A$192,"<="&$C7) -> 91919.117 | G7: =SUMIFS($F$13:$F$192,$D$13:$D$192,"Total interest-bearing deposits",$A$13:$A$192,">="&$B7,$A$13:$A$192,"<="&$C7)/COUNTIFS($D$13:$D$192,"Total interest-bearing deposits",$A$13:$A$192,">="&$B7,$A$13:$A$192,"<="&$C7) -> 401338.29 | H7: =SUMIFS($F$13:$F$192,$D$13:$D$192,"Non-interest-bearing deposits",$A$13:$A$192,">="&$B7,$A$13:$A$192,"<="&$C7)/COUNTIFS($D$13:$D$192,"Non-interest-bearing deposits",$A$13:$A$192,">="&$B7,$A$13:$A$192,"<="&$C7) -> 27477.875 | I7: =SUMIFS($F$13:$F$192,$D$13:$D$192,"Total deposits",$A$13:$A$192,">="&$B7,$A$13:$A$192,"<="&$C7)/COUNTIFS($D$13:$D$192,"Total deposits",$A$13:$A$192,">="&$B7,$A$13:$A$192,"<="&$C7) -> 428816.17 | J7: =SUMIFS($H$13:$H$192,$D$13:$D$192,"Total interest-bearing deposits",$A$13:$A$192,">="&$B7,$A$13:$A$192,"<="&$C7)*12/SUMIFS($F$13:$F$192,$D$13:$D$192,"Total interest-bearing deposits",$A$13:$A$192,">="&$B7,$A$13:$A$192,"<="&$C7) -> 0.032204752 | K7: =SUMIFS($H$13:$H$192,$D$13:$D$192,"Total deposits",$A$13:$A$192,">="&$B7,$A$13:$A$192,"<="&$C7)*12/SUMIFS($F$13:$F$192,$D$13:$D$192,"Total deposits",$A$13:$A$192,">="&$B7,$A$13:$A$192,"<="&$C7) -> 0.030141121
A8: H1 2026 | B8: 46053 | C8: 46203 | D8: =SUMIFS($F$13:$F$192,$D$13:$D$192,"Checking",$A$13:$A$192,">="&$B8,$A$13:$A$192,"<="&$C8)/COUNTIFS($D$13:$D$192,"Checking",$A$13:$A$192,">="&$B8,$A$13:$A$192,"<="&$C8) -> 39151.125 | E8: =SUMIFS($F$13:$F$192,$D$13:$D$192,"Savings",$A$13:$A$192,">="&$B8,$A$13:$A$192,"<="&$C8)/COUNTIFS($D$13:$D$192,"Savings",$A$13:$A$192,">="&$B8,$A$13:$A$192,"<="&$C8) -> 311465.18 | F8: =SUMIFS($F$13:$F$192,$D$13:$D$192,"Time deposits",$A$13:$A$192,">="&$B8,$A$13:$A$192,"<="&$C8)/COUNTIFS($D$13:$D$192,"Time deposits",$A$13:$A$192,">="&$B8,$A$13:$A$192,"<="&$C8) -> 103851.36 | G8: =SUMIFS($F$13:$F$192,$D$13:$D$192,"Total interest-bearing deposits",$A$13:$A$192,">="&$B8,$A$13:$A$192,"<="&$C8)/COUNTIFS($D$13:$D$192,"Total interest-bearing deposits",$A$13:$A$192,">="&$B8,$A$13:$A$192,"<="&$C8) -> 454467.67 | H8: =SUMIFS($F$13:$F$192,$D$13:$D$192,"Non-interest-bearing deposits",$A$13:$A$192,">="&$B8,$A$13:$A$192,"<="&$C8)/COUNTIFS($D$13:$D$192,"Non-interest-bearing deposits",$A$13:$A$192,">="&$B8,$A$13:$A$192,"<="&$C8) -> 28520.5 | I8: =SUMIFS($F$13:$F$192,$D$13:$D$192,"Total deposits",$A$13:$A$192,">="&$B8,$A$13:$A$192,"<="&$C8)/COUNTIFS($D$13:$D$192,"Total deposits",$A$13:$A$192,">="&$B8,$A$13:$A$192,"<="&$C8) -> 482988.17 | J8: =SUMIFS($H$13:$H$192,$D$13:$D$192,"Total interest-bearing deposits",$A$13:$A$192,">="&$B8,$A$13:$A$192,"<="&$C8)*12/SUMIFS($F$13:$F$192,$D$13:$D$192,"Total interest-bearing deposits",$A$13:$A$192,">="&$B8,$A$13:$A$192,"<="&$C8) -> 0.029595065 | K8: =SUMIFS($H$13:$H$192,$D$13:$D$192,"Total deposits",$A$13:$A$192,">="&$B8,$A$13:$A$192,"<="&$C8)*12/SUMIFS($F$13:$F$192,$D$13:$D$192,"Total deposits",$A$13:$A$192,">="&$B8,$A$13:$A$192,"<="&$C8) -> 0.027847473
A12: Month | B12: Year | C12: Quarter | D12: Deposit Type | E12: Interest Bearing | F12: Average Balance ($mm) | G12: Annualized Rate | H12: Monthly Interest Expense ($mm) | I12: Share of Total Deposits | J12: MoM Balance Change ($mm) | K12: MoM Balance Change (%) | L12: YoY Balance Change (%) | M12: Source Period | N12: Source Method | O12: Data Status
A13: 45322 | B13: 2024 | C13: Q1 | D13: Checking | E13: Yes | F13: ='Sources & Checks'!$C$61*'Sources & Checks'!$G$6 -> 35596.255 | G13: =H13*12/F13 -> 0.016638956 | H13: ='Sources & Checks'!$D$61*'Sources & Checks'!$D$6/'Sources & Checks'!$D$9 -> 49.357043 | I13: =F13/F18 -> 0.1032359 | J13: ="" | K13: ="" | L13: ="" | M13: 2024Q1 | N13: Quarter balance and expense mix applied to controlled totals | O13: Allocated from reported quarter actual
A14: 45322 | B14: 2024 | C14: Q1 | D14: Savings | E14: Yes | F14: ='Sources & Checks'!$C$61*'Sources & Checks'!$G$7 -> 205980.17 | G14: =H14*12/F14 -> 0.033436755 | H14: ='Sources & Checks'!$D$61*'Sources & Checks'!$D$7/'Sources & Checks'!$D$9 -> 573.94237 | I14: =F14/F18 -> 0.59738162 | J14: ="" | K14: ="" | L14: ="" | M14: 2024Q1 | N14: Quarter balance and expense mix applied to controlled totals | O14: Allocated from reported quarter actual
A15: 45322 | B15: 2024 | C15: Q1 | D15: Time deposits | E15: Yes | F15: ='Sources & Checks'!$C$61*'Sources & Checks'!$G$8 -> 75885.909 | G15: =H15*12/F15 -> 0.049730087 | H15: ='Sources & Checks'!$D$61*'Sources & Checks'!$D$8/'Sources & Checks'!$D$9 -> 314.4844 | I15: =F15/F18 -> 0.22008355 | J15: ="" | K15: ="" | L15: ="" | M15: 2024Q1 | N15: Quarter balance and expense mix applied to controlled totals | O15: Allocated from reported quarter actual
A16: 45322 | B16: 2024 | C16: Q1 | D16: Total interest-bearing deposits | E16: Yes | F16: =SUM(F13:F15) -> 317462.33 | G16: =H16*12/F16 -> 0.035448003 | H16: =SUM(H13:H15) -> 937.78382 | I16: =F16/F18 -> 0.92070107 | J16: ="" | K16: ="" | L16: ="" | M16: 2024Q1 | N16: Controlled monthly imputation | O16: Controlled monthly actual estimate
A17: 45322 | B17: 2024 | C17: Q1 | D17: Non-interest-bearing deposits | E17: No | F17: ='Sources & Checks'!$J$61 -> 27342.667 | G17: =0 -> 0 | H17: =0 -> 0 | I17: =F17/F18 -> 0.079298927 | J17: ="" | K17: ="" | L17: ="" | M17: 2024Q1 | N17: Quarterly average and EOP controlled interpolation | O17: Controlled monthly actual estimate
A18: 45322 | B18: 2024 | C18: Q1 | D18: Total deposits | E18: Mixed | F18: =SUM(F16,F17) -> 344805 | G18: =H18*12/F18 -> 0.032637015 | H18: =SUM(H16,H17) -> 937.78382 | I18: =F18/F18 -> 1 | J18: ="" | K18: ="" | L18: ="" | M18: 2024Q1 | N18: Interest-bearing plus non-interest-bearing deposits | O18: Calculated monthly total
A19: 45351 | B19: 2024 | C19: Q1 | D19: Checking | E19: Yes | F19: ='Sources & Checks'!$C$62*'Sources & Checks'!$G$6 -> 35323.468 | G19: =H19*12/F19 -> 0.016638956 | H19: ='Sources & Checks'!$D$62*'Sources & Checks'!$D$6/'Sources & Checks'!$D$9 -> 48.978801 | I19: =F19/F24 -> 0.10339897 | J19: =F19-F13 -> -272.7875 | K19: =IF(F13=0,"n.a.",F19/F13-1) -> -0.0076633763 | L19: ="" | M19: 2024Q1 | N19: Quarter balance and expense mix applied to controlled totals | O19: Allocated from reported quarter actual
A20: 45351 | B20: 2024 | C20: Q1 | D20: Savings | E20: Yes | F20: ='Sources & Checks'!$C$62*'Sources & Checks'!$G$7 -> 204401.67 | G20: =H20*12/F20 -> 0.033436755 | H20: ='Sources & Checks'!$D$62*'Sources & Checks'!$D$7/'Sources & Checks'!$D$9 -> 569.54404 | I20: =F20/F24 -> 0.59832525 | J20: =F20-F14 -> -1578.5036 | K20: =IF(F14=0,"n.a.",F20/F14-1) -> -0.0076633763 | L20: ="" | M20: 2024Q1 | N20: Quarter balance and expense mix applied to controlled totals | O20: Allocated from reported quarter actual
A21: 45351 | B21: 2024 | C21: Q1 | D21: Time deposits | E21: Yes | F21: ='Sources & Checks'!$C$62*'Sources & Checks'!$G$8 -> 75304.367 | G21: =H21*12/F21 -> 0.049730087 | H21: ='Sources & Checks'!$D$62*'Sources & Checks'!$D$8/'Sources & Checks'!$D$9 -> 312.07439 | I21: =F21/F24 -> 0.2204312 | J21: =F21-F15 -> -581.54228 | K21: =IF(F15=0,"n.a.",F21/F15-1) -> -0.0076633763 | L21: ="" | M21: 2024Q1 | N21: Quarter balance and expense mix applied to controlled totals | O21: Allocated from reported quarter actual
A22: 45351 | B22: 2024 | C22: Q1 | D22: Total interest-bearing deposits | E22: Yes | F22: =SUM(F19:F21) -> 315029.5 | G22: =H22*12/F22 -> 0.035448003 | H22: =SUM(H19:H21) -> 930.59723 | I22: =F22/F24 -> 0.92215542 | J22: =F22-F16 -> -2432.8333 | K22: =IF(F16=0,"n.a.",F22/F16-1) -> -0.0076633763 | L22: ="" | M22: 2024Q1 | N22: Controlled monthly imputation | O22: Controlled monthly actual estimate
A23: 45351 | B23: 2024 | C23: Q1 | D23: Non-interest-bearing deposits | E23: No | F23: ='Sources & Checks'!$J$62 -> 26593.5 | G23: =0 -> 0 | H23: =0 -> 0 | I23: =F23/F24 -> 0.077844583 | J23: =F23-F17 -> -749.16667 | K23: =IF(F17=0,"n.a.",F23/F17-1) -> -0.027399181 | L23: ="" | M23: 2024Q1 | N23: Quarterly average and EOP controlled interpolation | O23: Controlled monthly actual estimate
A24: 45351 | B24: 2024 | C24: Q1 | D24: Total deposits | E24: Mixed | F24: =SUM(F22,F23) -> 341623 | G24: =H24*12/F24 -> 0.032688568 | H24: =SUM(H22,H23) -> 930.59723 | I24: =F24/F24 -> 1 | J24: =F24-F18 -> -3182 | K24: =IF(F18=0,"n.a.",F24/F18-1) -> -0.0092284045 | L24: ="" | M24: 2024Q1 | N24: Interest-bearing plus non-interest-bearing deposits | O24: Calculated monthly total
A25: 45382 | B25: 2024 | C25: Q1 | D25: Checking | E25: Yes | F25: ='Sources & Checks'!$C$63*'Sources & Checks'!$G$6 -> 35817.745 | G25: =H25*12/F25 -> 0.016638956 | H25: ='Sources & Checks'!$D$63*'Sources & Checks'!$D$6/'Sources & Checks'!$D$9 -> 49.664155 | I25: =F25/F30 -> 0.10336743 | J25: =F25-F19 -> 494.27668 | K25: =IF(F19=0,"n.a.",F25/F19-1) -> 0.013992869 | L25: ="" | M25: 2024Q1 | N25: Quarter balance and expense mix applied to controlled totals | O25: Allocated from reported quarter actual
A26: 45382 | B26: 2024 | C26: Q1 | D26: Savings | E26: Yes | F26: ='Sources & Checks'!$C$63*'Sources & Checks'!$G$7 -> 207261.83 | G26: =H26*12/F26 -> 0.033436755 | H26: ='Sources & Checks'!$D$63*'Sources & Checks'!$D$7/'Sources & Checks'!$D$9 -> 577.51359 | I26: =F26/F30 -> 0.59814271 | J26: =F26-F20 -> 2860.1658 | K26: =IF(F20=0,"n.a.",F26/F20-1) -> 0.013992869 | L26: ="" | M26: 2024Q1 | N26: Quarter balance and expense mix applied to controlled totals | O26: Allocated from reported quarter actual
A27: 45382 | B27: 2024 | C27: Q1 | D27: Time deposits | E27: Yes | F27: ='Sources & Checks'!$C$63*'Sources & Checks'!$G$8 -> 76358.091 | G27: =H27*12/F27 -> 0.049730087 | H27: ='Sources & Checks'!$D$63*'Sources & Checks'!$D$8/'Sources & Checks'!$D$9 -> 316.44121 | I27: =F27/F30 -> 0.22036395 | J27: =F27-F21 -> 1053.7242 | K27: =IF(F21=0,"n.a.",F27/F21-1) -> 0.013992869 | L27: ="" | M27: 2024Q1 | N27: Quarter balance and expense mix applied to controlled totals | O27: Allocated from reported quarter actual
A28: 45382 | B28: 2024 | C28: Q1 | D28: Total interest-bearing deposits | E28: Yes | F28: =SUM(F25:F27) -> 319437.67 | G28: =H28*12/F28 -> 0.035448003 | H28: =SUM(H25:H27) -> 943.61895 | I28: =F28/F30 -> 0.92187408 | J28: =F28-F22 -> 4408.1667 | K28: =IF(F22=0,"n.a.",F28/F22-1) -> 0.013992869 | L28: ="" | M28: 2024Q1 | N28: Controlled monthly imputation | O28: Controlled monthly actual estimate
A29: 45382 | B29: 2024 | C29: Q1 | D29: Non-interest-bearing deposits | E29: No | F29: ='Sources & Checks'!$J$63 -> 27071.333 | G29: =0 -> 0 | H29: =0 -> 0 | I29: =F29/F30 -> 0.078125917 | J29: =F29-F23 -> 477.83333 | K29: =IF(F23=0,"n.a.",F29/F23-1) -> 0.01796805 | L29: ="" | M29: 2024Q1 | N29: Quarterly average and EOP controlled interpolation | O29: Controlled monthly actual estimate
A30: 45382 | B30: 2024 | C30: Q1 | D30: Total deposits | E30: Mixed | F30: =SUM(F28,F29) -> 346509 | G30: =H30*12/F30 -> 0.032678595 | H30: =SUM(H28,H29) -> 943.61895 | I30: =F30/F30 -> 1 | J30: =F30-F24 -> 4886 | K30: =IF(F24=0,"n.a.",F30/F24-1) -> 0.014302316 | L30: ="" | M30: 2024Q1 | N30: Interest-bearing plus non-interest-bearing deposits | O30: Calculated monthly total
A31: 45412 | B31: 2024 | C31: Q2 | D31: Checking | E31: Yes | F31: ='Sources & Checks'!$C$64*'Sources & Checks'!$G$11 -> 34815.922 | G31: =H31*12/F31 -> 0.015858564 | H31: ='Sources & Checks'!$D$64*'Sources & Checks'!$D$11/'Sources & Checks'!$D$14 -> 46.010876 | I31: =F31/F36 -> 0.099664754 | J31: =F31-F25 -> -1001.8228 | K31: =IF(F25=0,"n.a.",F31/F25-1) -> -0.027970014 | L31: ="" | M31: 2024Q2 | N31: Quarter balance and expense mix applied to controlled totals | O31: Allocated from reported quarter actual
A32: 45412 | B32: 2024 | C32: Q2 | D32: Savings | E32: Yes | F32: ='Sources & Checks'!$C$64*'Sources & Checks'!$G$12 -> 208597.86 | G32: =H32*12/F32 -> 0.033622865 | H32: ='Sources & Checks'!$D$64*'Sources & Checks'!$D$12/'Sources & Checks'!$D$14 -> 584.47149 | I32: =F32/F36 -> 0.59713642 | J32: =F32-F26 -> 1336.0336 | K32: =IF(F26=0,"n.a.",F32/F26-1) -> 0.0064461152 | L32: ="" | M32: 2024Q2 | N32: Quarter balance and expense mix applied to controlled totals | O32: Allocated from reported quarter actual
A33: 45412 | B33: 2024 | C33: Q2 | D33: Time deposits | E33: Yes | F33: ='Sources & Checks'!$C$64*'Sources & Checks'!$G$13 -> 78805.547 | G33: =H33*12/F33 -> 0.049906762 | H33: ='Sources & Checks'!$D$64*'Sources & Checks'!$D$13/'Sources & Checks'!$D$14 -> 327.74414 | I33: =F33/F36 -> 0.22559033 | J33: =F33-F27 -> 2447.4558 | K33: =IF(F27=0,"n.a.",F33/F27-1) -> 0.032052344 | L33: ="" | M33: 2024Q2 | N33: Quarter balance and expense mix applied to controlled totals | O33: Allocated from reported quarter actual
A34: 45412 | B34: 2024 | C34: Q2 | D34: Total interest-bearing deposits | E34: Yes | F34: =SUM(F31:F33) -> 322219.33 | G34: =H34*12/F34 -> 0.035685997 | H34: =SUM(H31:H33) -> 958.22651 | I34: =F34/F36 -> 0.92239151 | J34: =F34-F28 -> 2781.6667 | K34: =IF(F28=0,"n.a.",F34/F28-1) -> 0.0087080108 | L34: ="" | M34: 2024Q2 | N34: Controlled monthly imputation | O34: Controlled monthly actual estimate
A35: 45412 | B35: 2024 | C35: Q2 | D35: Non-interest-bearing deposits | E35: No | F35: ='Sources & Checks'!$J$64 -> 27111 | G35: =0 -> 0 | H35: =0 -> 0 | I35: =F35/F36 -> 0.077608491 | J35: =F35-F29 -> 39.666667 | K35: =IF(F29=0,"n.a.",F35/F29-1) -> 0.0014652646 | L35: ="" | M35: 2024Q2 | N35: Quarterly average and EOP controlled interpolation | O35: Controlled monthly actual estimate
A36: 45412 | B36: 2024 | C36: Q2 | D36: Total deposits | E36: Mixed | F36: =SUM(F34,F35) -> 349330.33 | G36: =H36*12/F36 -> 0.03291646 | H36: =SUM(H34,H35) -> 958.22651 | I36: =F36/F36 -> 1 | J36: =F36-F30 -> 2821.3333 | K36: =IF(F30=0,"n.a.",F36/F30-1) -> 0.0081421647 | L36: ="" | M36: 2024Q2 | N36: Interest-bearing plus non-interest-bearing deposits | O36: Calculated monthly total
A37: 45443 | B37: 2024 | C37: Q2 | D37: Checking | E37: Yes | F37: ='Sources & Checks'!$C$65*'Sources & Checks'!$G$11 -> 34713.076 | G37: =H37*12/F37 -> 0.015858564 | H37: ='Sources & Checks'!$D$65*'Sources & Checks'!$D$11/'Sources & Checks'!$D$14 -> 45.87496 | I37: =F37/F42 -> 0.099816045 | J37: =F37-F31 -> -102.84595 | K37: =IF(F31=0,"n.a.",F37/F31-1) -> -0.002953992 | L37: ="" | M37: 2024Q2 | N37: Quarter balance and expense mix applied to controlled totals | O37: Allocated from reported quarter actual
A38: 45443 | B38: 2024 | C38: Q2 | D38: Savings | E38: Yes | F38: ='Sources & Checks'!$C$65*'Sources & Checks'!$G$12 -> 207981.67 | G38: =H38*12/F38 -> 0.033622865 | H38: ='Sources & Checks'!$D$65*'Sources & Checks'!$D$12/'Sources & Checks'!$D$14 -> 582.74497 | I38: =F38/F42 -> 0.59804287 | J38: =F38-F32 -> -616.19642 | K38: =IF(F32=0,"n.a.",F38/F32-1) -> -0.002953992 | L38: ="" | M38: 2024Q2 | N38: Quarter balance and expense mix applied to controlled totals | O38: Allocated from reported quarter actual
A39: 45443 | B39: 2024 | C39: Q2 | D39: Time deposits | E39: Yes | F39: ='Sources & Checks'!$C$65*'Sources & Checks'!$G$13 -> 78572.756 | G39: =H39*12/F39 -> 0.049906762 | H39: ='Sources & Checks'!$D$65*'Sources & Checks'!$D$13/'Sources & Checks'!$D$14 -> 326.77599 | I39: =F39/F42 -> 0.22593278 | J39: =F39-F33 -> -232.79095 | K39: =IF(F33=0,"n.a.",F39/F33-1) -> -0.002953992 | L39: ="" | M39: 2024Q2 | N39: Quarter balance and expense mix applied to controlled totals | O39: Allocated from reported quarter actual
A40: 45443 | B40: 2024 | C40: Q2 | D40: Total interest-bearing deposits | E40: Yes | F40: =SUM(F37:F39) -> 321267.5 | G40: =H40*12/F40 -> 0.035685997 | H40: =SUM(H37:H39) -> 955.39591 | I40: =F40/F42 -> 0.9237917 | J40: =F40-F34 -> -951.83333 | K40: =IF(F34=0,"n.a.",F40/F34-1) -> -0.002953992 | L40: ="" | M40: 2024Q2 | N40: Controlled monthly imputation | O40: Controlled monthly actual estimate
A41: 45443 | B41: 2024 | C41: Q2 | D41: Non-interest-bearing deposits | E41: No | F41: ='Sources & Checks'!$J$65 -> 26503 | G41: =0 -> 0 | H41: =0 -> 0 | I41: =F41/F42 -> 0.076208304 | J41: =F41-F35 -> -608 | K41: =IF(F35=0,"n.a.",F41/F35-1) -> -0.022426321 | L41: ="" | M41: 2024Q2 | N41: Quarterly average and EOP controlled interpolation | O41: Controlled monthly actual estimate
A42: 45443 | B42: 2024 | C42: Q2 | D42: Total deposits | E42: Mixed | F42: =SUM(F40,F41) -> 347770.5 | G42: =H42*12/F42 -> 0.032966427 | H42: =SUM(H40,H41) -> 955.39591 | I42: =F42/F42 -> 1 | J42: =F42-F36 -> -1559.8333 | K42: =IF(F36=0,"n.a.",F42/F36-1) -> -0.0044652101 | L42: ="" | M42: 2024Q2 | N42: Interest-bearing plus non-interest-bearing deposits | O42: Calculated monthly total
A43: 45473 | B43: 2024 | C43: Q2 | D43: Checking | E43: Yes | F43: ='Sources & Checks'!$C$66*'Sources & Checks'!$G$11 -> 34894.078 | G43: =H43*12/F43 -> 0.015858564 | H43: ='Sources & Checks'!$D$66*'Sources & Checks'!$D$11/'Sources & Checks'!$D$14 -> 46.114164 | I43: =F43/F48 -> 0.0997984 | J43: =F43-F37 -> 181.0024 | K43: =IF(F37=0,"n.a.",F43/F37-1) -> 0.0052142425 | L43: ="" | M43: 2024Q2 | N43: Quarter balance and expense mix applied to controlled totals | O43: Allocated from reported quarter actual
A44: 45473 | B44: 2024 | C44: Q2 | D44: Savings | E44: Yes | F44: ='Sources & Checks'!$C$66*'Sources & Checks'!$G$12 -> 209066.14 | G44: =H44*12/F44 -> 0.033622865 | H44: ='Sources & Checks'!$D$66*'Sources & Checks'!$D$12/'Sources & Checks'!$D$14 -> 585.78354 | I44: =F44/F48 -> 0.59793716 | J44: =F44-F38 -> 1084.4669 | K44: =IF(F38=0,"n.a.",F44/F38-1) -> 0.0052142425 | L44: ="" | M44: 2024Q2 | N44: Quarter balance and expense mix applied to controlled totals | O44: Allocated from reported quarter actual
A45: 45473 | B45: 2024 | C45: Q2 | D45: Time deposits | E45: Yes | F45: ='Sources & Checks'!$C$66*'Sources & Checks'!$G$13 -> 78982.453 | G45: =H45*12/F45 -> 0.049906762 | H45: ='Sources & Checks'!$D$66*'Sources & Checks'!$D$13/'Sources & Checks'!$D$14 -> 328.47987 | I45: =F45/F48 -> 0.22589284 | J45: =F45-F39 -> 409.69741 | K45: =IF(F39=0,"n.a.",F45/F39-1) -> 0.0052142425 | L45: ="" | M45: 2024Q2 | N45: Quarter balance and expense mix applied to controlled totals | O45: Allocated from reported quarter actual
A46: 45473 | B46: 2024 | C46: Q2 | D46: Total interest-bearing deposits | E46: Yes | F46: =SUM(F43:F45) -> 322942.67 | G46: =H46*12/F46 -> 0.035685997 | H46: =SUM(H43:H45) -> 960.37758 | I46: =F46/F48 -> 0.9236284 | J46: =F46-F40 -> 1675.1667 | K46: =IF(F40=0,"n.a.",F46/F40-1) -> 0.0052142425 | L46: ="" | M46: 2024Q2 | N46: Controlled monthly imputation | O46: Controlled monthly actual estimate
A47: 45473 | B47: 2024 | C47: Q2 | D47: Non-interest-bearing deposits | E47: No | F47: ='Sources & Checks'!$J$66 -> 26703 | G47: =0 -> 0 | H47: =0 -> 0 | I47: =F47/F48 -> 0.076371603 | J47: =F47-F41 -> 200 | K47: =IF(F41=0,"n.a.",F47/F41-1) -> 0.0075463155 | L47: ="" | M47: 2024Q2 | N47: Quarterly average and EOP controlled interpolation | O47: Controlled monthly actual estimate
A48: 45473 | B48: 2024 | C48: Q2 | D48: Total deposits | E48: Mixed | F48: =SUM(F46,F47) -> 349645.67 | G48: =H48*12/F48 -> 0.0329606 | H48: =SUM(H46,H47) -> 960.37758 | I48: =F48/F48 -> 1 | J48: =F48-F42 -> 1875.1667 | K48: =IF(F42=0,"n.a.",F48/F42-1) -> 0.0053919659 | L48: ="" | M48: 2024Q2 | N48: Interest-bearing plus non-interest-bearing deposits | O48: Calculated monthly total
A49: 45504 | B49: 2024 | C49: Q3 | D49: Checking | E49: Yes | F49: ='Sources & Checks'!$C$67*'Sources & Checks'!$G$16 -> 33837.838 | G49: =H49*12/F49 -> 0.015934172 | H49: ='Sources & Checks'!$D$67*'Sources & Checks'!$D$16/'Sources & Checks'!$D$19 -> 44.931495 | I49: =F49/F54 -> 0.096570457 | J49: =F49-F43 -> -1056.2407 | K49: =IF(F43=0,"n.a.",F49/F43-1) -> -0.030269911 | L49: ="" | M49: 2024Q3 | N49: Quarter balance and expense mix applied to controlled totals | O49: Allocated from reported quarter actual
A50: 45504 | B50: 2024 | C50: Q3 | D50: Savings | E50: Yes | F50: ='Sources & Checks'!$C$67*'Sources & Checks'!$G$17 -> 210995.91 | G50: =H50*12/F50 -> 0.034545158 | H50: ='Sources & Checks'!$D$67*'Sources & Checks'!$D$17/'Sources & Checks'!$D$19 -> 607.40725 | I50: =F50/F54 -> 0.60216529 | J50: =F50-F44 -> 1929.7727 | K50: =IF(F44=0,"n.a.",F50/F44-1) -> 0.0092304415 | L50: ="" | M50: 2024Q3 | N50: Quarter balance and expense mix applied to controlled totals | O50: Allocated from reported quarter actual
A51: 45504 | B51: 2024 | C51: Q3 | D51: Time deposits | E51: Yes | F51: ='Sources & Checks'!$C$67*'Sources & Checks'!$G$18 -> 78736.588 | G51: =H51*12/F51 -> 0.049964091 | H51: ='Sources & Checks'!$D$67*'Sources & Checks'!$D$18/'Sources & Checks'!$D$19 -> 327.8335 | I51: =F51/F54 -> 0.22470787 | J51: =F51-F45 -> -245.86542 | K51: =IF(F45=0,"n.a.",F51/F45-1) -> -0.0031129119 | L51: ="" | M51: 2024Q3 | N51: Quarter balance and expense mix applied to controlled totals | O51: Allocated from reported quarter actual
A52: 45504 | B52: 2024 | C52: Q3 | D52: Total interest-bearing deposits | E52: Yes | F52: =SUM(F49:F51) -> 323570.33 | G52: =H52*12/F52 -> 0.036350882 | H52: =SUM(H49:H51) -> 980.17224 | I52: =F52/F54 -> 0.92344362 | J52: =F52-F46 -> 627.66667 | K52: =IF(F46=0,"n.a.",F52/F46-1) -> 0.0019435854 | L52: ="" | M52: 2024Q3 | N52: Controlled monthly imputation | O52: Controlled monthly actual estimate
A53: 45504 | B53: 2024 | C53: Q3 | D53: Non-interest-bearing deposits | E53: No | F53: ='Sources & Checks'!$J$67 -> 26825 | G53: =0 -> 0 | H53: =0 -> 0 | I53: =F53/F54 -> 0.076556385 | J53: =F53-F47 -> 122 | K53: =IF(F47=0,"n.a.",F53/F47-1) -> 0.004568775 | L53: ="" | M53: 2024Q3 | N53: Quarterly average and EOP controlled interpolation | O53: Controlled monthly actual estimate
A54: 45504 | B54: 2024 | C54: Q3 | D54: Total deposits | E54: Mixed | F54: =SUM(F52,F53) -> 350395.33 | G54: =H54*12/F54 -> 0.03356799 | H54: =SUM(H52,H53) -> 980.17224 | I54: =F54/F54 -> 1 | J54: =F54-F48 -> 749.66667 | K54: =IF(F48=0,"n.a.",F54/F48-1) -> 0.0021440754 | L54: ="" | M54: 2024Q3 | N54: Interest-bearing plus non-interest-bearing deposits | O54: Calculated monthly total
A55: 45535 | B55: 2024 | C55: Q3 | D55: Checking | E55: Yes | F55: ='Sources & Checks'!$C$68*'Sources & Checks'!$G$16 -> 33796.286 | G55: =H55*12/F55 -> 0.015934172 | H55: ='Sources & Checks'!$D$68*'Sources & Checks'!$D$16/'Sources & Checks'!$D$19 -> 44.876321 | I55: =F55/F60 -> 0.096639923 | J55: =F55-F49 -> -41.55171 | K55: =IF(F49=0,"n.a.",F55/F49-1) -> -0.0012279659 | L55: ="" | M55: 2024Q3 | N55: Quarter balance and expense mix applied to controlled totals | O55: Allocated from reported quarter actual
A56: 45535 | B56: 2024 | C56: Q3 | D56: Savings | E56: Yes | F56: ='Sources & Checks'!$C$68*'Sources & Checks'!$G$17 -> 210736.81 | G56: =H56*12/F56 -> 0.034545158 | H56: ='Sources & Checks'!$D$68*'Sources & Checks'!$D$17/'Sources & Checks'!$D$19 -> 606.66137 | I56: =F56/F60 -> 0.60259845 | J56: =F56-F50 -> -259.09578 | K56: =IF(F50=0,"n.a.",F56/F50-1) -> -0.0012279659 | L56: ="" | M56: 2024Q3 | N56: Quarter balance and expense mix applied to controlled totals | O56: Allocated from reported quarter actual
A57: 45535 | B57: 2024 | C57: Q3 | D57: Time deposits | E57: Yes | F57: ='Sources & Checks'!$C$68*'Sources & Checks'!$G$18 -> 78639.902 | G57: =H57*12/F57 -> 0.049964091 | H57: ='Sources & Checks'!$D$68*'Sources & Checks'!$D$18/'Sources & Checks'!$D$19 -> 327.43093 | I57: =F57/F60 -> 0.22486951 | J57: =F57-F51 -> -96.685844 | K57: =IF(F51=0,"n.a.",F57/F51-1) -> -0.0012279659 | L57: ="" | M57: 2024Q3 | N57: Quarter balance and expense mix applied to controlled totals | O57: Allocated from reported quarter actual
A58: 45535 | B58: 2024 | C58: Q3 | D58: Total interest-bearing deposits | E58: Yes | F58: =SUM(F55:F57) -> 323173 | G58: =H58*12/F58 -> 0.036350882 | H58: =SUM(H55:H57) -> 978.96862 | I58: =F58/F60 -> 0.92410788 | J58: =F58-F52 -> -397.33333 | K58: =IF(F52=0,"n.a.",F58/F52-1) -> -0.0012279659 | L58: ="" | M58: 2024Q3 | N58: Controlled monthly imputation | O58: Controlled monthly actual estimate
A59: 45535 | B59: 2024 | C59: Q3 | D59: Non-interest-bearing deposits | E59: No | F59: ='Sources & Checks'!$J$68 -> 26540.5 | G59: =0 -> 0 | H59: =0 -> 0 | I59: =F59/F60 -> 0.075892123 | J59: =F59-F53 -> -284.5 | K59: =IF(F53=0,"n.a.",F59/F53-1) -> -0.010605778 | L59: ="" | M59: 2024Q3 | N59: Quarterly average and EOP controlled interpolation | O59: Controlled monthly actual estimate
A60: 45535 | B60: 2024 | C60: Q3 | D60: Total deposits | E60: Mixed | F60: =SUM(F58,F59) -> 349713.5 | G60: =H60*12/F60 -> 0.033592136 | H60: =SUM(H58,H59) -> 978.96862 | I60: =F60/F60 -> 1 | J60: =F60-F54 -> -681.83333 | K60: =IF(F54=0,"n.a.",F60/F54-1) -> -0.0019458973 | L60: ="" | M60: 2024Q3 | N60: Interest-bearing plus non-interest-bearing deposits | O60: Calculated monthly total
A61: 45565 | B61: 2024 | C61: Q3 | D61: Checking | E61: Yes | F61: ='Sources & Checks'!$C$69*'Sources & Checks'!$G$16 -> 34034.162 | G61: =H61*12/F61 -> 0.015934172 | H61: ='Sources & Checks'!$D$69*'Sources & Checks'!$D$16/'Sources & Checks'!$D$19 -> 45.192184 | I61: =F61/F66 -> 0.096727898 | J61: =F61-F55 -> 237.87657 | K61: =IF(F55=0,"n.a.",F61/F55-1) -> 0.0070385418 | L61: ="" | M61: 2024Q3 | N61: Quarter balance and expense mix applied to controlled totals | O61: Allocated from reported quarter actual
A62: 45565 | B62: 2024 | C62: Q3 | D62: Savings | E62: Yes | F62: ='Sources & Checks'!$C$69*'Sources & Checks'!$G$17 -> 212220.09 | G62: =H62*12/F62 -> 0.034545158 | H62: ='Sources & Checks'!$D$69*'Sources & Checks'!$D$17/'Sources & Checks'!$D$19 -> 610.93138 | I62: =F62/F66 -> 0.60314702 | J62: =F62-F56 -> 1483.2799 | K62: =IF(F56=0,"n.a.",F62/F56-1) -> 0.0070385418 | L62: ="" | M62: 2024Q3 | N62: Quarter balance and expense mix applied to controlled totals | O62: Allocated from reported quarter actual
A63: 45565 | B63: 2024 | C63: Q3 | D63: Time deposits | E63: Yes | F63: ='Sources & Checks'!$C$69*'Sources & Checks'!$G$18 -> 79193.412 | G63: =H63*12/F63 -> 0.049964091 | H63: ='Sources & Checks'!$D$69*'Sources & Checks'!$D$18/'Sources & Checks'!$D$19 -> 329.73557 | I63: =F63/F66 -> 0.22507421 | J63: =F63-F57 -> 553.51024 | K63: =IF(F57=0,"n.a.",F63/F57-1) -> 0.0070385418 | L63: ="" | M63: 2024Q3 | N63: Quarter balance and expense mix applied to controlled totals | O63: Allocated from reported quarter actual
A64: 45565 | B64: 2024 | C64: Q3 | D64: Total interest-bearing deposits | E64: Yes | F64: =SUM(F61:F63) -> 325447.67 | G64: =H64*12/F64 -> 0.036350882 | H64: =SUM(H61:H63) -> 985.85914 | I64: =F64/F66 -> 0.92494913 | J64: =F64-F58 -> 2274.6667 | K64: =IF(F58=0,"n.a.",F64/F58-1) -> 0.0070385418 | L64: ="" | M64: 2024Q3 | N64: Controlled monthly imputation | O64: Controlled monthly actual estimate
A65: 45565 | B65: 2024 | C65: Q3 | D65: Non-interest-bearing deposits | E65: No | F65: ='Sources & Checks'!$J$69 -> 26407 | G65: =0 -> 0 | H65: =0 -> 0 | I65: =F65/F66 -> 0.075050873 | J65: =F65-F59 -> -133.5 | K65: =IF(F59=0,"n.a.",F65/F59-1) -> -0.0050300484 | L65: ="" | M65: 2024Q3 | N65: Quarterly average and EOP controlled interpolation | O65: Controlled monthly actual estimate
A66: 45565 | B66: 2024 | C66: Q3 | D66: Total deposits | E66: Mixed | F66: =SUM(F64,F65) -> 351854.67 | G66: =H66*12/F66 -> 0.033622716 | H66: =SUM(H64,H65) -> 985.85914 | I66: =F66/F66 -> 1 | J66: =F66-F60 -> 2141.1667 | K66: =IF(F60=0,"n.a.",F66/F60-1) -> 0.0061226309 | L66: ="" | M66: 2024Q3 | N66: Interest-bearing plus non-interest-bearing deposits | O66: Calculated monthly total
A67: 45596 | B67: 2024 | C67: Q4 | D67: Checking | E67: Yes | F67: ='Sources & Checks'!$C$70*'Sources & Checks'!$G$21 -> 34799.482 | G67: =H67*12/F67 -> 0.014009733 | H67: ='Sources & Checks'!$D$70*'Sources & Checks'!$D$21/'Sources & Checks'!$D$24 -> 40.627622 | I67: =F67/F72 -> 0.097929701 | J67: =F67-F61 -> 765.32002 | K67: =IF(F61=0,"n.a.",F67/F61-1) -> 0.022486818 | L67: ="" | M67: 2024Q4 | N67: Quarter balance and expense mix applied to controlled totals | O67: Allocated from derived Q4 actual
A68: 45596 | B68: 2024 | C68: Q4 | D68: Savings | E68: Yes | F68: ='Sources & Checks'!$C$70*'Sources & Checks'!$G$22 -> 215350.84 | G68: =H68*12/F68 -> 0.032835666 | H68: ='Sources & Checks'!$D$70*'Sources & Checks'!$D$22/'Sources & Checks'!$D$24 -> 589.26567 | I68: =F68/F72 -> 0.60602174 | J68: =F68-F62 -> 3130.7432 | K68: =IF(F62=0,"n.a.",F68/F62-1) -> 0.014752341 | L68: ="" | M68: 2024Q4 | N68: Quarter balance and expense mix applied to controlled totals | O68: Allocated from derived Q4 actual
A69: 45596 | B69: 2024 | C69: Q4 | D69: Time deposits | E69: Yes | F69: ='Sources & Checks'!$C$70*'Sources & Checks'!$G$23 -> 78359.016 | G69: =H69*12/F69 -> 0.048307208 | H69: ='Sources & Checks'!$D$70*'Sources & Checks'!$D$23/'Sources & Checks'!$D$24 -> 315.4421 | I69: =F69/F72 -> 0.22051118 | J69: =F69-F63 -> -834.39653 | K69: =IF(F63=0,"n.a.",F69/F63-1) -> -0.010536186 | L69: ="" | M69: 2024Q4 | N69: Quarter balance and expense mix applied to controlled totals | O69: Allocated from derived Q4 actual
A70: 45596 | B70: 2024 | C70: Q4 | D70: Total interest-bearing deposits | E70: Yes | F70: =SUM(F67:F69) -> 328509.33 | G70: =H70*12/F70 -> 0.034531819 | H70: =SUM(H67:H69) -> 945.33539 | I70: =F70/F72 -> 0.92446262 | J70: =F70-F64 -> 3061.6667 | K70: =IF(F64=0,"n.a.",F70/F64-1) -> 0.0094075545 | L70: ="" | M70: 2024Q4 | N70: Controlled monthly imputation | O70: Controlled monthly actual estimate
A71: 45596 | B71: 2024 | C71: Q4 | D71: Non-interest-bearing deposits | E71: No | F71: ='Sources & Checks'!$J$70 -> 26842.333 | G71: =0 -> 0 | H71: =0 -> 0 | I71: =F71/F72 -> 0.075537378 | J71: =F71-F65 -> 435.33333 | K71: =IF(F65=0,"n.a.",F71/F65-1) -> 0.016485528 | L71: ="" | M71: 2024Q4 | N71: Quarterly average and EOP controlled interpolation | O71: Controlled monthly estimate using derived Q4
A72: 45596 | B72: 2024 | C72: Q4 | D72: Total deposits | E72: Mixed | F72: =SUM(F70,F71) -> 355351.67 | G72: =H72*12/F72 -> 0.031923376 | H72: =SUM(H70,H71) -> 945.33539 | I72: =F72/F72 -> 1 | J72: =F72-F66 -> 3497 | K72: =IF(F66=0,"n.a.",F72/F66-1) -> 0.0099387626 | L72: ="" | M72: 2024Q4 | N72: Interest-bearing plus non-interest-bearing deposits | O72: Calculated monthly total
A73: 45626 | B73: 2024 | C73: Q4 | D73: Checking | E73: Yes | F73: ='Sources & Checks'!$C$71*'Sources & Checks'!$G$21 -> 35097.326 | G73: =H73*12/F73 -> 0.014009733 | H73: ='Sources & Checks'!$D$71*'Sources & Checks'!$D$21/'Sources & Checks'!$D$24 -> 40.975348 | I73: =F73/F78 -> 0.097877286 | J73: =F73-F67 -> 297.84403 | K73: =IF(F67=0,"n.a.",F73/F67-1) -> 0.0085588639 | L73: ="" | M73: 2024Q4 | N73: Quarter balance and expense mix applied to controlled totals | O73: Allocated from derived Q4 actual
A74: 45626 | B74: 2024 | C74: Q4 | D74: Savings | E74: Yes | F74: ='Sources & Checks'!$C$71*'Sources & Checks'!$G$22 -> 217193.99 | G74: =H74*12/F74 -> 0.032835666 | H74: ='Sources & Checks'!$D$71*'Sources & Checks'!$D$22/'Sources & Checks'!$D$24 -> 594.30911 | I74: =F74/F78 -> 0.60569738 | J74: =F74-F68 -> 1843.1585 | K74: =IF(F68=0,"n.a.",F74/F68-1) -> 0.0085588639 | L74: ="" | M74: 2024Q4 | N74: Quarter balance and expense mix applied to controlled totals | O74: Allocated from derived Q4 actual
A75: 45626 | B75: 2024 | C75: Q4 | D75: Time deposits | E75: Yes | F75: ='Sources & Checks'!$C$71*'Sources & Checks'!$G$23 -> 79029.68 | G75: =H75*12/F75 -> 0.048307208 | H75: ='Sources & Checks'!$D$71*'Sources & Checks'!$D$23/'Sources & Checks'!$D$24 -> 318.14193 | I75: =F75/F78 -> 0.22039316 | J75: =F75-F69 -> 670.66415 | K75: =IF(F69=0,"n.a.",F75/F69-1) -> 0.0085588639 | L75: ="" | M75: 2024Q4 | N75: Quarter balance and expense mix applied to controlled totals | O75: Allocated from derived Q4 actual
A76: 45626 | B76: 2024 | C76: Q4 | D76: Total interest-bearing deposits | E76: Yes | F76: =SUM(F73:F75) -> 331321 | G76: =H76*12/F76 -> 0.034531819 | H76: =SUM(H73:H75) -> 953.42639 | I76: =F76/F78 -> 0.92396782 | J76: =F76-F70 -> 2811.6667 | K76: =IF(F70=0,"n.a.",F76/F70-1) -> 0.0085588639 | L76: ="" | M76: 2024Q4 | N76: Controlled monthly imputation | O76: Controlled monthly actual estimate
A77: 45626 | B77: 2024 | C77: Q4 | D77: Non-interest-bearing deposits | E77: No | F77: ='Sources & Checks'!$J$71 -> 27264 | G77: =0 -> 0 | H77: =0 -> 0 | I77: =F77/F78 -> 0.076032182 | J77: =F77-F71 -> 421.66667 | K77: =IF(F71=0,"n.a.",F77/F71-1) -> 0.015709017 | L77: ="" | M77: 2024Q4 | N77: Quarterly average and EOP controlled interpolation | O77: Controlled monthly estimate using derived Q4
A78: 45626 | B78: 2024 | C78: Q4 | D78: Total deposits | E78: Mixed | F78: =SUM(F76,F77) -> 358585 | G78: =H78*12/F78 -> 0.031906289 | H78: =SUM(H76,H77) -> 953.42639 | I78: =F78/F78 -> 1 | J78: =F78-F72 -> 3233.3333 | K78: =IF(F72=0,"n.a.",F78/F72-1) -> 0.0090989677 | L78: ="" | M78: 2024Q4 | N78: Interest-bearing plus non-interest-bearing deposits | O78: Calculated monthly total
A79: 45657 | B79: 2024 | C79: Q4 | D79: Checking | E79: Yes | F79: ='Sources & Checks'!$C$72*'Sources & Checks'!$G$21 -> 35458.518 | G79: =H79*12/F79 -> 0.014009733 | H79: ='Sources & Checks'!$D$72*'Sources & Checks'!$D$21/'Sources & Checks'!$D$24 -> 41.39703 | I79: =F79/F84 -> 0.098113693 | J79: =F79-F73 -> 361.19106 | K79: =IF(F73=0,"n.a.",F79/F73-1) -> 0.010291128 | L79: ="" | M79: 2024Q4 | N79: Quarter balance and expense mix applied to controlled totals | O79: Allocated from derived Q4 actual
A80: 45657 | B80: 2024 | C80: Q4 | D80: Savings | E80: Yes | F80: ='Sources & Checks'!$C$72*'Sources & Checks'!$G$22 -> 219429.16 | G80: =H80*12/F80 -> 0.032835666 | H80: ='Sources & Checks'!$D$72*'Sources & Checks'!$D$22/'Sources & Checks'!$D$24 -> 600.42522 | I80: =F80/F84 -> 0.60716034 | J80: =F80-F74 -> 2235.1711 | K80: =IF(F74=0,"n.a.",F80/F74-1) -> 0.010291128 | L80: ="" | M80: 2024Q4 | N80: Quarter balance and expense mix applied to controlled totals | O80: Allocated from derived Q4 actual
A81: 45657 | B81: 2024 | C81: Q4 | D81: Time deposits | E81: Yes | F81: ='Sources & Checks'!$C$72*'Sources & Checks'!$G$23 -> 79842.984 | G81: =H81*12/F81 -> 0.048307208 | H81: ='Sources & Checks'!$D$72*'Sources & Checks'!$D$23/'Sources & Checks'!$D$24 -> 321.41597 | I81: =F81/F84 -> 0.22092548 | J81: =F81-F75 -> 813.30451 | K81: =IF(F75=0,"n.a.",F81/F75-1) -> 0.010291128 | L81: ="" | M81: 2024Q4 | N81: Quarter balance and expense mix applied to controlled totals | O81: Allocated from derived Q4 actual
A82: 45657 | B82: 2024 | C82: Q4 | D82: Total interest-bearing deposits | E82: Yes | F82: =SUM(F79:F81) -> 334730.67 | G82: =H82*12/F82 -> 0.034531819 | H82: =SUM(H79:H81) -> 963.23822 | I82: =F82/F84 -> 0.92619952 | J82: =F82-F76 -> 3409.6667 | K82: =IF(F76=0,"n.a.",F82/F76-1) -> 0.010291128 | L82: ="" | M82: 2024Q4 | N82: Controlled monthly imputation | O82: Controlled monthly actual estimate
A83: 45657 | B83: 2024 | C83: Q4 | D83: Non-interest-bearing deposits | E83: No | F83: ='Sources & Checks'!$J$72 -> 26671.667 | G83: =0 -> 0 | H83: =0 -> 0 | I83: =F83/F84 -> 0.073800483 | J83: =F83-F77 -> -592.33333 | K83: =IF(F77=0,"n.a.",F83/F77-1) -> -0.021725841 | L83: ="" | M83: 2024Q4 | N83: Quarterly average and EOP controlled interpolation | O83: Controlled monthly estimate using derived Q4
A84: 45657 | B84: 2024 | C84: Q4 | D84: Total deposits | E84: Mixed | F84: =SUM(F82,F83) -> 361402.33 | G84: =H84*12/F84 -> 0.031983354 | H84: =SUM(H82,H83) -> 963.23822 | I84: =F84/F84 -> 1 | J84: =F84-F78 -> 2817.3333 | K84: =IF(F78=0,"n.a.",F84/F78-1) -> 0.0078568075 | L84: ="" | M84: 2024Q4 | N84: Interest-bearing plus non-interest-bearing deposits | O84: Calculated monthly total
A85: 45688 | B85: 2025 | C85: Q1 | D85: Checking | E85: Yes | F85: ='Sources & Checks'!$C$73*'Sources & Checks'!$G$26 -> 36128.228 | G85: =H85*12/F85 -> 0.013130475 | H85: ='Sources & Checks'!$D$73*'Sources & Checks'!$D$26/'Sources & Checks'!$D$29 -> 39.531733 | I85: =F85/F90 -> 0.099666184 | J85: =F85-F79 -> 669.71 | K85: =IF(F79=0,"n.a.",F85/F79-1) -> 0.01888714 | L85: =IF(F13=0,"n.a.",F85/F13-1) -> 0.014944609 | M85: 2025Q1 | N85: Quarter balance and expense mix applied to controlled totals | O85: Allocated from reported quarter actual
A86: 45688 | B86: 2025 | C86: Q1 | D86: Savings | E86: Yes | F86: ='Sources & Checks'!$C$73*'Sources & Checks'!$G$27 -> 226795.86 | G86: =H86*12/F86 -> 0.031076155 | H86: ='Sources & Checks'!$D$73*'Sources & Checks'!$D$27/'Sources & Checks'!$D$29 -> 587.32861 | I86: =F86/F90 -> 0.62565698 | J86: =F86-F80 -> 7366.6922 | K86: =IF(F80=0,"n.a.",F86/F80-1) -> 0.033572074 | L86: =IF(F14=0,"n.a.",F86/F14-1) -> 0.10105676 | M86: 2025Q1 | N86: Quarter balance and expense mix applied to controlled totals | O86: Allocated from reported quarter actual
A87: 45688 | B87: 2025 | C87: Q1 | D87: Time deposits | E87: Yes | F87: ='Sources & Checks'!$C$73*'Sources & Checks'!$G$28 -> 73456.249 | G87: =H87*12/F87 -> 0.044934688 | H87: ='Sources & Checks'!$D$73*'Sources & Checks'!$D$28/'Sources & Checks'!$D$29 -> 275.06113 | I87: =F87/F90 -> 0.20264221 | J87: =F87-F81 -> -6386.7355 | K87: =IF(F81=0,"n.a.",F87/F81-1) -> -0.079991193 | L87: =IF(F15=0,"n.a.",F87/F15-1) -> -0.032017278 | M87: 2025Q1 | N87: Quarter balance and expense mix applied to controlled totals | O87: Allocated from reported quarter actual
A88: 45688 | B88: 2025 | C88: Q1 | D88: Total interest-bearing deposits | E88: Yes | F88: =SUM(F85:F87) -> 336380.33 | G88: =H88*12/F88 -> 0.032175061 | H88: =SUM(H85:H87) -> 901.92147 | I88: =F88/F90 -> 0.92796537 | J88: =F88-F82 -> 1649.6667 | K88: =IF(F82=0,"n.a.",F88/F82-1) -> 0.0049283404 | L88: =IF(F16=0,"n.a.",F88/F16-1) -> 0.059591322 | M88: 2025Q1 | N88: Controlled monthly imputation | O88: Controlled monthly actual estimate
A89: 45688 | B89: 2025 | C89: Q1 | D89: Non-interest-bearing deposits | E89: No | F89: ='Sources & Checks'!$J$73 -> 26112 | G89: =0 -> 0 | H89: =0 -> 0 | I89: =F89/F90 -> 0.072034627 | J89: =F89-F83 -> -559.66667 | K89: =IF(F83=0,"n.a.",F89/F83-1) -> -0.020983566 | L89: =IF(F17=0,"n.a.",F89/F17-1) -> -0.045009021 | M89: 2025Q1 | N89: Quarterly average and EOP controlled interpolation | O89: Controlled monthly actual estimate
A90: 45688 | B90: 2025 | C90: Q1 | D90: Total deposits | E90: Mixed | F90: =SUM(F88,F89) -> 362492.33 | G90: =H90*12/F90 -> 0.029857342 | H90: =SUM(H88,H89) -> 901.92147 | I90: =F90/F90 -> 1 | J90: =F90-F84 -> 1090 | K90: =IF(F84=0,"n.a.",F90/F84-1) -> 0.0030160292 | L90: =IF(F18=0,"n.a.",F90/F18-1) -> 0.051296627 | M90: 2025Q1 | N90: Interest-bearing plus non-interest-bearing deposits | O90: Calculated monthly total
A91: 45716 | B91: 2025 | C91: Q1 | D91: Checking | E91: Yes | F91: ='Sources & Checks'!$C$74*'Sources & Checks'!$G$26 -> 36184.632 | G91: =H91*12/F91 -> 0.013130475 | H91: ='Sources & Checks'!$D$74*'Sources & Checks'!$D$26/'Sources & Checks'!$D$29 -> 39.593451 | I91: =F91/F96 -> 0.099662826 | J91: =F91-F85 -> 56.40443 | K91: =IF(F85=0,"n.a.",F91/F85-1) -> 0.0015612288 | L91: =IF(F19=0,"n.a.",F91/F19-1) -> 0.024379375 | M91: 2025Q1 | N91: Quarter balance and expense mix applied to controlled totals | O91: Allocated from reported quarter actual
A92: 45716 | B92: 2025 | C92: Q1 | D92: Savings | E92: Yes | F92: ='Sources & Checks'!$C$74*'Sources & Checks'!$G$27 -> 227149.94 | G92: =H92*12/F92 -> 0.031076155 | H92: ='Sources & Checks'!$D$74*'Sources & Checks'!$D$27/'Sources & Checks'!$D$29 -> 588.24556 | I92: =F92/F96 -> 0.6256359 | J92: =F92-F86 -> 354.08023 | K92: =IF(F86=0,"n.a.",F92/F86-1) -> 0.0015612288 | L92: =IF(F20=0,"n.a.",F92/F20-1) -> 0.11129201 | M92: 2025Q1 | N92: Quarter balance and expense mix applied to controlled totals | O92: Allocated from reported quarter actual
A93: 45716 | B93: 2025 | C93: Q1 | D93: Time deposits | E93: Yes | F93: ='Sources & Checks'!$C$74*'Sources & Checks'!$G$28 -> 73570.931 | G93: =H93*12/F93 -> 0.044934688 | H93: ='Sources & Checks'!$D$74*'Sources & Checks'!$D$28/'Sources & Checks'!$D$29 -> 275.49057 | I93: =F93/F96 -> 0.20263539 | J93: =F93-F87 -> 114.68201 | K93: =IF(F87=0,"n.a.",F93/F87-1) -> 0.0015612288 | L93: =IF(F21=0,"n.a.",F93/F21-1) -> -0.023019063 | M93: 2025Q1 | N93: Quarter balance and expense mix applied to controlled totals | O93: Allocated from reported quarter actual
A94: 45716 | B94: 2025 | C94: Q1 | D94: Total interest-bearing deposits | E94: Yes | F94: =SUM(F91:F93) -> 336905.5 | G94: =H94*12/F94 -> 0.032175061 | H94: =SUM(H91:H93) -> 903.32958 | I94: =F94/F96 -> 0.92793411 | J94: =F94-F88 -> 525.16667 | K94: =IF(F88=0,"n.a.",F94/F88-1) -> 0.0015612288 | L94: =IF(F22=0,"n.a.",F94/F22-1) -> 0.069441116 | M94: 2025Q1 | N94: Controlled monthly imputation | O94: Controlled monthly actual estimate
A95: 45716 | B95: 2025 | C95: Q1 | D95: Non-interest-bearing deposits | E95: No | F95: ='Sources & Checks'!$J$74 -> 26165 | G95: =0 -> 0 | H95: =0 -> 0 | I95: =F95/F96 -> 0.072065894 | J95: =F95-F89 -> 53 | K95: =IF(F89=0,"n.a.",F95/F89-1) -> 0.0020297181 | L95: =IF(F23=0,"n.a.",F95/F23-1) -> -0.01611296 | M95: 2025Q1 | N95: Quarterly average and EOP controlled interpolation | O95: Controlled monthly actual estimate
A96: 45716 | B96: 2025 | C96: Q1 | D96: Total deposits | E96: Mixed | F96: =SUM(F94,F95) -> 363070.5 | G96: =H96*12/F96 -> 0.029856336 | H96: =SUM(H94,H95) -> 903.32958 | I96: =F96/F96 -> 1 | J96: =F96-F90 -> 578.16667 | K96: =IF(F90=0,"n.a.",F96/F90-1) -> 0.0015949763 | L96: =IF(F24=0,"n.a.",F96/F24-1) -> 0.062781194 | M96: 2025Q1 | N96: Interest-bearing plus non-interest-bearing deposits | O96: Calculated monthly total
A97: 45747 | B97: 2025 | C97: Q1 | D97: Checking | E97: Yes | F97: ='Sources & Checks'!$C$75*'Sources & Checks'!$G$26 -> 36441.772 | G97: =H97*12/F97 -> 0.013130475 | H97: ='Sources & Checks'!$D$75*'Sources & Checks'!$D$26/'Sources & Checks'!$D$29 -> 39.874816 | I97: =F97/F102 -> 0.099659266 | J97: =F97-F91 -> 257.14047 | K97: =IF(F91=0,"n.a.",F97/F91-1) -> 0.0071063449 | L97: =IF(F25=0,"n.a.",F97/F25-1) -> 0.01742231 | M97: 2025Q1 | N97: Quarter balance and expense mix applied to controlled totals | O97: Allocated from reported quarter actual
A98: 45747 | B98: 2025 | C98: Q1 | D98: Savings | E98: Yes | F98: ='Sources & Checks'!$C$75*'Sources & Checks'!$G$27 -> 228764.14 | G98: =H98*12/F98 -> 0.031076155 | H98: ='Sources & Checks'!$D$75*'Sources & Checks'!$D$27/'Sources & Checks'!$D$29 -> 592.42584 | I98: =F98/F102 -> 0.62561355 | J98: =F98-F92 -> 1614.2058 | K98: =IF(F92=0,"n.a.",F98/F92-1) -> 0.0071063449 | L98: =IF(F26=0,"n.a.",F98/F26-1) -> 0.10374468 | M98: 2025Q1 | N98: Quarter balance and expense mix applied to controlled totals | O98: Allocated from reported quarter actual
A99: 45747 | B99: 2025 | C99: Q1 | D99: Time deposits | E99: Yes | F99: ='Sources & Checks'!$C$75*'Sources & Checks'!$G$28 -> 74093.751 | G99: =H99*12/F99 -> 0.044934688 | H99: ='Sources & Checks'!$D$75*'Sources & Checks'!$D$28/'Sources & Checks'!$D$29 -> 277.4483 | I99: =F99/F102 -> 0.20262815 | J99: =F99-F93 -> 522.82041 | K99: =IF(F93=0,"n.a.",F99/F93-1) -> 0.0071063449 | L99: =IF(F27=0,"n.a.",F99/F27-1) -> -0.029654221 | M99: 2025Q1 | N99: Quarter balance and expense mix applied to controlled totals | O99: Allocated from reported quarter actual
A100: 45747 | B100: 2025 | C100: Q1 | D100: Total interest-bearing deposits | E100: Yes | F100: =SUM(F97:F99) -> 339299.67 | G100: =H100*12/F100 -> 0.032175061 | H100: =SUM(H97:H99) -> 909.74895 | I100: =F100/F102 -> 0.92790096 | J100: =F100-F94 -> 2394.1667 | K100: =IF(F94=0,"n.a.",F100/F94-1) -> 0.0071063449 | L100: =IF(F28=0,"n.a.",F100/F28-1) -> 0.062178015 | M100: 2025Q1 | N100: Controlled monthly imputation | O100: Controlled monthly actual estimate
A101: 45747 | B101: 2025 | C101: Q1 | D101: Non-interest-bearing deposits | E101: No | F101: ='Sources & Checks'!$J$75 -> 26364 | G101: =0 -> 0 | H101: =0 -> 0 | I101: =F101/F102 -> 0.072099042 | J101: =F101-F95 -> 199 | K101: =IF(F95=0,"n.a.",F101/F95-1) -> 0.00760558 | L101: =IF(F29=0,"n.a.",F101/F29-1) -> -0.0261285 | M101: 2025Q1 | N101: Quarterly average and EOP controlled interpolation | O101: Controlled monthly actual estimate
A102: 45747 | B102: 2025 | C102: Q1 | D102: Total deposits | E102: Mixed | F102: =SUM(F100,F101) -> 365663.67 | G102: =H102*12/F102 -> 0.02985527 | H102: =SUM(H100,H101) -> 909.74895 | I102: =F102/F102 -> 1 | J102: =F102-F96 -> 2593.1667 | K102: =IF(F96=0,"n.a.",F102/F96-1) -> 0.0071423227 | L102: =IF(F30=0,"n.a.",F102/F30-1) -> 0.055278987 | M102: 2025Q1 | N102: Interest-bearing plus non-interest-bearing deposits | O102: Calculated monthly total
A103: 45777 | B103: 2025 | C103: Q2 | D103: Checking | E103: Yes | F103: ='Sources & Checks'!$C$76*'Sources & Checks'!$G$31 -> 32718.204 | G103: =H103*12/F103 -> 0.012111199 | H103: ='Sources & Checks'!$D$76*'Sources & Checks'!$D$31/'Sources & Checks'!$D$34 -> 33.021391 | I103: =F103/F108 -> 0.085870194 | J103: =F103-F97 -> -3723.5684 | K103: =IF(F97=0,"n.a.",F103/F97-1) -> -0.10217858 | L103: =IF(F31=0,"n.a.",F103/F31-1) -> -0.060251678 | M103: 2025Q2 | N103: Quarter balance and expense mix applied to controlled totals | O103: Allocated from reported quarter actual
A104: 45777 | B104: 2025 | C104: Q2 | D104: Savings | E104: Yes | F104: ='Sources & Checks'!$C$76*'Sources & Checks'!$G$32 -> 242919.13 | G104: =H104*12/F104 -> 0.031174595 | H104: ='Sources & Checks'!$D$76*'Sources & Checks'!$D$32/'Sources & Checks'!$D$34 -> 631.07547 | I104: =F104/F108 -> 0.63755067 | J104: =F104-F98 -> 14154.987 | K104: =IF(F98=0,"n.a.",F104/F98-1) -> 0.061875899 | L104: =IF(F32=0,"n.a.",F104/F32-1) -> 0.16453316 | M104: 2025Q2 | N104: Quarter balance and expense mix applied to controlled totals | O104: Allocated from reported quarter actual
A105: 45777 | B105: 2025 | C105: Q2 | D105: Time deposits | E105: Yes | F105: ='Sources & Checks'!$C$76*'Sources & Checks'!$G$33 -> 78412.666 | G105: =H105*12/F105 -> 0.044358308 | H105: ='Sources & Checks'!$D$76*'Sources & Checks'!$D$33/'Sources & Checks'!$D$34 -> 289.85443 | I105: =F105/F108 -> 0.20579708 | J105: =F105-F99 -> 4318.9147 | K105: =IF(F99=0,"n.a.",F105/F99-1) -> 0.058289864 | L105: =IF(F33=0,"n.a.",F105/F33-1) -> -0.0049854474 | M105: 2025Q2 | N105: Quarter balance and expense mix applied to controlled totals | O105: Allocated from reported quarter actual
...

Sheet Sources & Checks
A2: Deposit rate and balance sources
A3: Quarterly average balances and interest expense come from Capital One filings. Monthly interest-bearing totals come from the controlled workbook.
A5: Source Period | B5: Deposit Type | C5: Reported Average Balance ($mm) | D5: Reported Interest Expense ($mm) | E5: Reported Average Rate | F5: Effective Rate | G5: Share of Interest-Bearing Balance | H5: Disclosure Basis | N5: Month | O5: IB Balance Difference | P5: IB Expense Difference | Q5: NIB Quarter-End Difference | R5: Status
A6: 2024Q1 | B6: Checking | C6: 35707 | D6: 148 | E6: 0.0166 | F6: =D6*4/C6 -> 0.016579382 | G6: =C6/C9 -> 0.11212749 | H6: Reported three-month average | N6: ='Deposit Actuals'!A16 -> 45322 | O6: =ROUND('Deposit Actuals'!F16-C61,2) -> 0 | P6: =ROUND('Deposit Actuals'!H16-D61,2) -> 0 | Q6: ="" | R6: =IF(AND(ABS(O6)<0.01,ABS(P6)<0.01),"OK","Review") -> OK
A7: 2024Q1 | B7: Savings | C7: 206621 | D7: 1721 | E7: 0.0333 | F7: =D7*4/C7 -> 0.033317039 | G7: =C7/C9 -> 0.64883341 | H7: Reported three-month average | N7: ='Deposit Actuals'!A22 -> 45351 | O7: =ROUND('Deposit Actuals'!F22-C62,2) -> 0 | P7: =ROUND('Deposit Actuals'!H22-D62,2) -> 0 | Q7: ="" | R7: =IF(AND(ABS(O7)<0.01,ABS(P7)<0.01),"OK","Review") -> OK
A8: 2024Q1 | B8: Time deposits | C8: 76122 | D8: 943 | E8: 0.0495 | F8: =D8*4/C8 -> 0.049552035 | G8: =C8/C9 -> 0.2390391 | H8: Reported three-month average | N8: ='Deposit Actuals'!A28 -> 45382 | O8: =ROUND('Deposit Actuals'!F28-C63,2) -> 0 | P8: =ROUND('Deposit Actuals'!H28-D63,2) -> 0 | Q8: =ROUND(I63-G63,2) -> 0 | R8: =IF(AND(ABS(O8)<0.01,ABS(P8)<0.01,ABS(Q8)<0.01),"OK","Review") -> OK
A9: 2024Q1 | B9: Total interest-bearing deposits | C9: 318450 | D9: 2812 | E9: 0.0353 | F9: =D9*4/C9 -> 0.035321087 | G9: =1 -> 1 | H9: Reported three-month average | N9: ='Deposit Actuals'!A34 -> 45412 | O9: =ROUND('Deposit Actuals'!F34-C64,2) -> 0 | P9: =ROUND('Deposit Actuals'!H34-D64,2) -> 0 | Q9: ="" | R9: =IF(AND(ABS(O9)<0.01,ABS(P9)<0.01),"OK","Review") -> OK
A10: 2024Q1 | B10: Non-interest-bearing deposits | C10: 27207 | D10: 0 | E10: 0 | F10: =0 -> 0 | G10: ="" | H10: Reported three-month average | N10: ='Deposit Actuals'!A40 -> 45443 | O10: =ROUND('Deposit Actuals'!F40-C65,2) -> 0 | P10: =ROUND('Deposit Actuals'!H40-D65,2) -> 0 | Q10: ="" | R10: =IF(AND(ABS(O10)<0.01,ABS(P10)<0.01),"OK","Review") -> OK
A11: 2024Q2 | B11: Checking | C11: 34855 | D11: 138 | E11: 0.0158 | F11: =D11*4/C11 -> 0.015837039 | G11: =C11/C14 -> 0.10805038 | H11: Reported three-month average | N11: ='Deposit Actuals'!A46 -> 45473 | O11: =ROUND('Deposit Actuals'!F46-C66,2) -> 0 | P11: =ROUND('Deposit Actuals'!H46-D66,2) -> 0 | Q11: =ROUND(I66-G66,2) -> 0 | R11: =IF(AND(ABS(O11)<0.01,ABS(P11)<0.01,ABS(Q11)<0.01),"OK","Review") -> OK
A12: 2024Q2 | B12: Savings | C12: 208832 | D12: 1753 | E12: 0.0336 | F12: =D12*4/C12 -> 0.03357723 | G12: =C12/C14 -> 0.64737849 | H12: Reported three-month average | N12: ='Deposit Actuals'!A52 -> 45504 | O12: =ROUND('Deposit Actuals'!F52-C67,2) -> 0 | P12: =ROUND('Deposit Actuals'!H52-D67,2) -> 0 | Q12: ="" | R12: =IF(AND(ABS(O12)<0.01,ABS(P12)<0.01),"OK","Review") -> OK
A13: 2024Q2 | B13: Time deposits | C13: 78894 | D13: 983 | E13: 0.0499 | F13: =D13*4/C13 -> 0.049839025 | G13: =C13/C14 -> 0.24457113 | H13: Reported three-month average | N13: ='Deposit Actuals'!A58 -> 45535 | O13: =ROUND('Deposit Actuals'!F58-C68,2) -> 0 | P13: =ROUND('Deposit Actuals'!H58-D68,2) -> 0 | Q13: ="" | R13: =IF(AND(ABS(O13)<0.01,ABS(P13)<0.01),"OK","Review") -> OK
A14: 2024Q2 | B14: Total interest-bearing deposits | C14: 322581 | D14: 2874 | E14: 0.0356 | F14: =D14*4/C14 -> 0.035637561 | G14: =1 -> 1 | H14: Reported three-month average | N14: ='Deposit Actuals'!A64 -> 45565 | O14: =ROUND('Deposit Actuals'!F64-C69,2) -> 0 | P14: =ROUND('Deposit Actuals'!H64-D69,2) -> 0 | Q14: =ROUND(I69-G69,2) -> 0 | R14: =IF(AND(ABS(O14)<0.01,ABS(P14)<0.01,ABS(Q14)<0.01),"OK","Review") -> OK
A15: 2024Q2 | B15: Non-interest-bearing deposits | C15: 26907 | D15: 0 | E15: 0 | F15: =0 -> 0 | G15: ="" | H15: Reported three-month average | N15: ='Deposit Actuals'!A70 -> 45596 | O15: =ROUND('Deposit Actuals'!F70-C70,2) -> 0 | P15: =ROUND('Deposit Actuals'!H70-D70,2) -> 0 | Q15: ="" | R15: =IF(AND(ABS(O15)<0.01,ABS(P15)<0.01),"OK","Review") -> OK
A16: 2024Q3 | B16: Checking | C16: 33936 | D16: 135 | E16: 0.0159 | F16: =D16*4/C16 -> 0.015912306 | G16: =C16/C19 -> 0.10457645 | H16: Reported three-month average | N16: ='Deposit Actuals'!A76 -> 45626 | O16: =ROUND('Deposit Actuals'!F76-C71,2) -> 0 | P16: =ROUND('Deposit Actuals'!H76-D71,2) -> 0 | Q16: ="" | R16: =IF(AND(ABS(O16)<0.01,ABS(P16)<0.01),"OK","Review") -> OK
A17: 2024Q3 | B17: Savings | C17: 211608 | D17: 1825 | E17: 0.0345 | F17: =D17*4/C17 -> 0.034497751 | G17: =C17/C19 -> 0.65208669 | H17: Reported three-month average | N17: ='Deposit Actuals'!A82 -> 45657 | O17: =ROUND('Deposit Actuals'!F82-C72,2) -> 0 | P17: =ROUND('Deposit Actuals'!H82-D72,2) -> 0 | Q17: =ROUND(I72-G72,2) -> 0 | R17: =IF(AND(ABS(O17)<0.01,ABS(P17)<0.01,ABS(Q17)<0.01),"OK","Review") -> OK
A18: 2024Q3 | B18: Time deposits | C18: 78965 | D18: 985 | E18: 0.0499 | F18: =D18*4/C18 -> 0.049895523 | G18: =C18/C19 -> 0.24333686 | H18: Reported three-month average | N18: ='Deposit Actuals'!A88 -> 45688 | O18: =ROUND('Deposit Actuals'!F88-C73,2) -> 0 | P18: =ROUND('Deposit Actuals'!H88-D73,2) -> 0 | Q18: ="" | R18: =IF(AND(ABS(O18)<0.01,ABS(P18)<0.01),"OK","Review") -> OK
A19: 2024Q3 | B19: Total interest-bearing deposits | C19: 324509 | D19: 2945 | E19: 0.0363 | F19: =D19*4/C19 -> 0.036300996 | G19: =1 -> 1 | H19: Reported three-month average | N19: ='Deposit Actuals'!A94 -> 45716 | O19: =ROUND('Deposit Actuals'!F94-C74,2) -> 0 | P19: =ROUND('Deposit Actuals'!H94-D74,2) -> 0 | Q19: ="" | R19: =IF(AND(ABS(O19)<0.01,ABS(P19)<0.01),"OK","Review") -> OK
A20: 2024Q3 | B20: Non-interest-bearing deposits | C20: 26616 | D20: 0 | E20: 0 | F20: =0 -> 0 | G20: ="" | H20: Reported three-month average | N20: ='Deposit Actuals'!A100 -> 45747 | O20: =ROUND('Deposit Actuals'!F100-C75,2) -> 0 | P20: =ROUND('Deposit Actuals'!H100-D75,2) -> 0 | Q20: =ROUND(I75-G75,2) -> 0 | R20: =IF(AND(ABS(O20)<0.01,ABS(P20)<0.01,ABS(Q20)<0.01),"OK","Review") -> OK
A21: 2024Q4 | B21: Checking | C21: 35129 | D21: 123 | E21: 0.014005523 | F21: =D21*4/C21 -> 0.014005523 | G21: =C21/C24 -> 0.10593149 | H21: Derived Q4 = full year less nine months | N21: ='Deposit Actuals'!A106 -> 45777 | O21: =ROUND('Deposit Actuals'!F106-C76,2) -> 0 | P21: =ROUND('Deposit Actuals'!H106-D76,2) -> 0 | Q21: ="" | R21: =IF(AND(ABS(O21)<0.01,ABS(P21)<0.01),"OK","Review") -> OK
A22: 2024Q4 | B22: Savings | C22: 217390 | D22: 1784 | E22: 0.032825797 | F22: =D22*4/C22 -> 0.032825797 | G22: =C22/C24 -> 0.65553947 | H22: Derived Q4 = full year less nine months | N22: ='Deposit Actuals'!A112 -> 45808 | O22: =ROUND('Deposit Actuals'!F112-C77,2) -> 0 | P22: =ROUND('Deposit Actuals'!H112-D77,2) -> 0 | Q22: ="" | R22: =IF(AND(ABS(O22)<0.01,ABS(P22)<0.01),"OK","Review") -> OK
A23: 2024Q4 | B23: Time deposits | C23: 79101 | D23: 955 | E23: 0.048292689 | F23: =D23*4/C23 -> 0.048292689 | G23: =C23/C24 -> 0.23852904 | H23: Derived Q4 = full year less nine months | N23: ='Deposit Actuals'!A118 -> 45838 | O23: =ROUND('Deposit Actuals'!F118-C78,2) -> 0 | P23: =ROUND('Deposit Actuals'!H118-D78,2) -> 0 | Q23: =ROUND(I78-G78,2) -> 0 | R23: =IF(AND(ABS(O23)<0.01,ABS(P23)<0.01,ABS(Q23)<0.01),"OK","Review") -> OK
A24: 2024Q4 | B24: Total interest-bearing deposits | C24: 331620 | D24: 2862 | E24: 0.03452144 | F24: =D24*4/C24 -> 0.03452144 | G24: =1 -> 1 | H24: Derived Q4 = full year less nine months | N24: ='Deposit Actuals'!A124 -> 45869 | O24: =ROUND('Deposit Actuals'!F124-C79,2) -> 0 | P24: =ROUND('Deposit Actuals'!H124-D79,2) -> 0 | Q24: ="" | R24: =IF(AND(ABS(O24)<0.01,ABS(P24)<0.01),"OK","Review") -> OK
A25: 2024Q4 | B25: Non-interest-bearing deposits | C25: 26757 | D25: 0 | E25: 0 | F25: =0 -> 0 | G25: ="" | H25: Derived Q4 = full year less nine months | N25: ='Deposit Actuals'!A130 -> 45900 | O25: =ROUND('Deposit Actuals'!F130-C80,2) -> 0 | P25: =ROUND('Deposit Actuals'!H130-D80,2) -> 0 | Q25: ="" | R25: =IF(AND(ABS(O25)<0.01,ABS(P25)<0.01),"OK","Review") -> OK
A26: 2025Q1 | B26: Checking | C26: 36285 | D26: 119 | E26: 0.0131 | F26: =D26*4/C26 -> 0.013118368 | G26: =C26/C29 -> 0.10740291 | H26: Reported three-month average | N26: ='Deposit Actuals'!A136 -> 45930 | O26: =ROUND('Deposit Actuals'!F136-C81,2) -> 0 | P26: =ROUND('Deposit Actuals'!H136-D81,2) -> 0 | Q26: =ROUND(I81-G81,2) -> 0 | R26: =IF(AND(ABS(O26)<0.01,ABS(P26)<0.01,ABS(Q26)<0.01),"OK","Review") -> OK
A27: 2025Q1 | B27: Savings | C27: 227780 | D27: 1768 | E27: 0.0311 | F27: =D27*4/C27 -> 0.031047502 | G27: =C27/C29 -> 0.67422448 | H27: Reported three-month average | N27: ='Deposit Actuals'!A142 -> 45961 | O27: =ROUND('Deposit Actuals'!F142-C82,2) -> 0 | P27: =ROUND('Deposit Actuals'!H142-D82,2) -> 0 | Q27: ="" | R27: =IF(AND(ABS(O27)<0.01,ABS(P27)<0.01),"OK","Review") -> OK
A28: 2025Q1 | B28: Time deposits | C28: 73775 | D28: 828 | E28: 0.0449 | F28: =D28*4/C28 -> 0.044893257 | G28: =C28/C29 -> 0.2183726 | H28: Reported three-month average | N28: ='Deposit Actuals'!A148 -> 45991 | O28: =ROUND('Deposit Actuals'!F148-C83,2) -> 0 | P28: =ROUND('Deposit Actuals'!H148-D83,2) -> 0 | Q28: ="" | R28: =IF(AND(ABS(O28)<0.01,ABS(P28)<0.01),"OK","Review") -> OK
A29: 2025Q1 | B29: Total interest-bearing deposits | C29: 337840 | D29: 2715 | E29: 0.0322 | F29: =D29*4/C29 -> 0.032145394 | G29: =1 -> 1 | H29: Reported three-month average | N29: ='Deposit Actuals'!A154 -> 46022 | O29: =ROUND('Deposit Actuals'!F154-C84,2) -> 0 | P29: =ROUND('Deposit Actuals'!H154-D84,2) -> 0 | Q29: =ROUND(I84-G84,2) -> 0 | R29: =IF(AND(ABS(O29)<0.01,ABS(P29)<0.01,ABS(Q29)<0.01),"OK","Review") -> OK
A30: 2025Q1 | B30: Non-interest-bearing deposits | C30: 26238 | D30: 0 | E30: 0 | F30: =0 -> 0 | G30: ="" | H30: Reported three-month average | N30: ='Deposit Actuals'!A160 -> 46053 | O30: =ROUND('Deposit Actuals'!F160-C85,2) -> 0 | P30: =ROUND('Deposit Actuals'!H160-D85,2) -> 0 | Q30: ="" | R30: =IF(AND(ABS(O30)<0.01,ABS(P30)<0.01),"OK","Review") -> OK
A31: 2025Q2 | B31: Checking | C31: 35776 | D31: 108 | E31: 0.012 | F31: =D31*4/C31 -> 0.012075134 | G31: =C31/C34 -> 0.092411253 | H31: Reported three-month average | N31: ='Deposit Actuals'!A166 -> 46081 | O31: =ROUND('Deposit Actuals'!F166-C86,2) -> 0 | P31: =ROUND('Deposit Actuals'!H166-D86,2) -> 0 | Q31: ="" | R31: =IF(AND(ABS(O31)<0.01,ABS(P31)<0.01),"OK","Review") -> OK
A32: 2025Q2 | B32: Savings | C32: 265622 | D32: 2064 | E32: 0.0311 | F32: =D32*4/C32 -> 0.031081763 | G32: =C32/C34 -> 0.68611532 | H32: Reported three-month average | N32: ='Deposit Actuals'!A172 -> 46112 | O32: =ROUND('Deposit Actuals'!F172-C87,2) -> 0 | P32: =ROUND('Deposit Actuals'!H172-D87,2) -> 0 | Q32: =ROUND(I87-G87,2) -> 0 | R32: =IF(AND(ABS(O32)<0.01,ABS(P32)<0.01,ABS(Q32)<0.01),"OK","Review") -> OK
A33: 2025Q2 | B33: Time deposits | C33: 85741 | D33: 948 | E33: 0.0442 | F33: =D33*4/C33 -> 0.044226216 | G33: =C33/C34 -> 0.22147342 | H33: Reported three-month average | N33: ='Deposit Actuals'!A178 -> 46142 | O33: =ROUND('Deposit Actuals'!F178-C88,2) -> 0 | P33: =ROUND('Deposit Actuals'!H178-D88,2) -> 0 | Q33: ="" | R33: =IF(AND(ABS(O33)<0.01,ABS(P33)<0.01),"OK","Review") -> OK
A34: 2025Q2 | B34: Total interest-bearing deposits | C34: 387139 | D34: 3120 | E34: 0.0322 | F34: =D34*4/C34 -> 0.032236484 | G34: =1 -> 1 | H34: Reported three-month average | N34: ='Deposit Actuals'!A184 -> 46173 | O34: =ROUND('Deposit Actuals'!F184-C89,2) -> 0 | P34: =ROUND('Deposit Actuals'!H184-D89,2) -> 0 | Q34: ="" | R34: =IF(AND(ABS(O34)<0.01,ABS(P34)<0.01),"OK","Review") -> OK
A35: 2025Q2 | B35: Non-interest-bearing deposits | C35: 27429 | D35: 0 | E35: 0 | F35: =0 -> 0 | G35: ="" | H35: Reported three-month average | N35: ='Deposit Actuals'!A190 -> 46203 | O35: =ROUND('Deposit Actuals'!F190-C90,2) -> 0 | P35: =ROUND('Deposit Actuals'!H190-D90,2) -> 0 | Q35: =ROUND(I90-G90,2) -> 0 | R35: =IF(AND(ABS(O35)<0.01,ABS(P35)<0.01,ABS(Q35)<0.01),"OK","Review") -> OK
A36: 2025Q3 | B36: Checking | C36: 35419 | D36: 107 | E36: 0.0121 | F36: =D36*4/C36 -> 0.01208391 | G36: =C36/C39 -> 0.080584355 | H36: Reported three-month average
A37: 2025Q3 | B37: Savings | C37: 300386 | D37: 2355 | E37: 0.0314 | F37: =D37*4/C37 -> 0.031359651 | G37: =C37/C39 -> 0.68343014 | H37: Reported three-month average
A38: 2025Q3 | B38: Time deposits | C38: 103722 | D38: 1135 | E38: 0.0438 | F38: =D38*4/C38 -> 0.043770849 | G38: =C38/C39 -> 0.2359855 | H38: Reported three-month average
A39: 2025Q3 | B39: Total interest-bearing deposits | C39: 439527 | D39: 3597 | E39: 0.0327 | F39: =D39*4/C39 -> 0.03273519 | G39: =1 -> 1 | H39: Reported three-month average | N39: Source Period | O39: Product Balance Difference | P39: Product Interest Difference | Q39: Status
A40: 2025Q3 | B40: Non-interest-bearing deposits | C40: 27753 | D40: 0 | E40: 0 | F40: =0 -> 0 | G40: ="" | H40: Reported three-month average | N40: ="2024Q1" -> 2024Q1 | O40: =ROUND(SUM(C6,C7,C8)-C9,2) -> 0 | P40: =ROUND(SUM(D6,D7,D8)-D9,2) -> 0 | Q40: =IF(AND(ABS(O40)<0.01,ABS(P40)<0.01),"OK","Review") -> OK
A41: 2025Q4 | B41: Checking | C41: 36304 | D41: 99 | E41: 0.010907889 | F41: =D41*4/C41 -> 0.010907889 | G41: =C41/C44 -> 0.081910955 | H41: Derived Q4 = full year less nine months | N41: ="2024Q2" -> 2024Q2 | O41: =ROUND(SUM(C11,C12,C13)-C14,2) -> 0 | P41: =ROUND(SUM(D11,D12,D13)-D14,2) -> 0 | Q41: =IF(AND(ABS(O41)<0.01,ABS(P41)<0.01),"OK","Review") -> OK
A42: 2025Q4 | B42: Savings | C42: 301934 | D42: 2314 | E42: 0.030655706 | F42: =D42*4/C42 -> 0.030655706 | G42: =C42/C44 -> 0.68123904 | H42: Derived Q4 = full year less nine months | N42: ="2024Q3" -> 2024Q3 | O42: =ROUND(SUM(C16,C17,C18)-C19,2) -> 0 | P42: =ROUND(SUM(D16,D17,D18)-D19,2) -> 0 | Q42: =IF(AND(ABS(O42)<0.01,ABS(P42)<0.01),"OK","Review") -> OK
A43: 2025Q4 | B43: Time deposits | C43: 104975 | D43: 1080 | E43: 0.041152655 | F43: =D43*4/C43 -> 0.041152655 | G43: =C43/C44 -> 0.23685 | H43: Derived Q4 = full year less nine months | N43: ="2024Q4" -> 2024Q4 | O43: =ROUND(SUM(C21,C22,C23)-C24,2) -> 0 | P43: =ROUND(SUM(D21,D22,D23)-D24,2) -> 0 | Q43: =IF(AND(ABS(O43)<0.01,ABS(P43)<0.01),"OK","Review") -> OK
A44: 2025Q4 | B44: Total interest-bearing deposits | C44: 443213 | D44: 3493 | E44: 0.031524346 | F44: =D44*4/C44 -> 0.031524346 | G44: =1 -> 1 | H44: Derived Q4 = full year less nine months | N44: ="2025Q1" -> 2025Q1 | O44: =ROUND(SUM(C26,C27,C28)-C29,2) -> 0 | P44: =ROUND(SUM(D26,D27,D28)-D29,2) -> 0 | Q44: =IF(AND(ABS(O44)<0.01,ABS(P44)<0.01),"OK","Review") -> OK
A45: 2025Q4 | B45: Non-interest-bearing deposits | C45: 28209 | D45: 0 | E45: 0 | F45: =0 -> 0 | G45: ="" | H45: Derived Q4 = full year less nine months | N45: ="2025Q2" -> 2025Q2 | O45: =ROUND(SUM(C31,C32,C33)-C34,2) -> 0 | P45: =ROUND(SUM(D31,D32,D33)-D34,2) -> 0 | Q45: =IF(AND(ABS(O45)<0.01,ABS(P45)<0.01),"OK","Review") -> OK
A46: 2026Q1 | B46: Checking | C46: 38642 | D46: 114 | E46: 0.0118 | F46: =D46*4/C46 -> 0.011800631 | G46: =C46/C49 -> 0.085499284 | H46: Reported three-month average | N46: ="2025Q3" -> 2025Q3 | O46: =ROUND(SUM(C36,C37,C38)-C39,2) -> 0 | P46: =ROUND(SUM(D36,D37,D38)-D39,2) -> 0 | Q46: =IF(AND(ABS(O46)<0.01,ABS(P46)<0.01),"OK","Review") -> OK
A47: 2026Q1 | B47: Savings | C47: 309341 | D47: 2263 | E47: 0.0293 | F47: =D47*4/C47 -> 0.029262206 | G47: =C47/C49 -> 0.68444786 | H47: Reported three-month average | N47: ="2025Q4" -> 2025Q4 | O47: =ROUND(SUM(C41,C42,C43)-C44,2) -> 0 | P47: =ROUND(SUM(D41,D42,D43)-D44,2) -> 0 | Q47: =IF(AND(ABS(O47)<0.01,ABS(P47)<0.01),"OK","Review") -> OK
A48: 2026Q1 | B48: Time deposits | C48: 103974 | D48: 1010 | E48: 0.0389 | F48: =D48*4/C48 -> 0.038855868 | G48: =C48/C49 -> 0.23005286 | H48: Reported three-month average | N48: ="2026Q1" -> 2026Q1 | O48: =ROUND(SUM(C46,C47,C48)-C49,2) -> 0 | P48: =ROUND(SUM(D46,D47,D48)-D49,2) -> 0 | Q48: =IF(AND(ABS(O48)<0.01,ABS(P48)<0.01),"OK","Review") -> OK
A49: 2026Q1 | B49: Total interest-bearing deposits | C49: 451957 | D49: 3387 | E49: 0.03 | F49: =D49*4/C49 -> 0.029976303 | G49: =1 -> 1 | H49: Reported three-month average | N49: ="2026Q2" -> 2026Q2 | O49: =ROUND(SUM(C51,C52,C53)-C54,2) -> 0 | P49: =ROUND(SUM(D51,D52,D53)-D54,2) -> 0 | Q49: =IF(AND(ABS(O49)<0.01,ABS(P49)<0.01),"OK","Review") -> OK
A50: 2026Q1 | B50: Non-interest-bearing deposits | C50: 28001 | D50: 0 | E50: 0 | F50: =0 -> 0 | G50: ="" | H50: Reported three-month average
A51: 2026Q2 | B51: Checking | C51: 39759 | D51: 116 | E51: 0.0117 | F51: =D51*4/C51 -> 0.011670314 | G51: =C51/C54 -> 0.08678541 | H51: Reported three-month average
A52: 2026Q2 | B52: Savings | C52: 314378 | D52: 2210 | E52: 0.0281 | F52: =D52*4/C52 -> 0.028119016 | G52: =C52/C54 -> 0.68622007 | H52: Reported three-month average
A53: 2026Q2 | B53: Time deposits | C53: 103993 | D53: 1012 | E53: 0.0389 | F53: =D53*4/C53 -> 0.038925697 | G53: =C53/C54 -> 0.22699452 | H53: Reported three-month average
A54: 2026Q2 | B54: Total interest-bearing deposits | C54: 458130 | D54: 3338 | E54: 0.0291 | F54: =D54*4/C54 -> 0.029144566 | G54: =1 -> 1 | H54: Reported three-month average
A55: 2026Q2 | B55: Non-interest-bearing deposits | C55: 28661 | D55: 0 | E55: 0 | F55: =0 -> 0 | G55: ="" | H55: Reported three-month average
A58: Monthly controlled inputs and non-interest-bearing balance build
A60: Month | B60: Source Period | C60: Controlled IB Average Balance ($mm) | D60: Controlled IB Interest Expense ($mm) | E60: Controlled IB Rate | F60: Prior Quarter-End NIB Balance ($mm) | G60: Current Quarter-End NIB Balance ($mm) | H60: Reported Quarterly NIB Average ($mm) | I60: Derived Month-End NIB Balance ($mm) | J60: Derived Monthly NIB Average ($mm)
A61: 45322 | B61: 2024Q1 | C61: 317462.33 | D61: 937.78382 | E61: 0.035448003 | F61: =$B$96 -> 28024 | G61: =$B$97 -> 27617 | H61: =$C$10 -> 27207 | I61: =F61+(G61-F61)/3+(2*H61-F61-G61) -> 26661.333 | J61: =AVERAGE(F61,I61) -> 27342.667
A62: 45351 | B62: 2024Q1 | C62: 315029.5 | D62: 930.59723 | E62: 0.035448003 | F62: =$B$96 -> 28024 | G62: =$B$97 -> 27617 | H62: =$C$10 -> 27207 | I62: =F62+2*(G62-F62)/3+(2*H62-F62-G62) -> 26525.667 | J62: =AVERAGE(I61,I62) -> 26593.5
A63: 45382 | B63: 2024Q1 | C63: 319437.67 | D63: 943.61895 | E63: 0.035448003 | F63: =$B$96 -> 28024 | G63: =$B$97 -> 27617 | H63: =$C$10 -> 27207 | I63: =G63 -> 27617 | J63: =AVERAGE(I62,I63) -> 27071.333
A64: 45412 | B64: 2024Q2 | C64: 322219.33 | D64: 958.22651 | E64: 0.035685997 | F64: =$B$97 -> 27617 | G64: =$B$98 -> 27005 | H64: =$C$15 -> 26907 | I64: =F64+(G64-F64)/3+(2*H64-F64-G64) -> 26605 | J64: =AVERAGE(F64,I64) -> 27111
A65: 45443 | B65: 2024Q2 | C65: 321267.5 | D65: 955.39591 | E65: 0.035685997 | F65: =$B$97 -> 27617 | G65: =$B$98 -> 27005 | H65: =$C$15 -> 26907 | I65: =F65+2*(G65-F65)/3+(2*H65-F65-G65) -> 26401 | J65: =AVERAGE(I64,I65) -> 26503
A66: 45473 | B66: 2024Q2 | C66: 322942.67 | D66: 960.37758 | E66: 0.035685997 | F66: =$B$97 -> 27617 | G66: =$B$98 -> 27005 | H66: =$C$15 -> 26907 | I66: =G66 -> 27005 | J66: =AVERAGE(I65,I66) -> 26703
A67: 45504 | B67: 2024Q3 | C67: 323570.33 | D67: 980.17224 | E67: 0.036350882 | F67: =$B$98 -> 27005 | G67: =$B$99 -> 26378 | H67: =$C$20 -> 26616 | I67: =F67+(G67-F67)/3+(2*H67-F67-G67) -> 26645 | J67: =AVERAGE(F67,I67) -> 26825
A68: 45535 | B68: 2024Q3 | C68: 323173 | D68: 978.96862 | E68: 0.036350882 | F68: =$B$98 -> 27005 | G68: =$B$99 -> 26378 | H68: =$C$20 -> 26616 | I68: =F68+2*(G68-F68)/3+(2*H68-F68-G68) -> 26436 | J68: =AVERAGE(I67,I68) -> 26540.5
A69: 45565 | B69: 2024Q3 | C69: 325447.67 | D69: 985.85914 | E69: 0.036350882 | F69: =$B$98 -> 27005 | G69: =$B$99 -> 26378 | H69: =$C$20 -> 26616 | I69: =G69 -> 26378 | J69: =AVERAGE(I68,I69) -> 26407
A70: 45596 | B70: 2024Q4 | C70: 328509.33 | D70: 945.33539 | E70: 0.034531819 | F70: =$B$99 -> 26378 | G70: =$B$100 -> 26122 | H70: =$C$25 -> 26757 | I70: =F70+(G70-F70)/3+(2*H70-F70-G70) -> 27306.667 | J70: =AVERAGE(F70,I70) -> 26842.333
A71: 45626 | B71: 2024Q4 | C71: 331321 | D71: 953.42639 | E71: 0.034531819 | F71: =$B$99 -> 26378 | G71: =$B$100 -> 26122 | H71: =$C$25 -> 26757 | I71: =F71+2*(G71-F71)/3+(2*H71-F71-G71) -> 27221.333 | J71: =AVERAGE(I70,I71) -> 27264
A72: 45657 | B72: 2024Q4 | C72: 334730.67 | D72: 963.23822 | E72: 0.034531819 | F72: =$B$99 -> 26378 | G72: =$B$100 -> 26122 | H72: =$C$25 -> 26757 | I72: =G72 -> 26122 | J72: =AVERAGE(I71,I72) -> 26671.667
A73: 45688 | B73: 2025Q1 | C73: 336380.33 | D73: 901.92147 | E73: 0.032175061 | F73: =$B$100 -> 26122 | G73: =$B$101 -> 26500 | H73: =$C$30 -> 26238 | I73: =F73+(G73-F73)/3+(2*H73-F73-G73) -> 26102 | J73: =AVERAGE(F73,I73) -> 26112
A74: 45716 | B74: 2025Q1 | C74: 336905.5 | D74: 903.32958 | E74: 0.032175061 | F74: =$B$100 -> 26122 | G74: =$B$101 -> 26500 | H74: =$C$30 -> 26238 | I74: =F74+2*(G74-F74)/3+(2*H74-F74-G74) -> 26228 | J74: =AVERAGE(I73,I74) -> 26165
A75: 45747 | B75: 2025Q1 | C75: 339299.67 | D75: 909.74895 | E75: 0.032175061 | F75: =$B$100 -> 26122 | G75: =$B$101 -> 26500 | H75: =$C$30 -> 26238 | I75: =G75 -> 26500 | J75: =AVERAGE(I74,I75) -> 26364
A76: 45777 | B76: 2025Q2 | C76: 354050 | D76: 953.95129 | E76: 0.032332765 | F76: =$B$101 -> 26500 | G76: =$B$102 -> 27879 | H76: =$C$35 -> 27429 | I76: =F76+(G76-F76)/3+(2*H76-F76-G76) -> 27438.667 | J76: =AVERAGE(F76,I76) -> 26969.333
A77: 45808 | B77: 2025Q2 | C77: 383680.5 | D77: 1033.7876 | E77: 0.032332765 | F77: =$B$101 -> 26500 | G77: =$B$102 -> 27879 | H77: =$C$35 -> 27429 | I77: =F77+2*(G77-F77)/3+(2*H77-F77-G77) -> 27898.333 | J77: =AVERAGE(I76,I77) -> 27668.5
A78: 45838 | B78: 2025Q2 | C78: 420228 | D78: 1132.2611 | E78: 0.032332765 | F78: =$B$101 -> 26500 | G78: =$B$102 -> 27879 | H78: =$C$35 -> 27429 | I78: =G78 -> 27879 | J78: =AVERAGE(I77,I78) -> 27888.667
A79: 45869 | B79: 2025Q3 | C79: 439225.33 | D79: 1199.2289 | E79: 0.032763927 | F79: =$B$102 -> 27879 | G79: =$B$103 -> 27649 | H79: =$C$40 -> 27753 | I79: =F79+(G79-F79)/3+(2*H79-F79-G79) -> 27780.333 | J79: =AVERAGE(F79,I79) -> 27829.667
A80: 45900 | B80: 2025Q3 | C80: 438370.5 | D80: 1196.8949 | E80: 0.032763927 | F80: =$B$102 -> 27879 | G80: =$B$103 -> 27649 | H80: =$C$40 -> 27753 | I80: =F80+2*(G80-F80)/3+(2*H80-F80-G80) -> 27703.667 | J80: =AVERAGE(I79,I80) -> 27742
A81: 45930 | B81: 2025Q3 | C81: 439828.67 | D81: 1200.8762 | E81: 0.032763927 | F81: =$B$102 -> 27879 | G81: =$B$103 -> 27649 | H81: =$C$40 -> 27753 | I81: =G81 -> 27649 | J81: =AVERAGE(I80,I81) -> 27676.333
A82: 45961 | B82: 2025Q4 | C82: 440796.33 | D82: 1159.3344 | E82: 0.03156109 | F82: =$B$103 -> 27649 | G82: =$B$104 -> 27385 | H82: =$C$45 -> 28209 | I82: =F82+(G82-F82)/3+(2*H82-F82-G82) -> 28945 | J82: =AVERAGE(F82,I82) -> 28297
A83: 45991 | B83: 2025Q4 | C83: 441665 | D83: 1161.6191 | E83: 0.03156109 | F83: =$B$103 -> 27649 | G83: =$B$104 -> 27385 | H83: =$C$45 -> 28209 | I83: =F83+2*(G83-F83)/3+(2*H83-F83-G83) -> 28857 | J83: =AVERAGE(I82,I83) -> 28901
A84: 46022 | B84: 2025Q4 | C84: 445629.67 | D84: 1172.0465 | E84: 0.03156109 | F84: =$B$103 -> 27649 | G84: =$B$104 -> 27385 | H84: =$C$45 -> 28209 | I84: =G84 -> 27385 | J84: =AVERAGE(I83,I84) -> 28121
A85: 46053 | B85: 2026Q1 | C85: 447713.33 | D85: 1120.709 | E85: 0.030038213 | F85: =$B$104 -> 27385 | G85: =$B$105 -> 27936 | H85: =$C$50 -> 28001 | I85: =F85+(G85-F85)/3+(2*H85-F85-G85) -> 28249.667 | J85: =AVERAGE(F85,I85) -> 27817.333
A86: 46081 | B86: 2026Q1 | C86: 449162.5 | D86: 1124.3366 | E86: 0.030038213 | F86: =$B$104 -> 27385 | G86: =$B$105 -> 27936 | H86: =$C$50 -> 28001 | I86: =F86+2*(G86-F86)/3+(2*H86-F86-G86) -> 28433.333 | J86: =AVERAGE(I85,I86) -> 28341.5
A87: 46112 | B87: 2026Q1 | C87: 456200.67 | D87: 1141.9544 | E87: 0.030038213 | F87: =$B$104 -> 27385 | G87: =$B$105 -> 27936 | H87: =$C$50 -> 28001 | I87: =G87 -> 27936 | J87: =AVERAGE(I86,I87) -> 28184.667
A88: 46142 | B88: 2026Q2 | C88: 459681 | D88: 1116.9704 | E88: 0.029158579 | F88: =$B$105 -> 27936 | G88: =$B$106 -> 27793 | H88: =$C$55 -> 28661 | I88: =F88+(G88-F88)/3+(2*H88-F88-G88) -> 29481.333 | J88: =AVERAGE(F88,I88) -> 28708.667
A89: 46173 | B89: 2026Q2 | C89: 457469.5 | D89: 1111.5967 | E89: 0.029158579 | F89: =$B$105 -> 27936 | G89: =$B$106 -> 27793 | H89: =$C$55 -> 28661 | I89: =F89+2*(G89-F89)/3+(2*H89-F89-G89) -> 29433.667 | J89: =AVERAGE(I88,I89) -> 29457.5
A90: 46203 | B90: 2026Q2 | C90: 456579 | D90: 1109.4329 | E90: 0.029158579 | F90: =$B$105 -> 27936 | G90: =$B$106 -> 27793 | H90: =$C$55 -> 28661 | I90: =G90 -> 27793 | J90: =AVERAGE(I89,I90) -> 28613.333
A93: Non-interest-bearing quarter-end anchors
A95: Period End | B95: Non-Interest-Bearing EOP Balance ($mm) | C95: Source Form
A96: 45291 | B96: 28024 | C96: 10-K
A97: 45382 | B97: 27617 | C97: 10-Q
A98: 45473 | B98: 27005 | C98: 10-Q
A99: 45565 | B99: 26378 | C99: 10-Q
A100: 45657 | B100: 26122 | C100: 10-K
A101: 45747 | B101: 26500 | C101: 10-Q
A102: 45838 | B102: 27879 | C102: 10-Q
A103: 45930 | B103: 27649 | C103: 10-Q
A104: 46022 | B104: 27385 | C104: 10-K
A105: 46112 | B105: 27936 | C105: 10-Q
A106: 46203 | B106: 27793 | C106: 10-Q
A109: Methodology
A111: Checking, savings, and time-deposit monthly balances use each reported quarter's average balance mix applied to the controlled monthly interest-bearing total.
...
