Workbook

Sheet Balance
A1: Capital One — Average Balance by line item ($mm)
A2: AVERAGE balance over the quarter, not period-end — will not tie to the balance sheet. Column header is the quarter-end date. (D) = Q4 derived as (FY avg x12 − 9M avg x9)/3. Source: COF 10-Q/10-K average balance table.
A4: Line item (as disclosed) | B4: 2023-03-31 | C4: 2023-06-30 | D4: 2023-09-30 | E4: 2023-12-31 (D) | F4: 2024-03-31 | G4: 2024-06-30 | H4: 2024-09-30 | I4: 2024-12-31 (D) | J4: 2025-03-31 | K4: 2025-06-30 | L4: 2025-09-30 | M4: 2025-12-31 (D) | N4: 2026-03-31 | O4: 2026-06-30
A5: INTEREST-EARNING ASSETS
A6: Credit card | B6: 134669 | C6: 138762 | D6: 144053 | E6: 149112 | F6: 150049 | G6: 150866 | H6: 154160 | I6: 157360 | J6: 156408 | K6: 209693 | L6: 269175 | M6: 272720 | N6: 270975 | O6: 271197
A7: Consumer banking | B7: 79000 | C7: 77699 | D7: 77154 | E7: 76224 | F7: 75091 | G7: 75386 | H7: 76182 | I7: 77231 | J7: 78480 | K7: 80095 | L7: 82295 | M7: 83988 | N7: 85701 | O7: 88583
A8: Commercial banking | B8: 94446 | C8: 93874 | D8: 92254 | E8: 91385 | F8: 90423 | G8: 89571 | H8: 88373 | I8: 87672 | J8: 87884 | K8: 88749 | L8: 88904 | M8: 89192 | N8: 90064 | O8: 91082
A9: Total loans (incl. HFS) | B9: 308115 | C9: 310335 | D9: 313461 | E9: 316721 | F9: 315563 | G9: 315823 | H9: 318715 | I9: 322263 | J9: 322772 | K9: 378537 | L9: 440374 | M9: 445900 | N9: 446740 | O9: 450862
A10: Investment securities | B10: 89960 | C10: 89994 | D10: 87845 | E10: 88643 | F10: 88581 | G10: 89501 | H10: 90644 | I10: 92260 | J10: 92659 | K10: 93024 | L10: 96186 | M10: 97330 | N10: 97803 | O10: 99339
A11: Cash equivalents and other | B11: 37124 | C11: 38810 | D11: 42226 | E11: 41625 | F11: 43659 | G11: 45584 | H11: 45125 | I11: 46167 | J11: 47340 | K11: 53368 | L11: 56687 | M11: 61127 | N11: 72630 | O11: 67382
A12: Total interest-earning assets | B12: 435199 | C12: 439139 | D12: 443532 | E12: 446989 | F12: 447803 | G12: 450908 | H12: 454484 | I12: 460690 | J12: 462771 | K12: 524929 | L12: 593247 | M12: 604357 | N12: 617173 | O12: 617583
A14: INTEREST-BEARING LIABILITIES
A15: Interest-bearing deposits | B15: 308788 | C15: 313207 | D15: 316032 | E15: 316842 | F15: 318450 | G15: 322581 | H15: 324509 | I15: 331620 | J15: 337840 | K15: 387139 | L15: 439527 | M15: 443213 | N15: 451957 | O15: 458130
A16: Securitized debt obligations | B16: 17251 | C16: 17771 | D16: 17649 | E16: 18026 | F16: 17836 | G16: 17452 | H16: 15833 | I16: 14920 | J16: 13731 | K16: 13043 | L16: 12919 | M16: 12668 | N16: 12476 | O16: 10190
A17: Senior and subordinated notes | B17: 30136 | C17: 30161 | D17: 31522 | E17: 32603 | F17: 32211 | G17: 30978 | H17: 32041 | I17: 30884 | J17: 30331 | K17: 32872 | L17: 36272 | M17: 36528 | N17: 37846 | O17: 37498
A18: Other borrowings | B18: 2335 | C18: 2419 | D18: 2473 | E18: 2346 | F18: 2373 | G18: 2502 | H18: 2389 | I18: 2430 | J18: 2312 | K18: 2872 | L18: 3120 | M18: 3751 | N18: 4238 | O18: 3838
A19: Total interest-bearing liabilities | B19: 358510 | C19: 363558 | D19: 367676 | E19: 369817 | F19: 370870 | G19: 373513 | H19: 374772 | I19: 379854 | J19: 384214 | K19: 435926 | L19: 491838 | M19: 496160 | N19: 506517 | O19: 509656
A21: Net earning assets (assets − liabilities) | B21: =B12-B19 -> 76689 | C21: =C12-C19 -> 75581 | D21: =D12-D19 -> 75856 | E21: =E12-E19 -> 77172 | F21: =F12-F19 -> 76933 | G21: =G12-G19 -> 77395 | H21: =H12-H19 -> 79712 | I21: =I12-I19 -> 80836 | ... O21: =O12-O19 -> 107927

Sheet Rate
A1: Capital One — Average Yield / Rate by line item (annualised)
A2: Annualised yield on assets and cost of funds on liabilities, as disclosed. (D) = Q4 recomputed as derived interest / derived balance x4; rates cannot be derived by subtraction. Stored as fractions.
A4: Line item (as disclosed) | B4: 2023-03-31 | C4: 2023-06-30 | D4: 2023-09-30 | E4: 2023-12-31 (D) | F4: 2024-03-31 | G4: 2024-06-30 | H4: 2024-09-30 | I4: 2024-12-31 (D) | J4: 2025-03-31 | K4: 2025-06-30 | L4: 2025-09-30 | M4: 2025-12-31 (D) | N4: 2026-03-31 | O4: 2026-06-30
A5: INTEREST-EARNING ASSETS
A6: Credit card | B6: 0.1798 | C6: 0.1817 | D6: 0.1902 | E6: 0.1894 | F6: 0.1884 | G6: 0.1879 | H6: 0.1966 | I6: 0.1905 | J6: 0.1854 | K6: 0.1794 | L6: 0.1799 | M6: 0.1767 | N6: 0.1717 | O6: 0.1721
A7: Consumer banking | B7: 0.074 | C7: 0.0765 | D7: 0.0797 | E7: 0.0817 | F7: 0.0833 | G7: 0.0854 | H7: 0.0888 | I7: 0.0904 | J7: 0.0903 | K7: 0.093 | L7: 0.0952 | M7: 0.0958 | N7: 0.0943 | O7: 0.0957
A8: Commercial banking | B8: 0.063 | C8: 0.0674 | D8: 0.0712 | E8: 0.0724 | F8: 0.0713 | G8: 0.0722 | H8: 0.0724 | I8: 0.0672 | J8: 0.0629 | K8: 0.064 | L8: 0.0642 | M8: 0.0608 | N8: 0.0568 | O8: 0.0575
A9: Total loans (incl. HFS) | B9: 0.1132 | C9: 0.1167 | D9: 0.1237 | E9: 0.1255 | F9: 0.1257 | G9: 0.1266 | H9: 0.1324 | I9: 0.1295 | J9: 0.1259 | K9: 0.1315 | L9: 0.1383 | M9: 0.1362 | N9: 0.1319 | O9: 0.1323
A10: Investment securities | B10: 0.0273 | C10: 0.0284 | D10: 0.0286 | E10: 0.0302 | F10: 0.031 | G10: 0.0313 | H10: 0.0324 | I10: 0.0326 | J10: 0.0332 | K10: 0.0337 | L10: 0.0342 | M10: 0.0346 | N10: 0.034 | O10: 0.0342
A11: Cash equivalents and other | B11: 0.0449 | C11: 0.0484 | D11: 0.0521 | E11: 0.0521 | F11: 0.0521 | G11: 0.0516 | H11: 0.0514 | I11: 0.0459 | J11: 0.0414 | K11: 0.0446 | L11: 0.0502 | M11: 0.0432 | N11: 0.0366 | O11: 0.037
A12: Total interest-earning assets | B12: 0.0896 | C12: 0.0926 | D12: 0.0981 | E12: 0.0997 | F12: 0.0998 | G12: 0.1001 | H12: 0.1044 | I12: 0.1017 | J12: 0.0987 | K12: 0.1054 | L12: 0.113 | M12: 0.1104 | N12: 0.1052 | O12: 0.1061
A14: INTEREST-BEARING LIABILITIES
A15: Interest-bearing deposits | B15: 0.024 | C15: 0.0291 | D15: 0.033 | E15: 0.0347 | F15: 0.0353 | G15: 0.0356 | H15: 0.0363 | I15: 0.0345 | J15: 0.0322 | K15: 0.0322 | L15: 0.0327 | M15: 0.0315 | N15: 0.03 | O15: 0.0291
A16: Securitized debt obligations | B16: 0.049 | C16: 0.0531 | D16: 0.0563 | E16: 0.0584 | F16: 0.0585 | G16: 0.0591 | H16: 0.0593 | I16: 0.055 | J16: 0.0511 | K16: 0.0506 | L16: 0.0511 | M16: 0.0489 | N16: 0.0452 | O16: 0.0459
A17: Senior and subordinated notes | B17: 0.0649 | C17: 0.07 | D17: 0.0736 | E17: 0.0746 | F17: 0.0752 | G17: 0.0764 | H17: 0.0743 | I17: 0.0699 | J17: 0.0666 | K17: 0.0651 | L17: 0.0641 | M17: 0.0602 | N17: 0.0563 | O17: 0.057
A18: Other borrowings | B18: 0.0208 | C18: 0.0195 | D18: 0.0179 | E18: 0.0171 | F18: 0.0178 | G18: 0.0173 | H18: 0.015 | I18: 0.0198 | J18: 0.0157 | K18: 0.0185 | L18: 0.0204 | M18: 0.0245 | N18: 0.0244 | O18: 0.023
A19: Total interest-bearing liabilities | B19: 0.0287 | C19: 0.0336 | D19: 0.0375 | E19: 0.0392 | F19: 0.0398 | G19: 0.04 | H19: 0.0404 | I19: 0.0381 | J19: 0.0354 | K19: 0.0352 | L19: 0.0355 | M19: 0.034 | N19: 0.0323 | O19: 0.0315
A21: Net interest spread (asset yield − funding cost) | B21: =B12-B19 -> 0.0609 | C21: =C12-C19 -> 0.059 | D21: =D12-D19 -> 0.0606 | E21: =E12-E19 -> 0.0605 | F21: =F12-F19 -> 0.06 | G21: =G12-G19 -> 0.0601 | H21: =H12-H19 -> 0.064 | I21: =I12-I19 -> 0.0636 | ... O21: =O12-O19 -> 0.0746
A22: Net interest margin (NII / avg earning assets) | B22: =IFERROR(('Net Interest Income'!B21*4)/Balance!B12,"") -> 0.066047946 | C22: =IFERROR(('Net Interest Income'!C21*4)/Balance!C12,"") -> 0.064790419 | D22: =IFERROR(('Net Interest Income'!D21*4)/Balance!D12,"") -> 0.066944437 | E22: =IFERROR(('Net Interest Income'!E21*4)/Balance!E12,"") -> 0.067285772 | F22: =IFERROR(('Net Interest Income'!F21*4)/Balance!F12,"") -> 0.066886555 | G22: =IFERROR(('Net Interest Income'!G21*4)/Balance!G12,"") -> 0.066940485 | H22: =IFERROR(('Net Interest Income'!H21*4)/Balance!H12,"") -> 0.07107841 | I22: =IFERROR(('Net Interest Income'!I21*4)/Balance!I12,"") -> 0.070311923 | ... O22: =IFERROR(('Net Interest Income'!O21*4)/Balance!O12,"") -> 0.080144693

Sheet Net Interest Income
A1: Capital One — Interest Income / Expense by line item ($mm, quarterly)
A2: Interest income on assets, interest expense on liabilities, as disclosed (expense shown positive). NII = total interest income − total interest expense. (D) = Q4 derived as FY − 9M; interest is additive so this is exact.
A4: Line item (as disclosed) | B4: 2023-03-31 | C4: 2023-06-30 | D4: 2023-09-30 | E4: 2023-12-31 (D) | F4: 2024-03-31 | G4: 2024-06-30 | H4: 2024-09-30 | I4: 2024-12-31 (D) | J4: 2025-03-31 | K4: 2025-06-30 | L4: 2025-09-30 | M4: 2025-12-31 (D) | N4: 2026-03-31 | O4: 2026-06-30
A5: INTEREST-EARNING ASSETS
A6: Credit card | B6: 6053 | C6: 6302 | D6: 6850 | E6: 7062 | F6: 7067 | G6: 7088 | H6: 7578 | I6: 7493 | J6: 7248 | K6: 9407 | L6: 12109 | M6: 12049 | N6: 11633 | O6: 11670
A7: Consumer banking | B7: 1461 | C7: 1486 | D7: 1537 | E7: 1557 | F7: 1564 | G7: 1611 | H7: 1692 | I7: 1745 | J7: 1773 | K7: 1861 | L7: 1958 | M7: 2012 | N7: 2020 | O7: 2121
A8: Commercial banking | B8: 1488 | C8: 1580 | D8: 1642 | E8: 1653 | F8: 1612 | G8: 1616 | H8: 1601 | I8: 1472 | J8: 1382 | K8: 1421 | L8: 1426 | M8: 1356 | N8: 1278 | O8: 1308
A9: Total loans (incl. HFS) | B9: 8723 | C9: 9057 | D9: 9696 | E9: 9934 | F9: 9920 | G9: 9993 | H9: 10547 | I9: 10434 | J9: 10157 | K9: 12449 | L9: 15229 | M9: 15186 | N9: 14735 | O9: 14911
A10: Investment securities | B10: 615 | C10: 639 | D10: 627 | E10: 669 | F10: 687 | G10: 700 | H10: 733 | I10: 753 | J10: 770 | K10: 784 | L10: 823 | M10: 841 | N10: 832 | O10: 850
A11: Cash equivalents and other | B11: 416 | C11: 470 | D11: 550 | E11: 542 | F11: 570 | G11: 587 | H11: 580 | I11: 530 | J11: 491 | K11: 595 | L11: 711 | M11: 660 | N11: 664 | O11: 624
A12: Total interest-earning assets | B12: 9754 | C12: 10166 | D12: 10873 | E12: 11145 | F12: 11177 | G12: 11280 | H12: 11860 | I12: 11717 | J12: 11418 | K12: 13828 | L12: 16763 | M12: 16687 | N12: 16231 | O12: 16385
A14: INTEREST-BEARING LIABILITIES
A15: Interest-bearing deposits | B15: 1856 | C15: 2277 | D15: 2611 | E15: 2745 | F15: 2812 | G15: 2874 | H15: 2945 | I15: 2862 | J15: 2715 | K15: 3120 | L15: 3597 | M15: 3493 | N15: 3387 | O15: 3338
A16: Securitized debt obligations | B16: 211 | C16: 236 | D16: 249 | E16: 263 | F16: 261 | G16: 258 | H16: 234 | I16: 205 | J16: 176 | K16: 164 | L16: 165 | M16: 155 | N16: 141 | O16: 117
A17: Senior and subordinated notes | B17: 489 | C17: 528 | D17: 579 | E17: 608 | F17: 606 | G17: 591 | H17: 596 | I17: 540 | J17: 505 | K17: 535 | L17: 582 | M17: 550 | N17: 532 | O17: 535
A18: Other borrowings | B18: 12 | C18: 12 | D18: 11 | E18: 10 | F18: 10 | G18: 11 | H18: 9 | I18: 12 | J18: 9 | K18: 14 | L18: 15 | M18: 23 | N18: 26 | O18: 21
A19: Total interest-bearing liabilities | B19: 2568 | C19: 3053 | D19: 3450 | E19: 3626 | F19: 3689 | G19: 3734 | H19: 3784 | I19: 3619 | J19: 3405 | K19: 3833 | L19: 4359 | M19: 4221 | N19: 4086 | O19: 4011
A21: NET INTEREST INCOME | B21: =B12-B19 -> 7186 | C21: =C12-C19 -> 7113 | D21: =D12-D19 -> 7423 | E21: =E12-E19 -> 7519 | F21: =F12-F19 -> 7488 | G21: =G12-G19 -> 7546 | H21: =H12-H19 -> 8076 | I21: =I12-I19 -> 8098 | ... O21: =O12-O19 -> 12374
A23: CHECK: NII vs income statement (flows.csv)
A24: Income statement NII (XBRL) | B24: 7186 | C24: 7113 | D24: 7423 | E24: 7519 | F24: 7488 | G24: 7546 | H24: 8076 | I24: 8098 | J24: 8013 | K24: 9995 | L24: 12404 | M24: 12466 | N24: 12145 | O24: 12374
A25: Difference | B25: =IF(B24="","",B21-B24) -> 0 | C25: =IF(C24="","",C21-C24) -> 0 | D25: =IF(D24="","",D21-D24) -> 0 | E25: =IF(E24="","",E21-E24) -> 0 | F25: =IF(F24="","",F21-F24) -> 0 | G25: =IF(G24="","",G21-G24) -> 0 | H25: =IF(H24="","",H21-H24) -> 0 | I25: =IF(I24="","",I21-I24) -> 0 | ... O25: =IF(O24="","",O21-O24) -> 0
A27: Blue = as disclosed. Green = from the XBRL income statement (independent source). Black = formula. Difference should be zero: the MD&A average-balance table and the income statement must agree on NII.

Sheet Notes & Sources
A1: Balance / Rate / Net Interest Income — Capital One
A3: ON "GL ACCOUNTS"
A4: SEC filings do not expose a general ledger. These rows are the line items Capital One discloses in its average-balance table — the finest account-level granularity available externally. They are groupings, not GL account numbers.
A6: WHAT EACH TABLE HOLDS
A7: Balance — AVERAGE balance over the quarter, in $mm. Not period-end; it will not tie to the balance sheet.
A8: Rate — annualised yield (assets) and cost of funds (liabilities), stored as fractions and displayed as percentages.
A9: Net Interest Income — interest income on assets and interest expense on liabilities, with NII computed as the difference of the totals.
A11: SOURCE
A12: Capital One Financial Corp (CIK 0000927628), Forms 10-Q and 10-K, MD&A table 'Average Balances, Net Interest Income and Net Interest Margin'. These MD&A tables are NOT XBRL-tagged, so values are parsed from the rendered HTML.
A14: Q4 DERIVATION, AND WHY IT IS SOUND
A15: No 3-month Q4 average-balance table is published: the 10-K table is annual and the 10-Q tables are 3/6/9-month. Q4 columns are marked (D).
A16: Two identities were tested against the actual data, both passing 48 of 48 cases: interest is additive (6M = Q1 + Q2), and average balances weight by months (6M avg = (Q1 avg x3 + Q2 avg x3) / 6).
... A23: Blue = as disclosed in the filing. Green = independent XBRL source. Black = live formula. Yellow = check cell, should read zero.
